Workbook

Sheet 参数输入表
D1: 【抽水蓄能】财务评价计算模型边界条件输入参数表
B3: 类别 | C3: 序号 | D3: 参数 | E3: 操作类型 | F3: 数据结构化整理 | G3: 收入/成本归类 | H3: 参数释义/计算公式 | I3: 数值 | J3: 单位 | K3: 取值说明 | L3: 备注
B4: 工程计划 | C4: 1 | D4: 建设期 | E4: 自动计算，向上取整 | I4: =ROUNDUP(I10,0) -> 8 | J4: 年 | K4: 占用的表格年度跨度，如7.5年需考虑8个会计年度
D5: 建设期起始日期 | E5: 下拉菜单选择【日历】 | I5: 44958 | K5: 输入完动工年月及建设期结束日期，自动配置出参数表及计算表中建设期所占报表年度（如建设期为7年5个月，建设期实际占8个报表年）
D6: 建设期首年年末 | I6: 45291
D7: 建设期结束日期 | E7: 下拉菜单选择【日历】 | I7: 47695
D8: 建设期末年年初 | I8: 47484
D9: 建设期月份数 | E9: 自动计算 | I9: =ROUND(DATEDIF(I5,I7,"D")/365*12,0) -> 90 | J9: 月
D10: 建设期月份数转化为年 | I10: =I9/12 -> 7.5 | J10: 年
D11: 建设期首年月份 | E11: 自动计算 | I11: =ROUND(DATEDIF(I5,I6,"D")/365*12,0) -> 11 | J11: 月
D12: 建设期末年月份 | E12: 自动计算 | I12: =ROUND(DATEDIF(I8,I7,"D")/365*12,0) -> 7 | J12: 月
C13: 2 | D13: 施工进度安排 | I13: =SUM(I14:I23) -> 1
D14: 2023年3月（自定义时间点1） | E14: 自动计算 | I14: =投资概算明细!F24 -> 0.032776537 | J14: % | K14: 2023.2.1-2023.3.31（2个月）
D15: 45261 | E15: 自动计算 | I15: =投资概算明细!G24 -> 0.076478585 | J15: % | K15: 2023.4.1-2023.12.31（9个月）
D16: 45627 | E16: 自动计算 | I16: =投资概算明细!H24 -> 0.10622378 | J16: % | K16: 2024.1.1-2024.12.31（12个月）
D17: 45992 | E17: 自动计算 | I17: =投资概算明细!I24 -> 0.12056456 | J17: % | K17: 2025.1.1-2025.12.31（12个月）
D18: 46357 | E18: 自动计算 | I18: =投资概算明细!J24 -> 0.1318463 | J18: % | K18: 2026.1.1-2026.12.31（12个月）
D19: 46722 | E19: 自动计算 | I19: =投资概算明细!K24 -> 0.176246 | J19: % | K19: 2027.1.1-2027.12.31（12个月）
D20: 47088 | E20: 自动计算 | I20: =投资概算明细!L24 -> 0.16159672 | J20: % | K20: 2028.1.1-2028.12.31（12个月）
D21: 2029年8月（自定义时间点1） | E21: 自动计算 | I21: =投资概算明细!M24 -> 0.081637444 | J21: % | K21: 2029.1.1-2029.8.31（8个月）
D22: 47453 | E22: 自动计算 | I22: =投资概算明细!N24 -> 0.054424963 | J22: % | K22: 2029.9.1-2029.12.31（4个月）
D23: 47665 | E23: 自动计算 | I23: =投资概算明细!O24 -> 0.058205099 | J23: % | K23: 2030.1.1-2030.7.31（7个月）
D24: …… | E24: 根据需要（向上取整）配置
C25: 3 | D25: 投产起始日期 | E25: 手动输入/下拉菜单选择【日历】 | I25: =YEAR(I27)-YEAR(I5)+1 -> 8 | J25: 第n年/第n月
C26: 4 | D26: 运营期/商业运营期 | E26: 手动输入 | I26: 40 | J26: 年
D27: 运营期起始日期 | E27: 自动计算 | I27: =I7+1 -> 47696 | K27: 建设期结束后1天既进入运营期
D28: 运营期结束日期 | E28: 自动计算 | I28: =I7+I26*365+INT(I26/4) -> 62305 | K28: 以建设期结束日期加运营期计算所得，同时考虑每4年出现闰年比非闰年多1天，运营期无法被4整除的按倍数取整
C29: 5 | D29: 试运营期 | E29: 选择时间区间 | J29: 年/月 | K29: 用于最后的累计盈余资金判定
C30: 6 | D30: 项目所在地 | E30: 下拉菜单选择 | K30: 判定是否属于西部地区
D31: 所在省份 | E31: 下拉菜单选择
D32: 所在市、县 | E32: 下拉菜单选择
B33: 生产技术 | C33: 1 | D33: 实际装机容量 | E33: 手动输入 | I33: 1400 | J33: MW | K33: 1MW=1000kW
C34: 2 | D34: 年利用小时数 | E34: 手动输入 | I34: 1169.2857 | J34: h
C35: 3 | D35: 新增投产比例
D36: 47150 | E36: 下拉菜单选择【日历】/手动输入 | I36: 0 | J36: %
D37: 47362 | E37: 下拉菜单选择【日历】/手动输入 | I37: 0 | J37: %
D38: 47543 | E38: 下拉菜单选择【日历】/手动输入 | I38: 0 | J38: %
D39: 47696 | E39: 下拉菜单选择【日历】/手动输入 | I39: 1 | J39: %
C40: 4 | D40: 达产率
C41: 4.1 | D41: 设备设施平均达产率
D42: 47150 | E42: 下拉菜单选择【日历】/手动输入 | I42: 0 | J42: %
D43: 47362 | E43: 下拉菜单选择【日历】/手动输入 | I43: 0 | J43: %
D44: 47543 | E44: 下拉菜单选择【日历】/手动输入 | I44: 0 | J44: %
D45: 47696 | E45: 下拉菜单选择【日历】/手动输入 | I45: 1 | J45: %
C46: 4.2 | D46: 年度达产率（全生命周期） | E46: 自动计算
D47: 合作期第1年 | E47: 自动计算 | I47: ='投产&达产比例'!Z11 -> 0 | J47: %
D48: 合作期第2年 | E48: 自动计算 | I48: ='投产&达产比例'!Z12 -> 0 | J48: %
D49: 合作期第3年 | E49: 自动计算 | I49: ='投产&达产比例'!Z13 -> 0 | J49: %
D50: 合作期第4年 | E50: 自动计算 | I50: ='投产&达产比例'!Z14 -> 0 | J50: %
D51: 合作期第5年 | E51: 自动计算 | I51: ='投产&达产比例'!Z15 -> 0 | J51: %
D52: 合作期第6年 | E52: 自动计算 | I52: ='投产&达产比例'!Z16 -> 0 | J52: %
D53: 合作期第7年 | E53: 自动计算 | I53: ='投产&达产比例'!Z17 -> 0 | J53: %
D54: 合作期第8年 | E54: 自动计算 | I54: ='投产&达产比例'!Z18 -> 0.41666667 | J54: %
D55: 合作期第9年 | E55: 自动计算 | I55: ='投产&达产比例'!Z19 -> 1 | J55: %
D56: 合作期第10年 | E56: 自动计算 | I56: ='投产&达产比例'!Z20 -> 1 | J56: %
D57: 合作期第11年 | E57: 自动计算 | I57: ='投产&达产比例'!Z21 -> 1 | J57: %
D58: 合作期第12年 | E58: 自动计算 | I58: ='投产&达产比例'!Z22 -> 1 | J58: %
... D94: 合作期第48年 | E94: 自动计算 | I94: ='投产&达产比例'!Z58 -> 0.58333333 | J94: %
C95: 5 | D95: 发电量 | E95: 自动计算 | H95: 抽水蓄能上网电量=年利用小时数*实际装机容量 | J95: MWh | K95: 1MWh=0.1万度电
D96: 合作期第1年 | E96: 自动计算 | I96: =$I$33*$I$34*I47 -> 0 | J96: MWh
D97: 合作期第2年 | E97: 自动计算 | I97: =$I$33*$I$34*I48 -> 0 | J97: MWh
D98: 合作期第3年 | E98: 自动计算 | I98: =$I$33*$I$34*I49 -> 0 | J98: MWh
D99: 合作期第4年 | E99: 自动计算 | I99: =$I$33*$I$34*I50 -> 0 | J99: MWh
D100: 合作期第5年 | E100: 自动计算 | I100: =$I$33*$I$34*I51 -> 0 | J100: MWh
D101: 合作期第6年 | E101: 自动计算 | I101: =$I$33*$I$34*I52 -> 0 | J101: MWh
D102: 合作期第7年 | E102: 自动计算 | I102: =$I$33*$I$34*I53 -> 0 | J102: MWh
D103: 合作期第8年 | E103: 自动计算 | I103: =$I$33*$I$34*I54 -> 682083.33 | J103: MWh
D104: 合作期第9年 | E104: 自动计算 | I104: =$I$33*$I$34*I55 -> 1637000 | J104: MWh
D105: 合作期第10年 | E105: 自动计算 | I105: =$I$33*$I$34*I56 -> 1637000 | J105: MWh
D106: 合作期第11年 | E106: 自动计算 | I106: =$I$33*$I$34*I57 -> 1637000 | J106: MWh
D107: 合作期第12年 | E107: 自动计算 | I107: =$I$33*$I$34*I58 -> 1637000 | J107: MWh
... D143: 合作期第48年 | E143: 自动计算 | I143: =$I$33*$I$34*I94 -> 954916.67 | J143: MWh
C144: 6 | D144: 上网电价 | E144: 手动输入 | I144: 0.35 | J144: 元/kWh
D145: 合作期第1年 | E145: 手动输入 | I145: =$I$144 -> 0.35 | J145: 元/kWh
D146: 合作期第2年 | E146: 手动输入 | I146: =$I$144 -> 0.35 | J146: 元/kWh
D147: 合作期第3年 | E147: 手动输入 | I147: =$I$144 -> 0.35 | J147: 元/kWh
D148: 合作期第4年 | E148: 手动输入 | I148: =$I$144 -> 0.35 | J148: 元/kWh
D149: 合作期第5年 | E149: 手动输入 | I149: =$I$144 -> 0.35 | J149: 元/kWh
D150: 合作期第6年 | E150: 手动输入 | I150: =$I$144 -> 0.35 | J150: 元/kWh
D151: 合作期第7年 | E151: 手动输入 | I151: =$I$144 -> 0.35 | J151: 元/kWh
D152: 合作期第8年 | E152: 手动输入 | I152: =$I$144 -> 0.35 | J152: 元/kWh
D153: 合作期第9年 | E153: 手动输入 | I153: =$I$144 -> 0.35 | J153: 元/kWh
D154: 合作期第10年 | E154: 手动输入 | I154: =$I$144 -> 0.35 | J154: 元/kWh
D155: 合作期第11年 | E155: 手动输入 | I155: =$I$144 -> 0.35 | J155: 元/kWh
D156: 合作期第12年 | E156: 手动输入 | I156: =$I$144 -> 0.35 | J156: 元/kWh
... D192: 合作期第48年 | E192: 手动输入 | I192: =$I$144 -> 0.35 | J192: 元/kWh
B193: 工程概算 | C193: 1 | D193: 枢纽工程 | E193: 自动计算 | I193: =SUM(I194:I200) -> 638349.96 | J193: 万元
C194: 1.1 | D194: 施工辅助工程 | E194: 手动输入/下拉菜单选择【增值税税率】 | G194: 0.09 | H194: 增值税税率（自动生成含税和不含税价）：13%/9%/6%/0% | I194: =投资概算明细!D5 -> 62992.58 | J194: 万元
C195: 1.2 | D195: 建筑工程 | E195: 手动输入/下拉菜单选择【增值税税率】 | G195: 0.09 | H195: 增值税税率（自动生成含税和不含税价）：13%/9%/6%/0% | I195: =投资概算明细!D6 -> 331236.41 | J195: 万元
C196: 1.3 | D196: 环境保护和水土保持专项工程 | E196: 手动输入/下拉菜单选择【增值税税率】 | G196: 0.09 | H196: 增值税税率（自动生成含税和不含税价）：13%/9%/6%/0% | I196: =投资概算明细!D7 -> 17893.9 | J196: 万元
C197: 1.4 | D197: 机电设备安装工程 | E197: 手动输入/下拉菜单选择【增值税税率】 | G197: 0.09 | H197: 增值税税率（自动生成含税和不含税价）：13%/9%/6%/0% | I197: =投资概算明细!D8 -> 68286.2 | J197: 万元
C198: 1.5 | D198: 金属结构设备安装工程 | E198: 手动输入/下拉菜单选择【增值税税率】 | G198: 0.09 | H198: 增值税税率（自动生成含税和不含税价）：13%/9%/6%/0% | I198: =投资概算明细!D9 -> 157940.87 | J198: 万元
C199: 1.6 | D199: 机电设备采购工程 | E199: 手动输入/下拉菜单选择【增值税税率】 | G199: 0.13 | H199: 增值税税率（自动生成含税和不含税价）：13%/9%/6%/0% | I199: =投资概算明细!D10 -> 0 | J199: 万元
C200: 1.7 | D200: 金属结构设备采购工程 | E200: 手动输入/下拉菜单选择【增值税税率】 | G200: 0.13 | H200: 增值税税率（自动生成含税和不含税价）：13%/9%/6%/0% | I200: =投资概算明细!D11 -> 0 | J200: 万元
C201: 2 | D201: 建设征地和移民安置补偿费用 | E201: 手动输入/下拉菜单选择【增值税税率】 | G201: 0 | H201: 增值税税率（自动生成含税和不含税价）：13%/9%/6%/0% | I201: =投资概算明细!D12 -> 5205.27 | J201: 万元
C202: 3 | D202: 独立费用 | E202: 自动计算 | H202: 增值税税率（自动生成含税和不含税价）：13%/9%/6%/0% | I202: =SUM(I203:I206) -> 122855.89 | J202: 万元
C203: 3.1 | D203: 建设管理费 | E203: 手动输入/下拉菜单选择【增值税税率】 | G203: 0.06 | H203: 增值税税率（自动生成含税和不含税价）：13%/9%/6%/0% | I203: =投资概算明细!D14 -> 54324.05 | J203: 万元
C204: 3.2 | D204: 生产准备费 | E204: 手动输入/下拉菜单选择【增值税税率】 | G204: 0 | H204: 增值税税率（自动生成含税和不含税价）：13%/9%/6%/0% | I204: =投资概算明细!D15 -> 8001.3 | J204: 万元
C205: 3.3 | D205: 科研勘查设计费 | E205: 手动输入/下拉菜单选择【增值税税率】 | G205: 0.06 | H205: 增值税税率（自动生成含税和不含税价）：13%/9%/6%/0% | I205: =投资概算明细!D16 -> 56990.05 | J205: 万元
C206: 3.4 | D206: 其他税费 | E206: 手动输入/下拉菜单选择【增值税税率】 | G206: 0 | H206: 增值税税率（自动生成含税和不含税价）：13%/9%/6%/0% | I206: =投资概算明细!D17 -> 3540.49 | J206: 万元
...

Sheet 时间序列
B3: 项目 | C3: 建设期开始 | D3: 建设期 | N3: 运营期 | BC3: 运营期结束
B4: 项目完整时间序列 | C4: =参数输入表!I5 -> 44958 | D4: 45016 | E4: 45291 | F4: 45657 | G4: 46022 | H4: 46387 | I4: 46752 | J4: 47118 | K4: 47361 | L4: 47483 | M4: 47695 | N4: =参数输入表!I250 -> 47726 | O4: 47848 | P4: 48213 | Q4: 48579 | R4: 48944 | S4: 49309 | T4: 49674 | U4: 50040 | V4: 50405 | W4: 50770 | X4: 51135 | Y4: 51501 | Z4: 51866 | AA4: 52231 | AB4: 52596 | AC4: 52962 | AD4: 53327 | AE4: 53692 | AF4: 54057 | AG4: 54423 | AH4: 54788 | AI4: 55153 | AJ4: 55518 | AK4: 55884 | AL4: 56249 | AM4: 56614 | AN4: 56979 | AO4: 57345 | AP4: 57710 | AQ4: 58075 | AR4: 58440 | AS4: 58806 | AT4: 59171 | AU4: 59536 | AV4: 59901 | AW4: 60267 | AX4: 60632 | AY4: 60997 | AZ4: 61362 | BA4: 61728 | BB4: 62093 | BC4: =参数输入表!I28 -> 62305
B5: 相邻时间节点间隔（月） | C5: 0 | D5: =ROUND(DATEDIF(C4,D4,"d")/30,0) -> 2 | E5: =ROUND(DATEDIF(D4,E4,"d")/30,0) -> 9 | F5: =ROUND(DATEDIF(E4,F4,"d")/30,0) -> 12 | G5: =ROUND(DATEDIF(F4,G4,"d")/30,0) -> 12 | H5: =ROUND(DATEDIF(G4,H4,"d")/30,0) -> 12 | I5: =ROUND(DATEDIF(H4,I4,"d")/30,0) -> 12 | J5: =ROUND(DATEDIF(I4,J4,"d")/30,0) -> 12 | K5: =ROUND(DATEDIF(J4,K4,"d")/30,0) -> 8 | ... BC5: =ROUND(DATEDIF(BB4,BC4,"d")/30,0) -> 7
B6: 时间节点所处年度 | C6: =YEAR(C4) -> 2023 | D6: =YEAR(D4) -> 2023 | E6: =YEAR(E4) -> 2023 | F6: =YEAR(F4) -> 2024 | G6: =YEAR(G4) -> 2025 | H6: =YEAR(H4) -> 2026 | I6: =YEAR(I4) -> 2027 | J6: =YEAR(J4) -> 2028 | ... BC6: =YEAR(BC4) -> 2070
B7: 时间序列（年） | C7: 2023 | D7: 2024 | E7: 2025 | F7: 2026 | G7: 2027 | H7: 2028 | I7: 2029 | J7: 2030 | K7: 2031 | L7: 2032 | M7: 2033 | N7: 2034 | O7: 2035 | P7: 2036 | Q7: 2037 | R7: 2038 | S7: 2039 | T7: 2040 | U7: 2041 | V7: 2042 | W7: 2043 | X7: 2044 | Y7: 2045 | Z7: 2046 | AA7: 2047 | AB7: 2048 | AC7: 2049 | AD7: 2050 | AE7: 2051 | AF7: 2052 | AG7: 2053 | AH7: 2054 | AI7: 2055 | AJ7: 2056 | AK7: 2057 | AL7: 2058 | AM7: 2059 | AN7: 2060 | AO7: 2061 | AP7: 2062 | AQ7: 2063 | AR7: 2064 | AS7: 2065 | AT7: 2066 | AU7: 2067 | AV7: 2068 | AW7: 2069 | AX7: 2070
B8: 当年占用时间（月） | C8: =SUMIF($C$6:$BC$6,C7,$C$5:$BC$5) -> 11 | D8: =SUMIF($C$6:$BC$6,D7,$C$5:$BC$5) -> 12 | E8: =SUMIF($C$6:$BC$6,E7,$C$5:$BC$5) -> 12 | F8: =SUMIF($C$6:$BC$6,F7,$C$5:$BC$5) -> 12 | G8: =SUMIF($C$6:$BC$6,G7,$C$5:$BC$5) -> 12 | H8: =SUMIF($C$6:$BC$6,H7,$C$5:$BC$5) -> 12 | I8: =SUMIF($C$6:$BC$6,I7,$C$5:$BC$5) -> 12 | J8: =SUMIF($C$6:$BC$6,J7,$C$5:$BC$5) -> 12 | ... AX8: =SUMIF($C$6:$BC$6,AX7,$C$5:$BC$5) -> 7
B10: 项目 | C10: 投产开始 | AS10: 运营期结束
B11: 项目投产时间序列 | C11: =参数输入表!D36 -> 47150 | D11: 47483 | E11: 47848 | F11: 48213 | G11: 48579 | H11: 48944 | I11: 49309 | J11: 49674 | K11: 50040 | L11: 50405 | M11: 50770 | N11: 51135 | O11: 51501 | P11: 51866 | Q11: 52231 | R11: 52596 | S11: 52962 | T11: 53327 | U11: 53692 | V11: 54057 | W11: 54423 | X11: 54788 | Y11: 55153 | Z11: 55518 | AA11: 55884 | AB11: 56249 | AC11: 56614 | AD11: 56979 | AE11: 57345 | AF11: 57710 | AG11: 58075 | AH11: 58440 | AI11: 58806 | AJ11: 59171 | AK11: 59536 | AL11: 59901 | AM11: 60267 | AN11: 60632 | AO11: 60997 | AP11: 61362 | AQ11: 61728 | AR11: 62093 | AS11: =参数输入表!I28 -> 62305
B12: 相邻时间节点间隔（月） | C12: 0 | D12: =ROUND(DATEDIF(C11,D11,"d")/30,0) -> 11 | E12: =ROUND(DATEDIF(D11,E11,"d")/30,0) -> 12 | F12: =ROUND(DATEDIF(E11,F11,"d")/30,0) -> 12 | G12: =ROUND(DATEDIF(F11,G11,"d")/30,0) -> 12 | H12: =ROUND(DATEDIF(G11,H11,"d")/30,0) -> 12 | I12: =ROUND(DATEDIF(H11,I11,"d")/30,0) -> 12 | J12: =ROUND(DATEDIF(I11,J11,"d")/30,0) -> 12 | K12: =ROUND(DATEDIF(J11,K11,"d")/30,0) -> 12 | ... AS12: =ROUND(DATEDIF(AR11,AS11,"d")/30,0) -> 7
B13: 时间节点所处年度 | C13: =YEAR(C11) -> 2029 | D13: =YEAR(D11) -> 2029 | E13: =YEAR(E11) -> 2030 | F13: =YEAR(F11) -> 2031 | G13: =YEAR(G11) -> 2032 | H13: =YEAR(H11) -> 2033 | I13: =YEAR(I11) -> 2034 | J13: =YEAR(J11) -> 2035 | ... AS13: =YEAR(AS11) -> 2070
B14: 时间序列（年） | C14: 2029 | D14: 2030 | E14: 2031 | F14: 2032 | G14: 2033 | H14: 2034 | I14: 2035 | J14: 2036 | K14: 2037 | L14: 2038 | M14: 2039 | N14: 2040 | O14: 2041 | P14: 2042 | Q14: 2043 | R14: 2044 | S14: 2045 | T14: 2046 | U14: 2047 | V14: 2048 | W14: 2049 | X14: 2050 | Y14: 2051 | Z14: 2052 | AA14: 2053 | AB14: 2054 | AC14: 2055 | AD14: 2056 | AE14: 2057 | AF14: 2058 | AG14: 2059 | AH14: 2060 | AI14: 2061 | AJ14: 2062 | AK14: 2063 | AL14: 2064 | AM14: 2065 | AN14: 2066 | AO14: 2067 | AP14: 2068 | AQ14: 2069 | AR14: 2070
B15: 当年占用时间（月） | C15: =SUMIF($C$13:$BB$13,C14,$C$12:$BB$12) -> 11 | D15: =SUMIF($C$13:$BB$13,D14,$C$12:$BB$12) -> 12 | E15: =SUMIF($C$13:$BB$13,E14,$C$12:$BB$12) -> 12 | F15: =SUMIF($C$13:$BB$13,F14,$C$12:$BB$12) -> 12 | G15: =SUMIF($C$13:$BB$13,G14,$C$12:$BB$12) -> 12 | H15: =SUMIF($C$13:$BB$13,H14,$C$12:$BB$12) -> 12 | I15: =SUMIF($C$13:$BB$13,I14,$C$12:$BB$12) -> 12 | J15: =SUMIF($C$13:$BB$13,J14,$C$12:$BB$12) -> 12 | ... AR15: =SUMIF($C$13:$BB$13,AR14,$C$12:$BB$12) -> 7
B17: 首批固定资产折旧开始-结束时点 | C17: =参数输入表!$D$36 -> 47150 | D17: =参数输入表!$D$36+参数输入表!$I$622*365+INT(参数输入表!$I$622/4) -> 57742
B18: 固定资产折旧摊销时间序列 | C18: =YEAR(C19) -> 2029 | D18: =YEAR(D19) -> 2029 | E18: =YEAR(E19) -> 2030 | F18: =YEAR(F19) -> 2031 | G18: =YEAR(G19) -> 2032 | H18: =YEAR(H19) -> 2033 | I18: =YEAR(I19) -> 2034 | J18: =YEAR(J19) -> 2035 | ... AG18: =YEAR(AG19) -> 2058
C19: =C17 -> 47150 | D19: 47483 | E19: 47848 | F19: 48213 | G19: 48579 | H19: 48944 | I19: 49309 | J19: 49674 | K19: 50040 | L19: 50405 | M19: 50770 | N19: 51135 | O19: 51501 | P19: 51866 | Q19: 52231 | R19: 52596 | S19: 52962 | T19: 53327 | U19: 53692 | V19: 54057 | W19: 54423 | X19: 54788 | Y19: 55153 | Z19: 55518 | AA19: 55884 | AB19: 56249 | AC19: 56614 | AD19: 56979 | AE19: 57345 | AF19: 57710 | AG19: =D17 -> 57742
B20: =SUM(C20:AX20) -> 348 | C20: 0 | D20: =ROUND((DATEDIF(C19,D19,"d"))/30,0) -> 11 | E20: =ROUND((DATEDIF(D19,E19,"d"))/30,0) -> 12 | F20: =ROUND((DATEDIF(E19,F19,"d"))/30,0) -> 12 | G20: =ROUND((DATEDIF(F19,G19,"d"))/30,0) -> 12 | H20: =ROUND((DATEDIF(G19,H19,"d"))/30,0) -> 12 | I20: =ROUND((DATEDIF(H19,I19,"d"))/30,0) -> 12 | J20: =ROUND((DATEDIF(I19,J19,"d"))/30,0) -> 12 | K20: =ROUND((DATEDIF(J19,K19,"d"))/30,0) -> 12 | ... AG20: =ROUND((DATEDIF(AF19,AG19,"d"))/30,0) -> 1
B21: 时间序列（年） | C21: 2023 | D21: 2024 | E21: 2025 | F21: 2026 | G21: 2027 | H21: 2028 | I21: 2029 | J21: 2030 | K21: 2031 | L21: 2032 | M21: 2033 | N21: 2034 | O21: 2035 | P21: 2036 | Q21: 2037 | R21: 2038 | S21: 2039 | T21: 2040 | U21: 2041 | V21: 2042 | W21: 2043 | X21: 2044 | Y21: 2045 | Z21: 2046 | AA21: 2047 | AB21: 2048 | AC21: 2049 | AD21: 2050 | AE21: 2051 | AF21: 2052 | AG21: 2053 | AH21: 2054 | AI21: 2055 | AJ21: 2056 | AK21: 2057 | AL21: 2058 | AM21: 2059 | AN21: 2060 | AO21: 2061 | AP21: 2062 | AQ21: 2063 | AR21: 2064 | AS21: 2065 | AT21: 2066 | AU21: 2067 | AV21: 2068 | AW21: 2069 | AX21: 2070
B22: 当年折旧月份数（固定资产） | C22: =SUMIF($C$18:$AG$18,C21,$C$20:$AG$20) -> 0 | D22: =SUMIF($C$18:$AG$18,D21,$C$20:$AG$20) -> 0 | E22: =SUMIF($C$18:$AG$18,E21,$C$20:$AG$20) -> 0 | F22: =SUMIF($C$18:$AG$18,F21,$C$20:$AG$20) -> 0 | G22: =SUMIF($C$18:$AG$18,G21,$C$20:$AG$20) -> 0 | H22: =SUMIF($C$18:$AG$18,H21,$C$20:$AG$20) -> 0 | I22: =SUMIF($C$18:$AG$18,I21,$C$20:$AG$20) -> 11 | J22: =SUMIF($C$18:$AG$18,J21,$C$20:$AG$20) -> 12 | ... AX22: =SUMIF($C$18:$AG$18,AX21,$C$20:$AG$20) -> 0
B23: 首批投产设备设施无形资产折旧开始-结束时点 | C23: =参数输入表!D36 -> 47150 | D23: =参数输入表!$D$36+参数输入表!$I$638*365+INT(参数输入表!$I$638/4) -> 53724
B24: 无形资产折旧摊销时间序列 | C24: =YEAR(C25) -> 2029 | D24: =YEAR(D25) -> 2029 | E24: =YEAR(E25) -> 2030 | F24: =YEAR(F25) -> 2031 | G24: =YEAR(G25) -> 2032 | H24: =YEAR(H25) -> 2033 | I24: =YEAR(I25) -> 2034 | J24: =YEAR(J25) -> 2035 | ... V24: =YEAR(V25) -> 2047
C25: =C23 -> 47150 | D25: 47483 | E25: 47848 | F25: 48213 | G25: 48579 | H25: 48944 | I25: 49309 | J25: 49674 | K25: 50040 | L25: 50405 | M25: 50770 | N25: 51135 | O25: 51501 | P25: 51866 | Q25: 52231 | R25: 52596 | S25: 52962 | T25: 53327 | U25: 53692 | V25: =D23 -> 53724
B26: =SUM(C26:AX26) -> 216 | C26: 0 | D26: =ROUND((DATEDIF(C25,D25,"d"))/30,0) -> 11 | E26: =ROUND((DATEDIF(D25,E25,"d"))/30,0) -> 12 | F26: =ROUND((DATEDIF(E25,F25,"d"))/30,0) -> 12 | G26: =ROUND((DATEDIF(F25,G25,"d"))/30,0) -> 12 | H26: =ROUND((DATEDIF(G25,H25,"d"))/30,0) -> 12 | I26: =ROUND((DATEDIF(H25,I25,"d"))/30,0) -> 12 | J26: =ROUND((DATEDIF(I25,J25,"d"))/30,0) -> 12 | K26: =ROUND((DATEDIF(J25,K25,"d"))/30,0) -> 12 | ... V26: =ROUND((DATEDIF(U25,V25,"d"))/30,0) -> 1
B27: 时间序列（年） | C27: 2023 | D27: 2024 | E27: 2025 | F27: 2026 | G27: 2027 | H27: 2028 | I27: 2029 | J27: 2030 | K27: 2031 | L27: 2032 | M27: 2033 | N27: 2034 | O27: 2035 | P27: 2036 | Q27: 2037 | R27: 2038 | S27: 2039 | T27: 2040 | U27: 2041 | V27: 2042 | W27: 2043 | X27: 2044 | Y27: 2045 | Z27: 2046 | AA27: 2047 | AB27: 2048 | AC27: 2049 | AD27: 2050 | AE27: 2051 | AF27: 2052 | AG27: 2053 | AH27: 2054 | AI27: 2055 | AJ27: 2056 | AK27: 2057 | AL27: 2058 | AM27: 2059 | AN27: 2060 | AO27: 2061 | AP27: 2062 | AQ27: 2063 | AR27: 2064 | AS27: 2065 | AT27: 2066 | AU27: 2067 | AV27: 2068 | AW27: 2069 | AX27: 2070
B28: 当年折旧月份数（无形资产） | C28: =SUMIF($C$24:$V$24,C27,$C$26:$V$26) -> 0 | D28: =SUMIF($C$24:$V$24,D27,$C$26:$V$26) -> 0 | E28: =SUMIF($C$24:$V$24,E27,$C$26:$V$26) -> 0 | F28: =SUMIF($C$24:$V$24,F27,$C$26:$V$26) -> 0 | G28: =SUMIF($C$24:$V$24,G27,$C$26:$V$26) -> 0 | H28: =SUMIF($C$24:$V$24,H27,$C$26:$V$26) -> 0 | I28: =SUMIF($C$24:$V$24,I27,$C$26:$V$26) -> 11 | J28: =SUMIF($C$24:$V$24,J27,$C$26:$V$26) -> 12 | ... AX28: =SUMIF($C$24:$V$24,AX27,$C$26:$V$26) -> 0
B29: 首批投产（储能资产）折旧开始-结束时点 | C29: =参数输入表!$D$36 -> 47150 | D29: =参数输入表!$D$36+参数输入表!$I$627*365+INT(参数输入表!$I$627/4) -> 51533
B30: （储能资产）折旧摊销时间序列 | C30: =YEAR(C31) -> 2029 | D30: =YEAR(D31) -> 2029 | E30: =YEAR(E31) -> 2030 | F30: =YEAR(F31) -> 2031 | G30: =YEAR(G31) -> 2032 | H30: =YEAR(H31) -> 2033 | I30: =YEAR(I31) -> 2034 | J30: =YEAR(J31) -> 2035 | ... P30: =YEAR(P31) -> 2041
C31: =C29 -> 47150 | D31: 47483 | E31: 47848 | F31: 48213 | G31: 48579 | H31: 48944 | I31: 49309 | J31: 49674 | K31: 50040 | L31: 50405 | M31: 50770 | N31: 51135 | O31: 51501 | P31: =D29 -> 51533
B32: =SUM(C32:AX32) -> 144 | C32: 0 | D32: =ROUND((DATEDIF(C31,D31,"d"))/30,0) -> 11 | E32: =ROUND((DATEDIF(D31,E31,"d"))/30,0) -> 12 | F32: =ROUND((DATEDIF(E31,F31,"d"))/30,0) -> 12 | G32: =ROUND((DATEDIF(F31,G31,"d"))/30,0) -> 12 | H32: =ROUND((DATEDIF(G31,H31,"d"))/30,0) -> 12 | I32: =ROUND((DATEDIF(H31,I31,"d"))/30,0) -> 12 | J32: =ROUND((DATEDIF(I31,J31,"d"))/30,0) -> 12 | K32: =ROUND((DATEDIF(J31,K31,"d"))/30,0) -> 12 | ... P32: =ROUND((DATEDIF(O31,P31,"d"))/30,0) -> 1
B33: 时间序列（年） | C33: 2023 | D33: 2024 | E33: 2025 | F33: 2026 | G33: 2027 | H33: 2028 | I33: 2029 | J33: 2030 | K33: 2031 | L33: 2032 | M33: 2033 | N33: 2034 | O33: 2035 | P33: 2036 | Q33: 2037 | R33: 2038 | S33: 2039 | T33: 2040 | U33: 2041 | V33: 2042 | W33: 2043 | X33: 2044 | Y33: 2045 | Z33: 2046 | AA33: 2047 | AB33: 2048 | AC33: 2049 | AD33: 2050 | AE33: 2051 | AF33: 2052 | AG33: 2053 | AH33: 2054 | AI33: 2055 | AJ33: 2056 | AK33: 2057 | AL33: 2058 | AM33: 2059 | AN33: 2060 | AO33: 2061 | AP33: 2062 | AQ33: 2063 | AR33: 2064 | AS33: 2065 | AT33: 2066 | AU33: 2067 | AV33: 2068 | AW33: 2069 | AX33: 2070
B34: 当年折旧月份数（储能资产） | C34: =SUMIF($C$30:$P$30,C33,$C$32:$P$32) -> 0 | D34: =SUMIF($C$30:$P$30,D33,$C$32:$P$32) -> 0 | E34: =SUMIF($C$30:$P$30,E33,$C$32:$P$32) -> 0 | F34: =SUMIF($C$30:$P$30,F33,$C$32:$P$32) -> 0 | G34: =SUMIF($C$30:$P$30,G33,$C$32:$P$32) -> 0 | H34: =SUMIF($C$30:$P$30,H33,$C$32:$P$32) -> 0 | I34: =SUMIF($C$30:$P$30,I33,$C$32:$P$32) -> 11 | J34: =SUMIF($C$30:$P$30,J33,$C$32:$P$32) -> 12 | ... AX34: =SUMIF($C$30:$P$30,AX33,$C$32:$P$32) -> 0
B35: 首批投产（固定资产3）折旧开始-结束时点 | C35: =参数输入表!$D$36 -> 47150 | D35: =参数输入表!$D$36+参数输入表!$I$632*365+INT(参数输入表!$I$632/4) -> 54455
B36: （固定资产3）折旧摊销时间序列 | C36: =YEAR(C37) -> 2029 | D36: =YEAR(D37) -> 2029 | E36: =YEAR(E37) -> 2030 | F36: =YEAR(F37) -> 2031 | G36: =YEAR(G37) -> 2032 | H36: =YEAR(H37) -> 2033 | I36: =YEAR(I37) -> 2034 | J36: =YEAR(J37) -> 2035 | ... X36: =YEAR(X37) -> 2049
C37: =C35 -> 47150 | D37: 47483 | E37: 47848 | F37: 48213 | G37: 48579 | H37: 48944 | I37: 49309 | J37: 49674 | K37: 50040 | L37: 50405 | M37: 50770 | N37: 51135 | O37: 51501 | P37: 51866 | Q37: 52231 | R37: 52596 | S37: 52962 | T37: 53327 | U37: 53692 | V37: 54057 | W37: 54423 | X37: =D35 -> 54455
B38: =SUM(C38:AX38) -> 240 | C38: 0 | D38: =ROUND((DATEDIF(C37,D37,"d"))/30,0) -> 11 | E38: =ROUND((DATEDIF(D37,E37,"d"))/30,0) -> 12 | F38: =ROUND((DATEDIF(E37,F37,"d"))/30,0) -> 12 | G38: =ROUND((DATEDIF(F37,G37,"d"))/30,0) -> 12 | H38: =ROUND((DATEDIF(G37,H37,"d"))/30,0) -> 12 | I38: =ROUND((DATEDIF(H37,I37,"d"))/30,0) -> 12 | J38: =ROUND((DATEDIF(I37,J37,"d"))/30,0) -> 12 | K38: =ROUND((DATEDIF(J37,K37,"d"))/30,0) -> 12 | ... X38: =ROUND((DATEDIF(W37,X37,"d"))/30,0) -> 1
B39: 时间序列（年） | C39: 2023 | D39: 2024 | E39: 2025 | F39: 2026 | G39: 2027 | H39: 2028 | I39: 2029 | J39: 2030 | K39: 2031 | L39: 2032 | M39: 2033 | N39: 2034 | O39: 2035 | P39: 2036 | Q39: 2037 | R39: 2038 | S39: 2039 | T39: 2040 | U39: 2041 | V39: 2042 | W39: 2043 | X39: 2044 | Y39: 2045 | Z39: 2046 | AA39: 2047 | AB39: 2048 | AC39: 2049 | AD39: 2050 | AE39: 2051 | AF39: 2052 | AG39: 2053 | AH39: 2054 | AI39: 2055 | AJ39: 2056 | AK39: 2057 | AL39: 2058 | AM39: 2059 | AN39: 2060 | AO39: 2061 | AP39: 2062 | AQ39: 2063 | AR39: 2064 | AS39: 2065 | AT39: 2066 | AU39: 2067 | AV39: 2068 | AW39: 2069 | AX39: 2070
B40: 当年折旧月份数（固定资产3） | C40: =SUMIF($C$36:$X$36,C39,$C$38:$X$38) -> 0 | D40: =SUMIF($C$36:$X$36,D39,$C$38:$X$38) -> 0 | E40: =SUMIF($C$36:$X$36,E39,$C$38:$X$38) -> 0 | F40: =SUMIF($C$36:$X$36,F39,$C$38:$X$38) -> 0 | G40: =SUMIF($C$36:$X$36,G39,$C$38:$X$38) -> 0 | H40: =SUMIF($C$36:$X$36,H39,$C$38:$X$38) -> 0 | I40: =SUMIF($C$36:$X$36,I39,$C$38:$X$38) -> 11 | J40: =SUMIF($C$36:$X$36,J39,$C$38:$X$38) -> 12 | ... AX40: =SUMIF($C$36:$X$36,AX39,$C$38:$X$38) -> 0
B41: Check固定资产 | C41: =B20-参数输入表!$I$622*12=0 -> TRUE | D41: =SUM(C22:AX22)-B20=0 -> TRUE
B42: Check无形资产 | C42: =B26-参数输入表!$I$638*12=0 -> TRUE | D42: =SUM(C28:AX28)-B26=0 -> TRUE
B43: Check（储能资产） | C43: =B32-参数输入表!$I$627*12=0 -> TRUE | D43: =SUM(C34:AX34)-B32=0 -> TRUE
B44: Check（固定资产3） | C44: =B38-参数输入表!$I$632*12=0 -> TRUE | D44: =SUM(C40:AX40)-B38=0 -> TRUE
B45: 第二批投产固定资产折旧开始-结束时点 | C45: =参数输入表!$D$37 -> 47362 | D45: =参数输入表!$D$37+参数输入表!$I$622*365+INT(参数输入表!$I$622/4) -> 57954
B46: 固定资产折旧摊销时间序列 | C46: =YEAR(C47) -> 2029 | D46: =YEAR(D47) -> 2029 | E46: =YEAR(E47) -> 2030 | F46: =YEAR(F47) -> 2031 | G46: =YEAR(G47) -> 2032 | H46: =YEAR(H47) -> 2033 | I46: =YEAR(I47) -> 2034 | J46: =YEAR(J47) -> 2035 | ... AG46: =YEAR(AG47) -> 2058
C47: =C45 -> 47362 | D47: 47483 | E47: 47848 | F47: 48213 | G47: 48579 | H47: 48944 | I47: 49309 | J47: 49674 | K47: 50040 | L47: 50405 | M47: 50770 | N47: 51135 | O47: 51501 | P47: 51866 | Q47: 52231 | R47: 52596 | S47: 52962 | T47: 53327 | U47: 53692 | V47: 54057 | W47: 54423 | X47: 54788 | Y47: 55153 | Z47: 55518 | AA47: 55884 | AB47: 56249 | AC47: 56614 | AD47: 56979 | AE47: 57345 | AF47: 57710 | AG47: =D45 -> 57954
B48: =SUM(C48:AX48) -> 348 | C48: 0 | D48: =ROUND((DATEDIF(C47,D47,"d"))/30,0) -> 4 | E48: =ROUND((DATEDIF(D47,E47,"d"))/30,0) -> 12 | F48: =ROUND((DATEDIF(E47,F47,"d"))/30,0) -> 12 | G48: =ROUND((DATEDIF(F47,G47,"d"))/30,0) -> 12 | H48: =ROUND((DATEDIF(G47,H47,"d"))/30,0) -> 12 | I48: =ROUND((DATEDIF(H47,I47,"d"))/30,0) -> 12 | J48: =ROUND((DATEDIF(I47,J47,"d"))/30,0) -> 12 | K48: =ROUND((DATEDIF(J47,K47,"d"))/30,0) -> 12 | ... AG48: =ROUND((DATEDIF(AF47,AG47,"d"))/30,0) -> 8
B49: 时间序列（年） | C49: 2023 | D49: 2024 | E49: 2025 | F49: 2026 | G49: 2027 | H49: 2028 | I49: 2029 | J49: 2030 | K49: 2031 | L49: 2032 | M49: 2033 | N49: 2034 | O49: 2035 | P49: 2036 | Q49: 2037 | R49: 2038 | S49: 2039 | T49: 2040 | U49: 2041 | V49: 2042 | W49: 2043 | X49: 2044 | Y49: 2045 | Z49: 2046 | AA49: 2047 | AB49: 2048 | AC49: 2049 | AD49: 2050 | AE49: 2051 | AF49: 2052 | AG49: 2053 | AH49: 2054 | AI49: 2055 | AJ49: 2056 | AK49: 2057 | AL49: 2058 | AM49: 2059 | AN49: 2060 | AO49: 2061 | AP49: 2062 | AQ49: 2063 | AR49: 2064 | AS49: 2065 | AT49: 2066 | AU49: 2067 | AV49: 2068 | AW49: 2069 | AX49: 2070
B50: 当年折旧月份数（固定资产） | C50: =SUMIF($C$46:$AG$46,C49,$C$48:$AG$48) -> 0 | D50: =SUMIF($C$46:$AG$46,D49,$C$48:$AG$48) -> 0 | E50: =SUMIF($C$46:$AG$46,E49,$C$48:$AG$48) -> 0 | F50: =SUMIF($C$46:$AG$46,F49,$C$48:$AG$48) -> 0 | G50: =SUMIF($C$46:$AG$46,G49,$C$48:$AG$48) -> 0 | H50: =SUMIF($C$46:$AG$46,H49,$C$48:$AG$48) -> 0 | I50: =SUMIF($C$46:$AG$46,I49,$C$48:$AG$48) -> 4 | J50: =SUMIF($C$46:$AG$46,J49,$C$48:$AG$48) -> 12 | ... AX50: =SUMIF($C$46:$AG$46,AX49,$C$48:$AG$48) -> 0
B51: 第二批投产设备设施无形资产折旧开始-结束时点 | C51: =参数输入表!$D$37 -> 47362 | D51: =参数输入表!$D$37+参数输入表!$I$638*365+INT(参数输入表!$I$638/4) -> 53936
B52: 无形资产折旧摊销时间序列 | C52: =YEAR(C53) -> 2029 | D52: =YEAR(D53) -> 2029 | E52: =YEAR(E53) -> 2030 | F52: =YEAR(F53) -> 2031 | G52: =YEAR(G53) -> 2032 | H52: =YEAR(H53) -> 2033 | I52: =YEAR(I53) -> 2034 | J52: =YEAR(J53) -> 2035 | ... V52: =YEAR(V53) -> 2047
C53: =C51 -> 47362 | D53: 47483 | E53: 47848 | F53: 48213 | G53: 48579 | H53: 48944 | I53: 49309 | J53: 49674 | K53: 50040 | L53: 50405 | M53: 50770 | N53: 51135 | O53: 51501 | P53: 51866 | Q53: 52231 | R53: 52596 | S53: 52962 | T53: 53327 | U53: 53692 | V53: =D51 -> 53936
B54: =SUM(C54:AX54) -> 216 | C54: 0 | D54: =ROUND((DATEDIF(C53,D53,"d"))/30,0) -> 4 | E54: =ROUND((DATEDIF(D53,E53,"d"))/30,0) -> 12 | F54: =ROUND((DATEDIF(E53,F53,"d"))/30,0) -> 12 | G54: =ROUND((DATEDIF(F53,G53,"d"))/30,0) -> 12 | H54: =ROUND((DATEDIF(G53,H53,"d"))/30,0) -> 12 | I54: =ROUND((DATEDIF(H53,I53,"d"))/30,0) -> 12 | J54: =ROUND((DATEDIF(I53,J53,"d"))/30,0) -> 12 | K54: =ROUND((DATEDIF(J53,K53,"d"))/30,0) -> 12 | ... V54: =ROUND((DATEDIF(U53,V53,"d"))/30,0) -> 8
B55: 时间序列（年） | C55: 2023 | D55: 2024 | E55: 2025 | F55: 2026 | G55: 2027 | H55: 2028 | I55: 2029 | J55: 2030 | K55: 2031 | L55: 2032 | M55: 2033 | N55: 2034 | O55: 2035 | P55: 2036 | Q55: 2037 | R55: 2038 | S55: 2039 | T55: 2040 | U55: 2041 | V55: 2042 | W55: 2043 | X55: 2044 | Y55: 2045 | Z55: 2046 | AA55: 2047 | AB55: 2048 | AC55: 2049 | AD55: 2050 | AE55: 2051 | AF55: 2052 | AG55: 2053 | AH55: 2054 | AI55: 2055 | AJ55: 2056 | AK55: 2057 | AL55: 2058 | AM55: 2059 | AN55: 2060 | AO55: 2061 | AP55: 2062 | AQ55: 2063 | AR55: 2064 | AS55: 2065 | AT55: 2066 | AU55: 2067 | AV55: 2068 | AW55: 2069 | AX55: 2070
B56: 当年折旧月份数（无形资产） | C56: =SUMIF($C$52:$V$52,C55,$C$54:$V$54) -> 0 | D56: =SUMIF($C$52:$V$52,D55,$C$54:$V$54) -> 0 | E56: =SUMIF($C$52:$V$52,E55,$C$54:$V$54) -> 0 | F56: =SUMIF($C$52:$V$52,F55,$C$54:$V$54) -> 0 | G56: =SUMIF($C$52:$V$52,G55,$C$54:$V$54) -> 0 | H56: =SUMIF($C$52:$V$52,H55,$C$54:$V$54) -> 0 | I56: =SUMIF($C$52:$V$52,I55,$C$54:$V$54) -> 4 | J56: =SUMIF($C$52:$V$52,J55,$C$54:$V$54) -> 12 | ... AX56: =SUMIF($C$52:$V$52,AX55,$C$54:$V$54) -> 0
B57: 第二批投产（储能资产）折旧开始-结束时点 | C57: =参数输入表!$D$37 -> 47362 | D57: =参数输入表!$D$37+参数输入表!$I$627*365+INT(参数输入表!$I$627/4) -> 51745
B58: （储能资产）折旧摊销时间序列 | C58: =YEAR(C59) -> 2029 | D58: =YEAR(D59) -> 2029 | E58: =YEAR(E59) -> 2030 | F58: =YEAR(F59) -> 2031 | G58: =YEAR(G59) -> 2032 | H58: =YEAR(H59) -> 2033 | I58: =YEAR(I59) -> 2034 | J58: =YEAR(J59) -> 2035 | ... P58: =YEAR(P59) -> 2041
C59: =C57 -> 47362 | D59: 47483 | E59: 47848 | F59: 48213 | G59: 48579 | H59: 48944 | I59: 49309 | J59: 49674 | K59: 50040 | L59: 50405 | M59: 50770 | N59: 51135 | O59: 51501 | P59: =D57 -> 51745
B60: =SUM(C60:AX60) -> 144 | C60: 0 | D60: =ROUND((DATEDIF(C59,D59,"d"))/30,0) -> 4 | E60: =ROUND((DATEDIF(D59,E59,"d"))/30,0) -> 12 | F60: =ROUND((DATEDIF(E59,F59,"d"))/30,0) -> 12 | G60: =ROUND((DATEDIF(F59,G59,"d"))/30,0) -> 12 | H60: =ROUND((DATEDIF(G59,H59,"d"))/30,0) -> 12 | I60: =ROUND((DATEDIF(H59,I59,"d"))/30,0) -> 12 | J60: =ROUND((DATEDIF(I59,J59,"d"))/30,0) -> 12 | K60: =ROUND((DATEDIF(J59,K59,"d"))/30,0) -> 12 | ... P60: =ROUND((DATEDIF(O59,P59,"d"))/30,0) -> 8
B61: 时间序列（年） | C61: 2023 | D61: 2024 | E61: 2025 | F61: 2026 | G61: 2027 | H61: 2028 | I61: 2029 | J61: 2030 | K61: 2031 | L61: 2032 | M61: 2033 | N61: 2034 | O61: 2035 | P61: 2036 | Q61: 2037 | R61: 2038 | S61: 2039 | T61: 2040 | U61: 2041 | V61: 2042 | W61: 2043 | X61: 2044 | Y61: 2045 | Z61: 2046 | AA61: 2047 | AB61: 2048 | AC61: 2049 | AD61: 2050 | AE61: 2051 | AF61: 2052 | AG61: 2053 | AH61: 2054 | AI61: 2055 | AJ61: 2056 | AK61: 2057 | AL61: 2058 | AM61: 2059 | AN61: 2060 | AO61: 2061 | AP61: 2062 | AQ61: 2063 | AR61: 2064 | AS61: 2065 | AT61: 2066 | AU61: 2067 | AV61: 2068 | AW61: 2069 | AX61: 2070
B62: 当年折旧月份数（储能资产） | C62: =SUMIF($C$58:$P$58,C61,$C$60:$P$60) -> 0 | D62: =SUMIF($C$58:$P$58,D61,$C$60:$P$60) -> 0 | E62: =SUMIF($C$58:$P$58,E61,$C$60:$P$60) -> 0 | F62: =SUMIF($C$58:$P$58,F61,$C$60:$P$60) -> 0 | G62: =SUMIF($C$58:$P$58,G61,$C$60:$P$60) -> 0 | H62: =SUMIF($C$58:$P$58,H61,$C$60:$P$60) -> 0 | I62: =SUMIF($C$58:$P$58,I61,$C$60:$P$60) -> 4 | J62: =SUMIF($C$58:$P$58,J61,$C$60:$P$60) -> 12 | ... AX62: =SUMIF($C$58:$P$58,AX61,$C$60:$P$60) -> 0
B63: 第二批投产（固定资产3）折旧开始-结束时点 | C63: =参数输入表!$D$37 -> 47362 | D63: =参数输入表!$D$37+参数输入表!$I$632*365+INT(参数输入表!$I$632/4) -> 54667
B64: （固定资产3）折旧摊销时间序列 | C64: =YEAR(C65) -> 2029 | D64: =YEAR(D65) -> 2029 | E64: =YEAR(E65) -> 2030 | F64: =YEAR(F65) -> 2031 | G64: =YEAR(G65) -> 2032 | H64: =YEAR(H65) -> 2033 | I64: =YEAR(I65) -> 2034 | J64: =YEAR(J65) -> 2035 | ... X64: =YEAR(X65) -> 2049
C65: =C63 -> 47362 | D65: 47483 | E65: 47848 | F65: 48213 | G65: 48579 | H65: 48944 | I65: 49309 | J65: 49674 | K65: 50040 | L65: 50405 | M65: 50770 | N65: 51135 | O65: 51501 | P65: 51866 | Q65: 52231 | R65: 52596 | S65: 52962 | T65: 53327 | U65: 53692 | V65: 54057 | W65: 54423 | X65: =D63 -> 54667
B66: =SUM(C66:AX66) -> 240 | C66: 0 | D66: =ROUND((DATEDIF(C65,D65,"d"))/30,0) -> 4 | E66: =ROUND((DATEDIF(D65,E65,"d"))/30,0) -> 12 | F66: =ROUND((DATEDIF(E65,F65,"d"))/30,0) -> 12 | G66: =ROUND((DATEDIF(F65,G65,"d"))/30,0) -> 12 | H66: =ROUND((DATEDIF(G65,H65,"d"))/30,0) -> 12 | I66: =ROUND((DATEDIF(H65,I65,"d"))/30,0) -> 12 | J66: =ROUND((DATEDIF(I65,J65,"d"))/30,0) -> 12 | K66: =ROUND((DATEDIF(J65,K65,"d"))/30,0) -> 12 | ... X66: =ROUND((DATEDIF(W65,X65,"d"))/30,0) -> 8
B67: 时间序列（年） | C67: 2023 | D67: 2024 | E67: 2025 | F67: 2026 | G67: 2027 | H67: 2028 | I67: 2029 | J67: 2030 | K67: 2031 | L67: 2032 | M67: 2033 | N67: 2034 | O67: 2035 | P67: 2036 | Q67: 2037 | R67: 2038 | S67: 2039 | T67: 2040 | U67: 2041 | V67: 2042 | W67: 2043 | X67: 2044 | Y67: 2045 | Z67: 2046 | AA67: 2047 | AB67: 2048 | AC67: 2049 | AD67: 2050 | AE67: 2051 | AF67: 2052 | AG67: 2053 | AH67: 2054 | AI67: 2055 | AJ67: 2056 | AK67: 2057 | AL67: 2058 | AM67: 2059 | AN67: 2060 | AO67: 2061 | AP67: 2062 | AQ67: 2063 | AR67: 2064 | AS67: 2065 | AT67: 2066 | AU67: 2067 | AV67: 2068 | AW67: 2069 | AX67: 2070
B68: 当年折旧月份数（固定资产3） | C68: =SUMIF($C$64:$X$64,C67,$C$66:$X$66) -> 0 | D68: =SUMIF($C$64:$X$64,D67,$C$66:$X$66) -> 0 | E68: =SUMIF($C$64:$X$64,E67,$C$66:$X$66) -> 0 | F68: =SUMIF($C$64:$X$64,F67,$C$66:$X$66) -> 0 | G68: =SUMIF($C$64:$X$64,G67,$C$66:$X$66) -> 0 | H68: =SUMIF($C$64:$X$64,H67,$C$66:$X$66) -> 0 | I68: =SUMIF($C$64:$X$64,I67,$C$66:$X$66) -> 4 | J68: =SUMIF($C$64:$X$64,J67,$C$66:$X$66) -> 12 | ... AX68: =SUMIF($C$64:$X$64,AX67,$C$66:$X$66) -> 0
B69: Check固定资产 | C69: =B48-参数输入表!$I$622*12=0 -> TRUE | D69: =SUM(C50:AX50)-B48=0 -> TRUE
B70: Check无形资产 | C70: =B54-参数输入表!$I$638*12=0 -> TRUE | D70: =SUM(C56:AX56)-B54=0 -> TRUE
B71: Check（储能资产） | C71: =B60-参数输入表!$I$627*12=0 -> TRUE | D71: =SUM(C62:AX62)-B60=0 -> TRUE
B72: Check（固定资产3） | C72: =B66-参数输入表!$I$632*12=0 -> TRUE | D72: =SUM(C68:AX68)-B66=0 -> TRUE
B73: 第三批投产固定资产折旧开始-结束时点 | C73: =参数输入表!$D$38 -> 47543 | D73: =参数输入表!$D$38+参数输入表!$I$622*365+INT(参数输入表!$I$622/4) -> 58135
B74: 固定资产折旧摊销时间序列 | C74: =YEAR(C75) -> 2030 | D74: =YEAR(D75) -> 2030 | E74: =YEAR(E75) -> 2031 | F74: =YEAR(F75) -> 2032 | G74: =YEAR(G75) -> 2033 | H74: =YEAR(H75) -> 2034 | I74: =YEAR(I75) -> 2035 | J74: =YEAR(J75) -> 2036 | ... AG74: =YEAR(AG75) -> 2059
C75: =C73 -> 47543 | D75: 47848 | E75: 48213 | F75: 48579 | G75: 48944 | H75: 49309 | I75: 49674 | J75: 50040 | K75: 50405 | L75: 50770 | M75: 51135 | N75: 51501 | O75: 51866 | P75: 52231 | Q75: 52596 | R75: 52962 | S75: 53327 | T75: 53692 | U75: 54057 | V75: 54423 | W75: 54788 | X75: 55153 | Y75: 55518 | Z75: 55884 | AA75: 56249 | AB75: 56614 | AC75: 56979 | AD75: 57345 | AE75: 57710 | AF75: 58075 | AG75: =D73 -> 58135
B76: =SUM(C76:AX76) -> 348 | C76: 0 | D76: =ROUND((DATEDIF(C75,D75,"d"))/30,0) -> 10 | E76: =ROUND((DATEDIF(D75,E75,"d"))/30,0) -> 12 | F76: =ROUND((DATEDIF(E75,F75,"d"))/30,0) -> 12 | G76: =ROUND((DATEDIF(F75,G75,"d"))/30,0) -> 12 | H76: =ROUND((DATEDIF(G75,H75,"d"))/30,0) -> 12 | I76: =ROUND((DATEDIF(H75,I75,"d"))/30,0) -> 12 | J76: =ROUND((DATEDIF(I75,J75,"d"))/30,0) -> 12 | K76: =ROUND((DATEDIF(J75,K75,"d"))/30,0) -> 12 | ... AG76: =ROUND((DATEDIF(AF75,AG75,"d"))/30,0) -> 2
B77: 时间序列（年） | C77: 2023 | D77: 2024 | E77: 2025 | F77: 2026 | G77: 2027 | H77: 2028 | I77: 2029 | J77: 2030 | K77: 2031 | L77: 2032 | M77: 2033 | N77: 2034 | O77: 2035 | P77: 2036 | Q77: 2037 | R77: 2038 | S77: 2039 | T77: 2040 | U77: 2041 | V77: 2042 | W77: 2043 | X77: 2044 | Y77: 2045 | Z77: 2046 | AA77: 2047 | AB77: 2048 | AC77: 2049 | AD77: 2050 | AE77: 2051 | AF77: 2052 | AG77: 2053 | AH77: 2054 | AI77: 2055 | AJ77: 2056 | AK77: 2057 | AL77: 2058 | AM77: 2059 | AN77: 2060 | AO77: 2061 | AP77: 2062 | AQ77: 2063 | AR77: 2064 | AS77: 2065 | AT77: 2066 | AU77: 2067 | AV77: 2068 | AW77: 2069 | AX77: 2070
B78: 当年折旧月份数（固定资产） | C78: =SUMIF($C$74:$AG$74,C77,$C$76:$AG$76) -> 0 | D78: =SUMIF($C$74:$AG$74,D77,$C$76:$AG$76) -> 0 | E78: =SUMIF($C$74:$AG$74,E77,$C$76:$AG$76) -> 0 | F78: =SUMIF($C$74:$AG$74,F77,$C$76:$AG$76) -> 0 | G78: =SUMIF($C$74:$AG$74,G77,$C$76:$AG$76) -> 0 | H78: =SUMIF($C$74:$AG$74,H77,$C$76:$AG$76) -> 0 | I78: =SUMIF($C$74:$AG$74,I77,$C$76:$AG$76) -> 0 | J78: =SUMIF($C$74:$AG$74,J77,$C$76:$AG$76) -> 10 | ... AX78: =SUMIF($C$74:$AG$74,AX77,$C$76:$AG$76) -> 0
B79: 第三批投产设备设施无形资产折旧开始-结束时点 | C79: =参数输入表!$D$38 -> 47543 | D79: =参数输入表!$D$38+参数输入表!$I$638*365+INT(参数输入表!$I$638/4) -> 54117
B80: 无形资产折旧摊销时间序列 | C80: =YEAR(C81) -> 2030 | D80: =YEAR(D81) -> 2030 | E80: =YEAR(E81) -> 2031 | F80: =YEAR(F81) -> 2032 | G80: =YEAR(G81) -> 2033 | H80: =YEAR(H81) -> 2034 | I80: =YEAR(I81) -> 2035 | J80: =YEAR(J81) -> 2036 | ... V80: =YEAR(V81) -> 2048
C81: =C79 -> 47543 | D81: 47848 | E81: 48213 | F81: 48579 | G81: 48944 | H81: 49309 | I81: 49674 | J81: 50040 | K81: 50405 | L81: 50770 | M81: 51135 | N81: 51501 | O81: 51866 | P81: 52231 | Q81: 52596 | R81: 52962 | S81: 53327 | T81: 53692 | U81: 54057 | V81: =D79 -> 54117
B82: =SUM(C82:AX82) -> 216 | C82: 0 | D82: =ROUND((DATEDIF(C81,D81,"d"))/30,0) -> 10 | E82: =ROUND((DATEDIF(D81,E81,"d"))/30,0) -> 12 | F82: =ROUND((DATEDIF(E81,F81,"d"))/30,0) -> 12 | G82: =ROUND((DATEDIF(F81,G81,"d"))/30,0) -> 12 | H82: =ROUND((DATEDIF(G81,H81,"d"))/30,0) -> 12 | I82: =ROUND((DATEDIF(H81,I81,"d"))/30,0) -> 12 | J82: =ROUND((DATEDIF(I81,J81,"d"))/30,0) -> 12 | K82: =ROUND((DATEDIF(J81,K81,"d"))/30,0) -> 12 | ... V82: =ROUND((DATEDIF(U81,V81,"d"))/30,0) -> 2
B83: 时间序列（年） | C83: 2023 | D83: 2024 | E83: 2025 | F83: 2026 | G83: 2027 | H83: 2028 | I83: 2029 | J83: 2030 | K83: 2031 | L83: 2032 | M83: 2033 | N83: 2034 | O83: 2035 | P83: 2036 | Q83: 2037 | R83: 2038 | S83: 2039 | T83: 2040 | U83: 2041 | V83: 2042 | W83: 2043 | X83: 2044 | Y83: 2045 | Z83: 2046 | AA83: 2047 | AB83: 2048 | AC83: 2049 | AD83: 2050 | AE83: 2051 | AF83: 2052 | AG83: 2053 | AH83: 2054 | AI83: 2055 | AJ83: 2056 | AK83: 2057 | AL83: 2058 | AM83: 2059 | AN83: 2060 | AO83: 2061 | AP83: 2062 | AQ83: 2063 | AR83: 2064 | AS83: 2065 | AT83: 2066 | AU83: 2067 | AV83: 2068 | AW83: 2069 | AX83: 2070
B84: 当年折旧月份数（无形资产） | C84: =SUMIF($C$80:$V$80,C83,$C$82:$V$82) -> 0 | D84: =SUMIF($C$80:$V$80,D83,$C$82:$V$82) -> 0 | E84: =SUMIF($C$80:$V$80,E83,$C$82:$V$82) -> 0 | F84: =SUMIF($C$80:$V$80,F83,$C$82:$V$82) -> 0 | G84: =SUMIF($C$80:$V$80,G83,$C$82:$V$82) -> 0 | H84: =SUMIF($C$80:$V$80,H83,$C$82:$V$82) -> 0 | I84: =SUMIF($C$80:$V$80,I83,$C$82:$V$82) -> 0 | J84: =SUMIF($C$80:$V$80,J83,$C$82:$V$82) -> 10 | ... AX84: =SUMIF($C$80:$V$80,AX83,$C$82:$V$82) -> 0
B85: 第三批投产（储能资产）折旧开始-结束时点 | C85: =参数输入表!$D$38 -> 47543 | D85: =参数输入表!$D$38+参数输入表!$I$627*365+INT(参数输入表!$I$627/4) -> 51926
B86: （储能资产）折旧摊销时间序列 | C86: =YEAR(C87) -> 2030 | D86: =YEAR(D87) -> 2030 | E86: =YEAR(E87) -> 2031 | F86: =YEAR(F87) -> 2032 | G86: =YEAR(G87) -> 2033 | H86: =YEAR(H87) -> 2034 | I86: =YEAR(I87) -> 2035 | J86: =YEAR(J87) -> 2036 | ... P86: =YEAR(P87) -> 2042
C87: =C85 -> 47543 | D87: 47848 | E87: 48213 | F87: 48579 | G87: 48944 | H87: 49309 | I87: 49674 | J87: 50040 | K87: 50405 | L87: 50770 | M87: 51135 | N87: 51501 | O87: 51866 | P87: =D85 -> 51926
B88: =SUM(C88:AX88) -> 144 | C88: 0 | D88: =ROUND((DATEDIF(C87,D87,"d"))/30,0) -> 10 | E88: =ROUND((DATEDIF(D87,E87,"d"))/30,0) -> 12 | F88: =ROUND((DATEDIF(E87,F87,"d"))/30,0) -> 12 | G88: =ROUND((DATEDIF(F87,G87,"d"))/30,0) -> 12 | H88: =ROUND((DATEDIF(G87,H87,"d"))/30,0) -> 12 | I88: =ROUND((DATEDIF(H87,I87,"d"))/30,0) -> 12 | J88: =ROUND((DATEDIF(I87,J87,"d"))/30,0) -> 12 | K88: =ROUND((DATEDIF(J87,K87,"d"))/30,0) -> 12 | ... P88: =ROUND((DATEDIF(O87,P87,"d"))/30,0) -> 2
B89: 时间序列（年） | C89: 2023 | D89: 2024 | E89: 2025 | F89: 2026 | G89: 2027 | H89: 2028 | I89: 2029 | J89: 2030 | K89: 2031 | L89: 2032 | M89: 2033 | N89: 2034 | O89: 2035 | P89: 2036 | Q89: 2037 | R89: 2038 | S89: 2039 | T89: 2040 | U89: 2041 | V89: 2042 | W89: 2043 | X89: 2044 | Y89: 2045 | Z89: 2046 | AA89: 2047 | AB89: 2048 | AC89: 2049 | AD89: 2050 | AE89: 2051 | AF89: 2052 | AG89: 2053 | AH89: 2054 | AI89: 2055 | AJ89: 2056 | AK89: 2057 | AL89: 2058 | AM89: 2059 | AN89: 2060 | AO89: 2061 | AP89: 2062 | AQ89: 2063 | AR89: 2064 | AS89: 2065 | AT89: 2066 | AU89: 2067 | AV89: 2068 | AW89: 2069 | AX89: 2070
B90: 当年折旧月份数（储能资产） | C90: =SUMIF($C$86:$P$86,C89,$C$88:$P$88) -> 0 | D90: =SUMIF($C$86:$P$86,D89,$C$88:$P$88) -> 0 | E90: =SUMIF($C$86:$P$86,E89,$C$88:$P$88) -> 0 | F90: =SUMIF($C$86:$P$86,F89,$C$88:$P$88) -> 0 | G90: =SUMIF($C$86:$P$86,G89,$C$88:$P$88) -> 0 | H90: =SUMIF($C$86:$P$86,H89,$C$88:$P$88) -> 0 | I90: =SUMIF($C$86:$P$86,I89,$C$88:$P$88) -> 0 | J90: =SUMIF($C$86:$P$86,J89,$C$88:$P$88) -> 10 | ... AX90: =SUMIF($C$86:$P$86,AX89,$C$88:$P$88) -> 0
B91: 第三批投产（固定资产3）折旧开始-结束时点 | C91: =参数输入表!$D$38 -> 47543 | D91: =参数输入表!$D$38+参数输入表!$I$632*365+INT(参数输入表!$I$632/4) -> 54848
B92: （固定资产3）折旧摊销时间序列 | C92: =YEAR(C93) -> 2030 | D92: =YEAR(D93) -> 2030 | E92: =YEAR(E93) -> 2031 | F92: =YEAR(F93) -> 2032 | G92: =YEAR(G93) -> 2033 | H92: =YEAR(H93) -> 2034 | I92: =YEAR(I93) -> 2035 | J92: =YEAR(J93) -> 2036 | ... X92: =YEAR(X93) -> 2050
C93: =C91 -> 47543 | D93: 47848 | E93: 48213 | F93: 48579 | G93: 48944 | H93: 49309 | I93: 49674 | J93: 50040 | K93: 50405 | L93: 50770 | M93: 51135 | N93: 51501 | O93: 51866 | P93: 52231 | Q93: 52596 | R93: 52962 | S93: 53327 | T93: 53692 | U93: 54057 | V93: 54423 | W93: 54788 | X93: =D91 -> 54848
B94: =SUM(C94:AX94) -> 240 | C94: 0 | D94: =ROUND((DATEDIF(C93,D93,"d"))/30,0) -> 10 | E94: =ROUND((DATEDIF(D93,E93,"d"))/30,0) -> 12 | F94: =ROUND((DATEDIF(E93,F93,"d"))/30,0) -> 12 | G94: =ROUND((DATEDIF(F93,G93,"d"))/30,0) -> 12 | H94: =ROUND((DATEDIF(G93,H93,"d"))/30,0) -> 12 | I94: =ROUND((DATEDIF(H93,I93,"d"))/30,0) -> 12 | J94: =ROUND((DATEDIF(I93,J93,"d"))/30,0) -> 12 | K94: =ROUND((DATEDIF(J93,K93,"d"))/30,0) -> 12 | ... X94: =ROUND((DATEDIF(W93,X93,"d"))/30,0) -> 2
B95: 时间序列（年） | C95: 2023 | D95: 2024 | E95: 2025 | F95: 2026 | G95: 2027 | H95: 2028 | I95: 2029 | J95: 2030 | K95: 2031 | L95: 2032 | M95: 2033 | N95: 2034 | O95: 2035 | P95: 2036 | Q95: 2037 | R95: 2038 | S95: 2039 | T95: 2040 | U95: 2041 | V95: 2042 | W95: 2043 | X95: 2044 | Y95: 2045 | Z95: 2046 | AA95: 2047 | AB95: 2048 | AC95: 2049 | AD95: 2050 | AE95: 2051 | AF95: 2052 | AG95: 2053 | AH95: 2054 | AI95: 2055 | AJ95: 2056 | AK95: 2057 | AL95: 2058 | AM95: 2059 | AN95: 2060 | AO95: 2061 | AP95: 2062 | AQ95: 2063 | AR95: 2064 | AS95: 2065 | AT95: 2066 | AU95: 2067 | AV95: 2068 | AW95: 2069 | AX95: 2070
B96: 当年折旧月份数（固定资产3） | C96: =SUMIF($C$92:$X$92,C95,$C$94:$X$94) -> 0 | D96: =SUMIF($C$92:$X$92,D95,$C$94:$X$94) -> 0 | E96: =SUMIF($C$92:$X$92,E95,$C$94:$X$94) -> 0 | F96: =SUMIF($C$92:$X$92,F95,$C$94:$X$94) -> 0 | G96: =SUMIF($C$92:$X$92,G95,$C$94:$X$94) -> 0 | H96: =SUMIF($C$92:$X$92,H95,$C$94:$X$94) -> 0 | I96: =SUMIF($C$92:$X$92,I95,$C$94:$X$94) -> 0 | J96: =SUMIF($C$92:$X$92,J95,$C$94:$X$94) -> 10 | ... AX96: =SUMIF($C$92:$X$92,AX95,$C$94:$X$94) -> 0
B97: Check固定资产 | C97: =B76-参数输入表!$I$622*12=0 -> TRUE | D97: =SUM(C78:AX78)-B76=0 -> TRUE
B98: Check无形资产 | C98: =B82-参数输入表!$I$638*12=0 -> TRUE | D98: =SUM(C84:AX84)-B82=0 -> TRUE
B99: Check（储能资产） | C99: =B88-参数输入表!$I$627*12=0 -> TRUE | D99: =SUM(C90:AX90)-B88=0 -> TRUE
B100: Check（固定资产3） | C100: =B94-参数输入表!$I$632*12=0 -> TRUE | D100: =SUM(C96:AX96)-B94=0 -> TRUE
B101: 完全投产固定资产折旧开始-结束时点 | C101: =参数输入表!$D$39 -> 47696 | D101: =参数输入表!$D$39+参数输入表!$I$622*365+INT(参数输入表!$I$622/4) -> 58288
B102: 固定资产折旧摊销时间序列 | C102: =YEAR(C103) -> 2030 | D102: =YEAR(D103) -> 2030 | E102: =YEAR(E103) -> 2031 | F102: =YEAR(F103) -> 2032 | G102: =YEAR(G103) -> 2033 | H102: =YEAR(H103) -> 2034 | I102: =YEAR(I103) -> 2035 | J102: =YEAR(J103) -> 2036 | ... AG102: =YEAR(AG103) -> 2059
C103: =C101 -> 47696 | D103: 47848 | E103: 48213 | F103: 48579 | G103: 48944 | H103: 49309 | I103: 49674 | J103: 50040 | K103: 50405 | L103: 50770 | M103: 51135 | N103: 51501 | O103: 51866 | P103: 52231 | Q103: 52596 | R103: 52962 | S103: 53327 | T103: 53692 | U103: 54057 | V103: 54423 | W103: 54788 | X103: 55153 | Y103: 55518 | Z103: 55884 | AA103: 56249 | AB103: 56614 | AC103: 56979 | AD103: 57345 | AE103: 57710 | AF103: 58075 | AG103: =D101 -> 58288
B104: =SUM(C104:AX104) -> 348 | C104: 0 | D104: =ROUND((DATEDIF(C103,D103,"d"))/30,0) -> 5 | E104: =ROUND((DATEDIF(D103,E103,"d"))/30,0) -> 12 | F104: =ROUND((DATEDIF(E103,F103,"d"))/30,0) -> 12 | G104: =ROUND((DATEDIF(F103,G103,"d"))/30,0) -> 12 | H104: =ROUND((DATEDIF(G103,H103,"d"))/30,0) -> 12 | I104: =ROUND((DATEDIF(H103,I103,"d"))/30,0) -> 12 | J104: =ROUND((DATEDIF(I103,J103,"d"))/30,0) -> 12 | K104: =ROUND((DATEDIF(J103,K103,"d"))/30,0) -> 12 | ... AG104: =ROUND((DATEDIF(AF103,AG103,"d"))/30,0) -> 7
...

Sheet 投产&达产比例
C2: 关键时间节点参数 （设备设施平均达产率） | G2: 关键时间节点参数 （设备设施累计投产比例）
C3: =参数输入表!I5 -> 44958 | D3: 0 | G3: =参数输入表!I5 -> 44958 | H3: 0
C4: =参数输入表!D42 -> 47150 | D4: =参数输入表!I42 -> 0 | F4: 首批投产 | G4: =参数输入表!D36 -> 47150 | H4: =H3+参数输入表!I36 -> 0
C5: =参数输入表!D43 -> 47362 | D5: =参数输入表!I43 -> 0 | F5: 第二批投产 | G5: =参数输入表!D37 -> 47362 | H5: =H4+参数输入表!I37 -> 0
C6: =参数输入表!D44 -> 47543 | D6: =参数输入表!I44 -> 0 | F6: 第三批投产 | G6: =参数输入表!D38 -> 47543 | H6: =H5+参数输入表!I38 -> 0
C7: =参数输入表!D45 -> 47696 | D7: =参数输入表!I45 -> 1 | F7: 完全投产 | G7: =参数输入表!D39 -> 47696 | H7: =H6+参数输入表!I39 -> 1
C9: 投产设施月平均达产率 | G9: 投产比例（生产） | K9: 投产比例（确认资产） | O9: 项目月达产率
B10: =YEAR(C10) -> 2023 | C10: 44985 | D10: =D3 -> 0 | F10: =YEAR(G10) -> 2023 | G10: 44985 | H10: =H3 -> 0 | J10: =YEAR(K10) -> 2023 | K10: =G3 -> 44958 | L10: =IF(K10=参数输入表!$I$7,100%,H10) -> 0 | N10: =YEAR(O10) -> 2023 | O10: 44985 | P10: =D10*H10 -> 0 | T10: 各年期末资产确认比例 | Y10: 年度达产率统计
B11: =YEAR(C11) -> 2023 | C11: 45016 | D11: =$D$10 -> 0 | F11: =YEAR(G11) -> 2023 | G11: 45016 | H11: =$H$10 -> 0 | J11: =YEAR(K11) -> 2023 | K11: 45016 | L11: =IF(K11=参数输入表!$I$7,100%,H11) -> 0 | N11: =YEAR(O11) -> 2023 | O11: 45016 | P11: =D11*H11 -> 0 | R11: 建设期第1年 | S11: 合作期第1年 | T11: 2023 | U11: =L20 -> 0 | W11: 建设期第1年 | X11: 合作期第1年 | Y11: 2023 | Z11: =SUMIF($N$10:$N$579,Y11,$P$10:$P$579)/12 -> 0
B12: =YEAR(C12) -> 2023 | C12: 45046 | D12: =$D$10 -> 0 | F12: =YEAR(G12) -> 2023 | G12: 45046 | H12: =$H$10 -> 0 | J12: =YEAR(K12) -> 2023 | K12: 45046 | L12: =IF(K12=参数输入表!$I$7,100%,H12) -> 0 | N12: =YEAR(O12) -> 2023 | O12: 45046 | P12: =D12*H12 -> 0 | R12: 建设期第2年 | S12: 合作期第2年 | T12: 2024 | U12: =L32 -> 0 | W12: 建设期第2年 | X12: 合作期第2年 | Y12: 2024 | Z12: =SUMIF($N$10:$N$579,Y12,$P$10:$P$579)/12 -> 0
B13: =YEAR(C13) -> 2023 | C13: 45077 | D13: =$D$10 -> 0 | F13: =YEAR(G13) -> 2023 | G13: 45077 | H13: =$H$10 -> 0 | J13: =YEAR(K13) -> 2023 | K13: 45077 | L13: =IF(K13=参数输入表!$I$7,100%,H13) -> 0 | N13: =YEAR(O13) -> 2023 | O13: 45077 | P13: =D13*H13 -> 0 | R13: 建设期第3年 | S13: 合作期第3年 | T13: 2025 | U13: =L44 -> 0 | W13: 建设期第3年 | X13: 合作期第3年 | Y13: 2025 | Z13: =SUMIF($N$10:$N$579,Y13,$P$10:$P$579)/12 -> 0
B14: =YEAR(C14) -> 2023 | C14: 45107 | D14: =$D$10 -> 0 | F14: =YEAR(G14) -> 2023 | G14: 45107 | H14: =$H$10 -> 0 | J14: =YEAR(K14) -> 2023 | K14: 45107 | L14: =IF(K14=参数输入表!$I$7,100%,H14) -> 0 | N14: =YEAR(O14) -> 2023 | O14: 45107 | P14: =D14*H14 -> 0 | R14: 建设期第4年 | S14: 合作期第4年 | T14: 2026 | U14: =L56 -> 0 | W14: 建设期第4年 | X14: 合作期第4年 | Y14: 2026 | Z14: =SUMIF($N$10:$N$579,Y14,$P$10:$P$579)/12 -> 0
B15: =YEAR(C15) -> 2023 | C15: 45138 | D15: =$D$10 -> 0 | F15: =YEAR(G15) -> 2023 | G15: 45138 | H15: =$H$10 -> 0 | J15: =YEAR(K15) -> 2023 | K15: 45138 | L15: =IF(K15=参数输入表!$I$7,100%,H15) -> 0 | N15: =YEAR(O15) -> 2023 | O15: 45138 | P15: =D15*H15 -> 0 | R15: 建设期第5年 | S15: 合作期第5年 | T15: 2027 | U15: =L68 -> 0 | W15: 建设期第5年 | X15: 合作期第5年 | Y15: 2027 | Z15: =SUMIF($N$10:$N$579,Y15,$P$10:$P$579)/12 -> 0
B16: =YEAR(C16) -> 2023 | C16: 45169 | D16: =$D$10 -> 0 | F16: =YEAR(G16) -> 2023 | G16: 45169 | H16: =$H$10 -> 0 | J16: =YEAR(K16) -> 2023 | K16: 45169 | L16: =IF(K16=参数输入表!$I$7,100%,H16) -> 0 | N16: =YEAR(O16) -> 2023 | O16: 45169 | P16: =D16*H16 -> 0 | R16: 建设期第6年 | S16: 合作期第6年 | T16: 2028 | U16: =L80 -> 0 | W16: 建设期第6年 | X16: 合作期第6年 | Y16: 2028 | Z16: =SUMIF($N$10:$N$579,Y16,$P$10:$P$579)/12 -> 0
B17: =YEAR(C17) -> 2023 | C17: 45199 | D17: =$D$10 -> 0 | F17: =YEAR(G17) -> 2023 | G17: 45199 | H17: =$H$10 -> 0 | J17: =YEAR(K17) -> 2023 | K17: 45199 | L17: =IF(K17=参数输入表!$I$7,100%,H17) -> 0 | N17: =YEAR(O17) -> 2023 | O17: 45199 | P17: =D17*H17 -> 0 | R17: 建设期第7年 | S17: 合作期第7年 | T17: 2029 | U17: =L92 -> 0 | W17: 建设期第7年 | X17: 合作期第7年 | Y17: 2029 | Z17: =SUMIF($N$10:$N$579,Y17,$P$10:$P$579)/12 -> 0
B18: =YEAR(C18) -> 2023 | C18: 45230 | D18: =$D$10 -> 0 | F18: =YEAR(G18) -> 2023 | G18: 45230 | H18: =$H$10 -> 0 | J18: =YEAR(K18) -> 2023 | K18: 45230 | L18: =IF(K18=参数输入表!$I$7,100%,H18) -> 0 | N18: =YEAR(O18) -> 2023 | O18: 45230 | P18: =D18*H18 -> 0 | R18: 建设期第8年 | S18: 合作期第8年 | T18: 2030 | U18: =L104 -> 1 | W18: 建设期第8年 | X18: 合作期第8年 | Y18: 2030 | Z18: =SUMIF($N$10:$N$579,Y18,$P$10:$P$579)/12 -> 0.41666667
B19: =YEAR(C19) -> 2023 | C19: 45260 | D19: =$D$10 -> 0 | F19: =YEAR(G19) -> 2023 | G19: 45260 | H19: =$H$10 -> 0 | J19: =YEAR(K19) -> 2023 | K19: 45260 | L19: =IF(K19=参数输入表!$I$7,100%,H19) -> 0 | N19: =YEAR(O19) -> 2023 | O19: 45260 | P19: =D19*H19 -> 0 | S19: 合作期第9年 | T19: 2031 | U19: =L116 -> 1 | X19: 合作期第9年 | Y19: 2031 | Z19: =SUMIF($N$10:$N$579,Y19,$P$10:$P$579)/12 -> 1
B20: =YEAR(C20) -> 2023 | C20: 45291 | D20: =$D$10 -> 0 | F20: =YEAR(G20) -> 2023 | G20: 45291 | H20: =$H$10 -> 0 | J20: =YEAR(K20) -> 2023 | K20: 45291 | L20: =IF(K20=参数输入表!$I$7,100%,H20) -> 0 | N20: =YEAR(O20) -> 2023 | O20: 45291 | P20: =D20*H20 -> 0 | S20: 合作期第10年 | T20: 2032 | U20: =L128 -> 1 | X20: 合作期第10年 | Y20: 2032 | Z20: =SUMIF($N$10:$N$579,Y20,$P$10:$P$579)/12 -> 1
B21: =YEAR(C21) -> 2024 | C21: 45322 | D21: =$D$10 -> 0 | F21: =YEAR(G21) -> 2024 | G21: 45322 | H21: =$H$10 -> 0 | J21: =YEAR(K21) -> 2024 | K21: 45322 | L21: =IF(K21=参数输入表!$I$7,100%,H21) -> 0 | N21: =YEAR(O21) -> 2024 | O21: 45322 | P21: =D21*H21 -> 0 | S21: 合作期第11年 | T21: 2033 | U21: =L140 -> 1 | X21: 合作期第11年 | Y21: 2033 | Z21: =SUMIF($N$10:$N$579,Y21,$P$10:$P$579)/12 -> 1
B22: =YEAR(C22) -> 2024 | C22: 45351 | D22: =$D$10 -> 0 | F22: =YEAR(G22) -> 2024 | G22: 45351 | H22: =$H$10 -> 0 | J22: =YEAR(K22) -> 2024 | K22: 45351 | L22: =IF(K22=参数输入表!$I$7,100%,H22) -> 0 | N22: =YEAR(O22) -> 2024 | O22: 45351 | P22: =D22*H22 -> 0 | S22: 合作期第12年 | T22: 2034 | U22: =L152 -> 1 | X22: 合作期第12年 | Y22: 2034 | Z22: =SUMIF($N$10:$N$579,Y22,$P$10:$P$579)/12 -> 1
B23: =YEAR(C23) -> 2024 | C23: 45382 | D23: =$D$10 -> 0 | F23: =YEAR(G23) -> 2024 | G23: 45382 | H23: =$H$10 -> 0 | J23: =YEAR(K23) -> 2024 | K23: 45382 | L23: =IF(K23=参数输入表!$I$7,100%,H23) -> 0 | N23: =YEAR(O23) -> 2024 | O23: 45382 | P23: =D23*H23 -> 0 | S23: 合作期第13年 | T23: 2035 | U23: =L164 -> 1 | X23: 合作期第13年 | Y23: 2035 | Z23: =SUMIF($N$10:$N$579,Y23,$P$10:$P$579)/12 -> 1
B24: =YEAR(C24) -> 2024 | C24: 45412 | D24: =$D$10 -> 0 | F24: =YEAR(G24) -> 2024 | G24: 45412 | H24: =$H$10 -> 0 | J24: =YEAR(K24) -> 2024 | K24: 45412 | L24: =IF(K24=参数输入表!$I$7,100%,H24) -> 0 | N24: =YEAR(O24) -> 2024 | O24: 45412 | P24: =D24*H24 -> 0 | S24: 合作期第14年 | T24: 2036 | U24: =L176 -> 1 | X24: 合作期第14年 | Y24: 2036 | Z24: =SUMIF($N$10:$N$579,Y24,$P$10:$P$579)/12 -> 1
B25: =YEAR(C25) -> 2024 | C25: 45443 | D25: =$D$10 -> 0 | F25: =YEAR(G25) -> 2024 | G25: 45443 | H25: =$H$10 -> 0 | J25: =YEAR(K25) -> 2024 | K25: 45443 | L25: =IF(K25=参数输入表!$I$7,100%,H25) -> 0 | N25: =YEAR(O25) -> 2024 | O25: 45443 | P25: =D25*H25 -> 0 | S25: 合作期第15年 | T25: 2037 | U25: =L188 -> 1 | X25: 合作期第15年 | Y25: 2037 | Z25: =SUMIF($N$10:$N$579,Y25,$P$10:$P$579)/12 -> 1
B26: =YEAR(C26) -> 2024 | C26: 45473 | D26: =$D$10 -> 0 | F26: =YEAR(G26) -> 2024 | G26: 45473 | H26: =$H$10 -> 0 | J26: =YEAR(K26) -> 2024 | K26: 45473 | L26: =IF(K26=参数输入表!$I$7,100%,H26) -> 0 | N26: =YEAR(O26) -> 2024 | O26: 45473 | P26: =D26*H26 -> 0 | S26: 合作期第16年 | T26: 2038 | U26: =L200 -> 1 | X26: 合作期第16年 | Y26: 2038 | Z26: =SUMIF($N$10:$N$579,Y26,$P$10:$P$579)/12 -> 1
B27: =YEAR(C27) -> 2024 | C27: 45504 | D27: =$D$10 -> 0 | F27: =YEAR(G27) -> 2024 | G27: 45504 | H27: =$H$10 -> 0 | J27: =YEAR(K27) -> 2024 | K27: 45504 | L27: =IF(K27=参数输入表!$I$7,100%,H27) -> 0 | N27: =YEAR(O27) -> 2024 | O27: 45504 | P27: =D27*H27 -> 0 | S27: 合作期第17年 | T27: 2039 | U27: =L212 -> 1 | X27: 合作期第17年 | Y27: 2039 | Z27: =SUMIF($N$10:$N$579,Y27,$P$10:$P$579)/12 -> 1
B28: =YEAR(C28) -> 2024 | C28: 45535 | D28: =$D$10 -> 0 | F28: =YEAR(G28) -> 2024 | G28: 45535 | H28: =$H$10 -> 0 | J28: =YEAR(K28) -> 2024 | K28: 45535 | L28: =IF(K28=参数输入表!$I$7,100%,H28) -> 0 | N28: =YEAR(O28) -> 2024 | O28: 45535 | P28: =D28*H28 -> 0 | S28: 合作期第18年 | T28: 2040 | U28: =L224 -> 1 | X28: 合作期第18年 | Y28: 2040 | Z28: =SUMIF($N$10:$N$579,Y28,$P$10:$P$579)/12 -> 1
B29: =YEAR(C29) -> 2024 | C29: 45565 | D29: =$D$10 -> 0 | F29: =YEAR(G29) -> 2024 | G29: 45565 | H29: =$H$10 -> 0 | J29: =YEAR(K29) -> 2024 | K29: 45565 | L29: =IF(K29=参数输入表!$I$7,100%,H29) -> 0 | N29: =YEAR(O29) -> 2024 | O29: 45565 | P29: =D29*H29 -> 0 | S29: 合作期第19年 | T29: 2041 | U29: =L236 -> 1 | X29: 合作期第19年 | Y29: 2041 | Z29: =SUMIF($N$10:$N$579,Y29,$P$10:$P$579)/12 -> 1
B30: =YEAR(C30) -> 2024 | C30: 45596 | D30: =$D$10 -> 0 | F30: =YEAR(G30) -> 2024 | G30: 45596 | H30: =$H$10 -> 0 | J30: =YEAR(K30) -> 2024 | K30: 45596 | L30: =IF(K30=参数输入表!$I$7,100%,H30) -> 0 | N30: =YEAR(O30) -> 2024 | O30: 45596 | P30: =D30*H30 -> 0 | S30: 合作期第20年 | T30: 2042 | U30: =L248 -> 1 | X30: 合作期第20年 | Y30: 2042 | Z30: =SUMIF($N$10:$N$579,Y30,$P$10:$P$579)/12 -> 1
B31: =YEAR(C31) -> 2024 | C31: 45626 | D31: =$D$10 -> 0 | F31: =YEAR(G31) -> 2024 | G31: 45626 | H31: =$H$10 -> 0 | J31: =YEAR(K31) -> 2024 | K31: 45626 | L31: =IF(K31=参数输入表!$I$7,100%,H31) -> 0 | N31: =YEAR(O31) -> 2024 | O31: 45626 | P31: =D31*H31 -> 0 | S31: 合作期第21年 | T31: 2043 | U31: =L260 -> 1 | X31: 合作期第21年 | Y31: 2043 | Z31: =SUMIF($N$10:$N$579,Y31,$P$10:$P$579)/12 -> 1
B32: =YEAR(C32) -> 2024 | C32: 45657 | D32: =$D$10 -> 0 | F32: =YEAR(G32) -> 2024 | G32: 45657 | H32: =$H$10 -> 0 | J32: =YEAR(K32) -> 2024 | K32: 45657 | L32: =IF(K32=参数输入表!$I$7,100%,H32) -> 0 | N32: =YEAR(O32) -> 2024 | O32: 45657 | P32: =D32*H32 -> 0 | S32: 合作期第22年 | T32: 2044 | U32: =L272 -> 1 | X32: 合作期第22年 | Y32: 2044 | Z32: =SUMIF($N$10:$N$579,Y32,$P$10:$P$579)/12 -> 1
B33: =YEAR(C33) -> 2025 | C33: 45688 | D33: =$D$10 -> 0 | F33: =YEAR(G33) -> 2025 | G33: 45688 | H33: =$H$10 -> 0 | J33: =YEAR(K33) -> 2025 | K33: 45688 | L33: =IF(K33=参数输入表!$I$7,100%,H33) -> 0 | N33: =YEAR(O33) -> 2025 | O33: 45688 | P33: =D33*H33 -> 0 | S33: 合作期第23年 | T33: 2045 | U33: =L284 -> 1 | X33: 合作期第23年 | Y33: 2045 | Z33: =SUMIF($N$10:$N$579,Y33,$P$10:$P$579)/12 -> 1
B34: =YEAR(C34) -> 2025 | C34: 45716 | D34: =$D$10 -> 0 | F34: =YEAR(G34) -> 2025 | G34: 45716 | H34: =$H$10 -> 0 | J34: =YEAR(K34) -> 2025 | K34: 45716 | L34: =IF(K34=参数输入表!$I$7,100%,H34) -> 0 | N34: =YEAR(O34) -> 2025 | O34: 45716 | P34: =D34*H34 -> 0 | S34: 合作期第24年 | T34: 2046 | U34: =L296 -> 1 | X34: 合作期第24年 | Y34: 2046 | Z34: =SUMIF($N$10:$N$579,Y34,$P$10:$P$579)/12 -> 1
B35: =YEAR(C35) -> 2025 | C35: 45747 | D35: =$D$10 -> 0 | F35: =YEAR(G35) -> 2025 | G35: 45747 | H35: =$H$10 -> 0 | J35: =YEAR(K35) -> 2025 | K35: 45747 | L35: =IF(K35=参数输入表!$I$7,100%,H35) -> 0 | N35: =YEAR(O35) -> 2025 | O35: 45747 | P35: =D35*H35 -> 0 | S35: 合作期第25年 | T35: 2047 | U35: =L308 -> 1 | X35: 合作期第25年 | Y35: 2047 | Z35: =SUMIF($N$10:$N$579,Y35,$P$10:$P$579)/12 -> 1
B36: =YEAR(C36) -> 2025 | C36: 45777 | D36: =$D$10 -> 0 | F36: =YEAR(G36) -> 2025 | G36: 45777 | H36: =$H$10 -> 0 | J36: =YEAR(K36) -> 2025 | K36: 45777 | L36: =IF(K36=参数输入表!$I$7,100%,H36) -> 0 | N36: =YEAR(O36) -> 2025 | O36: 45777 | P36: =D36*H36 -> 0 | S36: 合作期第26年 | T36: 2048 | U36: =L320 -> 1 | X36: 合作期第26年 | Y36: 2048 | Z36: =SUMIF($N$10:$N$579,Y36,$P$10:$P$579)/12 -> 1
B37: =YEAR(C37) -> 2025 | C37: 45808 | D37: =$D$10 -> 0 | F37: =YEAR(G37) -> 2025 | G37: 45808 | H37: =$H$10 -> 0 | J37: =YEAR(K37) -> 2025 | K37: 45808 | L37: =IF(K37=参数输入表!$I$7,100%,H37) -> 0 | N37: =YEAR(O37) -> 2025 | O37: 45808 | P37: =D37*H37 -> 0 | S37: 合作期第27年 | T37: 2049 | U37: =L332 -> 1 | X37: 合作期第27年 | Y37: 2049 | Z37: =SUMIF($N$10:$N$579,Y37,$P$10:$P$579)/12 -> 1
B38: =YEAR(C38) -> 2025 | C38: 45838 | D38: =$D$10 -> 0 | F38: =YEAR(G38) -> 2025 | G38: 45838 | H38: =$H$10 -> 0 | J38: =YEAR(K38) -> 2025 | K38: 45838 | L38: =IF(K38=参数输入表!$I$7,100%,H38) -> 0 | N38: =YEAR(O38) -> 2025 | O38: 45838 | P38: =D38*H38 -> 0 | S38: 合作期第28年 | T38: 2050 | U38: =L344 -> 1 | X38: 合作期第28年 | Y38: 2050 | Z38: =SUMIF($N$10:$N$579,Y38,$P$10:$P$579)/12 -> 1
B39: =YEAR(C39) -> 2025 | C39: 45869 | D39: =$D$10 -> 0 | F39: =YEAR(G39) -> 2025 | G39: 45869 | H39: =$H$10 -> 0 | J39: =YEAR(K39) -> 2025 | K39: 45869 | L39: =IF(K39=参数输入表!$I$7,100%,H39) -> 0 | N39: =YEAR(O39) -> 2025 | O39: 45869 | P39: =D39*H39 -> 0 | S39: 合作期第29年 | T39: 2051 | U39: =L356 -> 1 | X39: 合作期第29年 | Y39: 2051 | Z39: =SUMIF($N$10:$N$579,Y39,$P$10:$P$579)/12 -> 1
B40: =YEAR(C40) -> 2025 | C40: 45900 | D40: =$D$10 -> 0 | F40: =YEAR(G40) -> 2025 | G40: 45900 | H40: =$H$10 -> 0 | J40: =YEAR(K40) -> 2025 | K40: 45900 | L40: =IF(K40=参数输入表!$I$7,100%,H40) -> 0 | N40: =YEAR(O40) -> 2025 | O40: 45900 | P40: =D40*H40 -> 0 | S40: 合作期第30年 | T40: 2052 | U40: =L368 -> 1 | X40: 合作期第30年 | Y40: 2052 | Z40: =SUMIF($N$10:$N$579,Y40,$P$10:$P$579)/12 -> 1
B41: =YEAR(C41) -> 2025 | C41: 45930 | D41: =$D$10 -> 0 | F41: =YEAR(G41) -> 2025 | G41: 45930 | H41: =$H$10 -> 0 | J41: =YEAR(K41) -> 2025 | K41: 45930 | L41: =IF(K41=参数输入表!$I$7,100%,H41) -> 0 | N41: =YEAR(O41) -> 2025 | O41: 45930 | P41: =D41*H41 -> 0 | S41: 合作期第31年 | T41: 2053 | U41: =L380 -> 1 | X41: 合作期第31年 | Y41: 2053 | Z41: =SUMIF($N$10:$N$579,Y41,$P$10:$P$579)/12 -> 1
B42: =YEAR(C42) -> 2025 | C42: 45961 | D42: =$D$10 -> 0 | F42: =YEAR(G42) -> 2025 | G42: 45961 | H42: =$H$10 -> 0 | J42: =YEAR(K42) -> 2025 | K42: 45961 | L42: =IF(K42=参数输入表!$I$7,100%,H42) -> 0 | N42: =YEAR(O42) -> 2025 | O42: 45961 | P42: =D42*H42 -> 0 | S42: 合作期第32年 | T42: 2054 | U42: =L392 -> 1 | X42: 合作期第32年 | Y42: 2054 | Z42: =SUMIF($N$10:$N$579,Y42,$P$10:$P$579)/12 -> 1
B43: =YEAR(C43) -> 2025 | C43: 45991 | D43: =$D$10 -> 0 | F43: =YEAR(G43) -> 2025 | G43: 45991 | H43: =$H$10 -> 0 | J43: =YEAR(K43) -> 2025 | K43: 45991 | L43: =IF(K43=参数输入表!$I$7,100%,H43) -> 0 | N43: =YEAR(O43) -> 2025 | O43: 45991 | P43: =D43*H43 -> 0 | S43: 合作期第33年 | T43: 2055 | U43: =L404 -> 1 | X43: 合作期第33年 | Y43: 2055 | Z43: =SUMIF($N$10:$N$579,Y43,$P$10:$P$579)/12 -> 1
B44: =YEAR(C44) -> 2025 | C44: 46022 | D44: =$D$10 -> 0 | F44: =YEAR(G44) -> 2025 | G44: 46022 | H44: =$H$10 -> 0 | J44: =YEAR(K44) -> 2025 | K44: 46022 | L44: =IF(K44=参数输入表!$I$7,100%,H44) -> 0 | N44: =YEAR(O44) -> 2025 | O44: 46022 | P44: =D44*H44 -> 0 | S44: 合作期第34年 | T44: 2056 | U44: =L416 -> 1 | X44: 合作期第34年 | Y44: 2056 | Z44: =SUMIF($N$10:$N$579,Y44,$P$10:$P$579)/12 -> 1
B45: =YEAR(C45) -> 2026 | C45: 46053 | D45: =$D$10 -> 0 | F45: =YEAR(G45) -> 2026 | G45: 46053 | H45: =$H$10 -> 0 | J45: =YEAR(K45) -> 2026 | K45: 46053 | L45: =IF(K45=参数输入表!$I$7,100%,H45) -> 0 | N45: =YEAR(O45) -> 2026 | O45: 46053 | P45: =D45*H45 -> 0 | S45: 合作期第35年 | T45: 2057 | U45: =L428 -> 1 | X45: 合作期第35年 | Y45: 2057 | Z45: =SUMIF($N$10:$N$579,Y45,$P$10:$P$579)/12 -> 1
B46: =YEAR(C46) -> 2026 | C46: 46081 | D46: =$D$10 -> 0 | F46: =YEAR(G46) -> 2026 | G46: 46081 | H46: =$H$10 -> 0 | J46: =YEAR(K46) -> 2026 | K46: 46081 | L46: =IF(K46=参数输入表!$I$7,100%,H46) -> 0 | N46: =YEAR(O46) -> 2026 | O46: 46081 | P46: =D46*H46 -> 0 | S46: 合作期第36年 | T46: 2058 | U46: =L440 -> 1 | X46: 合作期第36年 | Y46: 2058 | Z46: =SUMIF($N$10:$N$579,Y46,$P$10:$P$579)/12 -> 1
B47: =YEAR(C47) -> 2026 | C47: 46112 | D47: =$D$10 -> 0 | F47: =YEAR(G47) -> 2026 | G47: 46112 | H47: =$H$10 -> 0 | J47: =YEAR(K47) -> 2026 | K47: 46112 | L47: =IF(K47=参数输入表!$I$7,100%,H47) -> 0 | N47: =YEAR(O47) -> 2026 | O47: 46112 | P47: =D47*H47 -> 0 | S47: 合作期第37年 | T47: 2059 | U47: =L452 -> 1 | X47: 合作期第37年 | Y47: 2059 | Z47: =SUMIF($N$10:$N$579,Y47,$P$10:$P$579)/12 -> 1
B48: =YEAR(C48) -> 2026 | C48: 46142 | D48: =$D$10 -> 0 | F48: =YEAR(G48) -> 2026 | G48: 46142 | H48: =$H$10 -> 0 | J48: =YEAR(K48) -> 2026 | K48: 46142 | L48: =IF(K48=参数输入表!$I$7,100%,H48) -> 0 | N48: =YEAR(O48) -> 2026 | O48: 46142 | P48: =D48*H48 -> 0 | S48: 合作期第38年 | T48: 2060 | U48: =L464 -> 1 | X48: 合作期第38年 | Y48: 2060 | Z48: =SUMIF($N$10:$N$579,Y48,$P$10:$P$579)/12 -> 1
B49: =YEAR(C49) -> 2026 | C49: 46173 | D49: =$D$10 -> 0 | F49: =YEAR(G49) -> 2026 | G49: 46173 | H49: =$H$10 -> 0 | J49: =YEAR(K49) -> 2026 | K49: 46173 | L49: =IF(K49=参数输入表!$I$7,100%,H49) -> 0 | N49: =YEAR(O49) -> 2026 | O49: 46173 | P49: =D49*H49 -> 0 | S49: 合作期第39年 | T49: 2061 | U49: =L476 -> 1 | X49: 合作期第39年 | Y49: 2061 | Z49: =SUMIF($N$10:$N$579,Y49,$P$10:$P$579)/12 -> 1
B50: =YEAR(C50) -> 2026 | C50: 46203 | D50: =$D$10 -> 0 | F50: =YEAR(G50) -> 2026 | G50: 46203 | H50: =$H$10 -> 0 | J50: =YEAR(K50) -> 2026 | K50: 46203 | L50: =IF(K50=参数输入表!$I$7,100%,H50) -> 0 | N50: =YEAR(O50) -> 2026 | O50: 46203 | P50: =D50*H50 -> 0 | S50: 合作期第40年 | T50: 2062 | U50: =L488 -> 1 | X50: 合作期第40年 | Y50: 2062 | Z50: =SUMIF($N$10:$N$579,Y50,$P$10:$P$579)/12 -> 1
B51: =YEAR(C51) -> 2026 | C51: 46234 | D51: =$D$10 -> 0 | F51: =YEAR(G51) -> 2026 | G51: 46234 | H51: =$H$10 -> 0 | J51: =YEAR(K51) -> 2026 | K51: 46234 | L51: =IF(K51=参数输入表!$I$7,100%,H51) -> 0 | N51: =YEAR(O51) -> 2026 | O51: 46234 | P51: =D51*H51 -> 0 | S51: 合作期第41年 | T51: 2063 | U51: =L500 -> 1 | X51: 合作期第41年 | Y51: 2063 | Z51: =SUMIF($N$10:$N$579,Y51,$P$10:$P$579)/12 -> 1
B52: =YEAR(C52) -> 2026 | C52: 46265 | D52: =$D$10 -> 0 | F52: =YEAR(G52) -> 2026 | G52: 46265 | H52: =$H$10 -> 0 | J52: =YEAR(K52) -> 2026 | K52: 46265 | L52: =IF(K52=参数输入表!$I$7,100%,H52) -> 0 | N52: =YEAR(O52) -> 2026 | O52: 46265 | P52: =D52*H52 -> 0 | S52: 合作期第42年 | T52: 2064 | U52: =L512 -> 1 | X52: 合作期第42年 | Y52: 2064 | Z52: =SUMIF($N$10:$N$579,Y52,$P$10:$P$579)/12 -> 1
B53: =YEAR(C53) -> 2026 | C53: 46295 | D53: =$D$10 -> 0 | F53: =YEAR(G53) -> 2026 | G53: 46295 | H53: =$H$10 -> 0 | J53: =YEAR(K53) -> 2026 | K53: 46295 | L53: =IF(K53=参数输入表!$I$7,100%,H53) -> 0 | N53: =YEAR(O53) -> 2026 | O53: 46295 | P53: =D53*H53 -> 0 | S53: 合作期第43年 | T53: 2065 | U53: =L524 -> 1 | X53: 合作期第43年 | Y53: 2065 | Z53: =SUMIF($N$10:$N$579,Y53,$P$10:$P$579)/12 -> 1
B54: =YEAR(C54) -> 2026 | C54: 46326 | D54: =$D$10 -> 0 | F54: =YEAR(G54) -> 2026 | G54: 46326 | H54: =$H$10 -> 0 | J54: =YEAR(K54) -> 2026 | K54: 46326 | L54: =IF(K54=参数输入表!$I$7,100%,H54) -> 0 | N54: =YEAR(O54) -> 2026 | O54: 46326 | P54: =D54*H54 -> 0 | S54: 合作期第44年 | T54: 2066 | U54: =L536 -> 1 | X54: 合作期第44年 | Y54: 2066 | Z54: =SUMIF($N$10:$N$579,Y54,$P$10:$P$579)/12 -> 1
B55: =YEAR(C55) -> 2026 | C55: 46356 | D55: =$D$10 -> 0 | F55: =YEAR(G55) -> 2026 | G55: 46356 | H55: =$H$10 -> 0 | J55: =YEAR(K55) -> 2026 | K55: 46356 | L55: =IF(K55=参数输入表!$I$7,100%,H55) -> 0 | N55: =YEAR(O55) -> 2026 | O55: 46356 | P55: =D55*H55 -> 0 | S55: 合作期第45年 | T55: 2067 | U55: =L548 -> 1 | X55: 合作期第45年 | Y55: 2067 | Z55: =SUMIF($N$10:$N$579,Y55,$P$10:$P$579)/12 -> 1
B56: =YEAR(C56) -> 2026 | C56: 46387 | D56: =$D$10 -> 0 | F56: =YEAR(G56) -> 2026 | G56: 46387 | H56: =$H$10 -> 0 | J56: =YEAR(K56) -> 2026 | K56: 46387 | L56: =IF(K56=参数输入表!$I$7,100%,H56) -> 0 | N56: =YEAR(O56) -> 2026 | O56: 46387 | P56: =D56*H56 -> 0 | S56: 合作期第46年 | T56: 2068 | U56: =L560 -> 1 | X56: 合作期第46年 | Y56: 2068 | Z56: =SUMIF($N$10:$N$579,Y56,$P$10:$P$579)/12 -> 1
B57: =YEAR(C57) -> 2027 | C57: 46418 | D57: =$D$10 -> 0 | F57: =YEAR(G57) -> 2027 | G57: 46418 | H57: =$H$10 -> 0 | J57: =YEAR(K57) -> 2027 | K57: 46418 | L57: =IF(K57=参数输入表!$I$7,100%,H57) -> 0 | N57: =YEAR(O57) -> 2027 | O57: 46418 | P57: =D57*H57 -> 0 | S57: 合作期第47年 | T57: 2069 | U57: =L572 -> 1 | X57: 合作期第47年 | Y57: 2069 | Z57: =SUMIF($N$10:$N$579,Y57,$P$10:$P$579)/12 -> 1
B58: =YEAR(C58) -> 2027 | C58: 46446 | D58: =$D$10 -> 0 | F58: =YEAR(G58) -> 2027 | G58: 46446 | H58: =$H$10 -> 0 | J58: =YEAR(K58) -> 2027 | K58: 46446 | L58: =IF(K58=参数输入表!$I$7,100%,H58) -> 0 | N58: =YEAR(O58) -> 2027 | O58: 46446 | P58: =D58*H58 -> 0 | S58: 合作期第48年 | T58: 2070 | U58: =L579 -> 1 | X58: 合作期第48年 | Y58: 2070 | Z58: =SUMIF($N$10:$N$579,Y58,$P$10:$P$579)/12 -> 0.58333333
B59: =YEAR(C59) -> 2027 | C59: 46477 | D59: =$D$10 -> 0 | F59: =YEAR(G59) -> 2027 | G59: 46477 | H59: =$H$10 -> 0 | J59: =YEAR(K59) -> 2027 | K59: 46477 | L59: =IF(K59=参数输入表!$I$7,100%,H59) -> 0 | N59: =YEAR(O59) -> 2027 | O59: 46477 | P59: =D59*H59 -> 0
B60: =YEAR(C60) -> 2027 | C60: 46507 | D60: =$D$10 -> 0 | F60: =YEAR(G60) -> 2027 | G60: 46507 | H60: =$H$10 -> 0 | J60: =YEAR(K60) -> 2027 | K60: 46507 | L60: =IF(K60=参数输入表!$I$7,100%,H60) -> 0 | N60: =YEAR(O60) -> 2027 | O60: 46507 | P60: =D60*H60 -> 0
B61: =YEAR(C61) -> 2027 | C61: 46538 | D61: =$D$10 -> 0 | F61: =YEAR(G61) -> 2027 | G61: 46538 | H61: =$H$10 -> 0 | J61: =YEAR(K61) -> 2027 | K61: 46538 | L61: =IF(K61=参数输入表!$I$7,100%,H61) -> 0 | N61: =YEAR(O61) -> 2027 | O61: 46538 | P61: =D61*H61 -> 0
B62: =YEAR(C62) -> 2027 | C62: 46568 | D62: =$D$10 -> 0 | F62: =YEAR(G62) -> 2027 | G62: 46568 | H62: =$H$10 -> 0 | J62: =YEAR(K62) -> 2027 | K62: 46568 | L62: =IF(K62=参数输入表!$I$7,100%,H62) -> 0 | N62: =YEAR(O62) -> 2027 | O62: 46568 | P62: =D62*H62 -> 0
B63: =YEAR(C63) -> 2027 | C63: 46599 | D63: =$D$10 -> 0 | F63: =YEAR(G63) -> 2027 | G63: 46599 | H63: =$H$10 -> 0 | J63: =YEAR(K63) -> 2027 | K63: 46599 | L63: =IF(K63=参数输入表!$I$7,100%,H63) -> 0 | N63: =YEAR(O63) -> 2027 | O63: 46599 | P63: =D63*H63 -> 0
B64: =YEAR(C64) -> 2027 | C64: 46630 | D64: =$D$10 -> 0 | F64: =YEAR(G64) -> 2027 | G64: 46630 | H64: =$H$10 -> 0 | J64: =YEAR(K64) -> 2027 | K64: 46630 | L64: =IF(K64=参数输入表!$I$7,100%,H64) -> 0 | N64: =YEAR(O64) -> 2027 | O64: 46630 | P64: =D64*H64 -> 0
B65: =YEAR(C65) -> 2027 | C65: 46660 | D65: =$D$10 -> 0 | F65: =YEAR(G65) -> 2027 | G65: 46660 | H65: =$H$10 -> 0 | J65: =YEAR(K65) -> 2027 | K65: 46660 | L65: =IF(K65=参数输入表!$I$7,100%,H65) -> 0 | N65: =YEAR(O65) -> 2027 | O65: 46660 | P65: =D65*H65 -> 0
B66: =YEAR(C66) -> 2027 | C66: 46691 | D66: =$D$10 -> 0 | F66: =YEAR(G66) -> 2027 | G66: 46691 | H66: =$H$10 -> 0 | J66: =YEAR(K66) -> 2027 | K66: 46691 | L66: =IF(K66=参数输入表!$I$7,100%,H66) -> 0 | N66: =YEAR(O66) -> 2027 | O66: 46691 | P66: =D66*H66 -> 0
B67: =YEAR(C67) -> 2027 | C67: 46721 | D67: =$D$10 -> 0 | F67: =YEAR(G67) -> 2027 | G67: 46721 | H67: =$H$10 -> 0 | J67: =YEAR(K67) -> 2027 | K67: 46721 | L67: =IF(K67=参数输入表!$I$7,100%,H67) -> 0 | N67: =YEAR(O67) -> 2027 | O67: 46721 | P67: =D67*H67 -> 0
B68: =YEAR(C68) -> 2027 | C68: 46752 | D68: =$D$10 -> 0 | F68: =YEAR(G68) -> 2027 | G68: 46752 | H68: =$H$10 -> 0 | J68: =YEAR(K68) -> 2027 | K68: 46752 | L68: =IF(K68=参数输入表!$I$7,100%,H68) -> 0 | N68: =YEAR(O68) -> 2027 | O68: 46752 | P68: =D68*H68 -> 0
B69: =YEAR(C69) -> 2028 | C69: 46783 | D69: =$D$10 -> 0 | F69: =YEAR(G69) -> 2028 | G69: 46783 | H69: =$H$10 -> 0 | J69: =YEAR(K69) -> 2028 | K69: 46783 | L69: =IF(K69=参数输入表!$I$7,100%,H69) -> 0 | N69: =YEAR(O69) -> 2028 | O69: 46783 | P69: =D69*H69 -> 0
B70: =YEAR(C70) -> 2028 | C70: 46812 | D70: =$D$10 -> 0 | F70: =YEAR(G70) -> 2028 | G70: 46812 | H70: =$H$10 -> 0 | J70: =YEAR(K70) -> 2028 | K70: 46812 | L70: =IF(K70=参数输入表!$I$7,100%,H70) -> 0 | N70: =YEAR(O70) -> 2028 | O70: 46812 | P70: =D70*H70 -> 0
... B99: =YEAR(C99) -> 2030 | C99: 47695 | D99: =$D$10 -> 0 | F99: =YEAR(G99) -> 2030 | G99: 47695 | H99: =$H$10 -> 0 | J99: =YEAR(K99) -> 2030 | K99: 47695 | L99: =IF(K99=参数输入表!$I$7,100%,H99) -> 1 | N99: =YEAR(O99) -> 2030 | O99: 47695 | P99: =D99*H99 -> 0
B100: =YEAR(C100) -> 2030 | C100: 47726 | D100: =D7 -> 1 | F100: =YEAR(G100) -> 2030 | G100: 47726 | H100: =H7 -> 1 | J100: =YEAR(K100) -> 2030 | K100: 47726 | L100: =IF(K100=参数输入表!$I$7,100%,H100) -> 1 | N100: =YEAR(O100) -> 2030 | O100: 47726 | P100: =D100*H100 -> 1
B101: =YEAR(C101) -> 2030 | C101: 47756 | D101: =$D$100 -> 1 | F101: =YEAR(G101) -> 2030 | G101: 47756 | H101: =$H$100 -> 1 | J101: =YEAR(K101) -> 2030 | K101: 47756 | L101: =IF(K101=参数输入表!$I$7,100%,H101) -> 1 | N101: =YEAR(O101) -> 2030 | O101: 47756 | P101: =D101*H101 -> 1
B102: =YEAR(C102) -> 2030 | C102: 47787 | D102: =$D$100 -> 1 | F102: =YEAR(G102) -> 2030 | G102: 47787 | H102: =$H$100 -> 1 | J102: =YEAR(K102) -> 2030 | K102: 47787 | L102: =IF(K102=参数输入表!$I$7,100%,H102) -> 1 | N102: =YEAR(O102) -> 2030 | O102: 47787 | P102: =D102*H102 -> 1
B103: =YEAR(C103) -> 2030 | C103: 47817 | D103: =$D$100 -> 1 | F103: =YEAR(G103) -> 2030 | G103: 47817 | H103: =$H$100 -> 1 | J103: =YEAR(K103) -> 2030 | K103: 47817 | L103: =IF(K103=参数输入表!$I$7,100%,H103) -> 1 | N103: =YEAR(O103) -> 2030 | O103: 47817 | P103: =D103*H103 -> 1
B104: =YEAR(C104) -> 2030 | C104: 47848 | D104: =$D$100 -> 1 | F104: =YEAR(G104) -> 2030 | G104: 47848 | H104: =$H$100 -> 1 | J104: =YEAR(K104) -> 2030 | K104: 47848 | L104: =IF(K104=参数输入表!$I$7,100%,H104) -> 1 | N104: =YEAR(O104) -> 2030 | O104: 47848 | P104: =D104*H104 -> 1
B105: =YEAR(C105) -> 2031 | C105: 47879 | D105: =$D$100 -> 1 | F105: =YEAR(G105) -> 2031 | G105: 47879 | H105: =$H$100 -> 1 | J105: =YEAR(K105) -> 2031 | K105: 47879 | L105: =IF(K105=参数输入表!$I$7,100%,H105) -> 1 | N105: =YEAR(O105) -> 2031 | O105: 47879 | P105: =D105*H105 -> 1
B106: =YEAR(C106) -> 2031 | C106: 47907 | D106: =$D$100 -> 1 | F106: =YEAR(G106) -> 2031 | G106: 47907 | H106: =$H$100 -> 1 | J106: =YEAR(K106) -> 2031 | K106: 47907 | L106: =IF(K106=参数输入表!$I$7,100%,H106) -> 1 | N106: =YEAR(O106) -> 2031 | O106: 47907 | P106: =D106*H106 -> 1
B107: =YEAR(C107) -> 2031 | C107: 47938 | D107: =$D$100 -> 1 | F107: =YEAR(G107) -> 2031 | G107: 47938 | H107: =$H$100 -> 1 | J107: =YEAR(K107) -> 2031 | K107: 47938 | L107: =IF(K107=参数输入表!$I$7,100%,H107) -> 1 | N107: =YEAR(O107) -> 2031 | O107: 47938 | P107: =D107*H107 -> 1
B108: =YEAR(C108) -> 2031 | C108: 47968 | D108: =$D$100 -> 1 | F108: =YEAR(G108) -> 2031 | G108: 47968 | H108: =$H$100 -> 1 | J108: =YEAR(K108) -> 2031 | K108: 47968 | L108: =IF(K108=参数输入表!$I$7,100%,H108) -> 1 | N108: =YEAR(O108) -> 2031 | O108: 47968 | P108: =D108*H108 -> 1
B109: =YEAR(C109) -> 2031 | C109: 47999 | D109: =$D$100 -> 1 | F109: =YEAR(G109) -> 2031 | G109: 47999 | H109: =$H$100 -> 1 | J109: =YEAR(K109) -> 2031 | K109: 47999 | L109: =IF(K109=参数输入表!$I$7,100%,H109) -> 1 | N109: =YEAR(O109) -> 2031 | O109: 47999 | P109: =D109*H109 -> 1
B110: =YEAR(C110) -> 2031 | C110: 48029 | D110: =$D$100 -> 1 | F110: =YEAR(G110) -> 2031 | G110: 48029 | H110: =$H$100 -> 1 | J110: =YEAR(K110) -> 2031 | K110: 48029 | L110: =IF(K110=参数输入表!$I$7,100%,H110) -> 1 | N110: =YEAR(O110) -> 2031 | O110: 48029 | P110: =D110*H110 -> 1
B111: =YEAR(C111) -> 2031 | C111: 48060 | D111: =$D$100 -> 1 | F111: =YEAR(G111) -> 2031 | G111: 48060 | H111: =$H$100 -> 1 | J111: =YEAR(K111) -> 2031 | K111: 48060 | L111: =IF(K111=参数输入表!$I$7,100%,H111) -> 1 | N111: =YEAR(O111) -> 2031 | O111: 48060 | P111: =D111*H111 -> 1
B112: =YEAR(C112) -> 2031 | C112: 48091 | D112: =$D$100 -> 1 | F112: =YEAR(G112) -> 2031 | G112: 48091 | H112: =$H$100 -> 1 | J112: =YEAR(K112) -> 2031 | K112: 48091 | L112: =IF(K112=参数输入表!$I$7,100%,H112) -> 1 | N112: =YEAR(O112) -> 2031 | O112: 48091 | P112: =D112*H112 -> 1
... B579: =YEAR(C579) -> 2070 | C579: 62305 | D579: =$D$100 -> 1 | F579: =YEAR(G579) -> 2070 | G579: 62305 | H579: =$H$100 -> 1 | J579: =YEAR(K579) -> 2070 | K579: 62305 | L579: =IF(K579=参数输入表!$I$7,100%,H579) -> 1 | N579: =YEAR(O579) -> 2070 | O579: 62305 | P579: =D579*H579 -> 1

Sheet 投资概算明细
B2: 工程分年度投资输入表（可插入月度数据）
B3: 序号 | C3: 科目 | D3: 合计 | E3: 单位 | F3: 45016 | G3: 2023 | H3: 2024 | I3: 2025 | J3: 2026 | K3: 2027 | L3: 2028 | M3: 47361 | N3: 2029 | O3: 47695 | P3: 增值税税率
B4: 1 | C4: 枢纽工程 | D4: =SUM(F4:O4) -> 638349.96 | E4: 万元 | F4: =SUM(F5:F11) -> 22265.592 | G4: =SUM(G5:G11) -> 51953.048 | H4: =SUM(H5:H11) -> 69974.41 | I4: =SUM(I5:I11) -> 77779.18 | J4: =SUM(J5:J11) -> 85342.6 | K4: =SUM(K5:K11) -> 113182.66 | L4: =SUM(L5:L11) -> 101185.18 | M4: =SUM(M5:M11) -> 50715.138 | ... O4: =SUM(O5:O11) -> 32142.06
B5: 1.1 | C5: 施工辅助工程 | D5: =SUM(F5:O5) -> 62992.58 | E5: 万元 | F5: 4412.391 | G5: 10295.579 | H5: 19706.12 | I5: 15924.17 | J5: 5522.19 | K5: 1601.06 | L5: 1555.86 | M5: 1529.73 | N5: 1019.82 | O5: 1425.66 | P5: =参数输入表!G194 -> 0.09
B6: 1.2 | C6: 建筑工程 | D6: =SUM(F6:O6) -> 331236.41 | E6: 万元 | F6: 17853.201 | G6: 41657.469 | H6: 46778.98 | I6: 55122.11 | J6: 67791.02 | K6: 52983.1 | L6: 36031.24 | M6: 7002.258 | N6: 4668.172 | O6: 1348.86 | P6: =参数输入表!G195 -> 0.09
B7: 1.3 | C7: 环境保护和水土保持专项工程 | D7: =SUM(F7:O7) -> 17893.9 | E7: 万元 | H7: 3489.31 | I7: 3489.31 | J7: 2863.02 | K7: 2415.68 | L7: 2505.15 | M7: 751.542 | N7: 501.028 | O7: 1878.86 | P7: =参数输入表!G196 -> 0.09
B8: 1.4 | C8: 机电设备安装工程 | D8: =SUM(F8:O8) -> 68286.2 | E8: 万元 | I8: 3243.59 | J8: 3243.59 | K8: 19461.57 | L8: 13315.82 | M8: 12291.516 | N8: 8194.344 | O8: 8535.77 | P8: =参数输入表!G197 -> 0.09
B9: 1.5 | C9: 金属结构设备安装工程 | D9: =SUM(F9:O9) -> 157940.87 | E9: 万元 | J9: 5922.78 | K9: 36721.25 | L9: 47777.11 | M9: 29140.092 | N9: 19426.728 | O9: 18952.91 | P9: =参数输入表!G198 -> 0.09
B10: 1.6 | C10: 机电设备采购工程 | D10: =SUM(F10:O10) -> 0 | E10: 万元 | P10: =参数输入表!G199 -> 0.13
B11: 1.7 | C11: 金属结构设备采购工程 | D11: =SUM(F11:O11) -> 0 | E11: 万元 | P11: =参数输入表!G200 -> 0.13
B12: 2 | C12: 建设征地和移民安置补偿费用 | D12: =SUM(F12:O12) -> 5205.27 | E12: 万元 | F12: 697.725 | G12: 1628.025 | H12: 2325.75 | I12: 332.26 | J12: 193.82 | M12: 16.614 | N12: 11.076 | P12: =参数输入表!G201 -> 0
B13: 3 | C13: 独立费用 | D13: =SUM(F13:O13) -> 122855.89 | E13: 万元 | F13: =SUM(F14:F17) -> 4309.572 | G13: =SUM(G14:G17) -> 10055.668 | H13: =SUM(H14:H17) -> 14510.03 | I13: =SUM(I14:I17) -> 17514.68 | J13: =SUM(J14:J17) -> 16533.47 | K13: =SUM(K14:K17) -> 17305.88 | L13: =SUM(L14:L17) -> 17315.25 | M13: =SUM(M14:M17) -> 8799.102 | ... O13: =SUM(O14:O17) -> 10646.17
B14: 3.1 | C14: 建设管理费 | D14: =SUM(F14:O14) -> 54324.05 | E14: 万元 | F14: 1333.542 | G14: 3111.598 | H14: 6381.84 | I14: 8283.43 | J14: 7074.83 | K14: 9259.39 | L14: 9470.09 | M14: 4203.762 | N14: 2802.508 | O14: 2403.06 | P14: =参数输入表!G203 -> 0.06
B15: 3.2 | C15: 生产准备费 | D15: =SUM(F15:O15) -> 8001.3 | E15: 万元 | K15: 663.35 | L15: 663.35 | M15: 936.234 | N15: 624.156 | O15: 5114.21 | P15: =参数输入表!G204 -> 0
B16: 3.3 | C16: 科研勘查设计费 | D16: =SUM(F16:O16) -> 56990.05 | E16: 万元 | F16: 2976.03 | G16: 6944.07 | H16: 7470.1 | I16: 8269.11 | J16: 8548.51 | K16: 6498.01 | L16: 7056.81 | M16: 3659.106 | N16: 2439.404 | O16: 3128.9 | P16: =参数输入表!G205 -> 0.06
B17: 3.4 | C17: 其他税费 | D17: =SUM(F17:O17) -> 3540.49 | E17: 万元 | H17: 658.09 | I17: 962.14 | J17: 910.13 | K17: 885.13 | L17: 125 | P17: =参数输入表!G206 -> 0
B18: 4 | C18: 基本预备费 | D18: =SUM(F18:O18) -> 38197.3 | E18: 万元 | F18: 1091.844 | G18: 2547.636 | H18: 3374.56 | I18: 4507.7 | J18: 5248.71 | K18: 7941.96 | L18: 6618.49 | M18: 3050.244 | N18: 2033.496 | O18: 1782.66 | P18: =参数输入表!G207 -> 0.09
B19: 5 | C19: 送出线路投资 | D19: =SUM(F19:O19) -> 0 | E19: 万元 | P19: =参数输入表!G208 -> 0
B20: 6 | C20: 储能投资（配储情形） | D20: =SUM(F20:O20) -> 6000 | E20: 万元 | F20: 150 | G20: 350 | H20: 800 | I20: 900 | J20: 600 | K20: 1100 | L20: 1000 | M20: 360 | N20: 240 | O20: 500 | P20: =参数输入表!G209 -> 0.13
B21: 7 | C21: 静态投资 | D21: =SUM(F21:O21) -> 810608.42 | E21: 万元 | F21: =F4+F12+F13+F18+F19+F20 -> 28514.733 | G21: =G4+G12+G13+G18+G19+G20 -> 66534.377 | H21: =H4+H12+H13+H18+H19+H20 -> 90984.75 | I21: =I4+I12+I13+I18+I19+I20 -> 101033.82 | J21: =J4+J12+J13+J18+J19+J20 -> 107918.6 | K21: =K4+K12+K13+K18+K19+K20 -> 139530.5 | L21: =L4+L12+L13+L18+L19+L20 -> 126118.92 | M21: =M4+M12+M13+M18+M19+M20 -> 62941.098 | ... O21: =O4+O12+O13+O18+O19+O20 -> 45070.89
B22: 8 | C22: 价差预备费 | D22: =SUM(F22:O22) -> 59365.53 | E22: 万元 | H22: 1427.17 | I22: 3854.21 | J22: 6784.25 | K22: 13798.93 | L22: 14466.02 | M22: 8081.352 | N22: 5387.568 | O22: 5566.03 | P22: =参数输入表!G212 -> 0.09
B23: 9 | C23: 建设投资 | D23: =SUM(F23:O23) -> 869973.95 | E23: 万元 | F23: =F21+F22 -> 28514.733 | G23: =G21+G22 -> 66534.377 | H23: =H21+H22 -> 92411.92 | I23: =I21+I22 -> 104888.03 | J23: =J21+J22 -> 114702.85 | K23: =K21+K22 -> 153329.43 | L23: =L21+L22 -> 140584.94 | M23: =M21+M22 -> 71022.45 | ... O23: =O21+O22 -> 50636.92
C24: 投资进度 | D24: =SUM(F24:O24) -> 1 | E24: 万元 | F24: =F23/$D$23 -> 0.032776537 | G24: =G23/$D$23 -> 0.076478585 | H24: =H23/$D$23 -> 0.10622378 | I24: =I23/$D$23 -> 0.12056456 | J24: =J23/$D$23 -> 0.1318463 | K24: =K23/$D$23 -> 0.176246 | L24: =L23/$D$23 -> 0.16159672 | M24: =M23/$D$23 -> 0.081637444 | ... O24: =O23/$D$23 -> 0.058205099
B26: 工程增值税进项税
B27: 序号 | C27: 科目 | D27: 合计 | E27: 单位 | F27: 45016 | G27: 2023 | H27: 2024 | I27: 2025 | J27: 2026 | K27: 2027 | L27: 2028 | M27: 47361 | N27: 2029 | O27: 47695
B28: 1 | C28: 枢纽工程 | D28: =SUM(F28:O28) -> 52707.795 | E28: 万元 | F28: =SUM(F29:F35) -> 1838.4434 | G28: =SUM(G29:G35) -> 4289.7012 | H28: =SUM(H29:H35) -> 5777.7036 | I28: =SUM(I29:I35) -> 6422.1341 | J28: =SUM(J29:J35) -> 7046.6367 | K28: =SUM(K29:K35) -> 9345.3572 | L28: =SUM(L29:L35) -> 8354.7396 | M28: =SUM(M29:M35) -> 4187.4885 | ... O28: =SUM(O29:O35) -> 2653.9316
B29: 1.1 | C29: 施工辅助工程 | D29: =SUM(F29:O29) -> 5201.2222 | E29: 万元 | F29: =F5/(1+$P$5)*$P$5 -> 364.32586 | G29: =G5/(1+$P$5)*$P$5 -> 850.09368 | H29: =H5/(1+$P$5)*$P$5 -> 1627.1108 | I29: =I5/(1+$P$5)*$P$5 -> 1314.8397 | J29: =J5/(1+$P$5)*$P$5 -> 455.96064 | K29: =K5/(1+$P$5)*$P$5 -> 132.19761 | L29: =L5/(1+$P$5)*$P$5 -> 128.4655 | M29: =M5/(1+$P$5)*$P$5 -> 126.30798 | ... O29: =O5/(1+$P$5)*$P$5 -> 117.71505
B30: 1.2 | C30: 建筑工程 | D30: =SUM(F30:O30) -> 27349.795 | E30: 万元 | F30: =F6/(1+$P$6)*$P$6 -> 1474.1175 | G30: =G6/(1+$P$6)*$P$6 -> 3439.6075 | H30: =H6/(1+$P$6)*$P$6 -> 3862.4846 | I30: =I6/(1+$P$6)*$P$6 -> 4551.3669 | J30: =J6/(1+$P$6)*$P$6 -> 5597.4237 | K30: =K6/(1+$P$6)*$P$6 -> 4374.7514 | L30: =L6/(1+$P$6)*$P$6 -> 2975.0565 | M30: =M6/(1+$P$6)*$P$6 -> 578.16809 | ... O30: =O6/(1+$P$6)*$P$6 -> 111.37376
B31: 1.3 | C31: 环境保护和水土保持专项工程 | D31: =SUM(F31:O31) -> 1477.478 | E31: 万元 | F31: =F7/(1+$P$7)*$P$7 -> 0 | G31: =G7/(1+$P$7)*$P$7 -> 0 | H31: =H7/(1+$P$7)*$P$7 -> 288.10817 | I31: =I7/(1+$P$7)*$P$7 -> 288.10817 | J31: =J7/(1+$P$7)*$P$7 -> 236.39615 | K31: =K7/(1+$P$7)*$P$7 -> 199.45982 | L31: =L7/(1+$P$7)*$P$7 -> 206.84725 | M31: =M7/(1+$P$7)*$P$7 -> 62.053927 | ... O31: =O7/(1+$P$7)*$P$7 -> 155.13523
B32: 1.4 | C32: 机电设备安装工程 | D32: =SUM(F32:O32) -> 5638.3101 | E32: 万元 | F32: =F8/(1+$P$8)*$P$8 -> 0 | G32: =G8/(1+$P$8)*$P$8 -> 0 | H32: =H8/(1+$P$8)*$P$8 -> 0 | I32: =I8/(1+$P$8)*$P$8 -> 267.81936 | J32: =J8/(1+$P$8)*$P$8 -> 267.81936 | K32: =K8/(1+$P$8)*$P$8 -> 1606.9186 | L32: =L8/(1+$P$8)*$P$8 -> 1099.4714 | M32: =M8/(1+$P$8)*$P$8 -> 1014.8958 | ... O32: =O8/(1+$P$8)*$P$8 -> 704.78835
B33: 1.5 | C33: 金属结构设备安装工程 | D33: =SUM(F33:O33) -> 13040.989 | E33: 万元 | F33: =F9/(1+$P$9)*$P$9 -> 0 | G33: =G9/(1+$P$9)*$P$9 -> 0 | H33: =H9/(1+$P$9)*$P$9 -> 0 | I33: =I9/(1+$P$9)*$P$9 -> 0 | J33: =J9/(1+$P$9)*$P$9 -> 489.03688 | K33: =K9/(1+$P$9)*$P$9 -> 3032.0298 | L33: =L9/(1+$P$9)*$P$9 -> 3944.899 | M33: =M9/(1+$P$9)*$P$9 -> 2406.0626 | ... O33: =O9/(1+$P$9)*$P$9 -> 1564.9192
B34: 1.6 | C34: 机电设备采购工程 | D34: =SUM(F34:O34) -> 0 | E34: 万元 | F34: =F10/(1+$P$10)*$P$10 -> 0 | G34: =G10/(1+$P$10)*$P$10 -> 0 | H34: =H10/(1+$P$10)*$P$10 -> 0 | I34: =I10/(1+$P$10)*$P$10 -> 0 | J34: =J10/(1+$P$10)*$P$10 -> 0 | K34: =K10/(1+$P$10)*$P$10 -> 0 | L34: =L10/(1+$P$10)*$P$10 -> 0 | M34: =M10/(1+$P$10)*$P$10 -> 0 | ... O34: =O10/(1+$P$10)*$P$10 -> 0
B35: 1.7 | C35: 金属结构设备采购工程 | D35: =SUM(F35:O35) -> 0 | E35: 万元 | F35: =F11/(1+$P$11)*$P$11 -> 0 | G35: =G11/(1+$P$11)*$P$11 -> 0 | H35: =H11/(1+$P$11)*$P$11 -> 0 | I35: =I11/(1+$P$11)*$P$11 -> 0 | J35: =J11/(1+$P$11)*$P$11 -> 0 | K35: =K11/(1+$P$11)*$P$11 -> 0 | L35: =L11/(1+$P$11)*$P$11 -> 0 | M35: =M11/(1+$P$11)*$P$11 -> 0 | ... O35: =O11/(1+$P$11)*$P$11 -> 0
B36: 2 | C36: 建设征地和移民安置补偿费用 | D36: =SUM(F36:O36) -> 0 | E36: 万元 | F36: =F12/(1+$P$12)*$P$12 -> 0 | G36: =G12/(1+$P$12)*$P$12 -> 0 | H36: =H12/(1+$P$12)*$P$12 -> 0 | I36: =I12/(1+$P$12)*$P$12 -> 0 | J36: =J12/(1+$P$12)*$P$12 -> 0 | K36: =K12/(1+$P$12)*$P$12 -> 0 | L36: =L12/(1+$P$12)*$P$12 -> 0 | M36: =M12/(1+$P$12)*$P$12 -> 0 | ... O36: =O12/(1+$P$12)*$P$12 -> 0
B37: 3 | C37: 独立费用 | D37: =SUM(F37:O37) -> 6300.7981 | E37: 万元 | F37: =SUM(F38:F41) -> 243.93804 | G37: =SUM(G38:G41) -> 569.18875 | H37: =SUM(H38:H41) -> 784.07208 | I37: =SUM(I38:I41) -> 936.93623 | J37: =SUM(J38:J41) -> 884.34 | K37: =SUM(K38:K41) -> 891.9283 | L37: =SUM(L38:L41) -> 935.48491 | M37: =SUM(M38:M41) -> 445.068 | ... O37: =SUM(O38:O41) -> 313.12981
B38: 3.1 | C38: 建设管理费 | D38: =SUM(F38:O38) -> 3074.9462 | E38: 万元 | F38: =F14/(1+$P$14)*$P$14 -> 75.483509 | G38: =G14/(1+$P$14)*$P$14 -> 176.12819 | H38: =H14/(1+$P$14)*$P$14 -> 361.23623 | I38: =I14/(1+$P$14)*$P$14 -> 468.8734 | J38: =J14/(1+$P$14)*$P$14 -> 400.46208 | K38: =K14/(1+$P$14)*$P$14 -> 524.11642 | L38: =L14/(1+$P$14)*$P$14 -> 536.04283 | M38: =M14/(1+$P$14)*$P$14 -> 237.94879 | ... O38: =O14/(1+$P$14)*$P$14 -> 136.02226
B39: 3.2 | C39: 生产准备费 | D39: =SUM(F39:O39) -> 0 | E39: 万元 | F39: =F15/(1+$P$15)*$P$15 -> 0 | G39: =G15/(1+$P$15)*$P$15 -> 0 | H39: =H15/(1+$P$15)*$P$15 -> 0 | I39: =I15/(1+$P$15)*$P$15 -> 0 | J39: =J15/(1+$P$15)*$P$15 -> 0 | K39: =K15/(1+$P$15)*$P$15 -> 0 | L39: =L15/(1+$P$15)*$P$15 -> 0 | M39: =M15/(1+$P$15)*$P$15 -> 0 | ... O39: =O15/(1+$P$15)*$P$15 -> 0
B40: 3.3 | C40: 科研勘查设计费 | D40: =SUM(F40:O40) -> 3225.8519 | E40: 万元 | F40: =F16/(1+$P$16)*$P$16 -> 168.45453 | G40: =G16/(1+$P$16)*$P$16 -> 393.06057 | H40: =H16/(1+$P$16)*$P$16 -> 422.83585 | I40: =I16/(1+$P$16)*$P$16 -> 468.06283 | J40: =J16/(1+$P$16)*$P$16 -> 483.87792 | K40: =K16/(1+$P$16)*$P$16 -> 367.81189 | L40: =L16/(1+$P$16)*$P$16 -> 399.44208 | M40: =M16/(1+$P$16)*$P$16 -> 207.11921 | ... O40: =O16/(1+$P$16)*$P$16 -> 177.10755
B41: 3.4 | C41: 其他税费 | D41: =SUM(F41:O41) -> 0 | E41: 万元 | F41: =F17/(1+$P$17)*$P$17 -> 0 | G41: =G17/(1+$P$17)*$P$17 -> 0 | H41: =H17/(1+$P$17)*$P$17 -> 0 | I41: =I17/(1+$P$17)*$P$17 -> 0 | J41: =J17/(1+$P$17)*$P$17 -> 0 | K41: =K17/(1+$P$17)*$P$17 -> 0 | L41: =L17/(1+$P$17)*$P$17 -> 0 | M41: =M17/(1+$P$17)*$P$17 -> 0 | ... O41: =O17/(1+$P$17)*$P$17 -> 0
B42: 4 | C42: 基本预备费 | D42: =SUM(F42:O42) -> 3153.9055 | E42: 万元 | F42: =F18/(1+$P$18)*$P$18 -> 90.152257 | G42: =G18/(1+$P$18)*$P$18 -> 210.35527 | H42: =H18/(1+$P$18)*$P$18 -> 278.63339 | I42: =I18/(1+$P$18)*$P$18 -> 372.19541 | J42: =J18/(1+$P$18)*$P$18 -> 433.37972 | K42: =K18/(1+$P$18)*$P$18 -> 655.75817 | L42: =L18/(1+$P$18)*$P$18 -> 546.48083 | M42: =M18/(1+$P$18)*$P$18 -> 251.85501 | ... O42: =O18/(1+$P$18)*$P$18 -> 147.19211
B43: 5 | C43: 储能投资（配储情形） | D43: =SUM(F43:O43) -> 0 | E43: 万元 | F43: =F19/(1+$P$19)*$P$19 -> 0 | G43: =G19/(1+$P$19)*$P$19 -> 0 | H43: =H19/(1+$P$19)*$P$19 -> 0 | I43: =I19/(1+$P$19)*$P$19 -> 0 | J43: =J19/(1+$P$19)*$P$19 -> 0 | K43: =K19/(1+$P$19)*$P$19 -> 0 | L43: =L19/(1+$P$19)*$P$19 -> 0 | M43: =M19/(1+$P$19)*$P$19 -> 0 | ... O43: =O19/(1+$P$19)*$P$19 -> 0
B44: 6 | C44: 配套支持资金 | D44: =SUM(F44:O44) -> 690.26549 | E44: 万元 | F44: =F20/(1+$P$20)*$P$20 -> 17.256637 | G44: =G20/(1+$P$20)*$P$20 -> 40.265487 | H44: =H20/(1+$P$20)*$P$20 -> 92.035398 | I44: =I20/(1+$P$20)*$P$20 -> 103.53982 | J44: =J20/(1+$P$20)*$P$20 -> 69.026549 | K44: =K20/(1+$P$20)*$P$20 -> 126.54867 | L44: =L20/(1+$P$20)*$P$20 -> 115.04425 | M44: =M20/(1+$P$20)*$P$20 -> 41.415929 | ... O44: =O20/(1+$P$20)*$P$20 -> 57.522124
B45: 7 | C45: 价差预备费 | D45: =SUM(F45:O45) -> 4901.741 | E45: 万元 | F45: =F22/(1+$P$22)*$P$22 -> 0 | G45: =G22/(1+$P$22)*$P$22 -> 0 | H45: =H22/(1+$P$22)*$P$22 -> 117.83972 | I45: =I22/(1+$P$22)*$P$22 -> 318.23752 | J45: =J22/(1+$P$22)*$P$22 -> 560.16743 | K45: =K22/(1+$P$22)*$P$22 -> 1139.3612 | L45: =L22/(1+$P$22)*$P$22 -> 1194.442 | M45: =M22/(1+$P$22)*$P$22 -> 667.2676 | ... O45: =O22/(1+$P$22)*$P$22 -> 459.58046
B46: 工程可抵扣进项税合计 | D46: =SUM(F46:O46) -> 67754.505 | E46: 万元 | F46: =F28+F36+F37+F42+F43+F44+F45 -> 2189.7903 | G46: =G28+G36+G37+G42+G43+G44+G45 -> 5109.5107 | H46: =H28+H36+H37+H42+H43+H44+H45 -> 7050.2842 | I46: =I28+I36+I37+I42+I43+I44+I45 -> 8153.0431 | J46: =J28+J36+J37+J42+J43+J44+J45 -> 8993.5504 | K46: =K28+K36+K37+K42+K43+K44+K45 -> 12158.954 | L46: =L28+L36+L37+L42+L43+L44+L45 -> 11146.192 | M46: =M28+M36+M37+M42+M43+M44+M45 -> 5593.095 | ... O46: =O28+O36+O37+O42+O43+O44+O45 -> 3631.3561
B47: 工程可抵扣进项税累计 | E47: 万元 | F47: =F46 -> 2189.7903 | G47: =F47+G46 -> 7299.301 | H47: =G47+H46 -> 14349.585 | I47: =H47+I46 -> 22502.628 | J47: =I47+J46 -> 31496.179 | K47: =J47+K46 -> 43655.132 | L47: =K47+L46 -> 54801.324 | M47: =L47+M46 -> 60394.419 | N47: =M47+N46 -> 64123.149 | O47: =N47+O46 -> 67754.505

Sheet 表1-资金筹措及还本付息表
B2: 资金筹措表 | F2: =时间序列!D5 -> 2 | G2: =时间序列!E5 -> 9 | H2: =时间序列!F5 -> 12 | I2: =时间序列!G5 -> 12 | J2: =时间序列!H5 -> 12 | K2: =时间序列!I5 -> 12 | L2: =时间序列!J5 -> 12 | M2: =时间序列!K5 -> 8 | ... BE2: =时间序列!BC5 -> 7
B3: 序号 | C3: 项目 | D3: 合计 | E3: 单位 | F3: 45016 | G3: 45291 | H3: 45657 | I3: 46022 | J3: 46387 | K3: 46752 | L3: 47118 | M3: 47361 | N3: 47483 | O3: 47695 | P3: =参数输入表!I250 -> 47726 | Q3: 47848 | R3: 48213 | S3: 48579 | T3: 48944 | U3: 49309 | V3: 49674 | W3: 50040 | X3: 50405 | Y3: 50770 | Z3: 51135 | AA3: 51501 | AB3: 51866 | AC3: 52231 | AD3: 52596 | AE3: 52962 | AF3: 53327 | AG3: 53692 | AH3: 54057 | AI3: 54423 | AJ3: 54788 | AK3: 55153 | AL3: 55518 | AM3: 55884 | AN3: 56249 | AO3: 56614 | AP3: 56979 | AQ3: 57345 | AR3: 57710 | AS3: 58075 | AT3: 58440 | AU3: 58806 | AV3: 59171 | AW3: 59536 | AX3: 59901 | AY3: 60267 | AZ3: 60632 | BA3: 60997 | BB3: 61362 | BC3: 61728 | BD3: 62093 | BE3: 62458
G4: 1 | H4: 2 | I4: 3 | J4: 4 | K4: 5 | L4: 6 | N4: 7 | Q4: 8 | R4: 9 | S4: 10 | T4: 11 | U4: 12 | V4: 13 | W4: 14 | X4: 15 | Y4: 16 | Z4: 17 | AA4: 18 | AB4: 19 | AC4: 20 | AD4: 21 | AE4: 22 | AF4: 23 | AG4: 24 | AH4: 25 | AI4: 26 | AJ4: 27 | AK4: 28 | AL4: 29 | AM4: 30 | AN4: 31 | AO4: 32 | AP4: 33 | AQ4: 34 | AR4: 35 | AS4: 36 | AT4: 37 | AU4: 38 | AV4: 39 | AW4: 40 | AX4: 41 | AY4: 42 | AZ4: 43 | BA4: 44 | BB4: 45 | BC4: 46 | BD4: 47 | BE4: 48
C5: 施工进度安排 | D5: =SUM(F5:BE5) -> 1 | F5: =参数输入表!I14 -> 0.032776537 | G5: =参数输入表!I15 -> 0.076478585 | H5: =参数输入表!I16 -> 0.10622378 | I5: =参数输入表!I17 -> 0.12056456 | J5: =参数输入表!I18 -> 0.1318463 | K5: =参数输入表!I19 -> 0.176246 | L5: =参数输入表!I20 -> 0.16159672 | M5: =参数输入表!I21 -> 0.081637444 | N5: =参数输入表!I22 -> 0.054424963 | O5: =参数输入表!I23 -> 0.058205099 | P5: 0 | Q5: 0 | R5: 0 | S5: 0 | T5: 0 | U5: 0 | V5: 0 | W5: 0 | X5: 0 | Y5: 0 | Z5: 0 | AA5: 0 | AB5: 0 | AC5: 0 | AD5: 0 | AE5: 0 | AF5: 0 | AG5: 0 | AH5: 0 | AI5: 0 | AJ5: 0 | AK5: 0 | AL5: 0 | AM5: 0 | AN5: 0 | AO5: 0 | AP5: 0 | AQ5: 0 | AR5: 0 | AS5: 0 | AT5: 0 | AU5: 0 | AV5: 0 | AW5: 0 | AX5: 0 | AY5: 0 | AZ5: 0 | BA5: 0 | BB5: 0 | BC5: 0 | BD5: 0 | BE5: 0
C6: 平均投产比例 | F6: ='投产&达产比例'!H10 -> 0 | G6: =AVERAGE('投产&达产比例'!H12:H20) -> 0 | H6: =AVERAGE('投产&达产比例'!H21:H32) -> 0 | I6: =AVERAGE('投产&达产比例'!H33:H44) -> 0 | J6: =AVERAGE('投产&达产比例'!H45:H56) -> 0 | K6: =AVERAGE('投产&达产比例'!H57:H68) -> 0 | L6: =AVERAGE('投产&达产比例'!H69:H80) -> 0 | M6: =AVERAGE('投产&达产比例'!H81:H88) -> 0 | N6: =AVERAGE('投产&达产比例'!H89:H92) -> 0 | O6: =AVERAGE('投产&达产比例'!H93:H99) -> 0 | P6: =AVERAGE('投产&达产比例'!H100:H101) -> 1 | Q6: =AVERAGE('投产&达产比例'!H102:H104) -> 1 | R6: =AVERAGE('投产&达产比例'!H105:H116) -> 1 | S6: =AVERAGE('投产&达产比例'!H117:H128) -> 1 | T6: =AVERAGE('投产&达产比例'!H129:H140) -> 1 | U6: =AVERAGE('投产&达产比例'!H141:H152) -> 1 | V6: =AVERAGE('投产&达产比例'!H153:H164) -> 1 | W6: =AVERAGE('投产&达产比例'!H165:H176) -> 1 | X6: =AVERAGE('投产&达产比例'!H177:H188) -> 1 | Y6: =AVERAGE('投产&达产比例'!H189:H200) -> 1 | Z6: =AVERAGE('投产&达产比例'!H201:H212) -> 1 | AA6: =AVERAGE('投产&达产比例'!H213:H224) -> 1 | AB6: =AVERAGE('投产&达产比例'!H225:H236) -> 1 | AC6: =AVERAGE('投产&达产比例'!H237:H248) -> 1 | AD6: =AVERAGE('投产&达产比例'!H249:H260) -> 1 | AE6: =AVERAGE('投产&达产比例'!H261:H272) -> 1 | AF6: =AVERAGE('投产&达产比例'!H273:H284) -> 1 | AG6: =AVERAGE('投产&达产比例'!H285:H296) -> 1 | AH6: =AVERAGE('投产&达产比例'!H297:H308) -> 1 | AI6: =AVERAGE('投产&达产比例'!H309:H320) -> 1 | AJ6: =AVERAGE('投产&达产比例'!H321:H332) -> 1 | AK6: =AVERAGE('投产&达产比例'!H333:H344) -> 1 | AL6: =AVERAGE('投产&达产比例'!H345:H356) -> 1 | AM6: =AVERAGE('投产&达产比例'!H357:H368) -> 1 | AN6: =AVERAGE('投产&达产比例'!H369:H380) -> 1 | AO6: =AVERAGE('投产&达产比例'!H381:H392) -> 1 | AP6: =AVERAGE('投产&达产比例'!H393:H404) -> 1 | AQ6: =AVERAGE('投产&达产比例'!H405:H416) -> 1 | AR6: =AVERAGE('投产&达产比例'!H417:H428) -> 1 | AS6: =AVERAGE('投产&达产比例'!H429:H440) -> 1 | AT6: =AVERAGE('投产&达产比例'!H441:H452) -> 1 | AU6: =AVERAGE('投产&达产比例'!H453:H464) -> 1 | AV6: =AVERAGE('投产&达产比例'!H465:H476) -> 1 | AW6: =AVERAGE('投产&达产比例'!H477:H488) -> 1 | AX6: =AVERAGE('投产&达产比例'!H489:H500) -> 1 | AY6: =AVERAGE('投产&达产比例'!H501:H512) -> 1 | AZ6: =AVERAGE('投产&达产比例'!H513:H524) -> 1 | BA6: =AVERAGE('投产&达产比例'!H525:H536) -> 1 | BB6: =AVERAGE('投产&达产比例'!H537:H548) -> 1 | BC6: =AVERAGE('投产&达产比例'!H549:H560) -> 1 | BD6: =AVERAGE('投产&达产比例'!H561:H572) -> 1 | BE6: =AVERAGE('投产&达产比例'!H573:H579) -> 1
B7: 1 | C7: 动态总投资（自主投资） | D7: =D8+D9+D35 -> 973381.77 | E7: 万元 | F7: =SUM(F8:F9)+F35 -> 28262.72 | G7: =SUM(G8:G9)+G35 -> 67248.597 | H7: =SUM(H8:H9)+H35 -> 95902.936 | I7: =SUM(I8:I9)+I35 -> 111527.37 | J7: =SUM(J8:J9)+J35 -> 124982.58 | K7: =SUM(K8:K9)+K35 -> 167811.54 | L7: =SUM(L8:L9)+L35 -> 160422.33 | M7: =SUM(M8:M9)+M35 -> 87218.189 | ... BE7: =SUM(BE8:BE9)+BE35 -> 0
B8: 1.1 | C8: 工程总投资（自主投资） | D8: =SUM(F8:BE8) -> 859973.95 | E8: 万元 | F8: =参数输入表!$I$214*F5 -> 28186.968 | G8: =参数输入表!$I$214*G5 -> 65769.591 | H8: =参数输入表!$I$214*H5 -> 91349.682 | I8: =参数输入表!$I$214*I5 -> 103682.38 | J8: =参数输入表!$I$214*J5 -> 113384.39 | K8: =参数输入表!$I$214*K5 -> 151566.97 | L8: =参数输入表!$I$214*L5 -> 138968.97 | M8: =参数输入表!$I$214*M5 -> 70206.076 | ... BE8: =参数输入表!$I$214*BE5 -> 0
B9: 1.2 | C9: 建设期利息（资本化） | D9: =SUM(F9:BE9) -> 106971.73 | E9: 万元 | F9: =SUM(F10:F21) -> 75.752476 | G9: =SUM(G10:G21) -> 1479.0055 | H9: =SUM(H10:H21) -> 4553.2536 | I9: =SUM(I10:I21) -> 7844.9881 | J9: =SUM(J10:J21) -> 11598.191 | K9: =SUM(K10:K21) -> 16244.573 | L9: =SUM(L10:L21) -> 21453.352 | M9: =SUM(M10:M21) -> 17012.114 | ... BE9: =SUM(BE10:BE21) -> 0
C10: 45016 | D10: =SUM(F10:BE10) -> 6759.8858 | E10: 万元 | F10: =IF(F3-参数输入表!$I$250<=0,IF($C$10-F3>=0,$F$42/2*(参数输入表!$I$251/12)*F2*(1-F6),($F$41-$F$44)*(参数输入表!$I$251/12)*F2*(1-F6)),0) -> 0 | G10: =IF(G3-参数输入表!$I$250<=0,IF($C$10-G3>=0,$F$42/2*(参数输入表!$I$251/12)*G2*(1-G6),($F$41-$F$44)*(参数输入表!$I$251/12)*G2*(1-G6)),0) -> 683.60454 | H10: =IF(H3-参数输入表!$I$250<=0,IF($C$10-H3>=0,$F$42/2*(参数输入表!$I$251/12)*H2*(1-H6),($F$41-$F$44)*(参数输入表!$I$251/12)*H2*(1-H6)),0) -> 911.47272 | I10: =IF(I3-参数输入表!$I$250<=0,IF($C$10-I3>=0,$F$42/2*(参数输入表!$I$251/12)*I2*(1-I6),($F$41-$F$44)*(参数输入表!$I$251/12)*I2*(1-I6)),0) -> 911.47272 | J10: =IF(J3-参数输入表!$I$250<=0,IF($C$10-J3>=0,$F$42/2*(参数输入表!$I$251/12)*J2*(1-J6),($F$41-$F$44)*(参数输入表!$I$251/12)*J2*(1-J6)),0) -> 911.47272 | K10: =IF(K3-参数输入表!$I$250<=0,IF($C$10-K3>=0,$F$42/2*(参数输入表!$I$251/12)*K2*(1-K6),($F$41-$F$44)*(参数输入表!$I$251/12)*K2*(1-K6)),0) -> 911.47272 | L10: =IF(L3-参数输入表!$I$250<=0,IF($C$10-L3>=0,$F$42/2*(参数输入表!$I$251/12)*L2*(1-L6),($F$41-$F$44)*(参数输入表!$I$251/12)*L2*(1-L6)),0) -> 911.47272 | M10: =IF(M3-参数输入表!$I$250<=0,IF($C$10-M3>=0,$F$42/2*(参数输入表!$I$251/12)*M2*(1-M6),($F$41-$F$44)*(参数输入表!$I$251/12)*M2*(1-M6)),0) -> 607.64848 | ... BE10: =IF(BE3-参数输入表!$I$250<=0,IF($C$10-BE3>=0,$F$42/2*(参数输入表!$I$251/12)*BE2*(1-BE6),($F$41-$F$44)*(参数输入表!$I$251/12)*BE2*(1-BE6)),0) -> 0
C11: 45291 | D11: =SUM(F11:BE11) -> 15073.119 | E11: 万元 | G11: =IF(G3-参数输入表!$I$250<=0,IF($C$11-G3>=0,$G$42/2*(参数输入表!$I$251/12)*G2*(1-G6),($G$41-$G$44)*(参数输入表!$I$251/12)*G2*(1-G6)),0) -> 795.40099 | H11: =IF(H3-参数输入表!$I$250<=0,IF($C$11-H3>=0,$G$42/2*(参数输入表!$I$251/12)*H2*(1-H6),($G$41-$G$44)*(参数输入表!$I$251/12)*H2*(1-H6)),0) -> 2168.7672 | I11: =IF(I3-参数输入表!$I$250<=0,IF($C$11-I3>=0,$G$42/2*(参数输入表!$I$251/12)*I2*(1-I6),($G$41-$G$44)*(参数输入表!$I$251/12)*I2*(1-I6)),0) -> 2168.7672 | J11: =IF(J3-参数输入表!$I$250<=0,IF($C$11-J3>=0,$G$42/2*(参数输入表!$I$251/12)*J2*(1-J6),($G$41-$G$44)*(参数输入表!$I$251/12)*J2*(1-J6)),0) -> 2168.7672 | K11: =IF(K3-参数输入表!$I$250<=0,IF($C$11-K3>=0,$G$42/2*(参数输入表!$I$251/12)*K2*(1-K6),($G$41-$G$44)*(参数输入表!$I$251/12)*K2*(1-K6)),0) -> 2168.7672 | L11: =IF(L3-参数输入表!$I$250<=0,IF($C$11-L3>=0,$G$42/2*(参数输入表!$I$251/12)*L2*(1-L6),($G$41-$G$44)*(参数输入表!$I$251/12)*L2*(1-L6)),0) -> 2168.7672 | M11: =IF(M3-参数输入表!$I$250<=0,IF($C$11-M3>=0,$G$42/2*(参数输入表!$I$251/12)*M2*(1-M6),($G$41-$G$44)*(参数输入表!$I$251/12)*M2*(1-M6)),0) -> 1445.8448 | N11: =IF(N3-参数输入表!$I$250<=0,IF($C$11-N3>=0,$G$42/2*(参数输入表!$I$251/12)*N2*(1-N6),($G$41-$G$44)*(参数输入表!$I$251/12)*N2*(1-N6)),0) -> 722.92241 | ... BE11: =IF(BE3-参数输入表!$I$250<=0,IF($C$11-BE3>=0,$G$42/2*(参数输入表!$I$251/12)*BE2*(1-BE6),($G$41-$G$44)*(参数输入表!$I$251/12)*BE2*(1-BE6)),0) -> 0
C12: 45657 | D12: =SUM(F12:BE12) -> 18741.536 | E12: 万元 | H12: =IF(H3-参数输入表!$I$250<=0,IF($C$12-H3>=0,$H$42/2*(参数输入表!$I$251/12)*H2*(1-H6),($H$41-$H$44)*(参数输入表!$I$251/12)*H2*(1-H6)),0) -> 1473.0136 | I12: =IF(I3-参数输入表!$I$250<=0,IF($C$12-I3>=0,$H$42/2*(参数输入表!$I$251/12)*I2*(1-I6),($H$41-$H$44)*(参数输入表!$I$251/12)*I2*(1-I6)),0) -> 3092.8697 | J12: =IF(J3-参数输入表!$I$250<=0,IF($C$12-J3>=0,$H$42/2*(参数输入表!$I$251/12)*J2*(1-J6),($H$41-$H$44)*(参数输入表!$I$251/12)*J2*(1-J6)),0) -> 3092.8697 | K12: =IF(K3-参数输入表!$I$250<=0,IF($C$12-K3>=0,$H$42/2*(参数输入表!$I$251/12)*K2*(1-K6),($H$41-$H$44)*(参数输入表!$I$251/12)*K2*(1-K6)),0) -> 3092.8697 | L12: =IF(L3-参数输入表!$I$250<=0,IF($C$12-L3>=0,$H$42/2*(参数输入表!$I$251/12)*L2*(1-L6),($H$41-$H$44)*(参数输入表!$I$251/12)*L2*(1-L6)),0) -> 3092.8697 | M12: =IF(M3-参数输入表!$I$250<=0,IF($C$12-M3>=0,$H$42/2*(参数输入表!$I$251/12)*M2*(1-M6),($H$41-$H$44)*(参数输入表!$I$251/12)*M2*(1-M6)),0) -> 2061.9131 | N12: =IF(N3-参数输入表!$I$250<=0,IF($C$12-N3>=0,$H$42/2*(参数输入表!$I$251/12)*N2*(1-N6),($H$41-$H$44)*(参数输入表!$I$251/12)*N2*(1-N6)),0) -> 1030.9566 | O12: =IF(O3-参数输入表!$I$250<=0,IF($C$12-O3>=0,$H$42/2*(参数输入表!$I$251/12)*O2*(1-O6),($H$41-$H$44)*(参数输入表!$I$251/12)*O2*(1-O6)),0) -> 1804.174 | ... BE12: =IF(BE3-参数输入表!$I$250<=0,IF($C$12-BE3>=0,$H$42/2*(参数输入表!$I$251/12)*BE2*(1-BE6),($H$41-$H$44)*(参数输入表!$I$251/12)*BE2*(1-BE6)),0) -> 0
C13: 46022 | D13: =SUM(F13:BE13) -> 18157.018 | E13: 万元 | I13: =IF(I3-参数输入表!$I$250<=0,IF($C$13-I3>=0,$I$42/2*(参数输入表!$I$251/12)*I2*(1-I6),($I$41-$I$44)*(参数输入表!$I$251/12)*I2*(1-I6)),0) -> 1671.8784 | J13: =IF(J3-参数输入表!$I$250<=0,IF($C$13-J3>=0,$I$42/2*(参数输入表!$I$251/12)*J2*(1-J6),($I$41-$I$44)*(参数输入表!$I$251/12)*J2*(1-J6)),0) -> 3596.7578 | K13: =IF(K3-参数输入表!$I$250<=0,IF($C$13-K3>=0,$I$42/2*(参数输入表!$I$251/12)*K2*(1-K6),($I$41-$I$44)*(参数输入表!$I$251/12)*K2*(1-K6)),0) -> 3596.7578 | L13: =IF(L3-参数输入表!$I$250<=0,IF($C$13-L3>=0,$I$42/2*(参数输入表!$I$251/12)*L2*(1-L6),($I$41-$I$44)*(参数输入表!$I$251/12)*L2*(1-L6)),0) -> 3596.7578 | M13: =IF(M3-参数输入表!$I$250<=0,IF($C$13-M3>=0,$I$42/2*(参数输入表!$I$251/12)*M2*(1-M6),($I$41-$I$44)*(参数输入表!$I$251/12)*M2*(1-M6)),0) -> 2397.8385 | N13: =IF(N3-参数输入表!$I$250<=0,IF($C$13-N3>=0,$I$42/2*(参数输入表!$I$251/12)*N2*(1-N6),($I$41-$I$44)*(参数输入表!$I$251/12)*N2*(1-N6)),0) -> 1198.9193 | O13: =IF(O3-参数输入表!$I$250<=0,IF($C$13-O3>=0,$I$42/2*(参数输入表!$I$251/12)*O2*(1-O6),($I$41-$I$44)*(参数输入表!$I$251/12)*O2*(1-O6)),0) -> 2098.1087 | P13: =IF(P3-参数输入表!$I$250<=0,IF($C$13-P3>=0,$I$42/2*(参数输入表!$I$251/12)*P2*(1-P6),($I$41-$I$44)*(参数输入表!$I$251/12)*P2*(1-P6)),0) -> 0 | ... BE13: =IF(BE3-参数输入表!$I$250<=0,IF($C$13-BE3>=0,$I$42/2*(参数输入表!$I$251/12)*BE2*(1-BE6),($I$41-$I$44)*(参数输入表!$I$251/12)*BE2*(1-BE6)),0) -> 0
C14: 46387 | D14: =SUM(F14:BE14) -> 16271.622 | E14: 万元 | J14: =IF(J3-参数输入表!$I$250<=0,IF($C$14-J3>=0,$J$42/2*(参数输入表!$I$251/12)*J2*(1-J6),($J$41-$J$44)*(参数输入表!$I$251/12)*J2*(1-J6)),0) -> 1828.3232 | K14: =IF(K3-参数输入表!$I$250<=0,IF($C$14-K3>=0,$J$42/2*(参数输入表!$I$251/12)*K2*(1-K6),($J$41-$J$44)*(参数输入表!$I$251/12)*K2*(1-K6)),0) -> 4030.6881 | L14: =IF(L3-参数输入表!$I$250<=0,IF($C$14-L3>=0,$J$42/2*(参数输入表!$I$251/12)*L2*(1-L6),($J$41-$J$44)*(参数输入表!$I$251/12)*L2*(1-L6)),0) -> 4030.6881 | M14: =IF(M3-参数输入表!$I$250<=0,IF($C$14-M3>=0,$J$42/2*(参数输入表!$I$251/12)*M2*(1-M6),($J$41-$J$44)*(参数输入表!$I$251/12)*M2*(1-M6)),0) -> 2687.1254 | N14: =IF(N3-参数输入表!$I$250<=0,IF($C$14-N3>=0,$J$42/2*(参数输入表!$I$251/12)*N2*(1-N6),($J$41-$J$44)*(参数输入表!$I$251/12)*N2*(1-N6)),0) -> 1343.5627 | O14: =IF(O3-参数输入表!$I$250<=0,IF($C$14-O3>=0,$J$42/2*(参数输入表!$I$251/12)*O2*(1-O6),($J$41-$J$44)*(参数输入表!$I$251/12)*O2*(1-O6)),0) -> 2351.2347 | P14: =IF(P3-参数输入表!$I$250<=0,IF($C$14-P3>=0,$J$42/2*(参数输入表!$I$251/12)*P2*(1-P6),($J$41-$J$44)*(参数输入表!$I$251/12)*P2*(1-P6)),0) -> 0 | Q14: =IF(Q3-参数输入表!$I$250<=0,IF($C$14-Q3>=0,$J$42/2*(参数输入表!$I$251/12)*Q2*(1-Q6),($J$41-$J$44)*(参数输入表!$I$251/12)*Q2*(1-Q6)),0) -> 0 | ... BE14: =IF(BE3-参数输入表!$I$250<=0,IF($C$14-BE3>=0,$J$42/2*(参数输入表!$I$251/12)*BE2*(1-BE6),($J$41-$J$44)*(参数输入表!$I$251/12)*BE2*(1-BE6)),0) -> 0
C15: 46752 | D15: =SUM(F15:BE15) -> 16424.817 | E15: 万元 | K15: =IF(K3-参数输入表!$I$250<=0,IF($C$15-K3>=0,$K$42/2*(参数输入表!$I$251/12)*K2*(1-K6),($K$41-$K$44)*(参数输入表!$I$251/12)*K2*(1-K6)),0) -> 2444.0174 | L15: =IF(L3-参数输入表!$I$250<=0,IF($C$15-L3>=0,$K$42/2*(参数输入表!$I$251/12)*L2*(1-L6),($K$41-$K$44)*(参数输入表!$I$251/12)*L2*(1-L6)),0) -> 5411.9223 | M15: =IF(M3-参数输入表!$I$250<=0,IF($C$15-M3>=0,$K$42/2*(参数输入表!$I$251/12)*M2*(1-M6),($K$41-$K$44)*(参数输入表!$I$251/12)*M2*(1-M6)),0) -> 3607.9482 | N15: =IF(N3-参数输入表!$I$250<=0,IF($C$15-N3>=0,$K$42/2*(参数输入表!$I$251/12)*N2*(1-N6),($K$41-$K$44)*(参数输入表!$I$251/12)*N2*(1-N6)),0) -> 1803.9741 | O15: =IF(O3-参数输入表!$I$250<=0,IF($C$15-O3>=0,$K$42/2*(参数输入表!$I$251/12)*O2*(1-O6),($K$41-$K$44)*(参数输入表!$I$251/12)*O2*(1-O6)),0) -> 3156.9547 | P15: =IF(P3-参数输入表!$I$250<=0,IF($C$15-P3>=0,$K$42/2*(参数输入表!$I$251/12)*P2*(1-P6),($K$41-$K$44)*(参数输入表!$I$251/12)*P2*(1-P6)),0) -> 0 | Q15: =IF(Q3-参数输入表!$I$250<=0,IF($C$15-Q3>=0,$K$42/2*(参数输入表!$I$251/12)*Q2*(1-Q6),($K$41-$K$44)*(参数输入表!$I$251/12)*Q2*(1-Q6)),0) -> 0 | R15: =IF(R3-参数输入表!$I$250<=0,IF($C$15-R3>=0,$K$42/2*(参数输入表!$I$251/12)*R2*(1-R6),($K$41-$K$44)*(参数输入表!$I$251/12)*R2*(1-R6)),0) -> 0 | ... BE15: =IF(BE3-参数输入表!$I$250<=0,IF($C$15-BE3>=0,$K$42/2*(参数输入表!$I$251/12)*BE2*(1-BE6),($K$41-$K$44)*(参数输入表!$I$251/12)*BE2*(1-BE6)),0) -> 0
C16: 47118 | D16: =SUM(F16:BE16) -> 10432.44 | E16: 万元 | L16: =IF(L3-参数输入表!$I$250<=0,IF($C$16-L3>=0,$L$42/2*(参数输入表!$I$251/12)*L2*(1-L6),($L$41-$L$44)*(参数输入表!$I$251/12)*L2*(1-L6)),0) -> 2240.8747 | M16: =IF(M3-参数输入表!$I$250<=0,IF($C$16-M3>=0,$L$42/2*(参数输入表!$I$251/12)*M2*(1-M6),($L$41-$L$44)*(参数输入表!$I$251/12)*M2*(1-M6)),0) -> 3449.08 | N16: =IF(N3-参数输入表!$I$250<=0,IF($C$16-N3>=0,$L$42/2*(参数输入表!$I$251/12)*N2*(1-N6),($L$41-$L$44)*(参数输入表!$I$251/12)*N2*(1-N6)),0) -> 1724.54 | O16: =IF(O3-参数输入表!$I$250<=0,IF($C$16-O3>=0,$L$42/2*(参数输入表!$I$251/12)*O2*(1-O6),($L$41-$L$44)*(参数输入表!$I$251/12)*O2*(1-O6)),0) -> 3017.945 | P16: =IF(P3-参数输入表!$I$250<=0,IF($C$16-P3>=0,$L$42/2*(参数输入表!$I$251/12)*P2*(1-P6),($L$41-$L$44)*(参数输入表!$I$251/12)*P2*(1-P6)),0) -> 0 | Q16: =IF(Q3-参数输入表!$I$250<=0,IF($C$16-Q3>=0,$L$42/2*(参数输入表!$I$251/12)*Q2*(1-Q6),($L$41-$L$44)*(参数输入表!$I$251/12)*Q2*(1-Q6)),0) -> 0 | R16: =IF(R3-参数输入表!$I$250<=0,IF($C$16-R3>=0,$L$42/2*(参数输入表!$I$251/12)*R2*(1-R6),($L$41-$L$44)*(参数输入表!$I$251/12)*R2*(1-R6)),0) -> 0 | S16: =IF(S3-参数输入表!$I$250<=0,IF($C$16-S3>=0,$L$42/2*(参数输入表!$I$251/12)*S2*(1-S6),($L$41-$L$44)*(参数输入表!$I$251/12)*S2*(1-S6)),0) -> 0 | ... BE16: =IF(BE3-参数输入表!$I$250<=0,IF($C$16-BE3>=0,$L$42/2*(参数输入表!$I$251/12)*BE2*(1-BE6),($L$41-$L$44)*(参数输入表!$I$251/12)*BE2*(1-BE6)),0) -> 0
C17: 47361 | D17: =SUM(F17:BE17) -> 3333.103 | E17: 万元 | M17: =IF(M3-参数输入表!$I$250<=0,IF($C$17-M3>=0,$M$42/2*(参数输入表!$I$251/12)*M2*(1-M6),($M$41-$M$44)*(参数输入表!$I$251/12)*M2*(1-M6)),0) -> 754.71531 | N17: =IF(N3-参数输入表!$I$250<=0,IF($C$17-N3>=0,$M$42/2*(参数输入表!$I$251/12)*N2*(1-N6),($M$41-$M$44)*(参数输入表!$I$251/12)*N2*(1-N6)),0) -> 937.59554 | O17: =IF(O3-参数输入表!$I$250<=0,IF($C$17-O3>=0,$M$42/2*(参数输入表!$I$251/12)*O2*(1-O6),($M$41-$M$44)*(参数输入表!$I$251/12)*O2*(1-O6)),0) -> 1640.7922 | P17: =IF(P3-参数输入表!$I$250<=0,IF($C$17-P3>=0,$M$42/2*(参数输入表!$I$251/12)*P2*(1-P6),($M$41-$M$44)*(参数输入表!$I$251/12)*P2*(1-P6)),0) -> 0 | Q17: =IF(Q3-参数输入表!$I$250<=0,IF($C$17-Q3>=0,$M$42/2*(参数输入表!$I$251/12)*Q2*(1-Q6),($M$41-$M$44)*(参数输入表!$I$251/12)*Q2*(1-Q6)),0) -> 0 | R17: =IF(R3-参数输入表!$I$250<=0,IF($C$17-R3>=0,$M$42/2*(参数输入表!$I$251/12)*R2*(1-R6),($M$41-$M$44)*(参数输入表!$I$251/12)*R2*(1-R6)),0) -> 0 | S17: =IF(S3-参数输入表!$I$250<=0,IF($C$17-S3>=0,$M$42/2*(参数输入表!$I$251/12)*S2*(1-S6),($M$41-$M$44)*(参数输入表!$I$251/12)*S2*(1-S6)),0) -> 0 | T17: =IF(T3-参数输入表!$I$250<=0,IF($C$17-T3>=0,$M$42/2*(参数输入表!$I$251/12)*T2*(1-T6),($M$41-$M$44)*(参数输入表!$I$251/12)*T2*(1-T6)),0) -> 0 | ... BE17: =IF(BE3-参数输入表!$I$250<=0,IF($C$17-BE3>=0,$M$42/2*(参数输入表!$I$251/12)*BE2*(1-BE6),($M$41-$M$44)*(参数输入表!$I$251/12)*BE2*(1-BE6)),0) -> 0
C18: 47483 | D18: =SUM(F18:BE18) -> 1307.3653 | E18: 万元 | N18: =IF(N3-参数输入表!$I$250<=0,IF($C$18-N3>=0,$N$42/2*(参数输入表!$I$251/12)*N2*(1-N6),($N$41-$N$44)*(参数输入表!$I$251/12)*N2*(1-N6)),0) -> 251.57177 | O18: =IF(O3-参数输入表!$I$250<=0,IF($C$18-O3>=0,$N$42/2*(参数输入表!$I$251/12)*O2*(1-O6),($N$41-$N$44)*(参数输入表!$I$251/12)*O2*(1-O6)),0) -> 1055.7936 | P18: =IF(P3-参数输入表!$I$250<=0,IF($C$18-P3>=0,$N$42/2*(参数输入表!$I$251/12)*P2*(1-P6),($N$41-$N$44)*(参数输入表!$I$251/12)*P2*(1-P6)),0) -> 0 | Q18: =IF(Q3-参数输入表!$I$250<=0,IF($C$18-Q3>=0,$N$42/2*(参数输入表!$I$251/12)*Q2*(1-Q6),($N$41-$N$44)*(参数输入表!$I$251/12)*Q2*(1-Q6)),0) -> 0 | R18: =IF(R3-参数输入表!$I$250<=0,IF($C$18-R3>=0,$N$42/2*(参数输入表!$I$251/12)*R2*(1-R6),($N$41-$N$44)*(参数输入表!$I$251/12)*R2*(1-R6)),0) -> 0 | S18: =IF(S3-参数输入表!$I$250<=0,IF($C$18-S3>=0,$N$42/2*(参数输入表!$I$251/12)*S2*(1-S6),($N$41-$N$44)*(参数输入表!$I$251/12)*S2*(1-S6)),0) -> 0 | T18: =IF(T3-参数输入表!$I$250<=0,IF($C$18-T3>=0,$N$42/2*(参数输入表!$I$251/12)*T2*(1-T6),($N$41-$N$44)*(参数输入表!$I$251/12)*T2*(1-T6)),0) -> 0 | U18: =IF(U3-参数输入表!$I$250<=0,IF($C$18-U3>=0,$N$42/2*(参数输入表!$I$251/12)*U2*(1-U6),($N$41-$N$44)*(参数输入表!$I$251/12)*U2*(1-U6)),0) -> 0 | ... BE18: =IF(BE3-参数输入表!$I$250<=0,IF($C$18-BE3>=0,$N$42/2*(参数输入表!$I$251/12)*BE2*(1-BE6),($N$41-$N$44)*(参数输入表!$I$251/12)*BE2*(1-BE6)),0) -> 0
C19: 47695 | D19: =SUM(F19:BE19) -> 470.82861 | E19: 万元 | O19: =IF(O3-参数输入表!$I$250<=0,IF($C$19-O3>=0,$O$42/2*(参数输入表!$I$251/12)*O2*(1-O6),($O$41-$O$44)*(参数输入表!$I$251/12)*O2*(1-O6)),0) -> 470.82861 | P19: =IF(P3-参数输入表!$I$250<=0,IF($C$19-P3>=0,$O$42/2*(参数输入表!$I$251/12)*P2*(1-P6),($O$41-$O$44)*(参数输入表!$I$251/12)*P2*(1-P6)),0) -> 0 | Q19: =IF(Q3-参数输入表!$I$250<=0,IF($C$19-Q3>=0,$O$42/2*(参数输入表!$I$251/12)*Q2*(1-Q6),($O$41-$O$44)*(参数输入表!$I$251/12)*Q2*(1-Q6)),0) -> 0 | R19: =IF(R3-参数输入表!$I$250<=0,IF($C$19-R3>=0,$O$42/2*(参数输入表!$I$251/12)*R2*(1-R6),($O$41-$O$44)*(参数输入表!$I$251/12)*R2*(1-R6)),0) -> 0 | S19: =IF(S3-参数输入表!$I$250<=0,IF($C$19-S3>=0,$O$42/2*(参数输入表!$I$251/12)*S2*(1-S6),($O$41-$O$44)*(参数输入表!$I$251/12)*S2*(1-S6)),0) -> 0 | T19: =IF(T3-参数输入表!$I$250<=0,IF($C$19-T3>=0,$O$42/2*(参数输入表!$I$251/12)*T2*(1-T6),($O$41-$O$44)*(参数输入表!$I$251/12)*T2*(1-T6)),0) -> 0 | U19: =IF(U3-参数输入表!$I$250<=0,IF($C$19-U3>=0,$O$42/2*(参数输入表!$I$251/12)*U2*(1-U6),($O$41-$O$44)*(参数输入表!$I$251/12)*U2*(1-U6)),0) -> 0 | V19: =IF(V3-参数输入表!$I$250<=0,IF($C$19-V3>=0,$O$42/2*(参数输入表!$I$251/12)*V2*(1-V6),($O$41-$O$44)*(参数输入表!$I$251/12)*V2*(1-V6)),0) -> 0 | ... BE19: =IF(BE3-参数输入表!$I$250<=0,IF($C$19-BE3>=0,$O$42/2*(参数输入表!$I$251/12)*BE2*(1-BE6),($O$41-$O$44)*(参数输入表!$I$251/12)*BE2*(1-BE6)),0) -> 0
C20: =P3 -> 47726 | D20: =SUM(F20:BE20) -> 0 | E20: 万元 | P20: =IF(P3-参数输入表!$I$250<=0,IF($C$20-P3>=0,$P$42/2*(参数输入表!$I$251/12)*P2*(1-P6),($P$41-$P$44)*(参数输入表!$I$251/12)*P2*(1-P6)),0) -> 0 | Q20: =IF(Q3-参数输入表!$I$250<=0,IF($C$20-Q3>=0,$P$42/2*(参数输入表!$I$251/12)*Q2*(1-Q6),($P$41-$P$44)*(参数输入表!$I$251/12)*Q2*(1-Q6)),0) -> 0 | R20: =IF(R3-参数输入表!$I$250<=0,IF($C$20-R3>=0,$P$42/2*(参数输入表!$I$251/12)*R2*(1-R6),($P$41-$P$44)*(参数输入表!$I$251/12)*R2*(1-R6)),0) -> 0 | S20: =IF(S3-参数输入表!$I$250<=0,IF($C$20-S3>=0,$P$42/2*(参数输入表!$I$251/12)*S2*(1-S6),($P$41-$P$44)*(参数输入表!$I$251/12)*S2*(1-S6)),0) -> 0 | T20: =IF(T3-参数输入表!$I$250<=0,IF($C$20-T3>=0,$P$42/2*(参数输入表!$I$251/12)*T2*(1-T6),($P$41-$P$44)*(参数输入表!$I$251/12)*T2*(1-T6)),0) -> 0 | U20: =IF(U3-参数输入表!$I$250<=0,IF($C$20-U3>=0,$P$42/2*(参数输入表!$I$251/12)*U2*(1-U6),($P$41-$P$44)*(参数输入表!$I$251/12)*U2*(1-U6)),0) -> 0 | V20: =IF(V3-参数输入表!$I$250<=0,IF($C$20-V3>=0,$P$42/2*(参数输入表!$I$251/12)*V2*(1-V6),($P$41-$P$44)*(参数输入表!$I$251/12)*V2*(1-V6)),0) -> 0 | W20: =IF(W3-参数输入表!$I$250<=0,IF($C$20-W3>=0,$P$42/2*(参数输入表!$I$251/12)*W2*(1-W6),($P$41-$P$44)*(参数输入表!$I$251/12)*W2*(1-W6)),0) -> 0 | ... BE20: =IF(BE3-参数输入表!$I$250<=0,IF($C$20-BE3>=0,$P$42/2*(参数输入表!$I$251/12)*BE2*(1-BE6),($P$41-$P$44)*(参数输入表!$I$251/12)*BE2*(1-BE6)),0) -> 0
C21: 47848 | D21: =SUM(F21:BE21) -> 0 | E21: 万元 | Q21: =IF(Q3-参数输入表!$I$250<=0,IF($C$21-Q3>=0,$Q$42/2*(参数输入表!$I$251/12)*Q2*(1-Q6),($Q$41-$Q$44)*(参数输入表!$I$251/12)*Q2*(1-Q6)),0) -> 0 | R21: =IF(R3-参数输入表!$I$250<=0,IF($C$21-R3>=0,$Q$42/2*(参数输入表!$I$251/12)*R2*(1-R6),($Q$41-$Q$44)*(参数输入表!$I$251/12)*R2*(1-R6)),0) -> 0 | S21: =IF(S3-参数输入表!$I$250<=0,IF($C$21-S3>=0,$Q$42/2*(参数输入表!$I$251/12)*S2*(1-S6),($Q$41-$Q$44)*(参数输入表!$I$251/12)*S2*(1-S6)),0) -> 0 | T21: =IF(T3-参数输入表!$I$250<=0,IF($C$21-T3>=0,$Q$42/2*(参数输入表!$I$251/12)*T2*(1-T6),($Q$41-$Q$44)*(参数输入表!$I$251/12)*T2*(1-T6)),0) -> 0 | U21: =IF(U3-参数输入表!$I$250<=0,IF($C$21-U3>=0,$Q$42/2*(参数输入表!$I$251/12)*U2*(1-U6),($Q$41-$Q$44)*(参数输入表!$I$251/12)*U2*(1-U6)),0) -> 0 | V21: =IF(V3-参数输入表!$I$250<=0,IF($C$21-V3>=0,$Q$42/2*(参数输入表!$I$251/12)*V2*(1-V6),($Q$41-$Q$44)*(参数输入表!$I$251/12)*V2*(1-V6)),0) -> 0 | W21: =IF(W3-参数输入表!$I$250<=0,IF($C$21-W3>=0,$Q$42/2*(参数输入表!$I$251/12)*W2*(1-W6),($Q$41-$Q$44)*(参数输入表!$I$251/12)*W2*(1-W6)),0) -> 0 | X21: =IF(X3-参数输入表!$I$250<=0,IF($C$21-X3>=0,$Q$42/2*(参数输入表!$I$251/12)*X2*(1-X6),($Q$41-$Q$44)*(参数输入表!$I$251/12)*X2*(1-X6)),0) -> 0 | ... BE21: =IF(BE3-参数输入表!$I$250<=0,IF($C$21-BE3>=0,$Q$42/2*(参数输入表!$I$251/12)*BE2*(1-BE6),($Q$41-$Q$44)*(参数输入表!$I$251/12)*BE2*(1-BE6)),0) -> 0
C22: 应计利息（隐藏） | D22: =SUM(F22:BE22) -> 109570.4 | E22: 万元 | F22: =SUM(F23:F34) -> 75.752476 | G22: =SUM(G23:G34) -> 1479.0055 | H22: =SUM(H23:H34) -> 4553.2536 | I22: =SUM(I23:I34) -> 7844.9881 | J22: =SUM(J23:J34) -> 11598.191 | K22: =SUM(K23:K34) -> 16244.573 | L22: =SUM(L23:L34) -> 21453.352 | M22: =SUM(M23:M34) -> 17012.114 | ... BE22: =SUM(BE23:BE34) -> 0
C23: 45016 | D23: =SUM(F23:BE23) -> 6835.8418 | E23: 万元 | F23: =IF(F3-参数输入表!$I$250<=0,IF($C$23-F3>=0,$F$42/2*(参数输入表!$I$251/12)*F2,($F$41-$F$44)*(参数输入表!$I$251/12)*F2),0) -> 75.752476 | G23: =IF(G3-参数输入表!$I$250<=0,IF($C$23-G3>=0,$F$42/2*(参数输入表!$I$251/12)*G2,($F$41-$F$44)*(参数输入表!$I$251/12)*G2),0) -> 683.60454 | H23: =IF(H3-参数输入表!$I$250<=0,IF($C$23-H3>=0,$F$42/2*(参数输入表!$I$251/12)*H2,($F$41-$F$44)*(参数输入表!$I$251/12)*H2),0) -> 911.47272 | I23: =IF(I3-参数输入表!$I$250<=0,IF($C$23-I3>=0,$F$42/2*(参数输入表!$I$251/12)*I2,($F$41-$F$44)*(参数输入表!$I$251/12)*I2),0) -> 911.47272 | J23: =IF(J3-参数输入表!$I$250<=0,IF($C$23-J3>=0,$F$42/2*(参数输入表!$I$251/12)*J2,($F$41-$F$44)*(参数输入表!$I$251/12)*J2),0) -> 911.47272 | K23: =IF(K3-参数输入表!$I$250<=0,IF($C$23-K3>=0,$F$42/2*(参数输入表!$I$251/12)*K2,($F$41-$F$44)*(参数输入表!$I$251/12)*K2),0) -> 911.47272 | L23: =IF(L3-参数输入表!$I$250<=0,IF($C$23-L3>=0,$F$42/2*(参数输入表!$I$251/12)*L2,($F$41-$F$44)*(参数输入表!$I$251/12)*L2),0) -> 911.47272 | M23: =IF(M3-参数输入表!$I$250<=0,IF($C$23-M3>=0,$F$42/2*(参数输入表!$I$251/12)*M2,($F$41-$F$44)*(参数输入表!$I$251/12)*M2),0) -> 607.64848 | ... BE23: =IF(BE3-参数输入表!$I$250<=0,IF($C$23-BE3>=0,$F$42/2*(参数输入表!$I$251/12)*BE2,($F$41-$F$44)*(参数输入表!$I$251/12)*BE2),0) -> 0
C24: 45291 | D24: =SUM(F24:BE24) -> 15253.849 | E24: 万元 | G24: =IF(G3-参数输入表!$I$250<=0,IF($C$24-G3>=0,$G$42/2*(参数输入表!$I$251/12)*G2,($G$41-$G$44)*(参数输入表!$I$251/12)*G2),0) -> 795.40099 | H24: =IF(H3-参数输入表!$I$250<=0,IF($C$24-H3>=0,$G$42/2*(参数输入表!$I$251/12)*H2,($G$41-$G$44)*(参数输入表!$I$251/12)*H2),0) -> 2168.7672 | I24: =IF(I3-参数输入表!$I$250<=0,IF($C$24-I3>=0,$G$42/2*(参数输入表!$I$251/12)*I2,($G$41-$G$44)*(参数输入表!$I$251/12)*I2),0) -> 2168.7672 | J24: =IF(J3-参数输入表!$I$250<=0,IF($C$24-J3>=0,$G$42/2*(参数输入表!$I$251/12)*J2,($G$41-$G$44)*(参数输入表!$I$251/12)*J2),0) -> 2168.7672 | K24: =IF(K3-参数输入表!$I$250<=0,IF($C$24-K3>=0,$G$42/2*(参数输入表!$I$251/12)*K2,($G$41-$G$44)*(参数输入表!$I$251/12)*K2),0) -> 2168.7672 | L24: =IF(L3-参数输入表!$I$250<=0,IF($C$24-L3>=0,$G$42/2*(参数输入表!$I$251/12)*L2,($G$41-$G$44)*(参数输入表!$I$251/12)*L2),0) -> 2168.7672 | M24: =IF(M3-参数输入表!$I$250<=0,IF($C$24-M3>=0,$G$42/2*(参数输入表!$I$251/12)*M2,($G$41-$G$44)*(参数输入表!$I$251/12)*M2),0) -> 1445.8448 | N24: =IF(N3-参数输入表!$I$250<=0,IF($C$24-N3>=0,$G$42/2*(参数输入表!$I$251/12)*N2,($G$41-$G$44)*(参数输入表!$I$251/12)*N2),0) -> 722.92241 | ... BE24: =IF(BE3-参数输入表!$I$250<=0,IF($C$24-BE3>=0,$G$42/2*(参数输入表!$I$251/12)*BE2,($G$41-$G$44)*(参数输入表!$I$251/12)*BE2),0) -> 0
C25: 45657 | D25: =SUM(F25:BE25) -> 18999.275 | E25: 万元 | H25: =IF(H3-参数输入表!$I$250<=0,IF($C$25-H3>=0,$H$42/2*(参数输入表!$I$251/12)*H2,($H$41-$H$44)*(参数输入表!$I$251/12)*H2),0) -> 1473.0136 | I25: =IF(I3-参数输入表!$I$250<=0,IF($C$25-I3>=0,$H$42/2*(参数输入表!$I$251/12)*I2,($H$41-$H$44)*(参数输入表!$I$251/12)*I2),0) -> 3092.8697 | J25: =IF(J3-参数输入表!$I$250<=0,IF($C$25-J3>=0,$H$42/2*(参数输入表!$I$251/12)*J2,($H$41-$H$44)*(参数输入表!$I$251/12)*J2),0) -> 3092.8697 | K25: =IF(K3-参数输入表!$I$250<=0,IF($C$25-K3>=0,$H$42/2*(参数输入表!$I$251/12)*K2,($H$41-$H$44)*(参数输入表!$I$251/12)*K2),0) -> 3092.8697 | L25: =IF(L3-参数输入表!$I$250<=0,IF($C$25-L3>=0,$H$42/2*(参数输入表!$I$251/12)*L2,($H$41-$H$44)*(参数输入表!$I$251/12)*L2),0) -> 3092.8697 | M25: =IF(M3-参数输入表!$I$250<=0,IF($C$25-M3>=0,$H$42/2*(参数输入表!$I$251/12)*M2,($H$41-$H$44)*(参数输入表!$I$251/12)*M2),0) -> 2061.9131 | N25: =IF(N3-参数输入表!$I$250<=0,IF($C$25-N3>=0,$H$42/2*(参数输入表!$I$251/12)*N2,($H$41-$H$44)*(参数输入表!$I$251/12)*N2),0) -> 1030.9566 | O25: =IF(O3-参数输入表!$I$250<=0,IF($C$25-O3>=0,$H$42/2*(参数输入表!$I$251/12)*O2,($H$41-$H$44)*(参数输入表!$I$251/12)*O2),0) -> 1804.174 | ... BE25: =IF(BE3-参数输入表!$I$250<=0,IF($C$25-BE3>=0,$H$42/2*(参数输入表!$I$251/12)*BE2,($H$41-$H$44)*(参数输入表!$I$251/12)*BE2),0) -> 0
C26: 46022 | D26: =SUM(F26:BE26) -> 18456.748 | E26: 万元 | I26: =IF(I3-参数输入表!$I$250<=0,IF($C$26-I3>=0,$I$42/2*(参数输入表!$I$251/12)*I2,($I$41-$I$44)*(参数输入表!$I$251/12)*I2),0) -> 1671.8784 | J26: =IF(J3-参数输入表!$I$250<=0,IF($C$26-J3>=0,$I$42/2*(参数输入表!$I$251/12)*J2,($I$41-$I$44)*(参数输入表!$I$251/12)*J2),0) -> 3596.7578 | K26: =IF(K3-参数输入表!$I$250<=0,IF($C$26-K3>=0,$I$42/2*(参数输入表!$I$251/12)*K2,($I$41-$I$44)*(参数输入表!$I$251/12)*K2),0) -> 3596.7578 | L26: =IF(L3-参数输入表!$I$250<=0,IF($C$26-L3>=0,$I$42/2*(参数输入表!$I$251/12)*L2,($I$41-$I$44)*(参数输入表!$I$251/12)*L2),0) -> 3596.7578 | M26: =IF(M3-参数输入表!$I$250<=0,IF($C$26-M3>=0,$I$42/2*(参数输入表!$I$251/12)*M2,($I$41-$I$44)*(参数输入表!$I$251/12)*M2),0) -> 2397.8385 | N26: =IF(N3-参数输入表!$I$250<=0,IF($C$26-N3>=0,$I$42/2*(参数输入表!$I$251/12)*N2,($I$41-$I$44)*(参数输入表!$I$251/12)*N2),0) -> 1198.9193 | O26: =IF(O3-参数输入表!$I$250<=0,IF($C$26-O3>=0,$I$42/2*(参数输入表!$I$251/12)*O2,($I$41-$I$44)*(参数输入表!$I$251/12)*O2),0) -> 2098.1087 | P26: =IF(P3-参数输入表!$I$250<=0,IF($C$26-P3>=0,$I$42/2*(参数输入表!$I$251/12)*P2,($I$41-$I$44)*(参数输入表!$I$251/12)*P2),0) -> 299.72981 | ... BE26: =IF(BE3-参数输入表!$I$250<=0,IF($C$26-BE3>=0,$I$42/2*(参数输入表!$I$251/12)*BE2,($I$41-$I$44)*(参数输入表!$I$251/12)*BE2),0) -> 0
C27: 46387 | D27: =SUM(F27:BE27) -> 16607.513 | E27: 万元 | J27: =IF(J3-参数输入表!$I$250<=0,IF($C$27-J3>=0,$J$42/2*(参数输入表!$I$251/12)*J2,($J$41-$J$44)*(参数输入表!$I$251/12)*J2),0) -> 1828.3232 | K27: =IF(K3-参数输入表!$I$250<=0,IF($C$27-K3>=0,$J$42/2*(参数输入表!$I$251/12)*K2,($J$41-$J$44)*(参数输入表!$I$251/12)*K2),0) -> 4030.6881 | L27: =IF(L3-参数输入表!$I$250<=0,IF($C$27-L3>=0,$J$42/2*(参数输入表!$I$251/12)*L2,($J$41-$J$44)*(参数输入表!$I$251/12)*L2),0) -> 4030.6881 | M27: =IF(M3-参数输入表!$I$250<=0,IF($C$27-M3>=0,$J$42/2*(参数输入表!$I$251/12)*M2,($J$41-$J$44)*(参数输入表!$I$251/12)*M2),0) -> 2687.1254 | N27: =IF(N3-参数输入表!$I$250<=0,IF($C$27-N3>=0,$J$42/2*(参数输入表!$I$251/12)*N2,($J$41-$J$44)*(参数输入表!$I$251/12)*N2),0) -> 1343.5627 | O27: =IF(O3-参数输入表!$I$250<=0,IF($C$27-O3>=0,$J$42/2*(参数输入表!$I$251/12)*O2,($J$41-$J$44)*(参数输入表!$I$251/12)*O2),0) -> 2351.2347 | P27: =IF(P3-参数输入表!$I$250<=0,IF($C$27-P3>=0,$J$42/2*(参数输入表!$I$251/12)*P2,($J$41-$J$44)*(参数输入表!$I$251/12)*P2),0) -> 335.89068 | Q27: =IF(Q3-参数输入表!$I$250<=0,IF($C$27-Q3>=0,$J$42/2*(参数输入表!$I$251/12)*Q2,($J$41-$J$44)*(参数输入表!$I$251/12)*Q2),0) -> 0 | ... BE27: =IF(BE3-参数输入表!$I$250<=0,IF($C$27-BE3>=0,$J$42/2*(参数输入表!$I$251/12)*BE2,($J$41-$J$44)*(参数输入表!$I$251/12)*BE2),0) -> 0
C28: 46752 | D28: =SUM(F28:BE28) -> 16875.81 | E28: 万元 | K28: =IF(K3-参数输入表!$I$250<=0,IF($C$28-K3>=0,$K$42/2*(参数输入表!$I$251/12)*K2,($K$41-$K$44)*(参数输入表!$I$251/12)*K2),0) -> 2444.0174 | L28: =IF(L3-参数输入表!$I$250<=0,IF($C$28-L3>=0,$K$42/2*(参数输入表!$I$251/12)*L2,($K$41-$K$44)*(参数输入表!$I$251/12)*L2),0) -> 5411.9223 | M28: =IF(M3-参数输入表!$I$250<=0,IF($C$28-M3>=0,$K$42/2*(参数输入表!$I$251/12)*M2,($K$41-$K$44)*(参数输入表!$I$251/12)*M2),0) -> 3607.9482 | N28: =IF(N3-参数输入表!$I$250<=0,IF($C$28-N3>=0,$K$42/2*(参数输入表!$I$251/12)*N2,($K$41-$K$44)*(参数输入表!$I$251/12)*N2),0) -> 1803.9741 | O28: =IF(O3-参数输入表!$I$250<=0,IF($C$28-O3>=0,$K$42/2*(参数输入表!$I$251/12)*O2,($K$41-$K$44)*(参数输入表!$I$251/12)*O2),0) -> 3156.9547 | P28: =IF(P3-参数输入表!$I$250<=0,IF($C$28-P3>=0,$K$42/2*(参数输入表!$I$251/12)*P2,($K$41-$K$44)*(参数输入表!$I$251/12)*P2),0) -> 450.99352 | Q28: =IF(Q3-参数输入表!$I$250<=0,IF($C$28-Q3>=0,$K$42/2*(参数输入表!$I$251/12)*Q2,($K$41-$K$44)*(参数输入表!$I$251/12)*Q2),0) -> 0 | R28: =IF(R3-参数输入表!$I$250<=0,IF($C$28-R3>=0,$K$42/2*(参数输入表!$I$251/12)*R2,($K$41-$K$44)*(参数输入表!$I$251/12)*R2),0) -> 0 | ... BE28: =IF(BE3-参数输入表!$I$250<=0,IF($C$28-BE3>=0,$K$42/2*(参数输入表!$I$251/12)*BE2,($K$41-$K$44)*(参数输入表!$I$251/12)*BE2),0) -> 0
C29: 47118 | D29: =SUM(F29:BE29) -> 10863.575 | E29: 万元 | L29: =IF(L3-参数输入表!$I$250<=0,IF($C$29-L3>=0,$L$42/2*(参数输入表!$I$251/12)*L2,($L$41-$L$44)*(参数输入表!$I$251/12)*L2),0) -> 2240.8747 | M29: =IF(M3-参数输入表!$I$250<=0,IF($C$29-M3>=0,$L$42/2*(参数输入表!$I$251/12)*M2,($L$41-$L$44)*(参数输入表!$I$251/12)*M2),0) -> 3449.08 | N29: =IF(N3-参数输入表!$I$250<=0,IF($C$29-N3>=0,$L$42/2*(参数输入表!$I$251/12)*N2,($L$41-$L$44)*(参数输入表!$I$251/12)*N2),0) -> 1724.54 | O29: =IF(O3-参数输入表!$I$250<=0,IF($C$29-O3>=0,$L$42/2*(参数输入表!$I$251/12)*O2,($L$41-$L$44)*(参数输入表!$I$251/12)*O2),0) -> 3017.945 | P29: =IF(P3-参数输入表!$I$250<=0,IF($C$29-P3>=0,$L$42/2*(参数输入表!$I$251/12)*P2,($L$41-$L$44)*(参数输入表!$I$251/12)*P2),0) -> 431.135 | Q29: =IF(Q3-参数输入表!$I$250<=0,IF($C$29-Q3>=0,$L$42/2*(参数输入表!$I$251/12)*Q2,($L$41-$L$44)*(参数输入表!$I$251/12)*Q2),0) -> 0 | R29: =IF(R3-参数输入表!$I$250<=0,IF($C$29-R3>=0,$L$42/2*(参数输入表!$I$251/12)*R2,($L$41-$L$44)*(参数输入表!$I$251/12)*R2),0) -> 0 | S29: =IF(S3-参数输入表!$I$250<=0,IF($C$29-S3>=0,$L$42/2*(参数输入表!$I$251/12)*S2,($L$41-$L$44)*(参数输入表!$I$251/12)*S2),0) -> 0 | ... BE29: =IF(BE3-参数输入表!$I$250<=0,IF($C$29-BE3>=0,$L$42/2*(参数输入表!$I$251/12)*BE2,($L$41-$L$44)*(参数输入表!$I$251/12)*BE2),0) -> 0
C30: 47361 | D30: =SUM(F30:BE30) -> 3567.5019 | E30: 万元 | M30: =IF(M3-参数输入表!$I$250<=0,IF($C$30-M3>=0,$M$42/2*(参数输入表!$I$251/12)*M2,($M$41-$M$44)*(参数输入表!$I$251/12)*M2),0) -> 754.71531 | N30: =IF(N3-参数输入表!$I$250<=0,IF($C$30-N3>=0,$M$42/2*(参数输入表!$I$251/12)*N2,($M$41-$M$44)*(参数输入表!$I$251/12)*N2),0) -> 937.59554 | O30: =IF(O3-参数输入表!$I$250<=0,IF($C$30-O3>=0,$M$42/2*(参数输入表!$I$251/12)*O2,($M$41-$M$44)*(参数输入表!$I$251/12)*O2),0) -> 1640.7922 | P30: =IF(P3-参数输入表!$I$250<=0,IF($C$30-P3>=0,$M$42/2*(参数输入表!$I$251/12)*P2,($M$41-$M$44)*(参数输入表!$I$251/12)*P2),0) -> 234.39888 | Q30: =IF(Q3-参数输入表!$I$250<=0,IF($C$30-Q3>=0,$M$42/2*(参数输入表!$I$251/12)*Q2,($M$41-$M$44)*(参数输入表!$I$251/12)*Q2),0) -> 0 | R30: =IF(R3-参数输入表!$I$250<=0,IF($C$30-R3>=0,$M$42/2*(参数输入表!$I$251/12)*R2,($M$41-$M$44)*(参数输入表!$I$251/12)*R2),0) -> 0 | S30: =IF(S3-参数输入表!$I$250<=0,IF($C$30-S3>=0,$M$42/2*(参数输入表!$I$251/12)*S2,($M$41-$M$44)*(参数输入表!$I$251/12)*S2),0) -> 0 | T30: =IF(T3-参数输入表!$I$250<=0,IF($C$30-T3>=0,$M$42/2*(参数输入表!$I$251/12)*T2,($M$41-$M$44)*(参数输入表!$I$251/12)*T2),0) -> 0 | ... BE30: =IF(BE3-参数输入表!$I$250<=0,IF($C$30-BE3>=0,$M$42/2*(参数输入表!$I$251/12)*BE2,($M$41-$M$44)*(参数输入表!$I$251/12)*BE2),0) -> 0
C31: 47483 | D31: =SUM(F31:BE31) -> 1458.193 | E31: 万元 | N31: =IF(N3-参数输入表!$I$250<=0,IF($C$31-N3>=0,$N$42/2*(参数输入表!$I$251/12)*N2,($N$41-$N$44)*(参数输入表!$I$251/12)*N2),0) -> 251.57177 | O31: =IF(O3-参数输入表!$I$250<=0,IF($C$31-O3>=0,$N$42/2*(参数输入表!$I$251/12)*O2,($N$41-$N$44)*(参数输入表!$I$251/12)*O2),0) -> 1055.7936 | P31: =IF(P3-参数输入表!$I$250<=0,IF($C$31-P3>=0,$N$42/2*(参数输入表!$I$251/12)*P2,($N$41-$N$44)*(参数输入表!$I$251/12)*P2),0) -> 150.82765 | Q31: =IF(Q3-参数输入表!$I$250<=0,IF($C$31-Q3>=0,$N$42/2*(参数输入表!$I$251/12)*Q2,($N$41-$N$44)*(参数输入表!$I$251/12)*Q2),0) -> 0 | R31: =IF(R3-参数输入表!$I$250<=0,IF($C$31-R3>=0,$N$42/2*(参数输入表!$I$251/12)*R2,($N$41-$N$44)*(参数输入表!$I$251/12)*R2),0) -> 0 | S31: =IF(S3-参数输入表!$I$250<=0,IF($C$31-S3>=0,$N$42/2*(参数输入表!$I$251/12)*S2,($N$41-$N$44)*(参数输入表!$I$251/12)*S2),0) -> 0 | T31: =IF(T3-参数输入表!$I$250<=0,IF($C$31-T3>=0,$N$42/2*(参数输入表!$I$251/12)*T2,($N$41-$N$44)*(参数输入表!$I$251/12)*T2),0) -> 0 | U31: =IF(U3-参数输入表!$I$250<=0,IF($C$31-U3>=0,$N$42/2*(参数输入表!$I$251/12)*U2,($N$41-$N$44)*(参数输入表!$I$251/12)*U2),0) -> 0 | ... BE31: =IF(BE3-参数输入表!$I$250<=0,IF($C$31-BE3>=0,$N$42/2*(参数输入表!$I$251/12)*BE2,($N$41-$N$44)*(参数输入表!$I$251/12)*BE2),0) -> 0
C32: 47695 | D32: =SUM(F32:BE32) -> 652.09379 | E32: 万元 | O32: =IF(O3-参数输入表!$I$250<=0,IF($C$32-O3>=0,$O$42/2*(参数输入表!$I$251/12)*O2,($O$41-$O$44)*(参数输入表!$I$251/12)*O2),0) -> 470.82861 | P32: =IF(P3-参数输入表!$I$250<=0,IF($C$32-P3>=0,$O$42/2*(参数输入表!$I$251/12)*P2,($O$41-$O$44)*(参数输入表!$I$251/12)*P2),0) -> 181.26518 | Q32: =IF(Q3-参数输入表!$I$250<=0,IF($C$32-Q3>=0,$O$42/2*(参数输入表!$I$251/12)*Q2,($O$41-$O$44)*(参数输入表!$I$251/12)*Q2),0) -> 0 | R32: =IF(R3-参数输入表!$I$250<=0,IF($C$32-R3>=0,$O$42/2*(参数输入表!$I$251/12)*R2,($O$41-$O$44)*(参数输入表!$I$251/12)*R2),0) -> 0 | S32: =IF(S3-参数输入表!$I$250<=0,IF($C$32-S3>=0,$O$42/2*(参数输入表!$I$251/12)*S2,($O$41-$O$44)*(参数输入表!$I$251/12)*S2),0) -> 0 | T32: =IF(T3-参数输入表!$I$250<=0,IF($C$32-T3>=0,$O$42/2*(参数输入表!$I$251/12)*T2,($O$41-$O$44)*(参数输入表!$I$251/12)*T2),0) -> 0 | U32: =IF(U3-参数输入表!$I$250<=0,IF($C$32-U3>=0,$O$42/2*(参数输入表!$I$251/12)*U2,($O$41-$O$44)*(参数输入表!$I$251/12)*U2),0) -> 0 | V32: =IF(V3-参数输入表!$I$250<=0,IF($C$32-V3>=0,$O$42/2*(参数输入表!$I$251/12)*V2,($O$41-$O$44)*(参数输入表!$I$251/12)*V2),0) -> 0 | ... BE32: =IF(BE3-参数输入表!$I$250<=0,IF($C$32-BE3>=0,$O$42/2*(参数输入表!$I$251/12)*BE2,($O$41-$O$44)*(参数输入表!$I$251/12)*BE2),0) -> 0
C33: =P3 -> 47726 | D33: =SUM(F33:BE33) -> 0 | E33: 万元 | P33: =IF(P3-参数输入表!$I$250<=0,IF($C$33-P3>=0,$P$42/2*(参数输入表!$I$251/12)*P2,($P$41-$P$44)*(参数输入表!$I$251/12)*P2),0) -> 0 | Q33: =IF(Q3-参数输入表!$I$250<=0,IF($C$33-Q3>=0,$P$42/2*(参数输入表!$I$251/12)*Q2,($P$41-$P$44)*(参数输入表!$I$251/12)*Q2),0) -> 0 | R33: =IF(R3-参数输入表!$I$250<=0,IF($C$33-R3>=0,$P$42/2*(参数输入表!$I$251/12)*R2,($P$41-$P$44)*(参数输入表!$I$251/12)*R2),0) -> 0 | S33: =IF(S3-参数输入表!$I$250<=0,IF($C$33-S3>=0,$P$42/2*(参数输入表!$I$251/12)*S2,($P$41-$P$44)*(参数输入表!$I$251/12)*S2),0) -> 0 | T33: =IF(T3-参数输入表!$I$250<=0,IF($C$33-T3>=0,$P$42/2*(参数输入表!$I$251/12)*T2,($P$41-$P$44)*(参数输入表!$I$251/12)*T2),0) -> 0 | U33: =IF(U3-参数输入表!$I$250<=0,IF($C$33-U3>=0,$P$42/2*(参数输入表!$I$251/12)*U2,($P$41-$P$44)*(参数输入表!$I$251/12)*U2),0) -> 0 | V33: =IF(V3-参数输入表!$I$250<=0,IF($C$33-V3>=0,$P$42/2*(参数输入表!$I$251/12)*V2,($P$41-$P$44)*(参数输入表!$I$251/12)*V2),0) -> 0 | W33: =IF(W3-参数输入表!$I$250<=0,IF($C$33-W3>=0,$P$42/2*(参数输入表!$I$251/12)*W2,($P$41-$P$44)*(参数输入表!$I$251/12)*W2),0) -> 0 | ... BE33: =IF(BE3-参数输入表!$I$250<=0,IF($C$33-BE3>=0,$P$42/2*(参数输入表!$I$251/12)*BE2,($P$41-$P$44)*(参数输入表!$I$251/12)*BE2),0) -> 0
C34: 47848 | D34: =SUM(F34:BE34) -> 0 | E34: 万元 | Q34: =IF(Q3-参数输入表!$I$250<=0,IF($C$34-Q3>=0,$Q$42/2*(参数输入表!$I$251/12)*Q2,($Q$41-$Q$44)*(参数输入表!$I$251/12)*Q2),0) -> 0 | R34: =IF(R3-参数输入表!$I$250<=0,IF($C$34-R3>=0,$Q$42/2*(参数输入表!$I$251/12)*R2,($Q$41-$Q$44)*(参数输入表!$I$251/12)*R2),0) -> 0 | S34: =IF(S3-参数输入表!$I$250<=0,IF($C$34-S3>=0,$Q$42/2*(参数输入表!$I$251/12)*S2,($Q$41-$Q$44)*(参数输入表!$I$251/12)*S2),0) -> 0 | T34: =IF(T3-参数输入表!$I$250<=0,IF($C$34-T3>=0,$Q$42/2*(参数输入表!$I$251/12)*T2,($Q$41-$Q$44)*(参数输入表!$I$251/12)*T2),0) -> 0 | U34: =IF(U3-参数输入表!$I$250<=0,IF($C$34-U3>=0,$Q$42/2*(参数输入表!$I$251/12)*U2,($Q$41-$Q$44)*(参数输入表!$I$251/12)*U2),0) -> 0 | V34: =IF(V3-参数输入表!$I$250<=0,IF($C$34-V3>=0,$Q$42/2*(参数输入表!$I$251/12)*V2,($Q$41-$Q$44)*(参数输入表!$I$251/12)*V2),0) -> 0 | W34: =IF(W3-参数输入表!$I$250<=0,IF($C$34-W3>=0,$Q$42/2*(参数输入表!$I$251/12)*W2,($Q$41-$Q$44)*(参数输入表!$I$251/12)*W2),0) -> 0 | X34: =IF(X3-参数输入表!$I$250<=0,IF($C$34-X3>=0,$Q$42/2*(参数输入表!$I$251/12)*X2,($Q$41-$Q$44)*(参数输入表!$I$251/12)*X2),0) -> 0 | ... BE34: =IF(BE3-参数输入表!$I$250<=0,IF($C$34-BE3>=0,$Q$42/2*(参数输入表!$I$251/12)*BE2,($Q$41-$Q$44)*(参数输入表!$I$251/12)*BE2),0) -> 0
B35: 1.3 | C35: 流动资金 | D35: =SUM(F35:BE35) -> 6436.0867 | E35: 万元 | F35: =IF(ISBLANK(F4),0,IF(F4-参数输入表!$I$25<0,0,IF(F4-参数输入表!$I$25>0,0,IF(参数输入表!$I$220="扩大指标估算法",参数输入表!$I$218,F320)))) -> 0 | G35: =IF(ISBLANK(G4),0,IF(G4-参数输入表!$I$25<0,0,IF(G4-参数输入表!$I$25>0,0,IF(参数输入表!$I$220="扩大指标估算法",参数输入表!$I$218,F320)))) -> 0 | H35: =IF(ISBLANK(H4),0,IF(H4-参数输入表!$I$25<0,0,IF(H4-参数输入表!$I$25>0,0,IF(参数输入表!$I$220="扩大指标估算法",参数输入表!$I$218,G320)))) -> 0 | I35: =IF(ISBLANK(I4),0,IF(I4-参数输入表!$I$25<0,0,IF(I4-参数输入表!$I$25>0,0,IF(参数输入表!$I$220="扩大指标估算法",参数输入表!$I$218,H320)))) -> 0 | J35: =IF(ISBLANK(J4),0,IF(J4-参数输入表!$I$25<0,0,IF(J4-参数输入表!$I$25>0,0,IF(参数输入表!$I$220="扩大指标估算法",参数输入表!$I$218,I320)))) -> 0 | K35: =IF(ISBLANK(K4),0,IF(K4-参数输入表!$I$25<0,0,IF(K4-参数输入表!$I$25>0,0,IF(参数输入表!$I$220="扩大指标估算法",参数输入表!$I$218,J320)))) -> 0 | L35: =IF(ISBLANK(L4),0,IF(L4-参数输入表!$I$25<0,0,IF(L4-参数输入表!$I$25>0,0,IF(参数输入表!$I$220="扩大指标估算法",参数输入表!$I$218,K320)))) -> 0 | M35: =IF(ISBLANK(M4),0,IF(M4-参数输入表!$I$25<0,0,IF(M4-参数输入表!$I$25>0,0,IF(参数输入表!$I$220="扩大指标估算法",参数输入表!$I$218,L320)))) -> 0 | N35: =IF(ISBLANK(N4),0,IF(N4-参数输入表!$I$25<0,0,IF(N4-参数输入表!$I$25>0,0,IF(参数输入表!$I$220="扩大指标估算法",参数输入表!$I$218,L320)))) -> 0 | O35: =IF(ISBLANK(O4),0,IF(O4-参数输入表!$I$25<0,0,IF(O4-参数输入表!$I$25>0,0,IF(参数输入表!$I$220="扩大指标估算法",参数输入表!$I$218,M320)))) -> 0 | P35: =IF(ISBLANK(P4),0,IF(P4-参数输入表!$I$25<0,0,IF(P4-参数输入表!$I$25>0,0,IF(参数输入表!$I$220="扩大指标估算法",参数输入表!$I$218,N320)))) -> 0 | Q35: =IF(ISBLANK(Q4),0,IF(Q4-参数输入表!$I$25<0,0,IF(Q4-参数输入表!$I$25>0,0,IF(参数输入表!$I$220="扩大指标估算法",参数输入表!$I$218,O320)))) -> 6436.0867 | R35: =IF(ISBLANK(R4),0,IF(R4-参数输入表!$I$25<0,0,IF(R4-参数输入表!$I$25>0,0,IF(参数输入表!$I$220="扩大指标估算法",参数输入表!$I$218,#REF!)))) -> 0 | S35: =IF(ISBLANK(S4),0,IF(S4-参数输入表!$I$25<0,0,IF(S4-参数输入表!$I$25>0,0,IF(参数输入表!$I$220="扩大指标估算法",参数输入表!$I$218,O320)))) -> 0 | T35: =IF(ISBLANK(T4),0,IF(T4-参数输入表!$I$25<0,0,IF(T4-参数输入表!$I$25>0,0,IF(参数输入表!$I$220="扩大指标估算法",参数输入表!$I$218,P320)))) -> 0 | U35: =IF(ISBLANK(U4),0,IF(U4-参数输入表!$I$25<0,0,IF(U4-参数输入表!$I$25>0,0,IF(参数输入表!$I$220="扩大指标估算法",参数输入表!$I$218,Q320)))) -> 0 | V35: =IF(ISBLANK(V4),0,IF(V4-参数输入表!$I$25<0,0,IF(V4-参数输入表!$I$25>0,0,IF(参数输入表!$I$220="扩大指标估算法",参数输入表!$I$218,R320)))) -> 0 | W35: =IF(ISBLANK(W4),0,IF(W4-参数输入表!$I$25<0,0,IF(W4-参数输入表!$I$25>0,0,IF(参数输入表!$I$220="扩大指标估算法",参数输入表!$I$218,S320)))) -> 0 | X35: =IF(ISBLANK(X4),0,IF(X4-参数输入表!$I$25<0,0,IF(X4-参数输入表!$I$25>0,0,IF(参数输入表!$I$220="扩大指标估算法",参数输入表!$I$218,T320)))) -> 0 | Y35: =IF(ISBLANK(Y4),0,IF(Y4-参数输入表!$I$25<0,0,IF(Y4-参数输入表!$I$25>0,0,IF(参数输入表!$I$220="扩大指标估算法",参数输入表!$I$218,U320)))) -> 0 | Z35: =IF(ISBLANK(Z4),0,IF(Z4-参数输入表!$I$25<0,0,IF(Z4-参数输入表!$I$25>0,0,IF(参数输入表!$I$220="扩大指标估算法",参数输入表!$I$218,V320)))) -> 0 | ... BE35: =IF(ISBLANK(BE4),0,IF(BE4-参数输入表!$I$25<0,0,IF(BE4-参数输入表!$I$25>0,0,IF(参数输入表!$I$220="扩大指标估算法",参数输入表!$I$218,BA320)))) -> 0
B36: 2 | C36: 资金来源 | D36: =SUM(F36:BE36) -> 973381.77 | E36: 万元 | F36: =F37+F41 -> 28262.72 | G36: =G37+G41 -> 67248.597 | H36: =H37+H41 -> 95902.936 | I36: =I37+I41 -> 111527.37 | J36: =J37+J41 -> 124982.58 | K36: =K37+K41 -> 167811.54 | L36: =L37+L41 -> 160422.33 | M36: =M37+M41 -> 87218.189 | ... BE36: =BE37+BE41 -> 0
B37: 2.1 | C37: 资本金 | D37: =SUM(F37:BE37) -> 243667.25 | E37: 万元 | F37: =SUM(F38:F40) -> 7065.68 | G37: =SUM(G38:G40) -> 16812.149 | H37: =SUM(H38:H40) -> 23975.734 | I37: =SUM(I38:I40) -> 27881.843 | J37: =SUM(J38:J40) -> 31245.644 | K37: =SUM(K38:K40) -> 41952.886 | L37: =SUM(L38:L40) -> 40105.581 | M37: =SUM(M38:M40) -> 21804.547 | ... BE37: =SUM(BE38:BE40) -> 0
B38: 2.1.1 | C38: 用于建设投资 | D38: =SUM(F38:BE38) -> 214993.49 | E38: 万元 | F38: =IF(参数输入表!$I$224="按比例输入",SUM(F8:F9)*参数输入表!$I$237-F39,IF(F4-参数输入表!$I$4>0,0,参数输入表!I226)) -> 7046.7419 | G38: =IF(参数输入表!$I$224="按比例输入",SUM(G8:G9)*参数输入表!$I$237-G39,IF(G4-参数输入表!$I$4>0,0,参数输入表!I227)) -> 16442.398 | H38: =IF(参数输入表!$I$224="按比例输入",SUM(H8:H9)*参数输入表!$I$237-H39,IF(H4-参数输入表!$I$4>0,0,参数输入表!I228)) -> 22837.421 | I38: =IF(参数输入表!$I$224="按比例输入",SUM(I8:I9)*参数输入表!$I$237-I39,IF(I4-参数输入表!$I$4>0,0,参数输入表!I229)) -> 25920.596 | J38: =IF(参数输入表!$I$224="按比例输入",SUM(J8:J9)*参数输入表!$I$237-J39,IF(J4-参数输入表!$I$4>0,0,参数输入表!I230)) -> 28346.097 | K38: =IF(参数输入表!$I$224="按比例输入",SUM(K8:K9)*参数输入表!$I$237-K39,IF(K4-参数输入表!$I$4>0,0,参数输入表!I231)) -> 37891.742 | L38: =IF(参数输入表!$I$224="按比例输入",SUM(L8:L9)*参数输入表!$I$237-L39,IF(L4-参数输入表!$I$4>0,0,参数输入表!I232)) -> 34742.243 | M38: =IF(参数输入表!$I$224="按比例输入",SUM(M8:M9)*参数输入表!$I$237-M39,IF(M4-参数输入表!$I$4>0,0,参数输入表!I233)) -> 17551.519 | N38: =IF(参数输入表!$I$224="按比例输入",SUM(N8:N9)*参数输入表!$I$237-N39,IF(N4-参数输入表!$I$4>0,0,参数输入表!I234)) -> 11701.013 | O38: =IF(参数输入表!$I$224="按比例输入",SUM(O8:O9)*参数输入表!$I$237-O39,IF(O4-参数输入表!$I$4>0,0,参数输入表!I235)) -> 12513.717 | P38: =IF(参数输入表!$I$224="按比例输入",SUM(P8:P9)*参数输入表!$I$237-P39,IF(P4-参数输入表!$I$4>0,0,0)) -> 0 | Q38: =IF(参数输入表!$I$224="按比例输入",SUM(Q8:Q9)*参数输入表!$I$237-Q39,IF(Q4-参数输入表!$I$4>0,0,0)) -> 0 | R38: =IF(参数输入表!$I$224="按比例输入",SUM(R8:R9)*参数输入表!$I$237-R39,IF(R4-参数输入表!$I$4>0,0,0)) -> 0 | S38: =IF(参数输入表!$I$224="按比例输入",SUM(S8:S9)*参数输入表!$I$237-S39,IF(S4-参数输入表!$I$4>0,0,0)) -> 0 | T38: =IF(参数输入表!$I$224="按比例输入",SUM(T8:T9)*参数输入表!$I$237-T39,IF(T4-参数输入表!$I$4>0,0,0)) -> 0 | U38: =IF(参数输入表!$I$224="按比例输入",SUM(U8:U9)*参数输入表!$I$237-U39,IF(U4-参数输入表!$I$4>0,0,0)) -> 0 | V38: =IF(参数输入表!$I$224="按比例输入",SUM(V8:V9)*参数输入表!$I$237-V39,IF(V4-参数输入表!$I$4>0,0,0)) -> 0 | W38: =IF(参数输入表!$I$224="按比例输入",SUM(W8:W9)*参数输入表!$I$237-W39,IF(W4-参数输入表!$I$4>0,0,0)) -> 0 | ... BE38: =IF(参数输入表!$I$224="按比例输入",SUM(BE8:BE9)*参数输入表!$I$237-BE39,IF(BE4-参数输入表!$I$4>0,0,0)) -> 0
B39: 2.1.2 | C39: 用于建设期利息 | D39: =SUM(F39:BE39) -> 26742.934 | E39: 万元 | F39: =IF(参数输入表!$I$224="按比例输入",F9*参数输入表!$I$237,0) -> 18.938119 | G39: =IF(参数输入表!$I$224="按比例输入",G9*参数输入表!$I$237,0) -> 369.75138 | H39: =IF(参数输入表!$I$224="按比例输入",H9*参数输入表!$I$237,0) -> 1138.3134 | I39: =IF(参数输入表!$I$224="按比例输入",I9*参数输入表!$I$237,0) -> 1961.247 | J39: =IF(参数输入表!$I$224="按比例输入",J9*参数输入表!$I$237,0) -> 2899.5477 | K39: =IF(参数输入表!$I$224="按比例输入",K9*参数输入表!$I$237,0) -> 4061.1432 | L39: =IF(参数输入表!$I$224="按比例输入",L9*参数输入表!$I$237,0) -> 5363.3381 | M39: =IF(参数输入表!$I$224="按比例输入",M9*参数输入表!$I$237,0) -> 4253.0285 | ... BE39: =IF(参数输入表!$I$224="按比例输入",BE9*参数输入表!$I$237,0) -> 0
B40: 2.1.3 | C40: 用于流动资金 | D40: =SUM(F40:BE40) -> 1930.826 | E40: 万元 | F40: =IF(参数输入表!$I$224="按比例输入",IF(F4-参数输入表!$I$25<0,0,IF(F4-参数输入表!$I$25>0,0,F35*参数输入表!$I$239)),0) -> 0 | G40: =IF(参数输入表!$I$224="按比例输入",IF(G4-参数输入表!$I$25<0,0,IF(G4-参数输入表!$I$25>0,0,G35*参数输入表!$I$239)),0) -> 0 | H40: =IF(参数输入表!$I$224="按比例输入",IF(H4-参数输入表!$I$25<0,0,IF(H4-参数输入表!$I$25>0,0,H35*参数输入表!$I$239)),0) -> 0 | I40: =IF(参数输入表!$I$224="按比例输入",IF(I4-参数输入表!$I$25<0,0,IF(I4-参数输入表!$I$25>0,0,I35*参数输入表!$I$239)),0) -> 0 | J40: =IF(参数输入表!$I$224="按比例输入",IF(J4-参数输入表!$I$25<0,0,IF(J4-参数输入表!$I$25>0,0,J35*参数输入表!$I$239)),0) -> 0 | K40: =IF(参数输入表!$I$224="按比例输入",IF(K4-参数输入表!$I$25<0,0,IF(K4-参数输入表!$I$25>0,0,K35*参数输入表!$I$239)),0) -> 0 | L40: =IF(参数输入表!$I$224="按比例输入",IF(L4-参数输入表!$I$25<0,0,IF(L4-参数输入表!$I$25>0,0,L35*参数输入表!$I$239)),0) -> 0 | M40: =IF(参数输入表!$I$224="按比例输入",IF(M4-参数输入表!$I$25<0,0,IF(M4-参数输入表!$I$25>0,0,M35*参数输入表!$I$239)),0) -> 0 | ... BE40: =IF(参数输入表!$I$224="按比例输入",IF(BE4-参数输入表!$I$25<0,0,IF(BE4-参数输入表!$I$25>0,0,BE35*参数输入表!$I$239)),0) -> 0
B41: 2.2 | C41: 债务资金 | D41: =SUM(F41:BE41) -> 729714.52 | E41: 万元 | F41: =SUM(F42:F43)+F44 -> 21197.04 | G41: =SUM(G42:G43)+G44 -> 50436.448 | H41: =SUM(H42:H43)+H44 -> 71927.202 | I41: =SUM(I42:I43)+I44 -> 83645.529 | J41: =SUM(J42:J43)+J44 -> 93736.933 | K41: =SUM(K42:K43)+K44 -> 125858.66 | L41: =SUM(L42:L43)+L44 -> 120316.74 | M41: =SUM(M42:M43)+M44 -> 65413.642 | ... BE41: =SUM(BE42:BE43)+BE44 -> 0
B42: 2.2.1 | C42: 用于建设投资 | D42: =SUM(F42:BE42) -> 644980.46 | E42: 万元 | F42: =IF(F4-参数输入表!$I$4>0,0,F8-F38) -> 21140.226 | G42: =IF(G4-参数输入表!$I$4>0,0,G8-G38) -> 49327.193 | H42: =IF(H4-参数输入表!$I$4>0,0,H8-H38) -> 68512.262 | I42: =IF(I4-参数输入表!$I$4>0,0,I8-I38) -> 77761.788 | J42: =IF(J4-参数输入表!$I$4>0,0,J8-J38) -> 85038.29 | K42: =IF(K4-参数输入表!$I$4>0,0,K8-K38) -> 113675.23 | L42: =IF(L4-参数输入表!$I$4>0,0,L8-L38) -> 104226.73 | M42: =IF(M4-参数输入表!$I$4>0,0,M8-M38) -> 52654.557 | ... BE42: =IF(BE4-参数输入表!$I$4>0,0,BE8-BE38) -> 0
B43: 2.2.2 | C43: 用于建设期利息 | D43: =SUM(F43:BE43) -> 80228.801 | E43: 万元 | F43: =F9-F39 -> 56.814357 | G43: =G9-G39 -> 1109.2542 | H43: =H9-H39 -> 3414.9402 | I43: =I9-I39 -> 5883.7411 | J43: =J9-J39 -> 8698.643 | K43: =K9-K39 -> 12183.43 | L43: =L9-L39 -> 16090.014 | M43: =M9-M39 -> 12759.085 | ... BE43: =BE9-BE39 -> 0
B44: 2.2.3 | C44: 用于流动资金 | D44: =SUM(F44:BE44) -> 4505.2607 | E44: 万元 | F44: =F35-F40 -> 0 | G44: =G35-G40 -> 0 | H44: =H35-H40 -> 0 | I44: =I35-I40 -> 0 | J44: =J35-J40 -> 0 | K44: =K35-K40 -> 0 | L44: =L35-L40 -> 0 | M44: =M35-M40 -> 0 | ... BE44: =BE35-BE40 -> 0
B46: 季度还款 | C46: 建设期 | D46: =参数输入表!I5 -> 44958
C47: 宽限期 | D47: =参数输入表!I249 -> 91 | E47: 月
D48: =EDATE(D46,D47)-1 -> 47726 | E48: 宽限期结束日
C49: 还款日期（首期） | D49: =EDATE(D46,D47+D51) -> 47818
C50: 还款期限 | D50: =参数输入表!I256 -> 15 | E50: 年
C51: 每期计息月份数 | D51: 3 | E51: 月
C52: 年还款次数 | D52: =12/D51 -> 4 | E52: 次
C53: 总还款期数 | D53: =D50*D52 -> 60 | E53: 期
C54: 还款日期（末期） | D54: =EDATE(D49,D50*12-D51) -> 53206 | E54: =BM58 -> 53206
C55: 贷款额 | D55: =SUM(D42:D43) -> 725209.26 | E55: 万元
C56: 季度利率 | D56: =参数输入表!$I$252/D52 -> 0.01075 | E56: %
C57: 还款计划安排（季度） | D57: 期数 | F57: 1 | G57: 2 | H57: 3 | I57: 4 | J57: 5 | K57: 6 | L57: 7 | M57: 8 | N57: 9 | O57: 10 | P57: 11 | Q57: 12 | R57: 13 | S57: 14 | T57: 15 | U57: 16 | V57: 17 | W57: 18 | X57: 19 | Y57: 20 | Z57: 21 | AA57: 22 | AB57: 23 | AC57: 24 | AD57: 25 | AE57: 26 | AF57: 27 | AG57: 28 | AH57: 29 | AI57: 30 | AJ57: 31 | AK57: 32 | AL57: 33 | AM57: 34 | AN57: 35 | AO57: 36 | AP57: 37 | AQ57: 38 | AR57: 39 | AS57: 40 | AT57: 41 | AU57: 42 | AV57: 43 | AW57: 44 | AX57: 45 | AY57: 46 | AZ57: 47 | BA57: 48 | BB57: 49 | BC57: 50 | BD57: 51 | BE57: 52 | BF57: 53 | BG57: 54 | BH57: 55 | BI57: 56 | BJ57: 57 | BK57: 58 | BL57: 59 | BM57: 60
D58: 日期 | F58: =D49 -> 47818 | G58: =EDATE(F58,$D$51) -> 47908 | H58: =EDATE(G58,$D$51) -> 48000 | I58: =EDATE(H58,$D$51) -> 48092 | J58: =EDATE(I58,$D$51) -> 48183 | K58: =EDATE(J58,$D$51) -> 48274 | L58: =EDATE(K58,$D$51) -> 48366 | M58: =EDATE(L58,$D$51) -> 48458 | N58: =EDATE(M58,$D$51) -> 48549 | ... BM58: =EDATE(BL58,$D$51) -> 53206
D59: 所属年度 | F59: =YEAR(F58) -> 2030 | G59: =YEAR(G58) -> 2031 | H59: =YEAR(H58) -> 2031 | I59: =YEAR(I58) -> 2031 | J59: =YEAR(J58) -> 2031 | K59: =YEAR(K58) -> 2032 | L59: =YEAR(L58) -> 2032 | M59: =YEAR(M58) -> 2032 | ... BM59: =YEAR(BM58) -> 2045
D60: 当年还款次数统计 | E60: =IF(E61=D53,"OK","F") -> OK | F60: 2023 | G60: 2024 | H60: 2025 | I60: 2026 | J60: 2027 | K60: 2028 | L60: 2029 | M60: 2030 | N60: 2031 | O60: 2032 | P60: 2033 | Q60: 2034 | R60: 2035 | S60: 2036 | T60: 2037 | U60: 2038 | V60: 2039 | W60: 2040 | X60: 2041 | Y60: 2042 | Z60: 2043 | AA60: 2044 | AB60: 2045 | AC60: 2046 | AD60: 2047 | AE60: 2048 | AF60: 2049 | AG60: 2050 | AH60: 2051 | AI60: 2052 | AJ60: 2053 | AK60: 2054 | AL60: 2055 | AM60: 2056 | AN60: 2057 | AO60: 2058 | AP60: 2059 | AQ60: 2060 | AR60: 2061 | AS60: 2062 | AT60: 2063 | AU60: 2064 | AV60: 2065 | AW60: 2066 | AX60: 2067 | AY60: 2068 | AZ60: 2069 | BA60: 2070
E61: =SUM(F61:BA61) -> 60 | F61: =COUNTIF($F$59:$BM$59,F60) -> 0 | G61: =COUNTIF($F$59:$BM$59,G60) -> 0 | H61: =COUNTIF($F$59:$BM$59,H60) -> 0 | I61: =COUNTIF($F$59:$BM$59,I60) -> 0 | J61: =COUNTIF($F$59:$BM$59,J60) -> 0 | K61: =COUNTIF($F$59:$BM$59,K60) -> 0 | L61: =COUNTIF($F$59:$BM$59,L60) -> 0 | M61: =COUNTIF($F$59:$BM$59,M60) -> 1 | ... BA61: =COUNTIF($F$59:$BM$59,BA60) -> 0
C62: 等额本息（季度） | D62: 期初借款累计 | F62: =D55 -> 725209.26 | G62: =F67 -> 716541.62 | H62: =G67 -> 707780.81 | I62: =H67 -> 698925.81 | J62: =I67 -> 689975.63 | K62: =J67 -> 680929.22 | L62: =K67 -> 671785.57 | M62: =L67 -> 662543.63 | N62: =M67 -> 653202.34 | ... BM62: =BL67 -> 16288.537
D63: 当期借款 | F63: 0 | G63: 0 | H63: 0 | I63: 0 | J63: 0 | K63: 0 | L63: 0 | M63: 0 | N63: 0 | O63: 0 | P63: 0 | Q63: 0 | R63: 0 | S63: 0 | T63: 0 | U63: 0 | V63: 0 | W63: 0 | X63: 0 | Y63: 0 | Z63: 0 | AA63: 0 | AB63: 0 | AC63: 0 | AD63: 0 | AE63: 0 | AF63: 0 | AG63: 0 | AH63: 0 | AI63: 0 | AJ63: 0 | AK63: 0 | AL63: 0 | AM63: 0 | AN63: 0 | AO63: 0 | AP63: 0 | AQ63: 0 | AR63: 0 | AS63: 0 | AT63: 0 | AU63: 0 | AV63: 0 | AW63: 0 | AX63: 0 | AY63: 0 | AZ63: 0 | BA63: 0 | BB63: 0 | BC63: 0 | BD63: 0 | BE63: 0 | BF63: 0 | BG63: 0 | BH63: 0 | BI63: 0 | BJ63: 0 | BK63: 0 | BL63: 0 | BM63: 0
D64: 当期还本付息 | E64: =SUM(F64:BM64) -> 987818.34 | F64: =-PMT($D$56,$D$53+1-F57,F62) -> 16463.639 | G64: =-PMT($D$56,$D$53+1-G57,G62) -> 16463.639 | H64: =-PMT($D$56,$D$53+1-H57,H62) -> 16463.639 | I64: =-PMT($D$56,$D$53+1-I57,I62) -> 16463.639 | J64: =-PMT($D$56,$D$53+1-J57,J62) -> 16463.639 | K64: =-PMT($D$56,$D$53+1-K57,K62) -> 16463.639 | L64: =-PMT($D$56,$D$53+1-L57,L62) -> 16463.639 | M64: =-PMT($D$56,$D$53+1-M57,M62) -> 16463.639 | ... BM64: =-PMT($D$56,$D$53+1-BM57,BM62) -> 16463.639
D65: 其中：还本 | E65: =SUM(F65:BM65) -> 725209.26 | F65: =F64-F66 -> 8667.6393 | G65: =G64-G66 -> 8760.8165 | H65: =H64-H66 -> 8854.9952 | I65: =I64-I66 -> 8950.1864 | J65: =J64-J66 -> 9046.401 | K65: =K64-K66 -> 9143.6498 | L65: =L64-L66 -> 9241.944 | M65: =M64-M66 -> 9341.2949 | ... BM65: =BM64-BM66 -> 16288.537
D66: 付息 | E66: =SUM(F66:BM66) -> 262609.07 | F66: =(F62+F63/2)*$D$56 -> 7795.9996 | G66: =(G62+G63/2)*$D$56 -> 7702.8225 | H66: =(H62+H63/2)*$D$56 -> 7608.6437 | I66: =(I62+I63/2)*$D$56 -> 7513.4525 | J66: =(J62+J63/2)*$D$56 -> 7417.238 | K66: =(K62+K63/2)*$D$56 -> 7319.9892 | L66: =(L62+L63/2)*$D$56 -> 7221.6949 | M66: =(M62+M63/2)*$D$56 -> 7122.344 | ... BM66: =(BM62+BM63/2)*$D$56 -> 175.10177
D67: 期末借款余额 | E67: =BM67 -> 5.6388672e-11 | F67: =F62+F63-F65 -> 716541.62 | G67: =G62+G63-G65 -> 707780.81 | H67: =H62+H63-H65 -> 698925.81 | I67: =I62+I63-I65 -> 689975.63 | J67: =J62+J63-J65 -> 680929.22 | K67: =K62+K63-K65 -> 671785.57 | L67: =L62+L63-L65 -> 662543.63 | M67: =M62+M63-M65 -> 653202.34 | ... BM67: =BM62+BM63-BM65 -> 5.6388672e-11
C68: 等额本金（季度） | D68: 期初借款累计 | F68: =D55 -> 725209.26 | G68: =F73 -> 713122.44 | H68: =G73 -> 701035.62 | I68: =H73 -> 688948.8 | J68: =I73 -> 676861.98 | K68: =J73 -> 664775.16 | L68: =K73 -> 652688.34 | M68: =L73 -> 640601.52 | N68: =M73 -> 628514.69 | ... BM68: =BL73 -> 12086.821
D69: 当期借款 | F69: 0 | G69: 0 | H69: 0 | I69: 0 | J69: 0 | K69: 0 | L69: 0 | M69: 0 | N69: 0 | O69: 0 | P69: 0 | Q69: 0 | R69: 0 | S69: 0 | T69: 0 | U69: 0 | V69: 0 | W69: 0 | X69: 0 | Y69: 0 | Z69: 0 | AA69: 0 | AB69: 0 | AC69: 0 | AD69: 0 | AE69: 0 | AF69: 0 | AG69: 0 | AH69: 0 | AI69: 0 | AJ69: 0 | AK69: 0 | AL69: 0 | AM69: 0 | AN69: 0 | AO69: 0 | AP69: 0 | AQ69: 0 | AR69: 0 | AS69: 0 | AT69: 0 | AU69: 0 | AV69: 0 | AW69: 0 | AX69: 0 | AY69: 0 | AZ69: 0 | BA69: 0 | BB69: 0 | BC69: 0 | BD69: 0 | BE69: 0 | BF69: 0 | BG69: 0 | BH69: 0 | BI69: 0 | BJ69: 0 | BK69: 0 | BL69: 0 | BM69: 0
D70: 当期还本付息 | E70: =SUM(F70:BM70) -> 962987.25 | F70: =SUM(F71:F72) -> 19882.821 | G70: =SUM(G71:G72) -> 19752.887 | H70: =SUM(H71:H72) -> 19622.954 | I70: =SUM(I71:I72) -> 19493.021 | J70: =SUM(J71:J72) -> 19363.087 | K70: =SUM(K71:K72) -> 19233.154 | L70: =SUM(L71:L72) -> 19103.221 | M70: =SUM(M71:M72) -> 18973.287 | ... BM70: =SUM(BM71:BM72) -> 12216.754
D71: 其中：还本 | E71: =SUM(F71:BM71) -> 725209.26 | F71: =$D$55/$D$53 -> 12086.821 | G71: =$D$55/$D$53 -> 12086.821 | H71: =$D$55/$D$53 -> 12086.821 | I71: =$D$55/$D$53 -> 12086.821 | J71: =$D$55/$D$53 -> 12086.821 | K71: =$D$55/$D$53 -> 12086.821 | L71: =$D$55/$D$53 -> 12086.821 | M71: =$D$55/$D$53 -> 12086.821 | ... BM71: =$D$55/$D$53 -> 12086.821
D72: 付息 | E72: =SUM(F72:BM72) -> 237777.99 | F72: =(F68+F69/2)*$D$56 -> 7795.9996 | G72: =(G68+G69/2)*$D$56 -> 7666.0663 | H72: =(H68+H69/2)*$D$56 -> 7536.1329 | I72: =(I68+I69/2)*$D$56 -> 7406.1996 | J72: =(J68+J69/2)*$D$56 -> 7276.2663 | K72: =(K68+K69/2)*$D$56 -> 7146.3329 | L72: =(L68+L69/2)*$D$56 -> 7016.3996 | M72: =(M68+M69/2)*$D$56 -> 6886.4663 | ... BM72: =(BM68+BM69/2)*$D$56 -> 129.93333
D73: 期末借款余额 | E73: =BM73 -> 4.2200554e-10 | F73: =F68+F69-F71 -> 713122.44 | G73: =G68+G69-G71 -> 701035.62 | H73: =H68+H69-H71 -> 688948.8 | I73: =I68+I69-I71 -> 676861.98 | J73: =J68+J69-J71 -> 664775.16 | K73: =K68+K69-K71 -> 652688.34 | L73: =L68+L69-L71 -> 640601.52 | M73: =M68+M69-M71 -> 628514.69 | ... BM73: =BM68+BM69-BM71 -> 4.2200554e-10
B75: 半年度还款 | C75: 建设期 | D75: =参数输入表!I5 -> 44958
C76: 宽限期 | D76: =D47 -> 91 | E76: 月
D77: =EDATE(D75,D76)-1 -> 47726 | E77: 宽限期结束日
C78: 还款日期（首期） | D78: =EDATE(D75,D76+D80) -> 47908
C79: 还款期限 | D79: =参数输入表!I256 -> 15 | E79: 年
C80: 每期计息月份数 | D80: 6 | E80: 月
C81: 年还款次数 | D81: =12/D80 -> 2 | E81: 次
C82: 总还款期数 | D82: =D79*D81 -> 30 | E82: 期
C83: 还款日期（末期） | D83: =EDATE(D78,D79*12-D80) -> 53206 | E83: =AI87 -> 53206
C84: 贷款额 | D84: =SUM(D42:D43) -> 725209.26 | E84: 万元
C85: 半年度利率 | D85: =参数输入表!$I$252/D81 -> 0.0215 | E85: %
C86: 还款计划安排（半年度） | D86: 期数 | F86: 1 | G86: 2 | H86: 3 | I86: 4 | J86: 5 | K86: 6 | L86: 7 | M86: 8 | N86: 9 | O86: 10 | P86: 11 | Q86: 12 | R86: 13 | S86: 14 | T86: 15 | U86: 16 | V86: 17 | W86: 18 | X86: 19 | Y86: 20 | Z86: 21 | AA86: 22 | AB86: 23 | AC86: 24 | AD86: 25 | AE86: 26 | AF86: 27 | AG86: 28 | AH86: 29 | AI86: 30
D87: 还款日期 | F87: =D78 -> 47908 | G87: =EDATE(F87,$D$80) -> 48092 | H87: =EDATE(G87,$D$80) -> 48274 | I87: =EDATE(H87,$D$80) -> 48458 | J87: =EDATE(I87,$D$80) -> 48639 | K87: =EDATE(J87,$D$80) -> 48823 | L87: =EDATE(K87,$D$80) -> 49004 | M87: =EDATE(L87,$D$80) -> 49188 | N87: =EDATE(M87,$D$80) -> 49369 | ... AI87: =EDATE(AH87,$D$80) -> 53206
D88: 所属年度 | F88: =YEAR(F87) -> 2031 | G88: =YEAR(G87) -> 2031 | H88: =YEAR(H87) -> 2032 | I88: =YEAR(I87) -> 2032 | J88: =YEAR(J87) -> 2033 | K88: =YEAR(K87) -> 2033 | L88: =YEAR(L87) -> 2034 | M88: =YEAR(M87) -> 2034 | ... AI88: =YEAR(AI87) -> 2045
D89: 当年还款次数统计 | E89: =IF(E90=D82,"OK","F") -> OK | F89: 2023 | G89: 2024 | H89: 2025 | I89: 2026 | J89: 2027 | K89: 2028 | L89: 2029 | M89: 2030 | N89: 2031 | O89: 2032 | P89: 2033 | Q89: 2034 | R89: 2035 | S89: 2036 | T89: 2037 | U89: 2038 | V89: 2039 | W89: 2040 | X89: 2041 | Y89: 2042 | Z89: 2043 | AA89: 2044 | AB89: 2045 | AC89: 2046 | AD89: 2047 | AE89: 2048 | AF89: 2049 | AG89: 2050 | AH89: 2051 | AI89: 2052 | AJ89: 2053 | AK89: 2054 | AL89: 2055 | AM89: 2056 | AN89: 2057 | AO89: 2058 | AP89: 2059 | AQ89: 2060 | AR89: 2061 | AS89: 2062 | AT89: 2063 | AU89: 2064 | AV89: 2065 | AW89: 2066 | AX89: 2067 | AY89: 2068 | AZ89: 2069 | BA89: 2070
E90: =SUM(F90:BA90) -> 30 | F90: =COUNTIF($F$88:$BM$88,F89) -> 0 | G90: =COUNTIF($F$88:$BM$88,G89) -> 0 | H90: =COUNTIF($F$88:$BM$88,H89) -> 0 | I90: =COUNTIF($F$88:$BM$88,I89) -> 0 | J90: =COUNTIF($F$88:$BM$88,J89) -> 0 | K90: =COUNTIF($F$88:$BM$88,K89) -> 0 | L90: =COUNTIF($F$88:$BM$88,L89) -> 0 | M90: =COUNTIF($F$88:$BM$88,M89) -> 0 | ... BA90: =COUNTIF($F$88:$BM$88,BA89) -> 0
C91: 等额本息（半年度） | D91: 期初借款累计 | F91: =D84 -> 725209.26 | G91: =F96 -> 707749.06 | H91: =G96 -> 689913.47 | I91: =H96 -> 671694.4 | J91: =I96 -> 653083.63 | K91: =J96 -> 634072.73 | L91: =K96 -> 614653.09 | M91: =L96 -> 594815.93 | N91: =M96 -> 574552.28 | ... AI91: =AH96 -> 32356.535
D92: 当期借款 | F92: 0 | G92: 0 | H92: 0 | I92: 0 | J92: 0 | K92: 0 | L92: 0 | M92: 0 | N92: 0 | O92: 0 | P92: 0 | Q92: 0 | R92: 0 | S92: 0 | T92: 0 | U92: 0 | V92: 0 | W92: 0 | X92: 0 | Y92: 0 | Z92: 0 | AA92: 0 | AB92: 0 | AC92: 0 | AD92: 0 | AE92: 0 | AF92: 0 | AG92: 0 | AH92: 0 | AI92: 0
D93: 当期还本付息 | E93: =SUM(F93:AI93) -> 991566.02 | F93: =-PMT($D$85,$D$82+1-F86,F91) -> 33052.201 | G93: =-PMT($D$85,$D$82+1-G86,G91) -> 33052.201 | H93: =-PMT($D$85,$D$82+1-H86,H91) -> 33052.201 | I93: =-PMT($D$85,$D$82+1-I86,I91) -> 33052.201 | J93: =-PMT($D$85,$D$82+1-J86,J91) -> 33052.201 | K93: =-PMT($D$85,$D$82+1-K86,K91) -> 33052.201 | L93: =-PMT($D$85,$D$82+1-L86,L91) -> 33052.201 | M93: =-PMT($D$85,$D$82+1-M86,M91) -> 33052.201 | ... AI93: =-PMT($D$85,$D$82+1-AI86,AI91) -> 33052.201
D94: 其中：还本 | E94: =SUM(F94:AI94) -> 725209.26 | F94: =F93-F95 -> 17460.202 | G94: =G93-G95 -> 17835.596 | H94: =H93-H95 -> 18219.061 | I94: =I93-I95 -> 18610.771 | J94: =J93-J95 -> 19010.903 | K94: =K93-K95 -> 19419.637 | L94: =L93-L95 -> 19837.159 | M94: =M93-M95 -> 20263.658 | ... AI94: =AI93-AI95 -> 32356.535
D95: 付息 | E95: =SUM(F95:AI95) -> 266356.76 | F95: =(F91+F92/2)*$D$85 -> 15591.999 | G95: =(G91+G92/2)*$D$85 -> 15216.605 | H95: =(H91+H92/2)*$D$85 -> 14833.14 | I95: =(I91+I92/2)*$D$85 -> 14441.43 | J95: =(J91+J92/2)*$D$85 -> 14041.298 | K95: =(K91+K92/2)*$D$85 -> 13632.564 | L95: =(L91+L92/2)*$D$85 -> 13215.042 | M95: =(M91+M92/2)*$D$85 -> 12788.543 | ... AI95: =(AI91+AI92/2)*$D$85 -> 695.66551
D96: 期末借款余额 | E96: =AI96 -> 1.1277734e-10 | F96: =F91+F92-F94 -> 707749.06 | G96: =G91+G92-G94 -> 689913.47 | H96: =H91+H92-H94 -> 671694.4 | I96: =I91+I92-I94 -> 653083.63 | J96: =J91+J92-J94 -> 634072.73 | K96: =K91+K92-K94 -> 614653.09 | L96: =L91+L92-L94 -> 594815.93 | M96: =M91+M92-M94 -> 574552.28 | ... AI96: =AI91+AI92-AI94 -> 1.1277734e-10
C97: 等额本金（半年度） | D97: 期初借款累计 | F97: =D84 -> 725209.26 | G97: =F102 -> 701035.62 | H97: =G102 -> 676861.98 | I97: =H102 -> 652688.34 | J97: =I102 -> 628514.69 | K97: =J102 -> 604341.05 | L97: =K102 -> 580167.41 | M97: =L102 -> 555993.77 | N97: =M102 -> 531820.13 | ... AI97: =AH102 -> 24173.642
D98: 当期借款 | F98: 0 | G98: 0 | H98: 0 | I98: 0 | J98: 0 | K98: 0 | L98: 0 | M98: 0 | N98: 0 | O98: 0 | P98: 0 | Q98: 0 | R98: 0 | S98: 0 | T98: 0 | U98: 0 | V98: 0 | W98: 0 | X98: 0 | Y98: 0 | Z98: 0 | AA98: 0 | AB98: 0 | AC98: 0 | AD98: 0 | AE98: 0 | AF98: 0 | AG98: 0 | AH98: 0 | AI98: 0
D99: 当期还本付息 | E99: =SUM(F99:AI99) -> 966885.25 | F99: =SUM(F100:F101) -> 39765.641 | G99: =SUM(G100:G101) -> 39245.908 | H99: =SUM(H100:H101) -> 38726.175 | I99: =SUM(I100:I101) -> 38206.441 | J99: =SUM(J100:J101) -> 37686.708 | K99: =SUM(K100:K101) -> 37166.975 | L99: =SUM(L100:L101) -> 36647.241 | M99: =SUM(M100:M101) -> 36127.508 | ... AI99: =SUM(AI100:AI101) -> 24693.375
D100: 其中：还本 | E100: =SUM(F100:AI100) -> 725209.26 | F100: =$D$84/$D$82 -> 24173.642 | G100: =$D$84/$D$82 -> 24173.642 | H100: =$D$84/$D$82 -> 24173.642 | I100: =$D$84/$D$82 -> 24173.642 | J100: =$D$84/$D$82 -> 24173.642 | K100: =$D$84/$D$82 -> 24173.642 | L100: =$D$84/$D$82 -> 24173.642 | M100: =$D$84/$D$82 -> 24173.642 | ... AI100: =$D$84/$D$82 -> 24173.642
D101: 付息 | E101: =SUM(F101:AI101) -> 241675.99 | F101: =(F97+F98/2)*$D$85 -> 15591.999 | G101: =(G97+G98/2)*$D$85 -> 15072.266 | H101: =(H97+H98/2)*$D$85 -> 14552.533 | I101: =(I97+I98/2)*$D$85 -> 14032.799 | J101: =(J97+J98/2)*$D$85 -> 13513.066 | K101: =(K97+K98/2)*$D$85 -> 12993.333 | L101: =(L97+L98/2)*$D$85 -> 12473.599 | M101: =(M97+M98/2)*$D$85 -> 11953.866 | ... AI101: =(AI97+AI98/2)*$D$85 -> 519.73331
D102: 期末借款余额 | E102: =AI102 -> 3.783498e-10 | F102: =F97+F98-F100 -> 701035.62 | G102: =G97+G98-G100 -> 676861.98 | H102: =H97+H98-H100 -> 652688.34 | I102: =I97+I98-I100 -> 628514.69 | J102: =J97+J98-J100 -> 604341.05 | K102: =K97+K98-K100 -> 580167.41 | L102: =L97+L98-L100 -> 555993.77 | M102: =M97+M98-M100 -> 531820.13 | ... AI102: =AI97+AI98-AI100 -> 3.783498e-10
B104: 月度还款 | C104: 建设期 | D104: =参数输入表!I5 -> 44958
...

Sheet 表2-折旧摊销表
C1: 中间过程引用（隐藏）
C2: 动态总投资（自主投资_不含流动资金） | D2: =参数输入表!I217 -> 966945.68
C3: 可抵扣进项税 | D3: =参数输入表!I221 -> 67754.505
C4: 固定资产原值 | D4: =D2-D15-D3 -> 819191.18 | F4: 固定资产原值=项目动态总投资（自主投资_不含流动资金）-可抵扣进项税-无形资产原值=项目静态总投资-建设补贴+建设期利息-可抵扣进项税-无形资产原值
C5: 折旧方式 | D5: 直线法/其他 | F5: 无形资产及固定资产均包含在动态总投资中
C6: 折旧年限 | D6: =参数输入表!I622 -> 29
C7: 残值率 | D7: =参数输入表!I623 -> 0.05
C8: 长期待摊费用（第1年） | D8: =参数输入表!I650/(1+参数输入表!I692) -> 458.7156 | F8: 长期待摊费用=计入长期待摊的成本项/（1+增值税税率）
C9: 长期待摊费用（第6年） | D9: =参数输入表!I655/(1+参数输入表!I692) -> 458.7156
C10: 长期待摊费用（第11年） | D10: =参数输入表!I660/(1+参数输入表!I692) -> 458.7156
C11: 长期待摊费用（第16年） | D11: =参数输入表!I665/(1+参数输入表!I692) -> 458.7156
C12: 长期待摊费用（第21年） | D12: =参数输入表!I670/(1+参数输入表!I692) -> 458.7156
C13: 摊销方式 | D13: 直线法/其他
C14: 摊销年限 | D14: =参数输入表!I691 -> 5
C15: 无形资产原值 | D15: =参数输入表!I636 -> 80000
C16: 摊销方式 | D16: 直线法/其他
C17: 摊销年限 | D17: =参数输入表!I638 -> 18
C18: 残值率 | D18: =参数输入表!I639 -> 0.05
C19: 大修及更新重置资产原值 | D19: =参数输入表!I712/(1+参数输入表!$I$745) -> 0
C20: 摊销方式 | D20: 直线法/其他
C21: 摊销年限 | D21: =参数输入表!I744 -> 10
D23: 增加验证条件： | E23: =IF((参数输入表!$I$217-参数输入表!$I$221)-(D40+D51+D114)>=0,"OK","F") -> OK
B24: 折旧摊销表-资本金
B25: 序号 | C25: 科目 | D25: 合计 | E25: 单位 | F25: 2023 | G25: 2024 | H25: 2025 | I25: 2026 | J25: 2027 | K25: 2028 | L25: 2029 | M25: 2030 | N25: 2031 | O25: 2032 | P25: 2033 | Q25: 2034 | R25: 2035 | S25: 2036 | T25: 2037 | U25: 2038 | V25: 2039 | W25: 2040 | X25: 2041 | Y25: 2042 | Z25: 2043 | AA25: 2044 | AB25: 2045 | AC25: 2046 | AD25: 2047 | AE25: 2048 | AF25: 2049 | AG25: 2050 | AH25: 2051 | AI25: 2052 | AJ25: 2053 | AK25: 2054 | AL25: 2055 | AM25: 2056 | AN25: 2057 | AO25: 2058 | AP25: 2059 | AQ25: 2060 | AR25: 2061 | AS25: 2062 | AT25: 2063 | AU25: 2064 | AV25: 2065 | AW25: 2066 | AX25: 2067 | AY25: 2068 | AZ25: 2069 | BA25: 2070
F26: 1 | G26: 2 | H26: 3 | I26: 4 | J26: 5 | K26: 6 | L26: 7 | M26: 8 | N26: 9 | O26: 10 | P26: 11 | Q26: 12 | R26: 13 | S26: 14 | T26: 15 | U26: 16 | V26: 17 | W26: 18 | X26: 19 | Y26: 20 | Z26: 21 | AA26: 22 | AB26: 23 | AC26: 24 | AD26: 25 | AE26: 26 | AF26: 27 | AG26: 28 | AH26: 29 | AI26: 30 | AJ26: 31 | AK26: 32 | AL26: 33 | AM26: 34 | AN26: 35 | AO26: 36 | AP26: 37 | AQ26: 38 | AR26: 39 | AS26: 40 | AT26: 41 | AU26: 42 | AV26: 43 | AW26: 44 | AX26: 45 | AY26: 46 | AZ26: 47 | BA26: 48
C27: 期末资产确认比例 | E27: % | F27: =SUMIF('投产&达产比例'!$T$11:$T$58,F25,'投产&达产比例'!$U$11:$U$58) -> 0 | G27: =SUMIF('投产&达产比例'!$T$11:$T$58,G25,'投产&达产比例'!$U$11:$U$58) -> 0 | H27: =SUMIF('投产&达产比例'!$T$11:$T$58,H25,'投产&达产比例'!$U$11:$U$58) -> 0 | I27: =SUMIF('投产&达产比例'!$T$11:$T$58,I25,'投产&达产比例'!$U$11:$U$58) -> 0 | J27: =SUMIF('投产&达产比例'!$T$11:$T$58,J25,'投产&达产比例'!$U$11:$U$58) -> 0 | K27: =SUMIF('投产&达产比例'!$T$11:$T$58,K25,'投产&达产比例'!$U$11:$U$58) -> 0 | L27: =SUMIF('投产&达产比例'!$T$11:$T$58,L25,'投产&达产比例'!$U$11:$U$58) -> 0 | M27: =SUMIF('投产&达产比例'!$T$11:$T$58,M25,'投产&达产比例'!$U$11:$U$58) -> 1 | ... BA27: =SUMIF('投产&达产比例'!$T$11:$T$58,BA25,'投产&达产比例'!$U$11:$U$58) -> 1
B28: 1.1 | C28: 期末固定资产原值 | E28: 万元 | F28: =(参数输入表!$I$217-参数输入表!$I$221-参数输入表!$I$625-参数输入表!$I$630-参数输入表!$I$636)*F27 -> 0 | G28: =(参数输入表!$I$217-参数输入表!$I$221-参数输入表!$I$625-参数输入表!$I$630-参数输入表!$I$636)*G27 -> 0 | H28: =(参数输入表!$I$217-参数输入表!$I$221-参数输入表!$I$625-参数输入表!$I$630-参数输入表!$I$636)*H27 -> 0 | I28: =(参数输入表!$I$217-参数输入表!$I$221-参数输入表!$I$625-参数输入表!$I$630-参数输入表!$I$636)*I27 -> 0 | J28: =(参数输入表!$I$217-参数输入表!$I$221-参数输入表!$I$625-参数输入表!$I$630-参数输入表!$I$636)*J27 -> 0 | K28: =(参数输入表!$I$217-参数输入表!$I$221-参数输入表!$I$625-参数输入表!$I$630-参数输入表!$I$636)*K27 -> 0 | L28: =(参数输入表!$I$217-参数输入表!$I$221-参数输入表!$I$625-参数输入表!$I$630-参数输入表!$I$636)*L27 -> 0 | M28: =(参数输入表!$I$217-参数输入表!$I$221-参数输入表!$I$625-参数输入表!$I$630-参数输入表!$I$636)*M27 -> 799991.18 | ... BA28: =(参数输入表!$I$217-参数输入表!$I$221-参数输入表!$I$625-参数输入表!$I$630-参数输入表!$I$636)*BA27 -> 799991.18
C29: 当期新增投资额 | D29: =SUM(F29:BA29) -> 799991.18 | E29: 万元 | F29: =IF(F26-参数输入表!$I$4>0,0,('表1-资金筹措及还本付息表'!F8+'表1-资金筹措及还本付息表'!G8+'表1-资金筹措及还本付息表'!F9+'表1-资金筹措及还本付息表'!G9-投资概算明细!F46-投资概算明细!G46)*(1-(参数输入表!$I$625+参数输入表!$I$630+参数输入表!$I$636)/(参数输入表!$I$217-参数输入表!$I$221))) -> 78480.346 | G29: =IF(G26-参数输入表!$I$4>0,0,('表1-资金筹措及还本付息表'!H8+'表1-资金筹措及还本付息表'!H9-投资概算明细!H46)*(1-(参数输入表!$I$625+参数输入表!$I$630+参数输入表!$I$636)/(参数输入表!$I$217-参数输入表!$I$221))) -> 79050.306 | H29: =IF(H26-参数输入表!$I$4>0,0,('表1-资金筹措及还本付息表'!I8+'表1-资金筹措及还本付息表'!I9-投资概算明细!I46)*(1-(参数输入表!$I$625+参数输入表!$I$630+参数输入表!$I$636)/(参数输入表!$I$217-参数输入表!$I$221))) -> 91969.932 | I29: =IF(I26-参数输入表!$I$4>0,0,('表1-资金筹措及还本付息表'!J8+'表1-资金筹措及还本付息表'!J9-投资概算明细!J46)*(1-(参数输入表!$I$625+参数输入表!$I$630+参数输入表!$I$636)/(参数输入表!$I$217-参数输入表!$I$221))) -> 103192.96 | J29: =IF(J26-参数输入表!$I$4>0,0,('表1-资金筹措及还本付息表'!K8+'表1-资金筹措及还本付息表'!K9-投资概算明细!K46)*(1-(参数输入表!$I$625+参数输入表!$I$630+参数输入表!$I$636)/(参数输入表!$I$217-参数输入表!$I$221))) -> 138480.78 | K29: =IF(K26-参数输入表!$I$4>0,0,('表1-资金筹措及还本付息表'!L8+'表1-资金筹措及还本付息表'!L9-投资概算明细!L46)*(1-(参数输入表!$I$625+参数输入表!$I$630+参数输入表!$I$636)/(参数输入表!$I$217-参数输入表!$I$221))) -> 132807.79 | L29: =IF(L26-参数输入表!$I$4>0,0,('表1-资金筹措及还本付息表'!M8+'表1-资金筹措及还本付息表'!N8+'表1-资金筹措及还本付息表'!M9+'表1-资金筹措及还本付息表'!N9-投资概算明细!M46-投资概算明细!N46)*(1-(参数输入表!$I$625+参数输入表!$I$630+参数输入表!$I$636)/(参数输入表!$I$217-参数输入表!$I$221))) -> 119233.2 | M29: =IF(M26-参数输入表!$I$4>0,0,('表1-资金筹措及还本付息表'!O8+'表1-资金筹措及还本付息表'!Q8+'表1-资金筹措及还本付息表'!O9+'表1-资金筹措及还本付息表'!Q9-投资概算明细!O46)*(1-(参数输入表!$I$625+参数输入表!$I$630+参数输入表!$I$636)/(参数输入表!$I$217-参数输入表!$I$221))) -> 56775.866 | N29: =IF(N26-参数输入表!$I$4>0,0,('表1-资金筹措及还本付息表'!R8+'表1-资金筹措及还本付息表'!R9-投资概算明细!P46)*(1-(参数输入表!$I$625+参数输入表!$I$630+参数输入表!$I$636)/(参数输入表!$I$217-参数输入表!$I$221))) -> 0 | O29: =IF(O26-参数输入表!$I$4>0,0,('表1-资金筹措及还本付息表'!S8+'表1-资金筹措及还本付息表'!S9-投资概算明细!Q46)*(1-(参数输入表!$I$625+参数输入表!$I$630+参数输入表!$I$636)/(参数输入表!$I$217-参数输入表!$I$221))) -> 0 | P29: =IF(P26-参数输入表!$I$4>0,0,('表1-资金筹措及还本付息表'!T8+'表1-资金筹措及还本付息表'!T9-投资概算明细!R46)*(1-(参数输入表!$I$625+参数输入表!$I$630+参数输入表!$I$636)/(参数输入表!$I$217-参数输入表!$I$221))) -> 0 | Q29: =IF(Q26-参数输入表!$I$4>0,0,('表1-资金筹措及还本付息表'!U8+'表1-资金筹措及还本付息表'!U9-投资概算明细!S46)*(1-(参数输入表!$I$625+参数输入表!$I$630+参数输入表!$I$636)/(参数输入表!$I$217-参数输入表!$I$221))) -> 0 | R29: =IF(R26-参数输入表!$I$4>0,0,('表1-资金筹措及还本付息表'!V8+'表1-资金筹措及还本付息表'!V9-投资概算明细!T46)*(1-(参数输入表!$I$625+参数输入表!$I$630+参数输入表!$I$636)/(参数输入表!$I$217-参数输入表!$I$221))) -> 0 | S29: =IF(S26-参数输入表!$I$4>0,0,('表1-资金筹措及还本付息表'!W8+'表1-资金筹措及还本付息表'!W9-投资概算明细!U46)*(1-(参数输入表!$I$625+参数输入表!$I$630+参数输入表!$I$636)/(参数输入表!$I$217-参数输入表!$I$221))) -> 0 | T29: =IF(T26-参数输入表!$I$4>0,0,('表1-资金筹措及还本付息表'!X8+'表1-资金筹措及还本付息表'!X9-投资概算明细!V46)*(1-(参数输入表!$I$625+参数输入表!$I$630+参数输入表!$I$636)/(参数输入表!$I$217-参数输入表!$I$221))) -> 0 | U29: =IF(U26-参数输入表!$I$4>0,0,('表1-资金筹措及还本付息表'!Y8+'表1-资金筹措及还本付息表'!Y9-投资概算明细!W46)*(1-(参数输入表!$I$625+参数输入表!$I$630+参数输入表!$I$636)/(参数输入表!$I$217-参数输入表!$I$221))) -> 0 | ... BA29: =IF(BA26-参数输入表!$I$4>0,0,('表1-资金筹措及还本付息表'!BE8+'表1-资金筹措及还本付息表'!BE9-投资概算明细!BC46)*(1-(参数输入表!$I$625+参数输入表!$I$630+参数输入表!$I$636)/(参数输入表!$I$217-参数输入表!$I$221))) -> 0
C30: 新增投资额累计 | E30: 万元 | F30: =F29 -> 78480.346 | G30: =F30+G29 -> 157530.65 | H30: =G30+H29 -> 249500.58 | I30: =H30+I29 -> 352693.54 | J30: =I30+J29 -> 491174.33 | K30: =J30+K29 -> 623982.11 | L30: =K30+L29 -> 743215.31 | M30: =L30+M29 -> 799991.18 | N30: =M30+N29 -> 799991.18 | ... BA30: =AZ30+BA29 -> 799991.18
C31: 期末在建工程 | E31: 万元 | F31: =F30-F28 -> 78480.346 | G31: =G30-G28 -> 157530.65 | H31: =H30-H28 -> 249500.58 | I31: =I30-I28 -> 352693.54 | J31: =J30-J28 -> 491174.33 | K31: =K30-K28 -> 623982.11 | L31: =L30-L28 -> 743215.31 | M31: =M30-M28 -> 0 | ... BA31: =BA30-BA28 -> 0
C32: 当期固定资产折旧 | D32: =SUM(F32:BA32) -> 759991.62 | E32: 万元 | F32: =SUM(F33:F36) -> 0 | G32: =SUM(G33:G36) -> 0 | H32: =SUM(H33:H36) -> 0 | I32: =SUM(I33:I36) -> 0 | J32: =SUM(J33:J36) -> 0 | K32: =SUM(K33:K36) -> 0 | L32: =SUM(L33:L36) -> 0 | M32: =SUM(M33:M36) -> 10919.42 | ... BA32: =SUM(BA33:BA36) -> 0
C33: 首批投产 | D33: =SUM(F33:BA33) -> 0 | E33: 万元 | F33: =(参数输入表!$I$217-参数输入表!$I$221-参数输入表!$I$625-参数输入表!$I$630-参数输入表!$I$636)*(1-参数输入表!$I$623)*参数输入表!$I$36*时间序列!C22/(参数输入表!$I$622*12) -> 0 | G33: =(参数输入表!$I$217-参数输入表!$I$221-参数输入表!$I$625-参数输入表!$I$630-参数输入表!$I$636)*(1-参数输入表!$I$623)*参数输入表!$I$36*时间序列!D22/(参数输入表!$I$622*12) -> 0 | H33: =(参数输入表!$I$217-参数输入表!$I$221-参数输入表!$I$625-参数输入表!$I$630-参数输入表!$I$636)*(1-参数输入表!$I$623)*参数输入表!$I$36*时间序列!E22/(参数输入表!$I$622*12) -> 0 | I33: =(参数输入表!$I$217-参数输入表!$I$221-参数输入表!$I$625-参数输入表!$I$630-参数输入表!$I$636)*(1-参数输入表!$I$623)*参数输入表!$I$36*时间序列!F22/(参数输入表!$I$622*12) -> 0 | J33: =(参数输入表!$I$217-参数输入表!$I$221-参数输入表!$I$625-参数输入表!$I$630-参数输入表!$I$636)*(1-参数输入表!$I$623)*参数输入表!$I$36*时间序列!G22/(参数输入表!$I$622*12) -> 0 | K33: =(参数输入表!$I$217-参数输入表!$I$221-参数输入表!$I$625-参数输入表!$I$630-参数输入表!$I$636)*(1-参数输入表!$I$623)*参数输入表!$I$36*时间序列!H22/(参数输入表!$I$622*12) -> 0 | L33: =(参数输入表!$I$217-参数输入表!$I$221-参数输入表!$I$625-参数输入表!$I$630-参数输入表!$I$636)*(1-参数输入表!$I$623)*参数输入表!$I$36*时间序列!I22/(参数输入表!$I$622*12) -> 0 | M33: =(参数输入表!$I$217-参数输入表!$I$221-参数输入表!$I$625-参数输入表!$I$630-参数输入表!$I$636)*(1-参数输入表!$I$623)*参数输入表!$I$36*时间序列!J22/(参数输入表!$I$622*12) -> 0 | ... BA33: =(参数输入表!$I$217-参数输入表!$I$221-参数输入表!$I$625-参数输入表!$I$630-参数输入表!$I$636)*(1-参数输入表!$I$623)*参数输入表!$I$36*时间序列!AX22/(参数输入表!$I$622*12) -> 0
C34: 第二批投产 | D34: =SUM(F34:BA34) -> 0 | E34: 万元 | F34: =(参数输入表!$I$217-参数输入表!$I$221-参数输入表!$I$625-参数输入表!$I$630-参数输入表!$I$636)*(1-参数输入表!$I$623)*参数输入表!$I$37*时间序列!C50/(参数输入表!$I$622*12) -> 0 | G34: =(参数输入表!$I$217-参数输入表!$I$221-参数输入表!$I$625-参数输入表!$I$630-参数输入表!$I$636)*(1-参数输入表!$I$623)*参数输入表!$I$37*时间序列!D50/(参数输入表!$I$622*12) -> 0 | H34: =(参数输入表!$I$217-参数输入表!$I$221-参数输入表!$I$625-参数输入表!$I$630-参数输入表!$I$636)*(1-参数输入表!$I$623)*参数输入表!$I$37*时间序列!E50/(参数输入表!$I$622*12) -> 0 | I34: =(参数输入表!$I$217-参数输入表!$I$221-参数输入表!$I$625-参数输入表!$I$630-参数输入表!$I$636)*(1-参数输入表!$I$623)*参数输入表!$I$37*时间序列!F50/(参数输入表!$I$622*12) -> 0 | J34: =(参数输入表!$I$217-参数输入表!$I$221-参数输入表!$I$625-参数输入表!$I$630-参数输入表!$I$636)*(1-参数输入表!$I$623)*参数输入表!$I$37*时间序列!G50/(参数输入表!$I$622*12) -> 0 | K34: =(参数输入表!$I$217-参数输入表!$I$221-参数输入表!$I$625-参数输入表!$I$630-参数输入表!$I$636)*(1-参数输入表!$I$623)*参数输入表!$I$37*时间序列!H50/(参数输入表!$I$622*12) -> 0 | L34: =(参数输入表!$I$217-参数输入表!$I$221-参数输入表!$I$625-参数输入表!$I$630-参数输入表!$I$636)*(1-参数输入表!$I$623)*参数输入表!$I$37*时间序列!I50/(参数输入表!$I$622*12) -> 0 | M34: =(参数输入表!$I$217-参数输入表!$I$221-参数输入表!$I$625-参数输入表!$I$630-参数输入表!$I$636)*(1-参数输入表!$I$623)*参数输入表!$I$37*时间序列!J50/(参数输入表!$I$622*12) -> 0 | ... BA34: =(参数输入表!$I$217-参数输入表!$I$221-参数输入表!$I$625-参数输入表!$I$630-参数输入表!$I$636)*(1-参数输入表!$I$623)*参数输入表!$I$37*时间序列!AX50/(参数输入表!$I$622*12) -> 0
C35: 第三批投产 | D35: =SUM(F35:BA35) -> 0 | E35: 万元 | F35: =(参数输入表!$I$217-参数输入表!$I$221-参数输入表!$I$625-参数输入表!$I$630-参数输入表!$I$636)*(1-参数输入表!$I$623)*参数输入表!$I$38*时间序列!C78/(参数输入表!$I$622*12) -> 0 | G35: =(参数输入表!$I$217-参数输入表!$I$221-参数输入表!$I$625-参数输入表!$I$630-参数输入表!$I$636)*(1-参数输入表!$I$623)*参数输入表!$I$38*时间序列!D78/(参数输入表!$I$622*12) -> 0 | H35: =(参数输入表!$I$217-参数输入表!$I$221-参数输入表!$I$625-参数输入表!$I$630-参数输入表!$I$636)*(1-参数输入表!$I$623)*参数输入表!$I$38*时间序列!E78/(参数输入表!$I$622*12) -> 0 | I35: =(参数输入表!$I$217-参数输入表!$I$221-参数输入表!$I$625-参数输入表!$I$630-参数输入表!$I$636)*(1-参数输入表!$I$623)*参数输入表!$I$38*时间序列!F78/(参数输入表!$I$622*12) -> 0 | J35: =(参数输入表!$I$217-参数输入表!$I$221-参数输入表!$I$625-参数输入表!$I$630-参数输入表!$I$636)*(1-参数输入表!$I$623)*参数输入表!$I$38*时间序列!G78/(参数输入表!$I$622*12) -> 0 | K35: =(参数输入表!$I$217-参数输入表!$I$221-参数输入表!$I$625-参数输入表!$I$630-参数输入表!$I$636)*(1-参数输入表!$I$623)*参数输入表!$I$38*时间序列!H78/(参数输入表!$I$622*12) -> 0 | L35: =(参数输入表!$I$217-参数输入表!$I$221-参数输入表!$I$625-参数输入表!$I$630-参数输入表!$I$636)*(1-参数输入表!$I$623)*参数输入表!$I$38*时间序列!I78/(参数输入表!$I$622*12) -> 0 | M35: =(参数输入表!$I$217-参数输入表!$I$221-参数输入表!$I$625-参数输入表!$I$630-参数输入表!$I$636)*(1-参数输入表!$I$623)*参数输入表!$I$38*时间序列!J78/(参数输入表!$I$622*12) -> 0 | ... BA35: =(参数输入表!$I$217-参数输入表!$I$221-参数输入表!$I$625-参数输入表!$I$630-参数输入表!$I$636)*(1-参数输入表!$I$623)*参数输入表!$I$38*时间序列!AX78/(参数输入表!$I$622*12) -> 0
C36: 完全投产 | D36: =SUM(F36:BA36) -> 759991.62 | E36: 万元 | F36: =(参数输入表!$I$217-参数输入表!$I$221-参数输入表!$I$625-参数输入表!$I$630-参数输入表!$I$636)*(1-参数输入表!$I$623)*参数输入表!$I$39*时间序列!C106/(参数输入表!$I$622*12) -> 0 | G36: =(参数输入表!$I$217-参数输入表!$I$221-参数输入表!$I$625-参数输入表!$I$630-参数输入表!$I$636)*(1-参数输入表!$I$623)*参数输入表!$I$39*时间序列!D106/(参数输入表!$I$622*12) -> 0 | H36: =(参数输入表!$I$217-参数输入表!$I$221-参数输入表!$I$625-参数输入表!$I$630-参数输入表!$I$636)*(1-参数输入表!$I$623)*参数输入表!$I$39*时间序列!E106/(参数输入表!$I$622*12) -> 0 | I36: =(参数输入表!$I$217-参数输入表!$I$221-参数输入表!$I$625-参数输入表!$I$630-参数输入表!$I$636)*(1-参数输入表!$I$623)*参数输入表!$I$39*时间序列!F106/(参数输入表!$I$622*12) -> 0 | J36: =(参数输入表!$I$217-参数输入表!$I$221-参数输入表!$I$625-参数输入表!$I$630-参数输入表!$I$636)*(1-参数输入表!$I$623)*参数输入表!$I$39*时间序列!G106/(参数输入表!$I$622*12) -> 0 | K36: =(参数输入表!$I$217-参数输入表!$I$221-参数输入表!$I$625-参数输入表!$I$630-参数输入表!$I$636)*(1-参数输入表!$I$623)*参数输入表!$I$39*时间序列!H106/(参数输入表!$I$622*12) -> 0 | L36: =(参数输入表!$I$217-参数输入表!$I$221-参数输入表!$I$625-参数输入表!$I$630-参数输入表!$I$636)*(1-参数输入表!$I$623)*参数输入表!$I$39*时间序列!I106/(参数输入表!$I$622*12) -> 0 | M36: =(参数输入表!$I$217-参数输入表!$I$221-参数输入表!$I$625-参数输入表!$I$630-参数输入表!$I$636)*(1-参数输入表!$I$623)*参数输入表!$I$39*时间序列!J106/(参数输入表!$I$622*12) -> 10919.42 | ... BA36: =(参数输入表!$I$217-参数输入表!$I$221-参数输入表!$I$625-参数输入表!$I$630-参数输入表!$I$636)*(1-参数输入表!$I$623)*参数输入表!$I$39*时间序列!AX106/(参数输入表!$I$622*12) -> 0
C37: 固定资产折旧累计 | E37: 万元 | F37: =F32 -> 0 | G37: =F37+G32 -> 0 | H37: =G37+H32 -> 0 | I37: =H37+I32 -> 0 | J37: =I37+J32 -> 0 | K37: =J37+K32 -> 0 | L37: =K37+L32 -> 0 | M37: =L37+M32 -> 10919.42 | N37: =M37+N32 -> 37126.027 | ... BA37: =AZ37+BA32 -> 759991.62
C38: 期末固定资产净值 | E38: 万元 | F38: =F28-F37 -> 0 | G38: =G28-G37 -> 0 | H38: =H28-H37 -> 0 | I38: =I28-I37 -> 0 | J38: =J28-J37 -> 0 | K38: =K28-K37 -> 0 | L38: =L28-L37 -> 0 | M38: =M28-M37 -> 789071.76 | ... BA38: =BA28-BA37 -> 39999.559
B39: 1.2 | C39: 期末（储能资产）原值 | E39: 万元 | F39: =参数输入表!$I$625*F27 -> 0 | G39: =参数输入表!$I$625*G27 -> 0 | H39: =参数输入表!$I$625*H27 -> 0 | I39: =参数输入表!$I$625*I27 -> 0 | J39: =参数输入表!$I$625*J27 -> 0 | K39: =参数输入表!$I$625*K27 -> 0 | L39: =参数输入表!$I$625*L27 -> 0 | M39: =参数输入表!$I$625*M27 -> 7200 | ... BA39: =参数输入表!$I$625*BA27 -> 7200
C40: 当期新增投资额 | D40: =SUM(F40:BA40) -> 7200 | E40: 万元 | F40: =IF(F26-参数输入表!$I$4>0,0,('表1-资金筹措及还本付息表'!F8+'表1-资金筹措及还本付息表'!G8+'表1-资金筹措及还本付息表'!F9+'表1-资金筹措及还本付息表'!G9-投资概算明细!F46-投资概算明细!G46)*(参数输入表!$I$625/(参数输入表!$I$217-参数输入表!$I$221))) -> 706.3309 | G40: =IF(G26-参数输入表!$I$4>0,0,('表1-资金筹措及还本付息表'!H8+'表1-资金筹措及还本付息表'!H9-投资概算明细!H46)*(参数输入表!$I$625/(参数输入表!$I$217-参数输入表!$I$221))) -> 711.4606 | H40: =IF(H26-参数输入表!$I$4>0,0,('表1-资金筹措及还本付息表'!I8+'表1-资金筹措及还本付息表'!I9-投资概算明细!I46)*(参数输入表!$I$625/(参数输入表!$I$217-参数输入表!$I$221))) -> 827.73851 | I40: =IF(I26-参数输入表!$I$4>0,0,('表1-资金筹措及还本付息表'!J8+'表1-资金筹措及还本付息表'!J9-投资概算明细!J46)*(参数输入表!$I$625/(参数输入表!$I$217-参数输入表!$I$221))) -> 928.74687 | J40: =IF(J26-参数输入表!$I$4>0,0,('表1-资金筹措及还本付息表'!K8+'表1-资金筹措及还本付息表'!K9-投资概算明细!K46)*(参数输入表!$I$625/(参数输入表!$I$217-参数输入表!$I$221))) -> 1246.3408 | K40: =IF(K26-参数输入表!$I$4>0,0,('表1-资金筹措及还本付息表'!L8+'表1-资金筹措及还本付息表'!L9-投资概算明细!L46)*(参数输入表!$I$625/(参数输入表!$I$217-参数输入表!$I$221))) -> 1195.2833 | L40: =IF(L26-参数输入表!$I$4>0,0,('表1-资金筹措及还本付息表'!M8+'表1-资金筹措及还本付息表'!N8+'表1-资金筹措及还本付息表'!M9+'表1-资金筹措及还本付息表'!N9-投资概算明细!M46-投资概算明细!N46)*(参数输入表!$I$625/(参数输入表!$I$217-参数输入表!$I$221))) -> 1073.1106 | M40: =IF(M26-参数输入表!$I$4>0,0,('表1-资金筹措及还本付息表'!O8+'表1-资金筹措及还本付息表'!Q8+'表1-资金筹措及还本付息表'!O9+'表1-资金筹措及还本付息表'!Q9-投资概算明细!O46)*(参数输入表!$I$625/(参数输入表!$I$217-参数输入表!$I$221))) -> 510.98843 | N40: =IF(N26-参数输入表!$I$4>0,0,('表1-资金筹措及还本付息表'!R8+'表1-资金筹措及还本付息表'!R9-投资概算明细!P46)*(参数输入表!$I$625/(参数输入表!$I$217-参数输入表!$I$221))) -> 0 | O40: =IF(O26-参数输入表!$I$4>0,0,('表1-资金筹措及还本付息表'!S8+'表1-资金筹措及还本付息表'!S9-投资概算明细!Q46)*(参数输入表!$I$625/(参数输入表!$I$217-参数输入表!$I$221))) -> 0 | P40: =IF(P26-参数输入表!$I$4>0,0,('表1-资金筹措及还本付息表'!T8+'表1-资金筹措及还本付息表'!T9-投资概算明细!R46)*(参数输入表!$I$625/(参数输入表!$I$217-参数输入表!$I$221))) -> 0 | Q40: =IF(Q26-参数输入表!$I$4>0,0,('表1-资金筹措及还本付息表'!U8+'表1-资金筹措及还本付息表'!U9-投资概算明细!S46)*(参数输入表!$I$625/(参数输入表!$I$217-参数输入表!$I$221))) -> 0 | R40: =IF(R26-参数输入表!$I$4>0,0,('表1-资金筹措及还本付息表'!V8+'表1-资金筹措及还本付息表'!V9-投资概算明细!T46)*(参数输入表!$I$625/(参数输入表!$I$217-参数输入表!$I$221))) -> 0 | S40: =IF(S26-参数输入表!$I$4>0,0,('表1-资金筹措及还本付息表'!W8+'表1-资金筹措及还本付息表'!W9-投资概算明细!U46)*(参数输入表!$I$625/(参数输入表!$I$217-参数输入表!$I$221))) -> 0 | T40: =IF(T26-参数输入表!$I$4>0,0,('表1-资金筹措及还本付息表'!X8+'表1-资金筹措及还本付息表'!X9-投资概算明细!V46)*(参数输入表!$I$625/(参数输入表!$I$217-参数输入表!$I$221))) -> 0 | U40: =IF(U26-参数输入表!$I$4>0,0,('表1-资金筹措及还本付息表'!Y8+'表1-资金筹措及还本付息表'!Y9-投资概算明细!W46)*(参数输入表!$I$625/(参数输入表!$I$217-参数输入表!$I$221))) -> 0 | ... BA40: =IF(BA26-参数输入表!$I$4>0,0,('表1-资金筹措及还本付息表'!BE8+'表1-资金筹措及还本付息表'!BE9-投资概算明细!BC46)*(参数输入表!$I$625/(参数输入表!$I$217-参数输入表!$I$221))) -> 0
C41: 新增投资额累计 | E41: 万元 | F41: =F40 -> 706.3309 | G41: =F41+G40 -> 1417.7915 | H41: =G41+H40 -> 2245.53 | I41: =H41+I40 -> 3174.2769 | J41: =I41+J40 -> 4420.6177 | K41: =J41+K40 -> 5615.9009 | L41: =K41+L40 -> 6689.0116 | M41: =L41+M40 -> 7200 | N41: =M41+N40 -> 7200 | ... BA41: =AZ41+BA40 -> 7200
C42: 期末在建工程（储能资产） | E42: 万元 | F42: =F41-F39 -> 706.3309 | G42: =G41-G39 -> 1417.7915 | H42: =H41-H39 -> 2245.53 | I42: =I41-I39 -> 3174.2769 | J42: =J41-J39 -> 4420.6177 | K42: =K41-K39 -> 5615.9009 | L42: =L41-L39 -> 6689.0116 | M42: =M41-M39 -> 0 | ... BA42: =BA41-BA39 -> 0
C43: 当期（储能资产）折旧 | D43: =SUM(F43:BA43) -> 6480 | E43: 万元 | F43: =SUM(F44:F47) -> 0 | G43: =SUM(G44:G47) -> 0 | H43: =SUM(H44:H47) -> 0 | I43: =SUM(I44:I47) -> 0 | J43: =SUM(J44:J47) -> 0 | K43: =SUM(K44:K47) -> 0 | L43: =SUM(L44:L47) -> 0 | M43: =SUM(M44:M47) -> 0 | ... BA43: =SUM(BA44:BA47) -> 0
C44: 首批投产 | D44: =SUM(F44:BA44) -> 0 | E44: 万元 | F44: =参数输入表!$I$625*(1-参数输入表!$I$628)*参数输入表!$I$36*时间序列!C34/(参数输入表!$I$627*12) -> 0 | G44: =参数输入表!$I$625*(1-参数输入表!$I$628)*参数输入表!$I$36*时间序列!D34/(参数输入表!$I$627*12) -> 0 | H44: =参数输入表!$I$625*(1-参数输入表!$I$628)*参数输入表!$I$36*时间序列!E34/(参数输入表!$I$627*12) -> 0 | I44: =参数输入表!$I$625*(1-参数输入表!$I$628)*参数输入表!$I$36*时间序列!F34/(参数输入表!$I$627*12) -> 0 | J44: =参数输入表!$I$625*(1-参数输入表!$I$628)*参数输入表!$I$36*时间序列!G34/(参数输入表!$I$627*12) -> 0 | K44: =参数输入表!$I$625*(1-参数输入表!$I$628)*参数输入表!$I$36*时间序列!H34/(参数输入表!$I$627*12) -> 0 | L44: =参数输入表!$I$625*(1-参数输入表!$I$628)*参数输入表!$I$36*时间序列!I34/(参数输入表!$I$627*12) -> 0 | M44: =参数输入表!$I$625*(1-参数输入表!$I$628)*参数输入表!$I$36*时间序列!J34/(参数输入表!$I$627*12) -> 0 | ... BA44: =参数输入表!$I$625*(1-参数输入表!$I$628)*参数输入表!$I$36*时间序列!AX34/(参数输入表!$I$627*12) -> 0
C45: 第二批投产 | D45: =SUM(F45:BA45) -> 0 | E45: 万元 | F45: =参数输入表!$I$625*(1-参数输入表!$I$628)*参数输入表!$I$37*时间序列!C62/(参数输入表!$I$627*12) -> 0 | G45: =参数输入表!$I$625*(1-参数输入表!$I$628)*参数输入表!$I$37*时间序列!D62/(参数输入表!$I$627*12) -> 0 | H45: =参数输入表!$I$625*(1-参数输入表!$I$628)*参数输入表!$I$37*时间序列!E62/(参数输入表!$I$627*12) -> 0 | I45: =参数输入表!$I$625*(1-参数输入表!$I$628)*参数输入表!$I$37*时间序列!F62/(参数输入表!$I$627*12) -> 0 | J45: =参数输入表!$I$625*(1-参数输入表!$I$628)*参数输入表!$I$37*时间序列!G62/(参数输入表!$I$627*12) -> 0 | K45: =参数输入表!$I$625*(1-参数输入表!$I$628)*参数输入表!$I$37*时间序列!H62/(参数输入表!$I$627*12) -> 0 | L45: =参数输入表!$I$625*(1-参数输入表!$I$628)*参数输入表!$I$37*时间序列!I62/(参数输入表!$I$627*12) -> 0 | M45: =参数输入表!$I$625*(1-参数输入表!$I$628)*参数输入表!$I$37*时间序列!J62/(参数输入表!$I$627*12) -> 0 | ... BA45: =参数输入表!$I$625*(1-参数输入表!$I$628)*参数输入表!$I$37*时间序列!AX62/(参数输入表!$I$627*12) -> 0
C46: 第三批投产 | D46: =SUM(F46:BA46) -> 0 | E46: 万元 | F46: =参数输入表!$I$625*(1-参数输入表!$I$628)*参数输入表!$I$38*时间序列!C90/(参数输入表!$I$627*12) -> 0 | G46: =参数输入表!$I$625*(1-参数输入表!$I$628)*参数输入表!$I$38*时间序列!D90/(参数输入表!$I$627*12) -> 0 | H46: =参数输入表!$I$625*(1-参数输入表!$I$628)*参数输入表!$I$38*时间序列!E90/(参数输入表!$I$627*12) -> 0 | I46: =参数输入表!$I$625*(1-参数输入表!$I$628)*参数输入表!$I$38*时间序列!F90/(参数输入表!$I$627*12) -> 0 | J46: =参数输入表!$I$625*(1-参数输入表!$I$628)*参数输入表!$I$38*时间序列!G90/(参数输入表!$I$627*12) -> 0 | K46: =参数输入表!$I$625*(1-参数输入表!$I$628)*参数输入表!$I$38*时间序列!H90/(参数输入表!$I$627*12) -> 0 | L46: =参数输入表!$I$625*(1-参数输入表!$I$628)*参数输入表!$I$38*时间序列!I90/(参数输入表!$I$627*12) -> 0 | M46: =参数输入表!$I$625*(1-参数输入表!$I$628)*参数输入表!$I$38*时间序列!J90/(参数输入表!$I$627*12) -> 0 | ... BA46: =参数输入表!$I$625*(1-参数输入表!$I$628)*参数输入表!$I$38*时间序列!AX90/(参数输入表!$I$627*12) -> 0
C47: 完全投产 | D47: =SUM(F47:BA47) -> 6480 | E47: 万元 | F47: =参数输入表!$I$625*(1-参数输入表!$I$628)*参数输入表!$I$39*时间序列!C118/(参数输入表!$I$627*12) -> 0 | G47: =参数输入表!$I$625*(1-参数输入表!$I$628)*参数输入表!$I$39*时间序列!D118/(参数输入表!$I$627*12) -> 0 | H47: =参数输入表!$I$625*(1-参数输入表!$I$628)*参数输入表!$I$39*时间序列!E118/(参数输入表!$I$627*12) -> 0 | I47: =参数输入表!$I$625*(1-参数输入表!$I$628)*参数输入表!$I$39*时间序列!F118/(参数输入表!$I$627*12) -> 0 | J47: =参数输入表!$I$625*(1-参数输入表!$I$628)*参数输入表!$I$39*时间序列!G118/(参数输入表!$I$627*12) -> 0 | K47: =参数输入表!$I$625*(1-参数输入表!$I$628)*参数输入表!$I$39*时间序列!H118/(参数输入表!$I$627*12) -> 0 | L47: =参数输入表!$I$625*(1-参数输入表!$I$628)*参数输入表!$I$39*时间序列!I118/(参数输入表!$I$627*12) -> 0 | M47: =参数输入表!$I$625*(1-参数输入表!$I$628)*参数输入表!$I$39*时间序列!J118/(参数输入表!$I$627*12) -> 0 | ... BA47: =参数输入表!$I$625*(1-参数输入表!$I$628)*参数输入表!$I$39*时间序列!AX118/(参数输入表!$I$627*12) -> 0
C48: （储能资产）折旧累计 | E48: 万元 | F48: =F43 -> 0 | G48: =F48+G43 -> 0 | H48: =G48+H43 -> 0 | I48: =H48+I43 -> 0 | J48: =I48+J43 -> 0 | K48: =J48+K43 -> 0 | L48: =K48+L43 -> 0 | M48: =L48+M43 -> 0 | N48: =M48+N43 -> 765 | ... BA48: =AZ48+BA43 -> 6480
C49: 期末（储能资产）净值 | E49: 万元 | F49: =F39-F48 -> 0 | G49: =G39-G48 -> 0 | H49: =H39-H48 -> 0 | I49: =I39-I48 -> 0 | J49: =J39-J48 -> 0 | K49: =K39-K48 -> 0 | L49: =L39-L48 -> 0 | M49: =M39-M48 -> 7200 | ... BA49: =BA39-BA48 -> 720
B50: 1.3 | C50: 期末（固定资产3）原值 | E50: 万元 | F50: =参数输入表!$I$630*F27 -> 0 | G50: =参数输入表!$I$630*G27 -> 0 | H50: =参数输入表!$I$630*H27 -> 0 | I50: =参数输入表!$I$630*I27 -> 0 | J50: =参数输入表!$I$630*J27 -> 0 | K50: =参数输入表!$I$630*K27 -> 0 | L50: =参数输入表!$I$630*L27 -> 0 | M50: =参数输入表!$I$630*M27 -> 12000 | ... BA50: =参数输入表!$I$630*BA27 -> 12000
C51: 当期新增投资额 | D51: =SUM(F51:BA51) -> 12000 | E51: 万元 | F51: =IF(F26-参数输入表!$I$4>0,0,('表1-资金筹措及还本付息表'!F8+'表1-资金筹措及还本付息表'!G8+'表1-资金筹措及还本付息表'!F9+'表1-资金筹措及还本付息表'!G9-投资概算明细!F46-投资概算明细!G46)*(参数输入表!$I$630/(参数输入表!$I$217-参数输入表!$I$221))) -> 1177.2182 | G51: =IF(G26-参数输入表!$I$4>0,0,('表1-资金筹措及还本付息表'!H8+'表1-资金筹措及还本付息表'!H9-投资概算明细!H46)*(参数输入表!$I$630/(参数输入表!$I$217-参数输入表!$I$221))) -> 1185.7677 | H51: =IF(H26-参数输入表!$I$4>0,0,('表1-资金筹措及还本付息表'!I8+'表1-资金筹措及还本付息表'!I9-投资概算明细!I46)*(参数输入表!$I$630/(参数输入表!$I$217-参数输入表!$I$221))) -> 1379.5642 | I51: =IF(I26-参数输入表!$I$4>0,0,('表1-资金筹措及还本付息表'!J8+'表1-资金筹措及还本付息表'!J9-投资概算明细!J46)*(参数输入表!$I$630/(参数输入表!$I$217-参数输入表!$I$221))) -> 1547.9115 | J51: =IF(J26-参数输入表!$I$4>0,0,('表1-资金筹措及还本付息表'!K8+'表1-资金筹措及还本付息表'!K9-投资概算明细!K46)*(参数输入表!$I$630/(参数输入表!$I$217-参数输入表!$I$221))) -> 2077.2346 | K51: =IF(K26-参数输入表!$I$4>0,0,('表1-资金筹措及还本付息表'!L8+'表1-资金筹措及还本付息表'!L9-投资概算明细!L46)*(参数输入表!$I$630/(参数输入表!$I$217-参数输入表!$I$221))) -> 1992.1388 | L51: =IF(L26-参数输入表!$I$4>0,0,('表1-资金筹措及还本付息表'!M8+'表1-资金筹措及还本付息表'!N8+'表1-资金筹措及还本付息表'!M9+'表1-资金筹措及还本付息表'!N9-投资概算明细!M46-投资概算明细!N46)*(参数输入表!$I$630/(参数输入表!$I$217-参数输入表!$I$221))) -> 1788.5177 | M51: =IF(M26-参数输入表!$I$4>0,0,('表1-资金筹措及还本付息表'!O8+'表1-资金筹措及还本付息表'!Q8+'表1-资金筹措及还本付息表'!O9+'表1-资金筹措及还本付息表'!Q9-投资概算明细!O46)*(参数输入表!$I$630/(参数输入表!$I$217-参数输入表!$I$221))) -> 851.64738 | N51: =IF(N26-参数输入表!$I$4>0,0,('表1-资金筹措及还本付息表'!R8+'表1-资金筹措及还本付息表'!R9-投资概算明细!P46)*(参数输入表!$I$630/(参数输入表!$I$217-参数输入表!$I$221))) -> 0 | O51: =IF(O26-参数输入表!$I$4>0,0,('表1-资金筹措及还本付息表'!S8+'表1-资金筹措及还本付息表'!S9-投资概算明细!Q46)*(参数输入表!$I$630/(参数输入表!$I$217-参数输入表!$I$221))) -> 0 | P51: =IF(P26-参数输入表!$I$4>0,0,('表1-资金筹措及还本付息表'!T8+'表1-资金筹措及还本付息表'!T9-投资概算明细!R46)*(参数输入表!$I$630/(参数输入表!$I$217-参数输入表!$I$221))) -> 0 | Q51: =IF(Q26-参数输入表!$I$4>0,0,('表1-资金筹措及还本付息表'!U8+'表1-资金筹措及还本付息表'!U9-投资概算明细!S46)*(参数输入表!$I$630/(参数输入表!$I$217-参数输入表!$I$221))) -> 0 | R51: =IF(R26-参数输入表!$I$4>0,0,('表1-资金筹措及还本付息表'!V8+'表1-资金筹措及还本付息表'!V9-投资概算明细!T46)*(参数输入表!$I$630/(参数输入表!$I$217-参数输入表!$I$221))) -> 0 | S51: =IF(S26-参数输入表!$I$4>0,0,('表1-资金筹措及还本付息表'!W8+'表1-资金筹措及还本付息表'!W9-投资概算明细!U46)*(参数输入表!$I$630/(参数输入表!$I$217-参数输入表!$I$221))) -> 0 | T51: =IF(T26-参数输入表!$I$4>0,0,('表1-资金筹措及还本付息表'!X8+'表1-资金筹措及还本付息表'!X9-投资概算明细!V46)*(参数输入表!$I$630/(参数输入表!$I$217-参数输入表!$I$221))) -> 0 | U51: =IF(U26-参数输入表!$I$4>0,0,('表1-资金筹措及还本付息表'!Y8+'表1-资金筹措及还本付息表'!Y9-投资概算明细!W46)*(参数输入表!$I$630/(参数输入表!$I$217-参数输入表!$I$221))) -> 0 | ... BA51: =IF(BA26-参数输入表!$I$4>0,0,('表1-资金筹措及还本付息表'!BE8+'表1-资金筹措及还本付息表'!BE9-投资概算明细!BC46)*(参数输入表!$I$630/(参数输入表!$I$217-参数输入表!$I$221))) -> 0
C52: 新增投资额累计 | E52: 万元 | F52: =F51 -> 1177.2182 | G52: =F52+G51 -> 2362.9858 | H52: =G52+H51 -> 3742.55 | I52: =H52+I51 -> 5290.4615 | J52: =I52+J51 -> 7367.6961 | K52: =J52+K51 -> 9359.8349 | L52: =K52+L51 -> 11148.353 | M52: =L52+M51 -> 12000 | N52: =M52+N51 -> 12000 | ... BA52: =AZ52+BA51 -> 12000
C53: 期末在建工程（固定资产3） | E53: 万元 | F53: =F52-F50 -> 1177.2182 | G53: =G52-G50 -> 2362.9858 | H53: =H52-H50 -> 3742.55 | I53: =I52-I50 -> 5290.4615 | J53: =J52-J50 -> 7367.6961 | K53: =K52-K50 -> 9359.8349 | L53: =L52-L50 -> 11148.353 | M53: =M52-M50 -> 0 | ... BA53: =BA52-BA50 -> 0
C54: 当期（固定资产3）折旧 | D54: =SUM(F54:BA54) -> 11400 | E54: 万元 | F54: =SUM(F55:F58) -> 0 | G54: =SUM(G55:G58) -> 0 | H54: =SUM(H55:H58) -> 0 | I54: =SUM(I55:I58) -> 0 | J54: =SUM(J55:J58) -> 0 | K54: =SUM(K55:K58) -> 0 | L54: =SUM(L55:L58) -> 0 | M54: =SUM(M55:M58) -> 0 | ... BA54: =SUM(BA55:BA58) -> 0
C55: 首批投产 | D55: =SUM(F55:BA55) -> 0 | E55: 万元 | F55: =参数输入表!$I$630*(1-参数输入表!$I$633)*参数输入表!$I$36*时间序列!C40/(参数输入表!$I$632*12) -> 0 | G55: =参数输入表!$I$630*(1-参数输入表!$I$633)*参数输入表!$I$36*时间序列!D40/(参数输入表!$I$632*12) -> 0 | H55: =参数输入表!$I$630*(1-参数输入表!$I$633)*参数输入表!$I$36*时间序列!E40/(参数输入表!$I$632*12) -> 0 | I55: =参数输入表!$I$630*(1-参数输入表!$I$633)*参数输入表!$I$36*时间序列!F40/(参数输入表!$I$632*12) -> 0 | J55: =参数输入表!$I$630*(1-参数输入表!$I$633)*参数输入表!$I$36*时间序列!G40/(参数输入表!$I$632*12) -> 0 | K55: =参数输入表!$I$630*(1-参数输入表!$I$633)*参数输入表!$I$36*时间序列!H40/(参数输入表!$I$632*12) -> 0 | L55: =参数输入表!$I$630*(1-参数输入表!$I$633)*参数输入表!$I$36*时间序列!I40/(参数输入表!$I$632*12) -> 0 | M55: =参数输入表!$I$630*(1-参数输入表!$I$633)*参数输入表!$I$36*时间序列!J40/(参数输入表!$I$632*12) -> 0 | ... BA55: =参数输入表!$I$630*(1-参数输入表!$I$633)*参数输入表!$I$36*时间序列!AX40/(参数输入表!$I$632*12) -> 0
C56: 第二批投产 | D56: =SUM(F56:BA56) -> 0 | E56: 万元 | F56: =参数输入表!$I$630*(1-参数输入表!$I$633)*参数输入表!$I$37*时间序列!C68/(参数输入表!$I$632*12) -> 0 | G56: =参数输入表!$I$630*(1-参数输入表!$I$633)*参数输入表!$I$37*时间序列!D68/(参数输入表!$I$632*12) -> 0 | H56: =参数输入表!$I$630*(1-参数输入表!$I$633)*参数输入表!$I$37*时间序列!E68/(参数输入表!$I$632*12) -> 0 | I56: =参数输入表!$I$630*(1-参数输入表!$I$633)*参数输入表!$I$37*时间序列!F68/(参数输入表!$I$632*12) -> 0 | J56: =参数输入表!$I$630*(1-参数输入表!$I$633)*参数输入表!$I$37*时间序列!G68/(参数输入表!$I$632*12) -> 0 | K56: =参数输入表!$I$630*(1-参数输入表!$I$633)*参数输入表!$I$37*时间序列!H68/(参数输入表!$I$632*12) -> 0 | L56: =参数输入表!$I$630*(1-参数输入表!$I$633)*参数输入表!$I$37*时间序列!I68/(参数输入表!$I$632*12) -> 0 | M56: =参数输入表!$I$630*(1-参数输入表!$I$633)*参数输入表!$I$37*时间序列!J68/(参数输入表!$I$632*12) -> 0 | ... BA56: =参数输入表!$I$630*(1-参数输入表!$I$633)*参数输入表!$I$37*时间序列!AX68/(参数输入表!$I$632*12) -> 0
C57: 第三批投产 | D57: =SUM(F57:BA57) -> 0 | E57: 万元 | F57: =参数输入表!$I$630*(1-参数输入表!$I$633)*参数输入表!$I$38*时间序列!C96/(参数输入表!$I$632*12) -> 0 | G57: =参数输入表!$I$630*(1-参数输入表!$I$633)*参数输入表!$I$38*时间序列!D96/(参数输入表!$I$632*12) -> 0 | H57: =参数输入表!$I$630*(1-参数输入表!$I$633)*参数输入表!$I$38*时间序列!E96/(参数输入表!$I$632*12) -> 0 | I57: =参数输入表!$I$630*(1-参数输入表!$I$633)*参数输入表!$I$38*时间序列!F96/(参数输入表!$I$632*12) -> 0 | J57: =参数输入表!$I$630*(1-参数输入表!$I$633)*参数输入表!$I$38*时间序列!G96/(参数输入表!$I$632*12) -> 0 | K57: =参数输入表!$I$630*(1-参数输入表!$I$633)*参数输入表!$I$38*时间序列!H96/(参数输入表!$I$632*12) -> 0 | L57: =参数输入表!$I$630*(1-参数输入表!$I$633)*参数输入表!$I$38*时间序列!I96/(参数输入表!$I$632*12) -> 0 | M57: =参数输入表!$I$630*(1-参数输入表!$I$633)*参数输入表!$I$38*时间序列!J96/(参数输入表!$I$632*12) -> 0 | ... BA57: =参数输入表!$I$630*(1-参数输入表!$I$633)*参数输入表!$I$38*时间序列!AX96/(参数输入表!$I$632*12) -> 0
C58: 完全投产 | D58: =SUM(F58:BA58) -> 11400 | E58: 万元 | F58: =参数输入表!$I$630*(1-参数输入表!$I$633)*参数输入表!$I$39*时间序列!C124/(参数输入表!$I$632*12) -> 0 | G58: =参数输入表!$I$630*(1-参数输入表!$I$633)*参数输入表!$I$39*时间序列!D124/(参数输入表!$I$632*12) -> 0 | H58: =参数输入表!$I$630*(1-参数输入表!$I$633)*参数输入表!$I$39*时间序列!E124/(参数输入表!$I$632*12) -> 0 | I58: =参数输入表!$I$630*(1-参数输入表!$I$633)*参数输入表!$I$39*时间序列!F124/(参数输入表!$I$632*12) -> 0 | J58: =参数输入表!$I$630*(1-参数输入表!$I$633)*参数输入表!$I$39*时间序列!G124/(参数输入表!$I$632*12) -> 0 | K58: =参数输入表!$I$630*(1-参数输入表!$I$633)*参数输入表!$I$39*时间序列!H124/(参数输入表!$I$632*12) -> 0 | L58: =参数输入表!$I$630*(1-参数输入表!$I$633)*参数输入表!$I$39*时间序列!I124/(参数输入表!$I$632*12) -> 0 | M58: =参数输入表!$I$630*(1-参数输入表!$I$633)*参数输入表!$I$39*时间序列!J124/(参数输入表!$I$632*12) -> 0 | ... BA58: =参数输入表!$I$630*(1-参数输入表!$I$633)*参数输入表!$I$39*时间序列!AX124/(参数输入表!$I$632*12) -> 0
C59: （固定资产3）折旧累计 | E59: 万元 | F59: =F54 -> 0 | G59: =F59+G54 -> 0 | H59: =G59+H54 -> 0 | I59: =H59+I54 -> 0 | J59: =I59+J54 -> 0 | K59: =J59+K54 -> 0 | L59: =K59+L54 -> 0 | M59: =L59+M54 -> 0 | N59: =M59+N54 -> 807.5 | ... BA59: =AZ59+BA54 -> 11400
C60: 期末（固定资产3）净值 | E60: 万元 | F60: =F50-F59 -> 0 | G60: =G50-G59 -> 0 | H60: =H50-H59 -> 0 | I60: =I50-I59 -> 0 | J60: =J50-J59 -> 0 | K60: =K50-K59 -> 0 | L60: =L50-L59 -> 0 | M60: =M50-M59 -> 12000 | ... BA60: =BA50-BA59 -> 600
B61: 2 | C61: 期初长期待摊费用 | E61: 万元 | F61: 0 | G61: =F112 -> 0 | H61: =G112 -> 0 | I61: =H112 -> 0 | J61: =I112 -> 0 | K61: =J112 -> 0 | L61: =K112 -> 0 | M61: =L112 -> 0 | N61: =M112 -> 0 | ... BA61: =AZ112 -> 244.64832
C62: 当期新增长期待摊费用 | D62: =SUM(F62:BA62) -> 4128.4404 | E62: 万元 | F62: =参数输入表!I642/(1+参数输入表!I692) -> 0 | G62: =参数输入表!I643/(1+参数输入表!I692) -> 0 | H62: =参数输入表!I644/(1+参数输入表!I692) -> 0 | I62: =参数输入表!I645/(1+参数输入表!I692) -> 0 | J62: =参数输入表!I646/(1+参数输入表!I692) -> 0 | K62: =参数输入表!I647/(1+参数输入表!I692) -> 0 | L62: =参数输入表!I648/(1+参数输入表!I692) -> 0 | M62: =参数输入表!I649/(1+参数输入表!I692) -> 0 | N62: =参数输入表!I650/(1+参数输入表!I692) -> 458.7156 | O62: =参数输入表!I651/(1+参数输入表!I692) -> 0 | P62: =参数输入表!I652/(1+参数输入表!I692) -> 0 | Q62: =参数输入表!I653/(1+参数输入表!I692) -> 0 | R62: =参数输入表!I654/(1+参数输入表!I692) -> 0 | S62: =参数输入表!I655/(1+参数输入表!I692) -> 458.7156 | T62: =参数输入表!I656/(1+参数输入表!I692) -> 0 | U62: =参数输入表!I657/(1+参数输入表!I692) -> 0 | V62: =参数输入表!I658/(1+参数输入表!I692) -> 0 | W62: =参数输入表!I659/(1+参数输入表!I692) -> 0 | X62: =参数输入表!I660/(1+参数输入表!I692) -> 458.7156 | Y62: =参数输入表!I661/(1+参数输入表!I692) -> 0 | Z62: =参数输入表!I662/(1+参数输入表!I692) -> 0 | AA62: =参数输入表!I663/(1+参数输入表!I692) -> 0 | AB62: =参数输入表!I664/(1+参数输入表!I692) -> 0 | AC62: =参数输入表!I665/(1+参数输入表!I692) -> 458.7156 | AD62: =参数输入表!I666/(1+参数输入表!I692) -> 0 | AE62: =参数输入表!I667/(1+参数输入表!I692) -> 0 | AF62: =参数输入表!I668/(1+参数输入表!I692) -> 0 | AG62: =参数输入表!I669/(1+参数输入表!I692) -> 0 | AH62: =参数输入表!I670/(1+参数输入表!I692) -> 458.7156 | AI62: =参数输入表!I671/(1+参数输入表!I692) -> 0 | AJ62: =参数输入表!I672/(1+参数输入表!I692) -> 0 | AK62: =参数输入表!I673/(1+参数输入表!I692) -> 0 | AL62: =参数输入表!I674/(1+参数输入表!I692) -> 0 | AM62: =参数输入表!I675/(1+参数输入表!I692) -> 458.7156 | AN62: =参数输入表!I676/(1+参数输入表!I692) -> 0 | AO62: =参数输入表!I677/(1+参数输入表!I692) -> 0 | AP62: =参数输入表!I678/(1+参数输入表!I692) -> 0 | AQ62: =参数输入表!I679/(1+参数输入表!I692) -> 0 | AR62: =参数输入表!I680/(1+参数输入表!I692) -> 458.7156 | AS62: =参数输入表!I681/(1+参数输入表!I692) -> 0 | AT62: =参数输入表!I682/(1+参数输入表!I692) -> 0 | AU62: =参数输入表!I683/(1+参数输入表!I692) -> 0 | AV62: =参数输入表!I684/(1+参数输入表!I692) -> 0 | AW62: =参数输入表!I685/(1+参数输入表!I692) -> 458.7156 | AX62: =参数输入表!I686/(1+参数输入表!I692) -> 0 | AY62: =参数输入表!I687/(1+参数输入表!I692) -> 458.7156 | AZ62: =参数输入表!I688/(1+参数输入表!I692) -> 0 | BA62: =参数输入表!I689/(1+参数输入表!I692) -> 0
C63: 当期摊销 | D63: =SUM(F63:BA63) -> 4128.4404 | E63: 万元 | F63: =SUM(F64:F111) -> 0 | G63: =SUM(G64:G111) -> 0 | H63: =SUM(H64:H111) -> 0 | I63: =SUM(I64:I111) -> 0 | J63: =SUM(J64:J111) -> 0 | K63: =SUM(K64:K111) -> 0 | L63: =SUM(L64:L111) -> 0 | M63: =SUM(M64:M111) -> 0 | ... BA63: =SUM(BA64:BA111) -> 244.64832
C64: 合作期第1年 | D64: =SUM(F64:BA64) -> 0 | E64: 万元 | F64: =IF('表2-折旧摊销表'!$BA$26+1-'表2-折旧摊销表'!$F$26>='表2-折旧摊销表'!$D$14,$F$62/$D$14,$F$62/('表2-折旧摊销表'!$BA$26+1-'表2-折旧摊销表'!$F$26)) -> 0 | G64: =IF('表2-折旧摊销表'!$BA$26+1-'表2-折旧摊销表'!$F$26>='表2-折旧摊销表'!$D$14,$F$62/$D$14,$F$62/('表2-折旧摊销表'!$BA$26+1-'表2-折旧摊销表'!$F$26)) -> 0 | H64: =IF('表2-折旧摊销表'!$BA$26+1-'表2-折旧摊销表'!$F$26>='表2-折旧摊销表'!$D$14,$F$62/$D$14,$F$62/('表2-折旧摊销表'!$BA$26+1-'表2-折旧摊销表'!$F$26)) -> 0 | I64: =IF('表2-折旧摊销表'!$BA$26+1-'表2-折旧摊销表'!$F$26>='表2-折旧摊销表'!$D$14,$F$62/$D$14,$F$62/('表2-折旧摊销表'!$BA$26+1-'表2-折旧摊销表'!$F$26)) -> 0 | J64: =IF('表2-折旧摊销表'!$BA$26+1-'表2-折旧摊销表'!$F$26>='表2-折旧摊销表'!$D$14,$F$62/$D$14,$F$62/('表2-折旧摊销表'!$BA$26+1-'表2-折旧摊销表'!$F$26)) -> 0
C65: 合作期第2年 | D65: =SUM(F65:BA65) -> 0 | E65: 万元 | G65: =IF('表2-折旧摊销表'!$BA$26+1-'表2-折旧摊销表'!$G$26>='表2-折旧摊销表'!$D$14,$G$62/$D$14,$G$62/('表2-折旧摊销表'!$BA$26+1-'表2-折旧摊销表'!$G$26)) -> 0 | H65: =IF('表2-折旧摊销表'!$BA$26+1-'表2-折旧摊销表'!$G$26>='表2-折旧摊销表'!$D$14,$G$62/$D$14,$G$62/('表2-折旧摊销表'!$BA$26+1-'表2-折旧摊销表'!$G$26)) -> 0 | I65: =IF('表2-折旧摊销表'!$BA$26+1-'表2-折旧摊销表'!$G$26>='表2-折旧摊销表'!$D$14,$G$62/$D$14,$G$62/('表2-折旧摊销表'!$BA$26+1-'表2-折旧摊销表'!$G$26)) -> 0 | J65: =IF('表2-折旧摊销表'!$BA$26+1-'表2-折旧摊销表'!$G$26>='表2-折旧摊销表'!$D$14,$G$62/$D$14,$G$62/('表2-折旧摊销表'!$BA$26+1-'表2-折旧摊销表'!$G$26)) -> 0 | K65: =IF('表2-折旧摊销表'!$BA$26+1-'表2-折旧摊销表'!$G$26>='表2-折旧摊销表'!$D$14,$G$62/$D$14,$G$62/('表2-折旧摊销表'!$BA$26+1-'表2-折旧摊销表'!$G$26)) -> 0
C66: 合作期第3年 | D66: =SUM(F66:BA66) -> 0 | E66: 万元 | H66: =IF('表2-折旧摊销表'!$BA$26+1-'表2-折旧摊销表'!$H$26>='表2-折旧摊销表'!$D$14,$H$62/$D$14,$H$62/('表2-折旧摊销表'!$BA$26+1-'表2-折旧摊销表'!$H$26)) -> 0 | I66: =IF('表2-折旧摊销表'!$BA$26+1-'表2-折旧摊销表'!$H$26>='表2-折旧摊销表'!$D$14,$H$62/$D$14,$H$62/('表2-折旧摊销表'!$BA$26+1-'表2-折旧摊销表'!$H$26)) -> 0 | J66: =IF('表2-折旧摊销表'!$BA$26+1-'表2-折旧摊销表'!$H$26>='表2-折旧摊销表'!$D$14,$H$62/$D$14,$H$62/('表2-折旧摊销表'!$BA$26+1-'表2-折旧摊销表'!$H$26)) -> 0 | K66: =IF('表2-折旧摊销表'!$BA$26+1-'表2-折旧摊销表'!$H$26>='表2-折旧摊销表'!$D$14,$H$62/$D$14,$H$62/('表2-折旧摊销表'!$BA$26+1-'表2-折旧摊销表'!$H$26)) -> 0 | L66: =IF('表2-折旧摊销表'!$BA$26+1-'表2-折旧摊销表'!$H$26>='表2-折旧摊销表'!$D$14,$H$62/$D$14,$H$62/('表2-折旧摊销表'!$BA$26+1-'表2-折旧摊销表'!$H$26)) -> 0
C67: 合作期第4年 | D67: =SUM(F67:BA67) -> 0 | E67: 万元 | I67: =IF('表2-折旧摊销表'!$BA$26+1-'表2-折旧摊销表'!$I$26>='表2-折旧摊销表'!$D$14,$I$62/$D$14,$I$62/('表2-折旧摊销表'!$BA$26+1-'表2-折旧摊销表'!$I$26)) -> 0 | J67: =IF('表2-折旧摊销表'!$BA$26+1-'表2-折旧摊销表'!$I$26>='表2-折旧摊销表'!$D$14,$I$62/$D$14,$I$62/('表2-折旧摊销表'!$BA$26+1-'表2-折旧摊销表'!$I$26)) -> 0 | K67: =IF('表2-折旧摊销表'!$BA$26+1-'表2-折旧摊销表'!$I$26>='表2-折旧摊销表'!$D$14,$I$62/$D$14,$I$62/('表2-折旧摊销表'!$BA$26+1-'表2-折旧摊销表'!$I$26)) -> 0 | L67: =IF('表2-折旧摊销表'!$BA$26+1-'表2-折旧摊销表'!$I$26>='表2-折旧摊销表'!$D$14,$I$62/$D$14,$I$62/('表2-折旧摊销表'!$BA$26+1-'表2-折旧摊销表'!$I$26)) -> 0 | M67: =IF('表2-折旧摊销表'!$BA$26+1-'表2-折旧摊销表'!$I$26>='表2-折旧摊销表'!$D$14,$I$62/$D$14,$I$62/('表2-折旧摊销表'!$BA$26+1-'表2-折旧摊销表'!$I$26)) -> 0
C68: 合作期第5年 | D68: =SUM(F68:BA68) -> 0 | E68: 万元 | J68: =IF('表2-折旧摊销表'!$BA$26+1-'表2-折旧摊销表'!$J$26>='表2-折旧摊销表'!$D$14,$J$62/$D$14,$J$62/('表2-折旧摊销表'!$BA$26+1-'表2-折旧摊销表'!$J$26)) -> 0 | K68: =IF('表2-折旧摊销表'!$BA$26+1-'表2-折旧摊销表'!$J$26>='表2-折旧摊销表'!$D$14,$J$62/$D$14,$J$62/('表2-折旧摊销表'!$BA$26+1-'表2-折旧摊销表'!$J$26)) -> 0 | L68: =IF('表2-折旧摊销表'!$BA$26+1-'表2-折旧摊销表'!$J$26>='表2-折旧摊销表'!$D$14,$J$62/$D$14,$J$62/('表2-折旧摊销表'!$BA$26+1-'表2-折旧摊销表'!$J$26)) -> 0 | M68: =IF('表2-折旧摊销表'!$BA$26+1-'表2-折旧摊销表'!$J$26>='表2-折旧摊销表'!$D$14,$J$62/$D$14,$J$62/('表2-折旧摊销表'!$BA$26+1-'表2-折旧摊销表'!$J$26)) -> 0 | N68: =IF('表2-折旧摊销表'!$BA$26+1-'表2-折旧摊销表'!$J$26>='表2-折旧摊销表'!$D$14,$J$62/$D$14,$J$62/('表2-折旧摊销表'!$BA$26+1-'表2-折旧摊销表'!$J$26)) -> 0
C69: 合作期第6年 | D69: =SUM(F69:BA69) -> 0 | E69: 万元 | K69: =IF('表2-折旧摊销表'!$BA$26+1-'表2-折旧摊销表'!$K$26>='表2-折旧摊销表'!$D$14,$K$62/$D$14,$K$62/('表2-折旧摊销表'!$BA$26+1-'表2-折旧摊销表'!$K$26)) -> 0 | L69: =IF('表2-折旧摊销表'!$BA$26+1-'表2-折旧摊销表'!$K$26>='表2-折旧摊销表'!$D$14,$K$62/$D$14,$K$62/('表2-折旧摊销表'!$BA$26+1-'表2-折旧摊销表'!$K$26)) -> 0 | M69: =IF('表2-折旧摊销表'!$BA$26+1-'表2-折旧摊销表'!$K$26>='表2-折旧摊销表'!$D$14,$K$62/$D$14,$K$62/('表2-折旧摊销表'!$BA$26+1-'表2-折旧摊销表'!$K$26)) -> 0 | N69: =IF('表2-折旧摊销表'!$BA$26+1-'表2-折旧摊销表'!$K$26>='表2-折旧摊销表'!$D$14,$K$62/$D$14,$K$62/('表2-折旧摊销表'!$BA$26+1-'表2-折旧摊销表'!$K$26)) -> 0 | O69: =IF('表2-折旧摊销表'!$BA$26+1-'表2-折旧摊销表'!$K$26>='表2-折旧摊销表'!$D$14,$K$62/$D$14,$K$62/('表2-折旧摊销表'!$BA$26+1-'表2-折旧摊销表'!$K$26)) -> 0
C70: 合作期第7年 | D70: =SUM(F70:BA70) -> 0 | E70: 万元 | L70: =IF('表2-折旧摊销表'!$BA$26+1-'表2-折旧摊销表'!$L$26>='表2-折旧摊销表'!$D$14,$L$62/$D$14,$L$62/('表2-折旧摊销表'!$BA$26+1-'表2-折旧摊销表'!$L$26)) -> 0 | M70: =IF('表2-折旧摊销表'!$BA$26+1-'表2-折旧摊销表'!$L$26>='表2-折旧摊销表'!$D$14,$L$62/$D$14,$L$62/('表2-折旧摊销表'!$BA$26+1-'表2-折旧摊销表'!$L$26)) -> 0 | N70: =IF('表2-折旧摊销表'!$BA$26+1-'表2-折旧摊销表'!$L$26>='表2-折旧摊销表'!$D$14,$L$62/$D$14,$L$62/('表2-折旧摊销表'!$BA$26+1-'表2-折旧摊销表'!$L$26)) -> 0 | O70: =IF('表2-折旧摊销表'!$BA$26+1-'表2-折旧摊销表'!$L$26>='表2-折旧摊销表'!$D$14,$L$62/$D$14,$L$62/('表2-折旧摊销表'!$BA$26+1-'表2-折旧摊销表'!$L$26)) -> 0 | P70: =IF('表2-折旧摊销表'!$BA$26+1-'表2-折旧摊销表'!$L$26>='表2-折旧摊销表'!$D$14,$L$62/$D$14,$L$62/('表2-折旧摊销表'!$BA$26+1-'表2-折旧摊销表'!$L$26)) -> 0
C71: 合作期第8年 | D71: =SUM(F71:BA71) -> 0 | E71: 万元 | M71: =IF('表2-折旧摊销表'!$BA$26+1-'表2-折旧摊销表'!$M$26>='表2-折旧摊销表'!$D$14,$M$62/$D$14,$M$62/('表2-折旧摊销表'!$BA$26+1-'表2-折旧摊销表'!$M$26)) -> 0 | N71: =IF('表2-折旧摊销表'!$BA$26+1-'表2-折旧摊销表'!$M$26>='表2-折旧摊销表'!$D$14,$M$62/$D$14,$M$62/('表2-折旧摊销表'!$BA$26+1-'表2-折旧摊销表'!$M$26)) -> 0 | O71: =IF('表2-折旧摊销表'!$BA$26+1-'表2-折旧摊销表'!$M$26>='表2-折旧摊销表'!$D$14,$M$62/$D$14,$M$62/('表2-折旧摊销表'!$BA$26+1-'表2-折旧摊销表'!$M$26)) -> 0 | P71: =IF('表2-折旧摊销表'!$BA$26+1-'表2-折旧摊销表'!$M$26>='表2-折旧摊销表'!$D$14,$M$62/$D$14,$M$62/('表2-折旧摊销表'!$BA$26+1-'表2-折旧摊销表'!$M$26)) -> 0 | Q71: =IF('表2-折旧摊销表'!$BA$26+1-'表2-折旧摊销表'!$M$26>='表2-折旧摊销表'!$D$14,$M$62/$D$14,$M$62/('表2-折旧摊销表'!$BA$26+1-'表2-折旧摊销表'!$M$26)) -> 0
C72: 合作期第9年 | D72: =SUM(F72:BA72) -> 458.7156 | E72: 万元 | N72: =IF('表2-折旧摊销表'!$BA$26+1-'表2-折旧摊销表'!$N$26>='表2-折旧摊销表'!$D$14,$N$62/$D$14,$N$62/('表2-折旧摊销表'!$BA$26+1-'表2-折旧摊销表'!$N$26)) -> 91.743119 | O72: =IF('表2-折旧摊销表'!$BA$26+1-'表2-折旧摊销表'!$N$26>='表2-折旧摊销表'!$D$14,$N$62/$D$14,$N$62/('表2-折旧摊销表'!$BA$26+1-'表2-折旧摊销表'!$N$26)) -> 91.743119 | P72: =IF('表2-折旧摊销表'!$BA$26+1-'表2-折旧摊销表'!$N$26>='表2-折旧摊销表'!$D$14,$N$62/$D$14,$N$62/('表2-折旧摊销表'!$BA$26+1-'表2-折旧摊销表'!$N$26)) -> 91.743119 | Q72: =IF('表2-折旧摊销表'!$BA$26+1-'表2-折旧摊销表'!$N$26>='表2-折旧摊销表'!$D$14,$N$62/$D$14,$N$62/('表2-折旧摊销表'!$BA$26+1-'表2-折旧摊销表'!$N$26)) -> 91.743119 | R72: =IF('表2-折旧摊销表'!$BA$26+1-'表2-折旧摊销表'!$N$26>='表2-折旧摊销表'!$D$14,$N$62/$D$14,$N$62/('表2-折旧摊销表'!$BA$26+1-'表2-折旧摊销表'!$N$26)) -> 91.743119
C73: 合作期第10年 | D73: =SUM(F73:BA73) -> 0 | E73: 万元 | O73: =IF('表2-折旧摊销表'!$BA$26+1-'表2-折旧摊销表'!$O$26>='表2-折旧摊销表'!$D$14,$O$62/$D$14,$O$62/('表2-折旧摊销表'!$BA$26+1-'表2-折旧摊销表'!$O$26)) -> 0 | P73: =IF('表2-折旧摊销表'!$BA$26+1-'表2-折旧摊销表'!$O$26>='表2-折旧摊销表'!$D$14,$O$62/$D$14,$O$62/('表2-折旧摊销表'!$BA$26+1-'表2-折旧摊销表'!$O$26)) -> 0 | Q73: =IF('表2-折旧摊销表'!$BA$26+1-'表2-折旧摊销表'!$O$26>='表2-折旧摊销表'!$D$14,$O$62/$D$14,$O$62/('表2-折旧摊销表'!$BA$26+1-'表2-折旧摊销表'!$O$26)) -> 0 | R73: =IF('表2-折旧摊销表'!$BA$26+1-'表2-折旧摊销表'!$O$26>='表2-折旧摊销表'!$D$14,$O$62/$D$14,$O$62/('表2-折旧摊销表'!$BA$26+1-'表2-折旧摊销表'!$O$26)) -> 0 | S73: =IF('表2-折旧摊销表'!$BA$26+1-'表2-折旧摊销表'!$O$26>='表2-折旧摊销表'!$D$14,$O$62/$D$14,$O$62/('表2-折旧摊销表'!$BA$26+1-'表2-折旧摊销表'!$O$26)) -> 0
C74: 合作期第11年 | D74: =SUM(F74:BA74) -> 0 | E74: 万元 | P74: =IF('表2-折旧摊销表'!$BA$26+1-'表2-折旧摊销表'!$P$26>='表2-折旧摊销表'!$D$14,$P$62/$D$14,$P$62/('表2-折旧摊销表'!$BA$26+1-'表2-折旧摊销表'!$P$26)) -> 0 | Q74: =IF('表2-折旧摊销表'!$BA$26+1-'表2-折旧摊销表'!$P$26>='表2-折旧摊销表'!$D$14,$P$62/$D$14,$P$62/('表2-折旧摊销表'!$BA$26+1-'表2-折旧摊销表'!$P$26)) -> 0 | R74: =IF('表2-折旧摊销表'!$BA$26+1-'表2-折旧摊销表'!$P$26>='表2-折旧摊销表'!$D$14,$P$62/$D$14,$P$62/('表2-折旧摊销表'!$BA$26+1-'表2-折旧摊销表'!$P$26)) -> 0 | S74: =IF('表2-折旧摊销表'!$BA$26+1-'表2-折旧摊销表'!$P$26>='表2-折旧摊销表'!$D$14,$P$62/$D$14,$P$62/('表2-折旧摊销表'!$BA$26+1-'表2-折旧摊销表'!$P$26)) -> 0 | T74: =IF('表2-折旧摊销表'!$BA$26+1-'表2-折旧摊销表'!$P$26>='表2-折旧摊销表'!$D$14,$P$62/$D$14,$P$62/('表2-折旧摊销表'!$BA$26+1-'表2-折旧摊销表'!$P$26)) -> 0
C75: 合作期第12年 | D75: =SUM(F75:BA75) -> 0 | E75: 万元 | Q75: =IF('表2-折旧摊销表'!$BA$26+1-'表2-折旧摊销表'!$Q$26>='表2-折旧摊销表'!$D$14,$Q$62/$D$14,$Q$62/('表2-折旧摊销表'!$BA$26+1-'表2-折旧摊销表'!$Q$26)) -> 0 | R75: =IF('表2-折旧摊销表'!$BA$26+1-'表2-折旧摊销表'!$Q$26>='表2-折旧摊销表'!$D$14,$Q$62/$D$14,$Q$62/('表2-折旧摊销表'!$BA$26+1-'表2-折旧摊销表'!$Q$26)) -> 0 | S75: =IF('表2-折旧摊销表'!$BA$26+1-'表2-折旧摊销表'!$Q$26>='表2-折旧摊销表'!$D$14,$Q$62/$D$14,$Q$62/('表2-折旧摊销表'!$BA$26+1-'表2-折旧摊销表'!$Q$26)) -> 0 | T75: =IF('表2-折旧摊销表'!$BA$26+1-'表2-折旧摊销表'!$Q$26>='表2-折旧摊销表'!$D$14,$Q$62/$D$14,$Q$62/('表2-折旧摊销表'!$BA$26+1-'表2-折旧摊销表'!$Q$26)) -> 0 | U75: =IF('表2-折旧摊销表'!$BA$26+1-'表2-折旧摊销表'!$Q$26>='表2-折旧摊销表'!$D$14,$Q$62/$D$14,$Q$62/('表2-折旧摊销表'!$BA$26+1-'表2-折旧摊销表'!$Q$26)) -> 0
C76: 合作期第13年 | D76: =SUM(F76:BA76) -> 0 | E76: 万元 | R76: =IF('表2-折旧摊销表'!$BA$26+1-'表2-折旧摊销表'!$R$26>='表2-折旧摊销表'!$D$14,$R$62/$D$14,$R$62/('表2-折旧摊销表'!$BA$26+1-'表2-折旧摊销表'!$R$26)) -> 0 | S76: =IF('表2-折旧摊销表'!$BA$26+1-'表2-折旧摊销表'!$R$26>='表2-折旧摊销表'!$D$14,$R$62/$D$14,$R$62/('表2-折旧摊销表'!$BA$26+1-'表2-折旧摊销表'!$R$26)) -> 0 | T76: =IF('表2-折旧摊销表'!$BA$26+1-'表2-折旧摊销表'!$R$26>='表2-折旧摊销表'!$D$14,$R$62/$D$14,$R$62/('表2-折旧摊销表'!$BA$26+1-'表2-折旧摊销表'!$R$26)) -> 0 | U76: =IF('表2-折旧摊销表'!$BA$26+1-'表2-折旧摊销表'!$R$26>='表2-折旧摊销表'!$D$14,$R$62/$D$14,$R$62/('表2-折旧摊销表'!$BA$26+1-'表2-折旧摊销表'!$R$26)) -> 0 | V76: =IF('表2-折旧摊销表'!$BA$26+1-'表2-折旧摊销表'!$R$26>='表2-折旧摊销表'!$D$14,$R$62/$D$14,$R$62/('表2-折旧摊销表'!$BA$26+1-'表2-折旧摊销表'!$R$26)) -> 0
C77: 合作期第14年 | D77: =SUM(F77:BA77) -> 458.7156 | E77: 万元 | S77: =IF('表2-折旧摊销表'!$BA$26+1-'表2-折旧摊销表'!$S$26>='表2-折旧摊销表'!$D$14,$S$62/$D$14,$S$62/('表2-折旧摊销表'!$BA$26+1-'表2-折旧摊销表'!$S$26)) -> 91.743119 | T77: =IF('表2-折旧摊销表'!$BA$26+1-'表2-折旧摊销表'!$S$26>='表2-折旧摊销表'!$D$14,$S$62/$D$14,$S$62/('表2-折旧摊销表'!$BA$26+1-'表2-折旧摊销表'!$S$26)) -> 91.743119 | U77: =IF('表2-折旧摊销表'!$BA$26+1-'表2-折旧摊销表'!$S$26>='表2-折旧摊销表'!$D$14,$S$62/$D$14,$S$62/('表2-折旧摊销表'!$BA$26+1-'表2-折旧摊销表'!$S$26)) -> 91.743119 | V77: =IF('表2-折旧摊销表'!$BA$26+1-'表2-折旧摊销表'!$S$26>='表2-折旧摊销表'!$D$14,$S$62/$D$14,$S$62/('表2-折旧摊销表'!$BA$26+1-'表2-折旧摊销表'!$S$26)) -> 91.743119 | W77: =IF('表2-折旧摊销表'!$BA$26+1-'表2-折旧摊销表'!$S$26>='表2-折旧摊销表'!$D$14,$S$62/$D$14,$S$62/('表2-折旧摊销表'!$BA$26+1-'表2-折旧摊销表'!$S$26)) -> 91.743119
C78: 合作期第15年 | D78: =SUM(F78:BA78) -> 0 | E78: 万元 | T78: =IF('表2-折旧摊销表'!$BA$26+1-'表2-折旧摊销表'!$T$26>='表2-折旧摊销表'!$D$14,$T$62/$D$14,$T$62/('表2-折旧摊销表'!$BA$26+1-'表2-折旧摊销表'!$T$26)) -> 0 | U78: =IF('表2-折旧摊销表'!$BA$26+1-'表2-折旧摊销表'!$T$26>='表2-折旧摊销表'!$D$14,$T$62/$D$14,$T$62/('表2-折旧摊销表'!$BA$26+1-'表2-折旧摊销表'!$T$26)) -> 0 | V78: =IF('表2-折旧摊销表'!$BA$26+1-'表2-折旧摊销表'!$T$26>='表2-折旧摊销表'!$D$14,$T$62/$D$14,$T$62/('表2-折旧摊销表'!$BA$26+1-'表2-折旧摊销表'!$T$26)) -> 0 | W78: =IF('表2-折旧摊销表'!$BA$26+1-'表2-折旧摊销表'!$T$26>='表2-折旧摊销表'!$D$14,$T$62/$D$14,$T$62/('表2-折旧摊销表'!$BA$26+1-'表2-折旧摊销表'!$T$26)) -> 0 | X78: =IF('表2-折旧摊销表'!$BA$26+1-'表2-折旧摊销表'!$T$26>='表2-折旧摊销表'!$D$14,$T$62/$D$14,$T$62/('表2-折旧摊销表'!$BA$26+1-'表2-折旧摊销表'!$T$26)) -> 0
C79: 合作期第16年 | D79: =SUM(F79:BA79) -> 0 | E79: 万元 | U79: =IF('表2-折旧摊销表'!$BA$26+1-'表2-折旧摊销表'!$U$26>='表2-折旧摊销表'!$D$14,$U$62/$D$14,$U$62/('表2-折旧摊销表'!$BA$26+1-'表2-折旧摊销表'!$U$26)) -> 0 | V79: =IF('表2-折旧摊销表'!$BA$26+1-'表2-折旧摊销表'!$U$26>='表2-折旧摊销表'!$D$14,$U$62/$D$14,$U$62/('表2-折旧摊销表'!$BA$26+1-'表2-折旧摊销表'!$U$26)) -> 0 | W79: =IF('表2-折旧摊销表'!$BA$26+1-'表2-折旧摊销表'!$U$26>='表2-折旧摊销表'!$D$14,$U$62/$D$14,$U$62/('表2-折旧摊销表'!$BA$26+1-'表2-折旧摊销表'!$U$26)) -> 0 | X79: =IF('表2-折旧摊销表'!$BA$26+1-'表2-折旧摊销表'!$U$26>='表2-折旧摊销表'!$D$14,$U$62/$D$14,$U$62/('表2-折旧摊销表'!$BA$26+1-'表2-折旧摊销表'!$U$26)) -> 0 | Y79: =IF('表2-折旧摊销表'!$BA$26+1-'表2-折旧摊销表'!$U$26>='表2-折旧摊销表'!$D$14,$U$62/$D$14,$U$62/('表2-折旧摊销表'!$BA$26+1-'表2-折旧摊销表'!$U$26)) -> 0
C80: 合作期第17年 | D80: =SUM(F80:BA80) -> 0 | E80: 万元 | V80: =IF('表2-折旧摊销表'!$BA$26+1-'表2-折旧摊销表'!$V$26>='表2-折旧摊销表'!$D$14,$V$62/$D$14,$V$62/('表2-折旧摊销表'!$BA$26+1-'表2-折旧摊销表'!$V$26)) -> 0 | W80: =IF('表2-折旧摊销表'!$BA$26+1-'表2-折旧摊销表'!$V$26>='表2-折旧摊销表'!$D$14,$V$62/$D$14,$V$62/('表2-折旧摊销表'!$BA$26+1-'表2-折旧摊销表'!$V$26)) -> 0 | X80: =IF('表2-折旧摊销表'!$BA$26+1-'表2-折旧摊销表'!$V$26>='表2-折旧摊销表'!$D$14,$V$62/$D$14,$V$62/('表2-折旧摊销表'!$BA$26+1-'表2-折旧摊销表'!$V$26)) -> 0 | Y80: =IF('表2-折旧摊销表'!$BA$26+1-'表2-折旧摊销表'!$V$26>='表2-折旧摊销表'!$D$14,$V$62/$D$14,$V$62/('表2-折旧摊销表'!$BA$26+1-'表2-折旧摊销表'!$V$26)) -> 0 | Z80: =IF('表2-折旧摊销表'!$BA$26+1-'表2-折旧摊销表'!$V$26>='表2-折旧摊销表'!$D$14,$V$62/$D$14,$V$62/('表2-折旧摊销表'!$BA$26+1-'表2-折旧摊销表'!$V$26)) -> 0
C81: 合作期第18年 | D81: =SUM(F81:BA81) -> 0 | E81: 万元 | W81: =IF('表2-折旧摊销表'!$BA$26+1-'表2-折旧摊销表'!$W$26>='表2-折旧摊销表'!$D$14,$W$62/$D$14,$W$62/('表2-折旧摊销表'!$BA$26+1-'表2-折旧摊销表'!$W$26)) -> 0 | X81: =IF('表2-折旧摊销表'!$BA$26+1-'表2-折旧摊销表'!$W$26>='表2-折旧摊销表'!$D$14,$W$62/$D$14,$W$62/('表2-折旧摊销表'!$BA$26+1-'表2-折旧摊销表'!$W$26)) -> 0 | Y81: =IF('表2-折旧摊销表'!$BA$26+1-'表2-折旧摊销表'!$W$26>='表2-折旧摊销表'!$D$14,$W$62/$D$14,$W$62/('表2-折旧摊销表'!$BA$26+1-'表2-折旧摊销表'!$W$26)) -> 0 | Z81: =IF('表2-折旧摊销表'!$BA$26+1-'表2-折旧摊销表'!$W$26>='表2-折旧摊销表'!$D$14,$W$62/$D$14,$W$62/('表2-折旧摊销表'!$BA$26+1-'表2-折旧摊销表'!$W$26)) -> 0 | AA81: =IF('表2-折旧摊销表'!$BA$26+1-'表2-折旧摊销表'!$W$26>='表2-折旧摊销表'!$D$14,$W$62/$D$14,$W$62/('表2-折旧摊销表'!$BA$26+1-'表2-折旧摊销表'!$W$26)) -> 0
C82: 合作期第19年 | D82: =SUM(F82:BA82) -> 458.7156 | E82: 万元 | X82: =IF('表2-折旧摊销表'!$BA$26+1-'表2-折旧摊销表'!$X$26>='表2-折旧摊销表'!$D$14,$X$62/$D$14,$X$62/('表2-折旧摊销表'!$BA$26+1-'表2-折旧摊销表'!$X$26)) -> 91.743119 | Y82: =IF('表2-折旧摊销表'!$BA$26+1-'表2-折旧摊销表'!$X$26>='表2-折旧摊销表'!$D$14,$X$62/$D$14,$X$62/('表2-折旧摊销表'!$BA$26+1-'表2-折旧摊销表'!$X$26)) -> 91.743119 | Z82: =IF('表2-折旧摊销表'!$BA$26+1-'表2-折旧摊销表'!$X$26>='表2-折旧摊销表'!$D$14,$X$62/$D$14,$X$62/('表2-折旧摊销表'!$BA$26+1-'表2-折旧摊销表'!$X$26)) -> 91.743119 | AA82: =IF('表2-折旧摊销表'!$BA$26+1-'表2-折旧摊销表'!$X$26>='表2-折旧摊销表'!$D$14,$X$62/$D$14,$X$62/('表2-折旧摊销表'!$BA$26+1-'表2-折旧摊销表'!$X$26)) -> 91.743119 | AB82: =IF('表2-折旧摊销表'!$BA$26+1-'表2-折旧摊销表'!$X$26>='表2-折旧摊销表'!$D$14,$X$62/$D$14,$X$62/('表2-折旧摊销表'!$BA$26+1-'表2-折旧摊销表'!$X$26)) -> 91.743119
C83: 合作期第20年 | D83: =SUM(F83:BA83) -> 0 | E83: 万元 | Y83: =IF('表2-折旧摊销表'!$BA$26+1-'表2-折旧摊销表'!$Y$26>='表2-折旧摊销表'!$D$14,$Y$62/$D$14,$Y$62/('表2-折旧摊销表'!$BA$26+1-'表2-折旧摊销表'!$Y$26)) -> 0 | Z83: =IF('表2-折旧摊销表'!$BA$26+1-'表2-折旧摊销表'!$Y$26>='表2-折旧摊销表'!$D$14,$Y$62/$D$14,$Y$62/('表2-折旧摊销表'!$BA$26+1-'表2-折旧摊销表'!$Y$26)) -> 0 | AA83: =IF('表2-折旧摊销表'!$BA$26+1-'表2-折旧摊销表'!$Y$26>='表2-折旧摊销表'!$D$14,$Y$62/$D$14,$Y$62/('表2-折旧摊销表'!$BA$26+1-'表2-折旧摊销表'!$Y$26)) -> 0 | AB83: =IF('表2-折旧摊销表'!$BA$26+1-'表2-折旧摊销表'!$Y$26>='表2-折旧摊销表'!$D$14,$Y$62/$D$14,$Y$62/('表2-折旧摊销表'!$BA$26+1-'表2-折旧摊销表'!$Y$26)) -> 0 | AC83: =IF('表2-折旧摊销表'!$BA$26+1-'表2-折旧摊销表'!$Y$26>='表2-折旧摊销表'!$D$14,$Y$62/$D$14,$Y$62/('表2-折旧摊销表'!$BA$26+1-'表2-折旧摊销表'!$Y$26)) -> 0
C84: 合作期第21年 | D84: =SUM(F84:BA84) -> 0 | E84: 万元 | Z84: =IF('表2-折旧摊销表'!$BA$26+1-'表2-折旧摊销表'!$Z$26>='表2-折旧摊销表'!$D$14,$Z$62/$D$14,$Z$62/('表2-折旧摊销表'!$BA$26+1-'表2-折旧摊销表'!$Z$26)) -> 0 | AA84: =IF('表2-折旧摊销表'!$BA$26+1-'表2-折旧摊销表'!$Z$26>='表2-折旧摊销表'!$D$14,$Z$62/$D$14,$Z$62/('表2-折旧摊销表'!$BA$26+1-'表2-折旧摊销表'!$Z$26)) -> 0 | AB84: =IF('表2-折旧摊销表'!$BA$26+1-'表2-折旧摊销表'!$Z$26>='表2-折旧摊销表'!$D$14,$Z$62/$D$14,$Z$62/('表2-折旧摊销表'!$BA$26+1-'表2-折旧摊销表'!$Z$26)) -> 0 | AC84: =IF('表2-折旧摊销表'!$BA$26+1-'表2-折旧摊销表'!$Z$26>='表2-折旧摊销表'!$D$14,$Z$62/$D$14,$Z$62/('表2-折旧摊销表'!$BA$26+1-'表2-折旧摊销表'!$Z$26)) -> 0 | AD84: =IF('表2-折旧摊销表'!$BA$26+1-'表2-折旧摊销表'!$Z$26>='表2-折旧摊销表'!$D$14,$Z$62/$D$14,$Z$62/('表2-折旧摊销表'!$BA$26+1-'表2-折旧摊销表'!$Z$26)) -> 0
C85: 合作期第22年 | D85: =SUM(F85:BA85) -> 0 | E85: 万元 | AA85: =IF('表2-折旧摊销表'!$BA$26+1-'表2-折旧摊销表'!$AA$26>='表2-折旧摊销表'!$D$14,$AA$62/$D$14,$AA$62/('表2-折旧摊销表'!$BA$26+1-'表2-折旧摊销表'!$AA$26)) -> 0 | AB85: =IF('表2-折旧摊销表'!$BA$26+1-'表2-折旧摊销表'!$AA$26>='表2-折旧摊销表'!$D$14,$AA$62/$D$14,$AA$62/('表2-折旧摊销表'!$BA$26+1-'表2-折旧摊销表'!$AA$26)) -> 0 | AC85: =IF('表2-折旧摊销表'!$BA$26+1-'表2-折旧摊销表'!$AA$26>='表2-折旧摊销表'!$D$14,$AA$62/$D$14,$AA$62/('表2-折旧摊销表'!$BA$26+1-'表2-折旧摊销表'!$AA$26)) -> 0 | AD85: =IF('表2-折旧摊销表'!$BA$26+1-'表2-折旧摊销表'!$AA$26>='表2-折旧摊销表'!$D$14,$AA$62/$D$14,$AA$62/('表2-折旧摊销表'!$BA$26+1-'表2-折旧摊销表'!$AA$26)) -> 0 | AE85: =IF('表2-折旧摊销表'!$BA$26+1-'表2-折旧摊销表'!$AA$26>='表2-折旧摊销表'!$D$14,$AA$62/$D$14,$AA$62/('表2-折旧摊销表'!$BA$26+1-'表2-折旧摊销表'!$AA$26)) -> 0
C86: 合作期第23年 | D86: =SUM(F86:BA86) -> 0 | E86: 万元 | AB86: =IF('表2-折旧摊销表'!$BA$26+1-'表2-折旧摊销表'!$AB$26>='表2-折旧摊销表'!$D$14,$AB$62/$D$14,$AB$62/('表2-折旧摊销表'!$BA$26+1-'表2-折旧摊销表'!$AB$26)) -> 0 | AC86: =IF('表2-折旧摊销表'!$BA$26+1-'表2-折旧摊销表'!$AB$26>='表2-折旧摊销表'!$D$14,$AB$62/$D$14,$AB$62/('表2-折旧摊销表'!$BA$26+1-'表2-折旧摊销表'!$AB$26)) -> 0 | AD86: =IF('表2-折旧摊销表'!$BA$26+1-'表2-折旧摊销表'!$AB$26>='表2-折旧摊销表'!$D$14,$AB$62/$D$14,$AB$62/('表2-折旧摊销表'!$BA$26+1-'表2-折旧摊销表'!$AB$26)) -> 0 | AE86: =IF('表2-折旧摊销表'!$BA$26+1-'表2-折旧摊销表'!$AB$26>='表2-折旧摊销表'!$D$14,$AB$62/$D$14,$AB$62/('表2-折旧摊销表'!$BA$26+1-'表2-折旧摊销表'!$AB$26)) -> 0 | AF86: =IF('表2-折旧摊销表'!$BA$26+1-'表2-折旧摊销表'!$AB$26>='表2-折旧摊销表'!$D$14,$AB$62/$D$14,$AB$62/('表2-折旧摊销表'!$BA$26+1-'表2-折旧摊销表'!$AB$26)) -> 0
C87: 合作期第24年 | D87: =SUM(F87:BA87) -> 458.7156 | E87: 万元 | AC87: =IF('表2-折旧摊销表'!$BA$26+1-'表2-折旧摊销表'!$AC$26>='表2-折旧摊销表'!$D$14,$AC$62/$D$14,$AC$62/('表2-折旧摊销表'!$BA$26+1-'表2-折旧摊销表'!$AC$26)) -> 91.743119 | AD87: =IF('表2-折旧摊销表'!$BA$26+1-'表2-折旧摊销表'!$AC$26>='表2-折旧摊销表'!$D$14,$AC$62/$D$14,$AC$62/('表2-折旧摊销表'!$BA$26+1-'表2-折旧摊销表'!$AC$26)) -> 91.743119 | AE87: =IF('表2-折旧摊销表'!$BA$26+1-'表2-折旧摊销表'!$AC$26>='表2-折旧摊销表'!$D$14,$AC$62/$D$14,$AC$62/('表2-折旧摊销表'!$BA$26+1-'表2-折旧摊销表'!$AC$26)) -> 91.743119 | AF87: =IF('表2-折旧摊销表'!$BA$26+1-'表2-折旧摊销表'!$AC$26>='表2-折旧摊销表'!$D$14,$AC$62/$D$14,$AC$62/('表2-折旧摊销表'!$BA$26+1-'表2-折旧摊销表'!$AC$26)) -> 91.743119 | AG87: =IF('表2-折旧摊销表'!$BA$26+1-'表2-折旧摊销表'!$AC$26>='表2-折旧摊销表'!$D$14,$AC$62/$D$14,$AC$62/('表2-折旧摊销表'!$BA$26+1-'表2-折旧摊销表'!$AC$26)) -> 91.743119
C88: 合作期第25年 | D88: =SUM(F88:BA88) -> 0 | E88: 万元 | AD88: =IF('表2-折旧摊销表'!$BA$26+1-'表2-折旧摊销表'!$AD$26>='表2-折旧摊销表'!$D$14,$AD$62/$D$14,$AD$62/('表2-折旧摊销表'!$BA$26+1-'表2-折旧摊销表'!$AD$26)) -> 0 | AE88: =IF('表2-折旧摊销表'!$BA$26+1-'表2-折旧摊销表'!$AD$26>='表2-折旧摊销表'!$D$14,$AD$62/$D$14,$AD$62/('表2-折旧摊销表'!$BA$26+1-'表2-折旧摊销表'!$AD$26)) -> 0 | AF88: =IF('表2-折旧摊销表'!$BA$26+1-'表2-折旧摊销表'!$AD$26>='表2-折旧摊销表'!$D$14,$AD$62/$D$14,$AD$62/('表2-折旧摊销表'!$BA$26+1-'表2-折旧摊销表'!$AD$26)) -> 0 | AG88: =IF('表2-折旧摊销表'!$BA$26+1-'表2-折旧摊销表'!$AD$26>='表2-折旧摊销表'!$D$14,$AD$62/$D$14,$AD$62/('表2-折旧摊销表'!$BA$26+1-'表2-折旧摊销表'!$AD$26)) -> 0 | AH88: =IF('表2-折旧摊销表'!$BA$26+1-'表2-折旧摊销表'!$AD$26>='表2-折旧摊销表'!$D$14,$AD$62/$D$14,$AD$62/('表2-折旧摊销表'!$BA$26+1-'表2-折旧摊销表'!$AD$26)) -> 0
C89: 合作期第26年 | D89: =SUM(F89:BA89) -> 0 | E89: 万元 | AE89: =IF('表2-折旧摊销表'!$BA$26+1-'表2-折旧摊销表'!$AE$26>='表2-折旧摊销表'!$D$14,$AE$62/$D$14,$AE$62/('表2-折旧摊销表'!$BA$26+1-'表2-折旧摊销表'!$AE$26)) -> 0 | AF89: =IF('表2-折旧摊销表'!$BA$26+1-'表2-折旧摊销表'!$AE$26>='表2-折旧摊销表'!$D$14,$AE$62/$D$14,$AE$62/('表2-折旧摊销表'!$BA$26+1-'表2-折旧摊销表'!$AE$26)) -> 0 | AG89: =IF('表2-折旧摊销表'!$BA$26+1-'表2-折旧摊销表'!$AE$26>='表2-折旧摊销表'!$D$14,$AE$62/$D$14,$AE$62/('表2-折旧摊销表'!$BA$26+1-'表2-折旧摊销表'!$AE$26)) -> 0 | AH89: =IF('表2-折旧摊销表'!$BA$26+1-'表2-折旧摊销表'!$AE$26>='表2-折旧摊销表'!$D$14,$AE$62/$D$14,$AE$62/('表2-折旧摊销表'!$BA$26+1-'表2-折旧摊销表'!$AE$26)) -> 0 | AI89: =IF('表2-折旧摊销表'!$BA$26+1-'表2-折旧摊销表'!$AE$26>='表2-折旧摊销表'!$D$14,$AE$62/$D$14,$AE$62/('表2-折旧摊销表'!$BA$26+1-'表2-折旧摊销表'!$AE$26)) -> 0
C90: 合作期第27年 | D90: =SUM(F90:BA90) -> 0 | E90: 万元 | AF90: =IF('表2-折旧摊销表'!$BA$26+1-'表2-折旧摊销表'!$AF$26>='表2-折旧摊销表'!$D$14,$AF$62/$D$14,$AF$62/('表2-折旧摊销表'!$BA$26+1-'表2-折旧摊销表'!$AF$26)) -> 0 | AG90: =IF('表2-折旧摊销表'!$BA$26+1-'表2-折旧摊销表'!$AF$26>='表2-折旧摊销表'!$D$14,$AF$62/$D$14,$AF$62/('表2-折旧摊销表'!$BA$26+1-'表2-折旧摊销表'!$AF$26)) -> 0 | AH90: =IF('表2-折旧摊销表'!$BA$26+1-'表2-折旧摊销表'!$AF$26>='表2-折旧摊销表'!$D$14,$AF$62/$D$14,$AF$62/('表2-折旧摊销表'!$BA$26+1-'表2-折旧摊销表'!$AF$26)) -> 0 | AI90: =IF('表2-折旧摊销表'!$BA$26+1-'表2-折旧摊销表'!$AF$26>='表2-折旧摊销表'!$D$14,$AF$62/$D$14,$AF$62/('表2-折旧摊销表'!$BA$26+1-'表2-折旧摊销表'!$AF$26)) -> 0 | AJ90: =IF('表2-折旧摊销表'!$BA$26+1-'表2-折旧摊销表'!$AF$26>='表2-折旧摊销表'!$D$14,$AF$62/$D$14,$AF$62/('表2-折旧摊销表'!$BA$26+1-'表2-折旧摊销表'!$AF$26)) -> 0
C91: 合作期第28年 | D91: =SUM(F91:BA91) -> 0 | E91: 万元 | AG91: =IF('表2-折旧摊销表'!$BA$26+1-'表2-折旧摊销表'!$AG$26>='表2-折旧摊销表'!$D$14,$AG$62/$D$14,$AG$62/('表2-折旧摊销表'!$BA$26+1-'表2-折旧摊销表'!$AG$26)) -> 0 | AH91: =IF('表2-折旧摊销表'!$BA$26+1-'表2-折旧摊销表'!$AG$26>='表2-折旧摊销表'!$D$14,$AG$62/$D$14,$AG$62/('表2-折旧摊销表'!$BA$26+1-'表2-折旧摊销表'!$AG$26)) -> 0 | AI91: =IF('表2-折旧摊销表'!$BA$26+1-'表2-折旧摊销表'!$AG$26>='表2-折旧摊销表'!$D$14,$AG$62/$D$14,$AG$62/('表2-折旧摊销表'!$BA$26+1-'表2-折旧摊销表'!$AG$26)) -> 0 | AJ91: =IF('表2-折旧摊销表'!$BA$26+1-'表2-折旧摊销表'!$AG$26>='表2-折旧摊销表'!$D$14,$AG$62/$D$14,$AG$62/('表2-折旧摊销表'!$BA$26+1-'表2-折旧摊销表'!$AG$26)) -> 0 | AK91: =IF('表2-折旧摊销表'!$BA$26+1-'表2-折旧摊销表'!$AG$26>='表2-折旧摊销表'!$D$14,$AG$62/$D$14,$AG$62/('表2-折旧摊销表'!$BA$26+1-'表2-折旧摊销表'!$AG$26)) -> 0
C92: 合作期第29年 | D92: =SUM(F92:BA92) -> 458.7156 | E92: 万元 | AH92: =IF('表2-折旧摊销表'!$BA$26+1-'表2-折旧摊销表'!$AH$26>='表2-折旧摊销表'!$D$14,$AH$62/$D$14,$AH$62/('表2-折旧摊销表'!$BA$26+1-'表2-折旧摊销表'!$AH$26)) -> 91.743119 | AI92: =IF('表2-折旧摊销表'!$BA$26+1-'表2-折旧摊销表'!$AH$26>='表2-折旧摊销表'!$D$14,$AH$62/$D$14,$AH$62/('表2-折旧摊销表'!$BA$26+1-'表2-折旧摊销表'!$AH$26)) -> 91.743119 | AJ92: =IF('表2-折旧摊销表'!$BA$26+1-'表2-折旧摊销表'!$AH$26>='表2-折旧摊销表'!$D$14,$AH$62/$D$14,$AH$62/('表2-折旧摊销表'!$BA$26+1-'表2-折旧摊销表'!$AH$26)) -> 91.743119 | AK92: =IF('表2-折旧摊销表'!$BA$26+1-'表2-折旧摊销表'!$AH$26>='表2-折旧摊销表'!$D$14,$AH$62/$D$14,$AH$62/('表2-折旧摊销表'!$BA$26+1-'表2-折旧摊销表'!$AH$26)) -> 91.743119 | AL92: =IF('表2-折旧摊销表'!$BA$26+1-'表2-折旧摊销表'!$AH$26>='表2-折旧摊销表'!$D$14,$AH$62/$D$14,$AH$62/('表2-折旧摊销表'!$BA$26+1-'表2-折旧摊销表'!$AH$26)) -> 91.743119
C93: 合作期第30年 | D93: =SUM(F93:BA93) -> 0 | E93: 万元 | AI93: =IF('表2-折旧摊销表'!$BA$26+1-'表2-折旧摊销表'!$AI$26>='表2-折旧摊销表'!$D$14,$AI$62/$D$14,$AI$62/('表2-折旧摊销表'!$BA$26+1-'表2-折旧摊销表'!$AI$26)) -> 0 | AJ93: =IF('表2-折旧摊销表'!$BA$26+1-'表2-折旧摊销表'!$AI$26>='表2-折旧摊销表'!$D$14,$AI$62/$D$14,$AI$62/('表2-折旧摊销表'!$BA$26+1-'表2-折旧摊销表'!$AI$26)) -> 0 | AK93: =IF('表2-折旧摊销表'!$BA$26+1-'表2-折旧摊销表'!$AI$26>='表2-折旧摊销表'!$D$14,$AI$62/$D$14,$AI$62/('表2-折旧摊销表'!$BA$26+1-'表2-折旧摊销表'!$AI$26)) -> 0 | AL93: =IF('表2-折旧摊销表'!$BA$26+1-'表2-折旧摊销表'!$AI$26>='表2-折旧摊销表'!$D$14,$AI$62/$D$14,$AI$62/('表2-折旧摊销表'!$BA$26+1-'表2-折旧摊销表'!$AI$26)) -> 0 | AM93: =IF('表2-折旧摊销表'!$BA$26+1-'表2-折旧摊销表'!$AI$26>='表2-折旧摊销表'!$D$14,$AI$62/$D$14,$AI$62/('表2-折旧摊销表'!$BA$26+1-'表2-折旧摊销表'!$AI$26)) -> 0
C94: 合作期第31年 | D94: =SUM(F94:BA94) -> 0 | E94: 万元 | AJ94: =IF('表2-折旧摊销表'!$BA$26+1-'表2-折旧摊销表'!$AJ$26>='表2-折旧摊销表'!$D$14,$AJ$62/$D$14,$AJ$62/('表2-折旧摊销表'!$BA$26+1-'表2-折旧摊销表'!$AJ$26)) -> 0 | AK94: =IF('表2-折旧摊销表'!$BA$26+1-'表2-折旧摊销表'!$AJ$26>='表2-折旧摊销表'!$D$14,$AJ$62/$D$14,$AJ$62/('表2-折旧摊销表'!$BA$26+1-'表2-折旧摊销表'!$AJ$26)) -> 0 | AL94: =IF('表2-折旧摊销表'!$BA$26+1-'表2-折旧摊销表'!$AJ$26>='表2-折旧摊销表'!$D$14,$AJ$62/$D$14,$AJ$62/('表2-折旧摊销表'!$BA$26+1-'表2-折旧摊销表'!$AJ$26)) -> 0 | AM94: =IF('表2-折旧摊销表'!$BA$26+1-'表2-折旧摊销表'!$AJ$26>='表2-折旧摊销表'!$D$14,$AJ$62/$D$14,$AJ$62/('表2-折旧摊销表'!$BA$26+1-'表2-折旧摊销表'!$AJ$26)) -> 0 | AN94: =IF('表2-折旧摊销表'!$BA$26+1-'表2-折旧摊销表'!$AJ$26>='表2-折旧摊销表'!$D$14,$AJ$62/$D$14,$AJ$62/('表2-折旧摊销表'!$BA$26+1-'表2-折旧摊销表'!$AJ$26)) -> 0
C95: 合作期第32年 | D95: =SUM(F95:BA95) -> 0 | E95: 万元 | AK95: =IF('表2-折旧摊销表'!$BA$26+1-'表2-折旧摊销表'!$AK$26>='表2-折旧摊销表'!$D$14,$AK$62/$D$14,$AK$62/('表2-折旧摊销表'!$BA$26+1-'表2-折旧摊销表'!$AK$26)) -> 0 | AL95: =IF('表2-折旧摊销表'!$BA$26+1-'表2-折旧摊销表'!$AK$26>='表2-折旧摊销表'!$D$14,$AK$62/$D$14,$AK$62/('表2-折旧摊销表'!$BA$26+1-'表2-折旧摊销表'!$AK$26)) -> 0 | AM95: =IF('表2-折旧摊销表'!$BA$26+1-'表2-折旧摊销表'!$AK$26>='表2-折旧摊销表'!$D$14,$AK$62/$D$14,$AK$62/('表2-折旧摊销表'!$BA$26+1-'表2-折旧摊销表'!$AK$26)) -> 0 | AN95: =IF('表2-折旧摊销表'!$BA$26+1-'表2-折旧摊销表'!$AK$26>='表2-折旧摊销表'!$D$14,$AK$62/$D$14,$AK$62/('表2-折旧摊销表'!$BA$26+1-'表2-折旧摊销表'!$AK$26)) -> 0 | AO95: =IF('表2-折旧摊销表'!$BA$26+1-'表2-折旧摊销表'!$AK$26>='表2-折旧摊销表'!$D$14,$AK$62/$D$14,$AK$62/('表2-折旧摊销表'!$BA$26+1-'表2-折旧摊销表'!$AK$26)) -> 0
C96: 合作期第33年 | D96: =SUM(F96:BA96) -> 0 | E96: 万元 | AL96: =IF('表2-折旧摊销表'!$BA$26+1-'表2-折旧摊销表'!$AL$26>='表2-折旧摊销表'!$D$14,$AL$62/$D$14,$AL$62/('表2-折旧摊销表'!$BA$26+1-'表2-折旧摊销表'!$AL$26)) -> 0 | AM96: =IF('表2-折旧摊销表'!$BA$26+1-'表2-折旧摊销表'!$AL$26>='表2-折旧摊销表'!$D$14,$AL$62/$D$14,$AL$62/('表2-折旧摊销表'!$BA$26+1-'表2-折旧摊销表'!$AL$26)) -> 0 | AN96: =IF('表2-折旧摊销表'!$BA$26+1-'表2-折旧摊销表'!$AL$26>='表2-折旧摊销表'!$D$14,$AL$62/$D$14,$AL$62/('表2-折旧摊销表'!$BA$26+1-'表2-折旧摊销表'!$AL$26)) -> 0 | AO96: =IF('表2-折旧摊销表'!$BA$26+1-'表2-折旧摊销表'!$AL$26>='表2-折旧摊销表'!$D$14,$AL$62/$D$14,$AL$62/('表2-折旧摊销表'!$BA$26+1-'表2-折旧摊销表'!$AL$26)) -> 0 | AP96: =IF('表2-折旧摊销表'!$BA$26+1-'表2-折旧摊销表'!$AL$26>='表2-折旧摊销表'!$D$14,$AL$62/$D$14,$AL$62/('表2-折旧摊销表'!$BA$26+1-'表2-折旧摊销表'!$AL$26)) -> 0
C97: 合作期第34年 | D97: =SUM(F97:BA97) -> 458.7156 | E97: 万元 | AM97: =IF('表2-折旧摊销表'!$BA$26+1-'表2-折旧摊销表'!$AM$26>='表2-折旧摊销表'!$D$14,$AM$62/$D$14,$AM$62/('表2-折旧摊销表'!$BA$26+1-'表2-折旧摊销表'!$AM$26)) -> 91.743119 | AN97: =IF('表2-折旧摊销表'!$BA$26+1-'表2-折旧摊销表'!$AM$26>='表2-折旧摊销表'!$D$14,$AM$62/$D$14,$AM$62/('表2-折旧摊销表'!$BA$26+1-'表2-折旧摊销表'!$AM$26)) -> 91.743119 | AO97: =IF('表2-折旧摊销表'!$BA$26+1-'表2-折旧摊销表'!$AM$26>='表2-折旧摊销表'!$D$14,$AM$62/$D$14,$AM$62/('表2-折旧摊销表'!$BA$26+1-'表2-折旧摊销表'!$AM$26)) -> 91.743119 | AP97: =IF('表2-折旧摊销表'!$BA$26+1-'表2-折旧摊销表'!$AM$26>='表2-折旧摊销表'!$D$14,$AM$62/$D$14,$AM$62/('表2-折旧摊销表'!$BA$26+1-'表2-折旧摊销表'!$AM$26)) -> 91.743119 | AQ97: =IF('表2-折旧摊销表'!$BA$26+1-'表2-折旧摊销表'!$AM$26>='表2-折旧摊销表'!$D$14,$AM$62/$D$14,$AM$62/('表2-折旧摊销表'!$BA$26+1-'表2-折旧摊销表'!$AM$26)) -> 91.743119
C98: 合作期第35年 | D98: =SUM(F98:BA98) -> 0 | E98: 万元 | AN98: =IF('表2-折旧摊销表'!$BA$26+1-'表2-折旧摊销表'!$AN$26>='表2-折旧摊销表'!$D$14,$AN$62/$D$14,$AN$62/('表2-折旧摊销表'!$BA$26+1-'表2-折旧摊销表'!$AN$26)) -> 0 | AO98: =IF('表2-折旧摊销表'!$BA$26+1-'表2-折旧摊销表'!$AN$26>='表2-折旧摊销表'!$D$14,$AN$62/$D$14,$AN$62/('表2-折旧摊销表'!$BA$26+1-'表2-折旧摊销表'!$AN$26)) -> 0 | AP98: =IF('表2-折旧摊销表'!$BA$26+1-'表2-折旧摊销表'!$AN$26>='表2-折旧摊销表'!$D$14,$AN$62/$D$14,$AN$62/('表2-折旧摊销表'!$BA$26+1-'表2-折旧摊销表'!$AN$26)) -> 0 | AQ98: =IF('表2-折旧摊销表'!$BA$26+1-'表2-折旧摊销表'!$AN$26>='表2-折旧摊销表'!$D$14,$AN$62/$D$14,$AN$62/('表2-折旧摊销表'!$BA$26+1-'表2-折旧摊销表'!$AN$26)) -> 0 | AR98: =IF('表2-折旧摊销表'!$BA$26+1-'表2-折旧摊销表'!$AN$26>='表2-折旧摊销表'!$D$14,$AN$62/$D$14,$AN$62/('表2-折旧摊销表'!$BA$26+1-'表2-折旧摊销表'!$AN$26)) -> 0
C99: 合作期第36年 | D99: =SUM(F99:BA99) -> 0 | E99: 万元 | AO99: =IF('表2-折旧摊销表'!$BA$26+1-'表2-折旧摊销表'!$AO$26>='表2-折旧摊销表'!$D$14,$AO$62/$D$14,$AO$62/('表2-折旧摊销表'!$BA$26+1-'表2-折旧摊销表'!$AO$26)) -> 0 | AP99: =IF('表2-折旧摊销表'!$BA$26+1-'表2-折旧摊销表'!$AO$26>='表2-折旧摊销表'!$D$14,$AO$62/$D$14,$AO$62/('表2-折旧摊销表'!$BA$26+1-'表2-折旧摊销表'!$AO$26)) -> 0 | AQ99: =IF('表2-折旧摊销表'!$BA$26+1-'表2-折旧摊销表'!$AO$26>='表2-折旧摊销表'!$D$14,$AO$62/$D$14,$AO$62/('表2-折旧摊销表'!$BA$26+1-'表2-折旧摊销表'!$AO$26)) -> 0 | AR99: =IF('表2-折旧摊销表'!$BA$26+1-'表2-折旧摊销表'!$AO$26>='表2-折旧摊销表'!$D$14,$AO$62/$D$14,$AO$62/('表2-折旧摊销表'!$BA$26+1-'表2-折旧摊销表'!$AO$26)) -> 0 | AS99: =IF('表2-折旧摊销表'!$BA$26+1-'表2-折旧摊销表'!$AO$26>='表2-折旧摊销表'!$D$14,$AO$62/$D$14,$AO$62/('表2-折旧摊销表'!$BA$26+1-'表2-折旧摊销表'!$AO$26)) -> 0
C100: 合作期第37年 | D100: =SUM(F100:BA100) -> 0 | E100: 万元 | AP100: =IF('表2-折旧摊销表'!$BA$26+1-'表2-折旧摊销表'!$AP$26>='表2-折旧摊销表'!$D$14,$AP$62/$D$14,$AP$62/('表2-折旧摊销表'!$BA$26+1-'表2-折旧摊销表'!$AP$26)) -> 0 | AQ100: =IF('表2-折旧摊销表'!$BA$26+1-'表2-折旧摊销表'!$AP$26>='表2-折旧摊销表'!$D$14,$AP$62/$D$14,$AP$62/('表2-折旧摊销表'!$BA$26+1-'表2-折旧摊销表'!$AP$26)) -> 0 | AR100: =IF('表2-折旧摊销表'!$BA$26+1-'表2-折旧摊销表'!$AP$26>='表2-折旧摊销表'!$D$14,$AP$62/$D$14,$AP$62/('表2-折旧摊销表'!$BA$26+1-'表2-折旧摊销表'!$AP$26)) -> 0 | AS100: =IF('表2-折旧摊销表'!$BA$26+1-'表2-折旧摊销表'!$AP$26>='表2-折旧摊销表'!$D$14,$AP$62/$D$14,$AP$62/('表2-折旧摊销表'!$BA$26+1-'表2-折旧摊销表'!$AP$26)) -> 0 | AT100: =IF('表2-折旧摊销表'!$BA$26+1-'表2-折旧摊销表'!$AP$26>='表2-折旧摊销表'!$D$14,$AP$62/$D$14,$AP$62/('表2-折旧摊销表'!$BA$26+1-'表2-折旧摊销表'!$AP$26)) -> 0
C101: 合作期第38年 | D101: =SUM(F101:BA101) -> 0 | E101: 万元 | AQ101: =IF('表2-折旧摊销表'!$BA$26+1-'表2-折旧摊销表'!$AQ$26>='表2-折旧摊销表'!$D$14,$AQ$62/$D$14,$AQ$62/('表2-折旧摊销表'!$BA$26+1-'表2-折旧摊销表'!$AQ$26)) -> 0 | AR101: =IF('表2-折旧摊销表'!$BA$26+1-'表2-折旧摊销表'!$AQ$26>='表2-折旧摊销表'!$D$14,$AQ$62/$D$14,$AQ$62/('表2-折旧摊销表'!$BA$26+1-'表2-折旧摊销表'!$AQ$26)) -> 0 | AS101: =IF('表2-折旧摊销表'!$BA$26+1-'表2-折旧摊销表'!$AQ$26>='表2-折旧摊销表'!$D$14,$AQ$62/$D$14,$AQ$62/('表2-折旧摊销表'!$BA$26+1-'表2-折旧摊销表'!$AQ$26)) -> 0 | AT101: =IF('表2-折旧摊销表'!$BA$26+1-'表2-折旧摊销表'!$AQ$26>='表2-折旧摊销表'!$D$14,$AQ$62/$D$14,$AQ$62/('表2-折旧摊销表'!$BA$26+1-'表2-折旧摊销表'!$AQ$26)) -> 0 | AU101: =IF('表2-折旧摊销表'!$BA$26+1-'表2-折旧摊销表'!$AQ$26>='表2-折旧摊销表'!$D$14,$AQ$62/$D$14,$AQ$62/('表2-折旧摊销表'!$BA$26+1-'表2-折旧摊销表'!$AQ$26)) -> 0
...

Sheet 表3-成本费用表
B2: 成本费用表-资本金
B3: 序号 | C3: 项目 | D3: 合计 | E3: 单位 | F3: 2023 | G3: 2024 | H3: 2025 | I3: 2026 | J3: 2027 | K3: 2028 | L3: 2029 | M3: 2030 | N3: 2031 | O3: 2032 | P3: 2033 | Q3: 2034 | R3: 2035 | S3: 2036 | T3: 2037 | U3: 2038 | V3: 2039 | W3: 2040 | X3: 2041 | Y3: 2042 | Z3: 2043 | AA3: 2044 | AB3: 2045 | AC3: 2046 | AD3: 2047 | AE3: 2048 | AF3: 2049 | AG3: 2050 | AH3: 2051 | AI3: 2052 | AJ3: 2053 | AK3: 2054 | AL3: 2055 | AM3: 2056 | AN3: 2057 | AO3: 2058 | AP3: 2059 | AQ3: 2060 | AR3: 2061 | AS3: 2062 | AT3: 2063 | AU3: 2064 | AV3: 2065 | AW3: 2066 | AX3: 2067 | AY3: 2068 | AZ3: 2069 | BA3: 2070
F4: 1 | G4: 2 | H4: 3 | I4: 4 | J4: 5 | K4: 6 | L4: 7 | M4: 8 | N4: 9 | O4: 10 | P4: 11 | Q4: 12 | R4: 13 | S4: 14 | T4: 15 | U4: 16 | V4: 17 | W4: 18 | X4: 19 | Y4: 20 | Z4: 21 | AA4: 22 | AB4: 23 | AC4: 24 | AD4: 25 | AE4: 26 | AF4: 27 | AG4: 28 | AH4: 29 | AI4: 30 | AJ4: 31 | AK4: 32 | AL4: 33 | AM4: 34 | AN4: 35 | AO4: 36 | AP4: 37 | AQ4: 38 | AR4: 39 | AS4: 40 | AT4: 41 | AU4: 42 | AV4: 43 | AW4: 44 | AX4: 45 | AY4: 46 | AZ4: 47 | BA4: 48
C5: 投产比例 | F5: =参数输入表!$I$47 -> 0 | G5: =参数输入表!$I$48 -> 0 | H5: =参数输入表!$I$49 -> 0 | I5: =参数输入表!$I$50 -> 0 | J5: =参数输入表!$I$51 -> 0 | K5: =参数输入表!$I$52 -> 0 | L5: =参数输入表!$I$53 -> 0 | M5: =参数输入表!$I$54 -> 0.41666667 | N5: =参数输入表!$I$55 -> 1 | O5: =参数输入表!$I$56 -> 1 | P5: =参数输入表!$I$57 -> 1 | Q5: =参数输入表!$I$58 -> 1 | R5: =参数输入表!$I$59 -> 1 | S5: =参数输入表!$I$60 -> 1 | T5: =参数输入表!$I$61 -> 1 | U5: =参数输入表!$I$62 -> 1 | V5: =参数输入表!$I$63 -> 1 | W5: =参数输入表!$I$64 -> 1 | X5: =参数输入表!$I$65 -> 1 | Y5: =参数输入表!$I$66 -> 1 | Z5: =参数输入表!$I$67 -> 1 | AA5: =参数输入表!$I$68 -> 1 | AB5: =参数输入表!$I$69 -> 1 | AC5: =参数输入表!$I$70 -> 1 | AD5: =参数输入表!$I$71 -> 1 | AE5: =参数输入表!$I$72 -> 1 | AF5: =参数输入表!$I$73 -> 1 | AG5: =参数输入表!$I$74 -> 1 | AH5: =参数输入表!$I$75 -> 1 | AI5: =参数输入表!$I$76 -> 1 | AJ5: =参数输入表!$I$77 -> 1 | AK5: =参数输入表!$I$78 -> 1 | AL5: =参数输入表!$I$79 -> 1 | AM5: =参数输入表!$I$80 -> 1 | AN5: =参数输入表!$I$81 -> 1 | AO5: =参数输入表!$I$82 -> 1 | AP5: =参数输入表!$I$83 -> 1 | AQ5: =参数输入表!$I$84 -> 1 | AR5: =参数输入表!$I$85 -> 1 | AS5: =参数输入表!$I$86 -> 1 | AT5: =参数输入表!$I$87 -> 1 | AU5: =参数输入表!$I$88 -> 1 | AV5: =参数输入表!$I$89 -> 1 | AW5: =参数输入表!$I$90 -> 1 | AX5: =参数输入表!$I$91 -> 1 | AY5: =参数输入表!$I$92 -> 1 | AZ5: =参数输入表!$I$93 -> 1 | BA5: =参数输入表!$I$94 -> 0.58333333
B6: 一 | C6: 生产经营成本 | D6: =SUM(F6:BA6) -> 3797098 | E6: 万元 | F6: =F7+F27+F28+F30+F31 -> 0 | G6: =G7+G27+G28+G30+G31 -> 0 | H6: =H7+H27+H28+H30+H31 -> 0 | I6: =I7+I27+I28+I30+I31 -> 0 | J6: =J7+J27+J28+J30+J31 -> 0 | K6: =K7+K27+K28+K30+K31 -> 0 | L6: =L7+L27+L28+L30+L31 -> 0 | M6: =M7+M27+M28+M30+M31 -> 49337.524 | ... BA6: =BA7+BA27+BA28+BA30+BA31 -> 39318.477
