Workbook

Sheet 说明
B2: 参数输入表中：
C3: 标黄项为相对固定模块
C4: 标绿项为对成本类、收入类数据进行分类，成本参数按照：“生产成本/销售费用/管理费用/研发费用”划分；收入参数按照：“营业收入/其他收入/营业外收入”划分
C5: 标橙项为固定的分类原则
C6: 标紫项为在参数表中不需要手动输入、勾选的内容，根据其他输入参数自动计算得出，可不在参数输入界面呈现。
C7: 标红项为引用同样红色sheet中相关数据
C8: 标蓝项为可不展示内容，大部分为中间过程计算表/中间计算过程
C10: 【成本费用表】、【收入税金表】、【利润表】体现的是会计报表相关数据，涉及到的收入及成本数据均为不含增值税金额，不含税金额计算公式为： 【含税金额/（1+增值税税率）】；增值税计算公式为：【不含税金额*增值税税率】或【含税金额/（1+增值税税率）*增值税税率】
C12: 【成本费用表】中各项成本按照：一、营业总成本：（1）生产成本；（2）销售费用；（3）管理费用；（4）研发费用；（5）财务费用；二、营业外支出，进行划分，其中需重点关注长期待摊费用成本项，在成本费用表中以逐年摊销的形式出现。
C14: 【成本费用表】中标蓝的内容为不展示内容，为中间计算表，其中数据均还原成含税金额，用于后续的【现金流量表】引用
C16: 【收入表】中各项收入按照：一、营业收入；二、其他收入；三、营业外收入，营业收入及营业外收入需展示二级目录（具体的收入项）
C18: 【现金流量表】体现的是公司账上实际收到或支付的现金流，因此涉及到的收入及成本数据均为含增值税金额，数据需引用成本费用表中还原后的含税金额或参数输入表中的含税金额。同时，收入数据需关注付款比例及回款期限的应用。原理为当年的部分比例收入的滞后支付，第一年的某项收入现金流为预测现金流*首年支付比例，第二年的某项收入现金流为：当年预测现金流*当年支付比例+上一年预测现金流*（1-上一年支付比例）
C20: 【现金流量表-财务计划】增加IF判定条件，当某年的累计盈余资金<MAX(“流动资金（本项目为960万元）”,“当年的生产经营现金支出合计（成本费用表标蓝表第一行）)，给出明显提示（允许用户在参数输入界面填写各年度短期借款当期借款金额及还本金额，再重新生成新的结果）

Sheet 新建及改扩建项目投资概算明细 (光伏)
B2: 工程分年度投资输入表（可研中抓取数据） | I2: 错误计算进项税的方式
B3: 序号 | C3: 科目 | D3: 合计 | E3: 单位 | F3: 2023年 | G3: 2024年 | H3: 增值税税率 | I3: 2023年 | J3: 2024年 | K3: 合计 | L3: 差额
B4: 1 | C4: 设备购置费 | D4: =SUM(F4:G4) -> 100000 | E4: 万元 | F4: 30000 | G4: 70000 | H4: =参数输入表!G134 -> 0.13 | I4: =F4*H4 -> 3900 | J4: =G4*H4 -> 9100 | K4: =D4*H4 -> 13000 | L4: =K4-D18 -> 1495.5752
B5: 2 | C5: 建安工程费 | D5: =SUM(F5:G5) -> 20000 | E5: 万元 | F5: 6000 | G5: 14000 | H5: =参数输入表!G135 -> 0.09 | I5: =F5*H5 -> 540 | J5: =G5*H5 -> 1260 | K5: =D5*H5 -> 1800 | L5: =K5-D19 -> 148.62385
B6: 3 | C6: 其他费用 | D6: =SUM(F6:G6) -> 12000 | E6: 万元 | F6: 3600 | G6: 8400 | H6: =参数输入表!G136 -> 0.06 | I6: =F6*H6 -> 216 | J6: =G6*H6 -> 504 | K6: =D6*H6 -> 720 | L6: =K6-D20 -> 40.754717
B7: 4 | C7: 基本预备费 | D7: =SUM(F7:G7) -> 2500 | E7: 万元 | F7: 750 | G7: 1750 | H7: =参数输入表!G137 -> 0 | I7: =F7*H7 -> 0 | J7: =G7*H7 -> 0 | K7: =D7*H7 -> 0 | L7: =K7-D21 -> 0
B8: 5 | C8: 储能投资 | D8: =SUM(F8:G8) -> 500 | E8: 万元 | F8: 150 | G8: 350 | H8: =参数输入表!G138 -> 0.13 | I8: =F8*H8 -> 19.5 | J8: =G8*H8 -> 45.5 | K8: =D8*H8 -> 65 | L8: =K8-D22 -> 7.4778761
B9: 6 | C9: 送出线路投资 | D9: =SUM(F9:G9) -> 4000 | E9: 万元 | F9: 1200 | G9: 2800 | H9: =参数输入表!G139 -> 0.09 | I9: =F9*H9 -> 108 | J9: =G9*H9 -> 252 | K9: =D9*H9 -> 360 | L9: =K9-D23 -> 29.724771
B10: 7 | C10: 配套支持资金 | D10: =SUM(F10:G10) -> 0 | E10: 万元 | F10: 0 | G10: 0 | H10: =参数输入表!G140 -> 0 | I10: =F10*H10 -> 0 | J10: =G10*H10 -> 0 | K10: =D10*H10 -> 0 | L10: =K10-D24 -> 0
B11: 8 | C11: 静态投资 | D11: =SUM(F11:G11) -> 139000 | E11: 万元 | F11: =SUM(F4:F10) -> 41700 | G11: =SUM(G4:G10) -> 97300 | I11: =F11*H11 -> 0 | J11: =G11*H11 -> 0 | K11: =D11*H11 -> 0 | L11: =K11-D25 -> 0
B12: 9 | C12: 价差预备费 | D12: =SUM(F12:G12) -> 0 | E12: 万元 | F12: 0 | G12: 0 | H12: =参数输入表!G143 -> 0 | I12: =F12*H12 -> 0 | J12: =G12*H12 -> 0
B13: 10 | C13: 建设投资 | D13: =SUM(F13:G13) -> 139000 | E13: 万元 | F13: =F11+F12 -> 41700 | G13: =G11+G12 -> 97300
C14: 投资进度 | D14: =SUM(F14:G14) -> 1 | E14: 万元 | F14: =F13/$D$13 -> 0.3 | G14: =G13/$D$13 -> 0.7 | I14: =SUM(I4:I11) -> 4783.5 | J14: =SUM(J4:J11) -> 11161.5 | K14: =SUM(K4:K11) -> 15945 | L14: =SUM(L4:L11) -> 1722.1564
B16: 工程增值税进项税
B17: 序号 | C17: 科目 | D17: 合计 | E17: 单位 | F17: =F3 -> 2023年 | G17: =G3 -> 2024年
B18: 1 | C18: 设备购置费 | D18: =SUM(F18:G18) -> 11504.425 | E18: 万元 | F18: =F4/(1+$H$4)*$H$4 -> 3451.3274 | G18: =G4/(1+$H$4)*$H$4 -> 8053.0973
B19: 2 | C19: 建安工程费 | D19: =SUM(F19:G19) -> 1651.3761 | E19: 万元 | F19: =F5/(1+$H$5)*$H$5 -> 495.41284 | G19: =G5/(1+$H$5)*$H$5 -> 1155.9633
B20: 3 | C20: 其他费用 | D20: =SUM(F20:G20) -> 679.24528 | E20: 万元 | F20: =F6/(1+$H$6)*$H$6 -> 203.77358 | G20: =G6/(1+$H$6)*$H$6 -> 475.4717
B21: 4 | C21: 基本预备费 | D21: =SUM(F21:G21) -> 0 | E21: 万元 | F21: =F7/(1+$H$7)*$H$7 -> 0 | G21: =G7/(1+$H$7)*$H$7 -> 0
B22: 5 | C22: 储能投资 | D22: =SUM(F22:G22) -> 57.522124 | E22: 万元 | F22: =F8/(1+$H$8)*$H$8 -> 17.256637 | G22: =G8/(1+$H$8)*$H$8 -> 40.265487
B23: 6 | C23: 送出线路投资 | D23: =SUM(F23:G23) -> 330.27523 | E23: 万元 | F23: =F9/(1+$H$9)*$H$9 -> 99.082569 | G23: =G9/(1+$H$9)*$H$9 -> 231.19266
B24: 7 | C24: 配套支持资金 | D24: =SUM(F24:G24) -> 0 | E24: 万元 | F24: =F10/(1+$H$10)*$H$10 -> 0 | G24: =G10/(1+$H$10)*$H$10 -> 0
B25: 8 | C25: 价差预备费 | D25: =SUM(F25:G25) -> 0 | E25: 万元 | F25: =F12/(1+$H$12)*$H$12 -> 0 | G25: =G12/(1+$H$12)*$H$12 -> 0
B26: 工程可抵扣进项税合计 | D26: =SUM(F26:G26) -> 14222.844 | E26: 万元 | F26: =SUM(F18:F25) -> 4266.8531 | G26: =SUM(G18:G25) -> 9955.9905
B27: 工程可抵扣进项税累计 | E27: 万元 | F27: =F26 -> 4266.8531 | G27: =F27+G26 -> 14222.844
C29: 可抵扣进项税为后台计算，不需要作为成果展示

Sheet 参数输入表
D1: 【光伏】财务评价计算模型边界条件输入参数表
B3: 类别 | C3: 序号 | D3: 参数 | E3: 操作类型 | F3: 数据结构化整理 | G3: 收入/成本归类 | H3: 参数释义/计算公式 | I3: 数值 | J3: 单位 | K3: 取值说明 | L3: 备注
C4: 1 | D4: 项目投产日 | E4: 下拉菜单选择【日历】 | I4: 43921
D5: 项目运营期 | E5: 手动输入 | I5: 25 | J5: 年
D6: 项目结束日 | E6: 自动计算 | I6: =I4+365*I5 -> 53046
D7: 审计期间 | E7: 手动输入 | I7: 4 | J7: 年 | K7: 历史数据占用的年度范围
D8: 评估基准日 | E8: 手动输入 | I8: 45107
D9: 预测期 | E9: 自动计算 | I9: =IF(MONTH(I8)=12,YEAR(I6)-YEAR(I8),YEAR(I6)-YEAR(I8)+1) -> 23 | K9: 预测期占用的年度范围
C10: 2 | D10: 估值结果
D11: 股权价值 | E11: 手动输入 | I11: 8000 | J11: 万元
D12: 企业价值 | E12: 手动输入 | I12: 47000 | J12: 万元
C13: 3 | D13: 新建及改扩建项目
B14: 基础信息 | C14: 3.1 | D14: 建设期 | E14: 自动计算，向上取整 | I14: 2 | J14: 年 | K14: 测算表占用的年度范围
D15: 建设期起始日期 | E15: 下拉菜单选择【日历】 | I15: 45107 | J15: 年/月 | K15: 输入完动工年月及建设期结束日期，自动配置出参数表及计算表中建设期所占报表年度（如建设期为7年5个月，建设期实际占8个报表年）
D16: 建设期结束日期 | E16: 下拉菜单选择【日历】 | I16: 45627 | J16: 年/月
C17: 3.2 | D17: 施工进度安排 | I17: =SUM(I18:I19) -> 1
D18: 建设期第1年 | E18: 自动计算 | I18: ='新建及改扩建项目投资概算明细 (光伏)'!F14 -> 0.3 | J18: %
D19: 建设期第2年 | E19: 自动计算 | I19: ='新建及改扩建项目投资概算明细 (光伏)'!G14 -> 0.7 | J19: %
D20: …… | E20: 根据需要（向上取整）配置
C21: 3.3 | D21: 投产起始日期 | E21: 手动输入/下拉菜单选择【日历】 | I21: 7 | J21: 第n年/第n月
D22: 运营期 | E22: 手动输入 | I22: 25 | J22: 年
C23: 3.4 | D23: 试运营期 | E23: 选择时间区间 | J23: 年/月 | K23: 用于最后的累计盈余资金判定
C24: 4 | D24: 项目所在地 | E24: 下拉菜单选择 | K24: 判定是否属于西部地区
D25: 所在省份 | E25: 下拉菜单选择
D26: 所在市、县 | E26: 下拉菜单选择
C27: 5 | D27: 全生命周期小时数 | E27: 手动输入 | I27: 26000 | J27: h
C28: 6 | D28: 基准日累计发电小时数 | E28: 手动输入 | I28: 3500 | J28: h
C29: 7 | D29: 国补最晚截止日 | E29: 自动计算 | I29: =I4+365*20 -> 51221
B30: 生产相关 | C30: 8 | D30: 总装机容量 | E30: 自动计算 | I30: =I31+I32 -> 320 | J30: MW | K30: 1MW=1000kW
C31: 8.1 | D31: 其中：基准日实际装机容量 | E31: 手动输入 | I31: 10 | J31: MW
C32: 8.2 | D32: 新增及改扩建装机容量 | E32: 手动输入 | I32: 310 | J32: MW
C33: 9 | D33: 年利用小时数 | E33: 手动输入 | I33: 1551 | J33: h
C34: 10 | D34: 新建及改扩建项目投产比例
D35: 建设期第1年 | E35: 手动输入 | I35: 0.15 | J35: %
D36: 建设期第2年 | E36: 手动输入 | I36: 0.75 | J36: %
D37: 建设期后 | E37: 手动输入 | I37: 0.1 | J37: %
D38: 全生命周期投产比例
D39: 合作期第1年 | E39: 手动输入 | I39: 0 | J39: %
D40: 合作期第2年 | E40: 手动输入 | I40: =I31/I30 -> 0.03125 | J40: %
D41: 合作期第3年 | E41: 手动输入 | I41: =I40 -> 0.03125 | J41: %
D42: 合作期第4年 | E42: 手动输入 | I42: =I41 -> 0.03125 | J42: %
D43: 合作期第5年 | E43: 手动输入 | I43: =($I$31+$I$32*I35)/$I$30 -> 0.1765625 | J43: %
D44: 合作期第6年 | E44: 手动输入 | I44: =($I$31+$I$32*I36)/$I$30 -> 0.7578125 | J44: %
D45: 合作期第7年 | E45: 手动输入 | I45: 1 | J45: %
D46: 合作期第8年 | E46: 手动输入 | I46: 1 | J46: %
D47: 合作期第9年 | E47: 手动输入 | I47: 1 | J47: %
D48: 合作期第10年 | E48: 手动输入 | I48: 1 | J48: %
D49: 合作期第11年 | E49: 手动输入 | I49: 1 | J49: %
D50: 合作期第12年 | E50: 手动输入 | I50: 1 | J50: %
D51: 合作期第13年 | E51: 手动输入 | I51: 1 | J51: %
D52: 合作期第14年 | E52: 手动输入 | I52: 1 | J52: %
D53: 合作期第15年 | E53: 手动输入 | I53: 1 | J53: %
D54: 合作期第16年 | E54: 手动输入 | I54: 1 | J54: %
D55: 合作期第17年 | E55: 手动输入 | I55: 1 | J55: %
D56: 合作期第18年 | E56: 手动输入 | I56: 1 | J56: %
... D65: 合作期第27年 | E65: 手动输入 | I65: 1 | J65: %
D66: 发电量 | H66: 抽水蓄能上网电量=年利用小时数*实际装机容量 | J66: MWh | K66: 1MWh=0.1万度电
D67: 总装机容量 | E67: 引用 | I67: =I30 -> 320 | J67: MW
D68: 年利用小时数 | E68: 引用 | I68: =I33 -> 1551 | J68: h
D69: 衰减率
D70: 合作期第1年 | E70: 手动输入 | I70: 0 | J70: %
D71: 合作期第2年 | E71: 手动输入 | I71: 0 | J71: %
D72: 合作期第3年 | E72: 手动输入 | I72: 0 | J72: %
D73: 合作期第4年 | E73: 手动输入 | I73: 0.0045 | J73: %
D74: 合作期第5年 | E74: 手动输入 | I74: =I73+0.45% -> 0.009 | J74: %
D75: 合作期第6年 | E75: 手动输入 | I75: =I74+0.45% -> 0.0135 | J75: %
D76: 合作期第7年 | E76: 手动输入 | I76: =I75+0.45% -> 0.018 | J76: %
D77: 合作期第8年 | E77: 手动输入 | I77: =I76+0.45% -> 0.0225 | J77: %
D78: 合作期第9年 | E78: 手动输入 | I78: =I77+0.45% -> 0.027 | J78: %
D79: 合作期第10年 | E79: 手动输入 | I79: =I78+0.45% -> 0.0315 | J79: %
D80: 合作期第11年 | E80: 手动输入 | I80: =I79+0.45% -> 0.036 | J80: %
D81: 合作期第12年 | E81: 手动输入 | I81: =I80+0.45% -> 0.0405 | J81: %
D82: 合作期第13年 | E82: 手动输入 | I82: =I81+0.45% -> 0.045 | J82: %
D83: 合作期第14年 | E83: 手动输入 | I83: =I82+0.45% -> 0.0495 | J83: %
D84: 合作期第15年 | E84: 手动输入 | I84: =I83+0.45% -> 0.054 | J84: %
D85: 合作期第16年 | E85: 手动输入 | I85: =I84+0.45% -> 0.0585 | J85: %
... D96: 合作期第27年 | E96: 手动输入 | I96: =I95+0.45% -> 0.108 | J96: %
D97: 限电率
D98: 合作期第1年 | E98: 手动输入 | I98: 0 | J98: %
D99: 合作期第2年 | E99: 手动输入 | I99: 0 | J99: %
D100: 合作期第3年 | E100: 手动输入 | I100: 0 | J100: %
D101: 合作期第4年 | E101: 手动输入 | I101: 0 | J101: %
D102: 合作期第5年 | E102: 手动输入 | I102: 0 | J102: %
D103: 合作期第6年 | E103: 手动输入 | I103: 0 | J103: %
D104: 合作期第7年 | E104: 手动输入 | I104: 0 | J104: %
D105: 合作期第8年 | E105: 手动输入 | I105: 0 | J105: %
D106: 合作期第9年 | E106: 手动输入 | I106: 0 | J106: %
D107: 合作期第10年 | E107: 手动输入 | I107: 0 | J107: %
D108: 合作期第11年 | E108: 手动输入 | I108: 0 | J108: %
D109: 合作期第12年 | E109: 手动输入 | I109: 0 | J109: %
... D127: 现货市场交易电量占比 | E127: 手动输入 | I127: 0.1 | J127: %
D128: 售电电价
D129: 保障内交易电价（合作期1-27年） | E129: 手动输入 | I129: 0.35 | J129: 元/kWh
D130: 市场化交易电价（合作期1-27年） | E130: 手动输入 | I130: 0.25 | J130: 元/kWh
D131: 现货市场交易电价（合作期1-27年） | E131: 手动输入 | I131: 0.21 | J131: 元/kWh
D132: 加权平均电价（合作期1-27年） | E132: 自动计算 | I132: =I129*I125+I130*I126+I131*I127 -> 0.316 | J132: 元/kWh
D133: 补贴电价 | E133: 手动输入 | I133: 0.1 | J133: 元/kWh
B134: 新建及改扩建项目投资概算 | C134: 1 | D134: 设备购置费 | E134: 手动输入/下拉菜单选择【增值税税率】 | G134: 0.13 | H134: 增值税税率（自动生成含税和不含税价）：13%/9%/6%/0% | I134: ='新建及改扩建项目投资概算明细 (光伏)'!D4 -> 100000 | J134: 万元
C135: 2 | D135: 建安工程费用 | E135: 手动输入/下拉菜单选择【增值税税率】 | G135: 0.09 | H135: 增值税税率（自动生成含税和不含税价）：13%/9%/6%/0% | I135: ='新建及改扩建项目投资概算明细 (光伏)'!D5 -> 20000 | J135: 万元
C136: 3 | D136: 其他费用 | E136: 手动输入/下拉菜单选择【增值税税率】 | G136: 0.06 | H136: 增值税税率（自动生成含税和不含税价）：13%/9%/6%/0% | I136: ='新建及改扩建项目投资概算明细 (光伏)'!D6 -> 12000 | J136: 万元
...

Sheet 表1-资金筹措及还本付息表
B2: 新建及改扩建项目资金筹措表
B3: 序号 | C3: 项目 | D3: 合计 | E3: 单位 | F3: 2020年 | G3: 2021年 | H3: 2022年 | I3: 45107 | J3: 45261 | K3: 2024年 | L3: 2025年 | M3: 2026年 | N3: 2027年 | O3: 2028年 | P3: 2029年 | Q3: 2030年 | R3: 2031年 | S3: 2032年 | T3: 2033年 | U3: 2034年 | V3: 2035年 | W3: 2036年 | X3: 2037年 | Y3: 2038年 | Z3: 2039年 | AA3: 2040年 | AB3: 2041年 | AC3: 2042年 | AD3: 2043年 | AE3: 2044年 | AF3: 53051
F4: 1 | G4: 2 | H4: 3 | I4: 4 | J4: 5 | K4: 6 | L4: 7 | M4: 8 | N4: 9 | O4: 10 | P4: 11 | Q4: 12 | R4: 13 | S4: 14 | T4: 15 | U4: 16 | V4: 17 | W4: 18 | X4: 19 | Y4: 20 | Z4: 21 | AA4: 22 | AB4: 23 | AC4: 24 | AD4: 25 | AE4: 26 | AF4: 27
C5: 施工进度安排 | D5: =SUM(F5:AF5) -> 1 | J5: =参数输入表!I18 -> 0.3 | K5: =参数输入表!I19 -> 0.7
C6: 期末投产比例 | J6: =参数输入表!I35 -> 0.15 | K6: =参数输入表!I36+J6 -> 0.9
B7: 1 | C7: 动态总投资（自主投资,含流动资金） | D7: =D8+D9+D10 -> 140377.27 | E7: 万元 | J7: =SUM(J8:J10) -> 41985.124 | K7: =SUM(K8:K10) -> 97592.141 | L7: =SUM(L8:L10) -> 800 | M7: =SUM(M8:M10) -> 0 | N7: =SUM(N8:N10) -> 0 | O7: =SUM(O8:O10) -> 0 | P7: =SUM(P8:P10) -> 0 | Q7: =SUM(Q8:Q10) -> 0 | ... AF7: =SUM(AF8:AF10) -> 0
B8: 1.1 | C8: 静态总投资（自主投资） | D8: =SUM(F8:AF8) -> 139000 | E8: 万元 | J8: =参数输入表!$I$145*J5 -> 41700 | K8: =参数输入表!$I$145*K5 -> 97300 | L8: =IF(L$4-参数输入表!$I$14-参数输入表!$I$7>0,0) -> 0 | M8: =IF(M$4-参数输入表!$I$14-参数输入表!$I$7>0,0) -> 0 | N8: =IF(N$4-参数输入表!$I$14-参数输入表!$I$7>0,0) -> 0 | O8: =IF(O$4-参数输入表!$I$14-参数输入表!$I$7>0,0) -> 0 | P8: =IF(P$4-参数输入表!$I$14-参数输入表!$I$7>0,0) -> 0 | Q8: =IF(Q$4-参数输入表!$I$14-参数输入表!$I$7>0,0) -> 0 | R8: =IF(R$4-参数输入表!$I$14-参数输入表!$I$7>0,0) -> 0 | S8: =IF(S$4-参数输入表!$I$14-参数输入表!$I$7>0,0) -> 0 | ... AF8: =IF(AF$4-参数输入表!$I$14-参数输入表!$I$7>0,0) -> 0
B9: 1.2 | C9: 建设期利息 | D9: =SUM(F9:AF9) -> 577.26523 | E9: 万元 | J9: =J17 -> 285.12398 | K9: =K17 -> 292.14125 | L9: =L17 -> 0 | M9: =M17 -> 0 | N9: =N17 -> 0 | O9: =O17 -> 0 | P9: =P17 -> 0 | Q9: =Q17 -> 0 | ... AF9: =AF17 -> 0
B10: 1.3 | C10: 流动资金 | D10: =SUM(F10:AF10) -> 800 | E10: 万元 | J10: =IF(AND(J4-参数输入表!$I$21=0,参数输入表!$I$149="手动输入"),参数输入表!$I$151,IF(AND(J4-参数输入表!$I$21=0,参数输入表!$I$149="单位千瓦指标计算"),参数输入表!$I$150*参数输入表!$I$32/10,0)) -> 0 | K10: =IF(AND(K4-参数输入表!$I$21=0,参数输入表!$I$149="手动输入"),参数输入表!$I$151,IF(AND(K4-参数输入表!$I$21=0,参数输入表!$I$149="单位千瓦指标计算"),参数输入表!$I$150*参数输入表!$I$32/10,0)) -> 0 | L10: =IF(AND(L4-参数输入表!$I$21=0,参数输入表!$I$149="手动输入"),参数输入表!$I$151,IF(AND(L4-参数输入表!$I$21=0,参数输入表!$I$149="单位千瓦指标计算"),参数输入表!$I$150*参数输入表!$I$32/10,0)) -> 800 | M10: =IF(AND(M4-参数输入表!$I$21=0,参数输入表!$I$149="手动输入"),参数输入表!$I$151,IF(AND(M4-参数输入表!$I$21=0,参数输入表!$I$149="单位千瓦指标计算"),参数输入表!$I$150*参数输入表!$I$32/10,0)) -> 0 | N10: =IF(AND(N4-参数输入表!$I$21=0,参数输入表!$I$149="手动输入"),参数输入表!$I$151,IF(AND(N4-参数输入表!$I$21=0,参数输入表!$I$149="单位千瓦指标计算"),参数输入表!$I$150*参数输入表!$I$32/10,0)) -> 0 | O10: =IF(AND(O4-参数输入表!$I$21=0,参数输入表!$I$149="手动输入"),参数输入表!$I$151,IF(AND(O4-参数输入表!$I$21=0,参数输入表!$I$149="单位千瓦指标计算"),参数输入表!$I$150*参数输入表!$I$32/10,0)) -> 0 | P10: =IF(AND(P4-参数输入表!$I$21=0,参数输入表!$I$149="手动输入"),参数输入表!$I$151,IF(AND(P4-参数输入表!$I$21=0,参数输入表!$I$149="单位千瓦指标计算"),参数输入表!$I$150*参数输入表!$I$32/10,0)) -> 0 | Q10: =IF(AND(Q4-参数输入表!$I$21=0,参数输入表!$I$149="手动输入"),参数输入表!$I$151,IF(AND(Q4-参数输入表!$I$21=0,参数输入表!$I$149="单位千瓦指标计算"),参数输入表!$I$150*参数输入表!$I$32/10,0)) -> 0 | ... AF10: =IF(AND(AF4-参数输入表!$I$21=0,参数输入表!$I$149="手动输入"),参数输入表!$I$151,IF(AND(AF4-参数输入表!$I$21=0,参数输入表!$I$149="单位千瓦指标计算"),参数输入表!$I$150*参数输入表!$I$32/10,0)) -> 0
B11: 2 | C11: 资金来源
B12: 2.1 | C12: 资本金 | D12: =SUM(F12:AF12) -> 35134.316 | E12: 万元 | J12: =SUM(J13:J14) -> 10496.281 | K12: =SUM(K13:K14) -> 24398.035 | L12: =SUM(L13:L14) -> 240 | M12: =SUM(M13:M14) -> 0 | N12: =SUM(N13:N14) -> 0 | O12: =SUM(O13:O14) -> 0 | P12: =SUM(P13:P14) -> 0 | Q12: =SUM(Q13:Q14) -> 0 | ... AF12: =SUM(AF13:AF14) -> 0
B13: 2.1.1 | C13: 用于建设投资 | D13: =SUM(F13:AF13) -> 34894.316 | E13: 万元 | J13: =(J8+J9)*参数输入表!$I$215 -> 10496.281 | K13: =(K8+K9)*参数输入表!$I$215 -> 24398.035 | L13: =(L8+L9)*参数输入表!$I$215 -> 0 | M13: =(M8+M9)*参数输入表!$I$215 -> 0 | N13: =(N8+N9)*参数输入表!$I$215 -> 0 | O13: =(O8+O9)*参数输入表!$I$215 -> 0 | P13: =(P8+P9)*参数输入表!$I$215 -> 0 | Q13: =(Q8+Q9)*参数输入表!$I$215 -> 0 | ... AF13: =(AF8+AF9)*参数输入表!$I$215 -> 0
B14: 2.1.2 | C14: 用于流动资金 | D14: =SUM(F14:AF14) -> 240 | E14: 万元 | J14: =IF(AND(J4-参数输入表!$I$21=0,参数输入表!$I$149="手动输入"),参数输入表!$I$151*参数输入表!$I$223,IF(AND(J4-参数输入表!$I$21=0,参数输入表!$I$149="单位千瓦指标计算"),参数输入表!$I$150*参数输入表!$I$32/10*参数输入表!$I$223,0)) -> 0 | K14: =IF(AND(K4-参数输入表!$I$21=0,参数输入表!$I$149="手动输入"),参数输入表!$I$151*参数输入表!$I$223,IF(AND(K4-参数输入表!$I$21=0,参数输入表!$I$149="单位千瓦指标计算"),参数输入表!$I$150*参数输入表!$I$32/10*参数输入表!$I$223,0)) -> 0 | L14: =IF(AND(L4-参数输入表!$I$21=0,参数输入表!$I$149="手动输入"),参数输入表!$I$151*参数输入表!$I$223,IF(AND(L4-参数输入表!$I$21=0,参数输入表!$I$149="单位千瓦指标计算"),参数输入表!$I$150*参数输入表!$I$32/10*参数输入表!$I$223,0)) -> 240 | M14: =IF(AND(M4-参数输入表!$I$21=0,参数输入表!$I$149="手动输入"),参数输入表!$I$151*参数输入表!$I$223,IF(AND(M4-参数输入表!$I$21=0,参数输入表!$I$149="单位千瓦指标计算"),参数输入表!$I$150*参数输入表!$I$32/10*参数输入表!$I$223,0)) -> 0 | N14: =IF(AND(N4-参数输入表!$I$21=0,参数输入表!$I$149="手动输入"),参数输入表!$I$151*参数输入表!$I$223,IF(AND(N4-参数输入表!$I$21=0,参数输入表!$I$149="单位千瓦指标计算"),参数输入表!$I$150*参数输入表!$I$32/10*参数输入表!$I$223,0)) -> 0 | O14: =IF(AND(O4-参数输入表!$I$21=0,参数输入表!$I$149="手动输入"),参数输入表!$I$151*参数输入表!$I$223,IF(AND(O4-参数输入表!$I$21=0,参数输入表!$I$149="单位千瓦指标计算"),参数输入表!$I$150*参数输入表!$I$32/10*参数输入表!$I$223,0)) -> 0 | P14: =IF(AND(P4-参数输入表!$I$21=0,参数输入表!$I$149="手动输入"),参数输入表!$I$151*参数输入表!$I$223,IF(AND(P4-参数输入表!$I$21=0,参数输入表!$I$149="单位千瓦指标计算"),参数输入表!$I$150*参数输入表!$I$32/10*参数输入表!$I$223,0)) -> 0 | Q14: =IF(AND(Q4-参数输入表!$I$21=0,参数输入表!$I$149="手动输入"),参数输入表!$I$151*参数输入表!$I$223,IF(AND(Q4-参数输入表!$I$21=0,参数输入表!$I$149="单位千瓦指标计算"),参数输入表!$I$150*参数输入表!$I$32/10*参数输入表!$I$223,0)) -> 0 | ... AF14: =IF(AND(AF4-参数输入表!$I$21=0,参数输入表!$I$149="手动输入"),参数输入表!$I$151*参数输入表!$I$223,IF(AND(AF4-参数输入表!$I$21=0,参数输入表!$I$149="单位千瓦指标计算"),参数输入表!$I$150*参数输入表!$I$32/10*参数输入表!$I$223,0)) -> 0
B15: 2.2 | C15: 债务资金 | D15: =SUM(F15:AF15) -> 105242.95 | E15: 万元 | J15: =SUM(J16:J17)+J19 -> 31488.843 | K15: =SUM(K16:K17)+K19 -> 73194.106 | L15: =SUM(L16:L17)+L19 -> 560 | M15: =SUM(M16:M17)+M19 -> 0 | N15: =SUM(N16:N17)+N19 -> 0 | O15: =SUM(O16:O17)+O19 -> 0 | P15: =SUM(P16:P17)+P19 -> 0 | Q15: =SUM(Q16:Q17)+Q19 -> 0 | ... AF15: =SUM(AF16:AF17)+AF19 -> 0
B16: 2.2.1 | C16: 用于建设投资 | D16: =SUM(F16:AF16) -> 104105.68 | E16: 万元 | J16: =J8-J13 -> 31203.719 | K16: =K8-K13 -> 72901.965 | L16: =IF(L$4-参数输入表!$I$14-参数输入表!$I$7>0,0) -> 0 | M16: =IF(M$4-参数输入表!$I$14-参数输入表!$I$7>0,0) -> 0 | N16: =IF(N$4-参数输入表!$I$14-参数输入表!$I$7>0,0) -> 0 | O16: =IF(O$4-参数输入表!$I$14-参数输入表!$I$7>0,0) -> 0 | P16: =IF(P$4-参数输入表!$I$14-参数输入表!$I$7>0,0) -> 0 | Q16: =IF(Q$4-参数输入表!$I$14-参数输入表!$I$7>0,0) -> 0 | R16: =IF(R$4-参数输入表!$I$14-参数输入表!$I$7>0,0) -> 0 | S16: =IF(S$4-参数输入表!$I$14-参数输入表!$I$7>0,0) -> 0 | ... AF16: =IF(AF$4-参数输入表!$I$14-参数输入表!$I$7>0,0) -> 0
B17: 2.2.2 | C17: 用于建设期利息 | D17: =SUM(F17:AF17) -> 577.26523 | E17: 万元 | J17: =J16/2*参数输入表!$I$218*(12-MONTH(参数输入表!I8))/12*(1-J6) -> 285.12398 | K17: =(J16+J17+K16/2)*参数输入表!$I$218*(1-K6) -> 292.14125 | L17: =IF(L$4-参数输入表!$I$14-参数输入表!$I$7>0,0) -> 0 | M17: =IF(M$4-参数输入表!$I$14-参数输入表!$I$7>0,0) -> 0 | N17: =IF(N$4-参数输入表!$I$14-参数输入表!$I$7>0,0) -> 0 | O17: =IF(O$4-参数输入表!$I$14-参数输入表!$I$7>0,0) -> 0 | P17: =IF(P$4-参数输入表!$I$14-参数输入表!$I$7>0,0) -> 0 | Q17: =IF(Q$4-参数输入表!$I$14-参数输入表!$I$7>0,0) -> 0 | R17: =IF(R$4-参数输入表!$I$14-参数输入表!$I$7>0,0) -> 0 | S17: =IF(S$4-参数输入表!$I$14-参数输入表!$I$7>0,0) -> 0 | ... AF17: =IF(AF$4-参数输入表!$I$14-参数输入表!$I$7>0,0) -> 0
C18: 应计利息（隐藏） | D18: =SUM(F18:AF18) -> 3256.8525 | E18: 万元 | J18: =J16/2*参数输入表!$I$218*(12-MONTH(参数输入表!I8))/12 -> 335.43998 | K18: =(J16+J17+K16/2)*参数输入表!$I$218 -> 2921.4125 | L18: =IF(L$4-参数输入表!$I$14-参数输入表!$I$7>0,0) -> 0 | M18: =IF(M$4-参数输入表!$I$14-参数输入表!$I$7>0,0) -> 0 | N18: =IF(N$4-参数输入表!$I$14-参数输入表!$I$7>0,0) -> 0 | O18: =IF(O$4-参数输入表!$I$14-参数输入表!$I$7>0,0) -> 0 | P18: =IF(P$4-参数输入表!$I$14-参数输入表!$I$7>0,0) -> 0 | Q18: =IF(Q$4-参数输入表!$I$14-参数输入表!$I$7>0,0) -> 0 | R18: =IF(R$4-参数输入表!$I$14-参数输入表!$I$7>0,0) -> 0 | S18: =IF(S$4-参数输入表!$I$14-参数输入表!$I$7>0,0) -> 0 | ... AF18: =IF(AF$4-参数输入表!$I$14-参数输入表!$I$7>0,0) -> 0
B19: 2.2.3 | C19: 用于流动资金 | D19: =SUM(F19:AF19) -> 560 | E19: 万元 | J19: =J10-J14 -> 0 | K19: =K10-K14 -> 0 | L19: =L10-L14 -> 560 | M19: =M10-M14 -> 0 | N19: =N10-N14 -> 0 | O19: =O10-O14 -> 0 | P19: =P10-P14 -> 0 | Q19: =Q10-Q14 -> 0 | ... AF19: =AF10-AF14 -> 0
B21: 营运资本变动
B22: 序号 | C22: 项目 | D22: 合计 | E22: 单位 | F22: 建设期 | H22: 运营期
F23: 1 | G23: 2 | H23: 1 | I23: 2 | J23: 3 | K23: 4 | L23: 5 | M23: 6 | N23: 7 | O23: 8 | P23: 9 | Q23: 10 | R23: 11 | S23: 12 | T23: 13 | U23: 14 | V23: 15 | W23: 16 | X23: 17 | Y23: 18 | Z23: 19 | AA23: 20 | AB23: 21 | AC23: 22 | AD23: 23 | AE23: 24 | AF23: 25
B24: 1 | C24: 流动资产 | D24: =SUM(F24:AF24) -> 0 | E24: 万元
C25: 货币资金 | D25: =SUM(F25:AF25) -> 0 | E25: 万元
C26: 应收账款 | D26: =SUM(F26:AF26) -> 0 | E26: 万元
C27: 存货 | D27: =SUM(F27:AF27) -> 0 | E27: 万元
C28: 其他流动资产（留抵税额） | D28: =SUM(F28:AF28) -> 0 | E28: 万元
B29: 2 | C29: 流动负债 | D29: =SUM(F29:AF29) -> 0 | E29: 万元
C30: 短期借款 | D30: =SUM(F30:AF30) -> 0 | E30: 万元
C31: 预收款项 | D31: =SUM(F31:AF31) -> 0 | E31: 万元
C32: 应付职工薪酬 | D32: =SUM(F32:AF32) -> 0 | E32: 万元
C33: 应交税费 | D33: =SUM(F33:AF33) -> 0 | E33: 万元
C34: 应付股利 | D34: =SUM(F34:AF34) -> 0 | E34: 万元
C35: 其他流动负债 | D35: =SUM(F35:AF35) -> 0 | E35: 万元
B37: 借款还本付息表（新增及改扩建项目长期借款）
B38: 序号 | C38: 项目 | D38: 合计 | E38: 单位 | F38: 2020年 | G38: 2021年 | H38: 2022年 | I38: 45107 | J38: 45261 | K38: 2024年 | L38: 2025年 | M38: 2026年 | N38: 2027年 | O38: 2028年 | P38: 2029年 | Q38: 2030年 | R38: 2031年 | S38: 2032年 | T38: 2033年 | U38: 2034年 | V38: 2035年 | W38: 2036年 | X38: 2037年 | Y38: 2038年 | Z38: 2039年 | AA38: 2040年 | AB38: 2041年 | AC38: 2042年 | AD38: 2043年 | AE38: 2044年 | AF38: 53051
F39: 1 | G39: 2 | H39: 3 | I39: 4 | J39: 5 | K39: 6 | L39: 7 | M39: 8 | N39: 9 | O39: 10 | P39: 11 | Q39: 12 | R39: 13 | S39: 14 | T39: 15 | U39: 16 | V39: 17 | W39: 18 | X39: 19 | Y39: 20 | Z39: 21 | AA39: 22 | AB39: 23 | AC39: 24 | AD39: 25 | AE39: 26 | AF39: 27
B40: 1 | C40: 期初借款累计 | E40: 万元 | J40: 0 | K40: =J45 -> 31488.843 | L40: =K45 -> 104682.95 | M40: =L45 -> 99570.445 | N40: =M45 -> 94238.104 | O40: =N45 -> 88676.471 | P40: =O45 -> 82875.689 | Q40: =P45 -> 76825.473 | R40: =Q45 -> 70515.098 | ... AF40: =AE45 -> -1.7961463e-11
B41: 2 | C41: 当期借款 | D41: =SUM(F41:AF41) -> 104682.95 | E41: 万元 | J41: =J16+J17 -> 31488.843 | K41: =K16+K17 -> 73194.106 | L41: =L16+L17 -> 0 | M41: =M16+M17 -> 0 | N41: =N16+N17 -> 0 | O41: =O16+O17 -> 0 | P41: =P16+P17 -> 0 | Q41: =Q16+Q17 -> 0 | ... AF41: =AF16+AF17 -> 0
B42: 3 | C42: 当期还本付息 | D42: =SUM(F42:AF42) -> 146887.65 | E42: 万元 | J42: =IF(J39-参数输入表!$I$217-参数输入表!$I$7<=0,SUM(J43:J44),IF(J39-参数输入表!$I$217-参数输入表!$I$7<=参数输入表!$I$222,-PMT(参数输入表!$I$219,参数输入表!$I$222,'表1-资金筹措及还本付息表'!$D$41),0)) -> 50.315997 | K42: =IF(K39-参数输入表!$I$217-参数输入表!$I$7<=0,SUM(K43:K44),IF(K39-参数输入表!$I$217-参数输入表!$I$7<=参数输入表!$I$222,-PMT(参数输入表!$I$219,参数输入表!$I$222,'表1-资金筹措及还本付息表'!$D$41),0)) -> 2629.2712 | L42: =IF(L39-参数输入表!$I$217-参数输入表!$I$7<=0,SUM(L43:L44),IF(L39-参数输入表!$I$217-参数输入表!$I$7<=参数输入表!$I$222,-PMT(参数输入表!$I$219,参数输入表!$I$222,'表1-资金筹措及还本付息表'!$D$41),0)) -> 9613.8707 | M42: =IF(M39-参数输入表!$I$217-参数输入表!$I$7<=0,SUM(M43:M44),IF(M39-参数输入表!$I$217-参数输入表!$I$7<=参数输入表!$I$222,-PMT(参数输入表!$I$219,参数输入表!$I$222,'表1-资金筹措及还本付息表'!$D$41),0)) -> 9613.8707 | N42: =IF(N39-参数输入表!$I$217-参数输入表!$I$7<=0,SUM(N43:N44),IF(N39-参数输入表!$I$217-参数输入表!$I$7<=参数输入表!$I$222,-PMT(参数输入表!$I$219,参数输入表!$I$222,'表1-资金筹措及还本付息表'!$D$41),0)) -> 9613.8707 | O42: =IF(O39-参数输入表!$I$217-参数输入表!$I$7<=0,SUM(O43:O44),IF(O39-参数输入表!$I$217-参数输入表!$I$7<=参数输入表!$I$222,-PMT(参数输入表!$I$219,参数输入表!$I$222,'表1-资金筹措及还本付息表'!$D$41),0)) -> 9613.8707 | P42: =IF(P39-参数输入表!$I$217-参数输入表!$I$7<=0,SUM(P43:P44),IF(P39-参数输入表!$I$217-参数输入表!$I$7<=参数输入表!$I$222,-PMT(参数输入表!$I$219,参数输入表!$I$222,'表1-资金筹措及还本付息表'!$D$41),0)) -> 9613.8707 | Q42: =IF(Q39-参数输入表!$I$217-参数输入表!$I$7<=0,SUM(Q43:Q44),IF(Q39-参数输入表!$I$217-参数输入表!$I$7<=参数输入表!$I$222,-PMT(参数输入表!$I$219,参数输入表!$I$222,'表1-资金筹措及还本付息表'!$D$41),0)) -> 9613.8707 | ... AF42: =IF(AF39-参数输入表!$I$217-参数输入表!$I$7<=0,SUM(AF43:AF44),IF(AF39-参数输入表!$I$217-参数输入表!$I$7<=参数输入表!$I$222,-PMT(参数输入表!$I$219,参数输入表!$I$222,'表1-资金筹措及还本付息表'!$D$41),0)) -> 0
C43: 其中：还本（等额本息） | D43: =SUM(F43:AF43) -> 104682.95 | E43: 万元 | J43: =IF(J39-参数输入表!$I$217-参数输入表!$I$7<=0,0,J42-J44) -> 0 | K43: =IF(K39-参数输入表!$I$217-参数输入表!$I$7<=0,0,K42-K44) -> 0 | L43: =IF(L39-参数输入表!$I$217-参数输入表!$I$7<=0,0,L42-L44) -> 5112.5039 | M43: =IF(M39-参数输入表!$I$217-参数输入表!$I$7<=0,0,M42-M44) -> 5332.3415 | N43: =IF(N39-参数输入表!$I$217-参数输入表!$I$7<=0,0,N42-N44) -> 5561.6322 | O43: =IF(O39-参数输入表!$I$217-参数输入表!$I$7<=0,0,O42-O44) -> 5800.7824 | P43: =IF(P39-参数输入表!$I$217-参数输入表!$I$7<=0,0,P42-P44) -> 6050.216 | Q43: =IF(Q39-参数输入表!$I$217-参数输入表!$I$7<=0,0,Q42-Q44) -> 6310.3753 | ... AF43: =IF(AF39-参数输入表!$I$217-参数输入表!$I$7<=0,0,AF42-AF44) -> 1.9308572e-13
C44: 付息 | D44: =SUM(F44:AF44) -> 42204.698 | E44: 万元 | J44: =IF(J39-参数输入表!$I$217-参数输入表!$I$7<=0,J18-J17,(J40+J41/2)*参数输入表!$I$219*(12-MONTH(参数输入表!I8))/12) -> 50.315997 | K44: =IF(K39-参数输入表!$I$217-参数输入表!$I$7<=0,K18-K17,(K40+K41/2)*参数输入表!$I$219) -> 2629.2712 | L44: =IF(L39-参数输入表!$I$217-参数输入表!$I$7<=0,L18-L17,(L40+L41/2)*参数输入表!$I$219) -> 4501.3668 | M44: =IF(M39-参数输入表!$I$217-参数输入表!$I$7<=0,M18-M17,(M40+M41/2)*参数输入表!$I$219) -> 4281.5291 | N44: =IF(N39-参数输入表!$I$217-参数输入表!$I$7<=0,N18-N17,(N40+N41/2)*参数输入表!$I$219) -> 4052.2385 | O44: =IF(O39-参数输入表!$I$217-参数输入表!$I$7<=0,O18-O17,(O40+O41/2)*参数输入表!$I$219) -> 3813.0883 | P44: =IF(P39-参数输入表!$I$217-参数输入表!$I$7<=0,P18-P17,(P40+P41/2)*参数输入表!$I$219) -> 3563.6546 | Q44: =IF(Q39-参数输入表!$I$217-参数输入表!$I$7<=0,Q18-Q17,(Q40+Q41/2)*参数输入表!$I$219) -> 3303.4953 | R44: =IF(R39-参数输入表!$I$217-参数输入表!$I$7<=0,R18-R17,(R40+R41/2)*参数输入表!$I$219) -> 3032.1492 | ... AE44: =IF(AE39-参数输入表!$I$217-参数输入表!$I$7<=0,AE18-AE17,(AE40+AE41/2)*参数输入表!$I$219) -> -7.4050133e-13 | AF44: =IF(AF39-参数输入表!$I$217-参数输入表!$I$7<=0,AF18-AF17,(AF40+AF41/2)*参数输入表!$I$219*MONTH(参数输入表!$I$6)/12) -> -1.9308572e-13
B45: 4 | C45: 期末借款余额 | D45: =AF45 -> -1.8154548e-11 | E45: 万元 | J45: =J40+J41-J43 -> 31488.843 | K45: =K40+K41-K43 -> 104682.95 | L45: =L40+L41-L43 -> 99570.445 | M45: =M40+M41-M43 -> 94238.104 | N45: =N40+N41-N43 -> 88676.471 | O45: =O40+O41-O43 -> 82875.689 | P45: =P40+P41-P43 -> 76825.473 | Q45: =Q40+Q41-Q43 -> 70515.098 | ... AF45: =AF40+AF41-AF43 -> -1.8154548e-11
B47: 借款还本付息表（新增及改扩建项目长期借款）
B48: 序号 | C48: 项目 | D48: 合计 | E48: 单位 | F48: 2020年 | G48: 2021年 | H48: 2022年 | I48: 45107 | J48: 45261 | K48: 2024年 | L48: 2025年 | M48: 2026年 | N48: 2027年 | O48: 2028年 | P48: 2029年 | Q48: 2030年 | R48: 2031年 | S48: 2032年 | T48: 2033年 | U48: 2034年 | V48: 2035年 | W48: 2036年 | X48: 2037年 | Y48: 2038年 | Z48: 2039年 | AA48: 2040年 | AB48: 2041年 | AC48: 2042年 | AD48: 2043年 | AE48: 2044年 | AF48: 53051
F49: 1 | G49: 2 | H49: 3 | I49: 4 | J49: 5 | K49: 6 | L49: 7 | M49: 8 | N49: 9 | O49: 10 | P49: 11 | Q49: 12 | R49: 13 | S49: 14 | T49: 15 | U49: 16 | V49: 17 | W49: 18 | X49: 19 | Y49: 20 | Z49: 21 | AA49: 22 | AB49: 23 | AC49: 24 | AD49: 25 | AE49: 26 | AF49: 27
B50: 1 | C50: 期初借款累计 | E50: 万元 | J50: 0 | K50: =J55 -> 31488.843 | L50: =K55 -> 104682.95 | M50: =L55 -> 97704.086 | N50: =M55 -> 90725.222 | O50: =N55 -> 83746.359 | P50: =O55 -> 76767.496 | Q50: =P55 -> 69788.633 | R50: =Q55 -> 62809.769 | ... AF50: =AE55 -> -4.0017767e-11
B51: 2 | C51: 当期借款 | D51: =SUM(F51:AF51) -> 104682.95 | E51: 万元 | J51: =J16+J17 -> 31488.843 | K51: =K16+K17 -> 73194.106 | L51: =L16+L17 -> 0 | M51: =M16+M17 -> 0 | N51: =N16+N17 -> 0 | O51: =O16+O17 -> 0 | P51: =P16+P17 -> 0 | Q51: =Q16+Q17 -> 0 | ... AF51: =AF16+AF17 -> 0
B52: 3 | C52: 当期还本付息 | D52: =SUM(F52:AF52) -> 140693.88 | E52: 万元 | J52: =SUM(J53:J54) -> 0 | K52: =SUM(K53:K54) -> 0 | L52: =SUM(L53:L54) -> 11480.23 | M52: =SUM(M53:M54) -> 11180.139 | N52: =SUM(N53:N54) -> 10880.048 | O52: =SUM(O53:O54) -> 10579.957 | P52: =SUM(P53:P54) -> 10279.866 | Q52: =SUM(Q53:Q54) -> 9979.7745 | ... AF52: =SUM(AF53:AF54) -> -4.3019099e-13
C53: 其中：还本（等额本金） | D53: =SUM(F53:AF53) -> 104682.95 | E53: 万元 | J53: =IF(J49-参数输入表!$I$217-参数输入表!$I$7<=0,0,IF(J49-参数输入表!$I$217-参数输入表!$I$7<=参数输入表!$I$222,$D$51/参数输入表!$I$222,0)) -> 0 | K53: =IF(K49-参数输入表!$I$217-参数输入表!$I$7<=0,0,IF(K49-参数输入表!$I$217-参数输入表!$I$7<=参数输入表!$I$222,$D$51/参数输入表!$I$222,0)) -> 0 | L53: =IF(L49-参数输入表!$I$217-参数输入表!$I$7<=0,0,IF(L49-参数输入表!$I$217-参数输入表!$I$7<=参数输入表!$I$222,$D$51/参数输入表!$I$222,0)) -> 6978.8633 | M53: =IF(M49-参数输入表!$I$217-参数输入表!$I$7<=0,0,IF(M49-参数输入表!$I$217-参数输入表!$I$7<=参数输入表!$I$222,$D$51/参数输入表!$I$222,0)) -> 6978.8633 | N53: =IF(N49-参数输入表!$I$217-参数输入表!$I$7<=0,0,IF(N49-参数输入表!$I$217-参数输入表!$I$7<=参数输入表!$I$222,$D$51/参数输入表!$I$222,0)) -> 6978.8633 | O53: =IF(O49-参数输入表!$I$217-参数输入表!$I$7<=0,0,IF(O49-参数输入表!$I$217-参数输入表!$I$7<=参数输入表!$I$222,$D$51/参数输入表!$I$222,0)) -> 6978.8633 | P53: =IF(P49-参数输入表!$I$217-参数输入表!$I$7<=0,0,IF(P49-参数输入表!$I$217-参数输入表!$I$7<=参数输入表!$I$222,$D$51/参数输入表!$I$222,0)) -> 6978.8633 | Q53: =IF(Q49-参数输入表!$I$217-参数输入表!$I$7<=0,0,IF(Q49-参数输入表!$I$217-参数输入表!$I$7<=参数输入表!$I$222,$D$51/参数输入表!$I$222,0)) -> 6978.8633 | ... AF53: =IF(AF49-参数输入表!$I$217-参数输入表!$I$7<=0,0,IF(AF49-参数输入表!$I$217-参数输入表!$I$7<=参数输入表!$I$222,$D$51/参数输入表!$I$222,0)) -> 0
C54: 付息 | D54: =SUM(F54:AF54) -> 36010.934 | E54: 万元 | J54: =IF(J49-参数输入表!$I$217-参数输入表!$I$7<=0,0,(J50+J51/2)*参数输入表!$I$219*(12-MONTH(参数输入表!I8))/12) -> 0 | K54: =IF(K49-参数输入表!$I$217-参数输入表!$I$7<=0,0,(K50+K51/2)*参数输入表!$I$219) -> 0 | L54: =IF(L49-参数输入表!$I$217-参数输入表!$I$7<=0,0,(L50+L51/2)*参数输入表!$I$219) -> 4501.3668 | M54: =IF(M49-参数输入表!$I$217-参数输入表!$I$7<=0,0,(M50+M51/2)*参数输入表!$I$219) -> 4201.2757 | N54: =IF(N49-参数输入表!$I$217-参数输入表!$I$7<=0,0,(N50+N51/2)*参数输入表!$I$219) -> 3901.1846 | O54: =IF(O49-参数输入表!$I$217-参数输入表!$I$7<=0,0,(O50+O51/2)*参数输入表!$I$219) -> 3601.0934 | P54: =IF(P49-参数输入表!$I$217-参数输入表!$I$7<=0,0,(P50+P51/2)*参数输入表!$I$219) -> 3301.0023 | Q54: =IF(Q49-参数输入表!$I$217-参数输入表!$I$7<=0,0,(Q50+Q51/2)*参数输入表!$I$219) -> 3000.9112 | R54: =IF(R49-参数输入表!$I$217-参数输入表!$I$7<=0,0,(R50+R51/2)*参数输入表!$I$219) -> 2700.8201 | ... AE54: =IF(AE49-参数输入表!$I$217-参数输入表!$I$7<=0,0,(AE50+AE51/2)*参数输入表!$I$219) -> -1.720764e-12 | AF54: =IF(AF49-参数输入表!$I$217-参数输入表!$I$7<=0,0,(AF50+AF51/2)*参数输入表!$I$219*MONTH(参数输入表!$I$6)/12) -> -4.3019099e-13
B55: 4 | C55: 期末借款余额 | D55: =AF55 -> -4.0017767e-11 | E55: 万元 | J55: =J50+J51-J53 -> 31488.843 | K55: =K50+K51-K53 -> 104682.95 | L55: =L50+L51-L53 -> 97704.086 | M55: =M50+M51-M53 -> 90725.222 | N55: =N50+N51-N53 -> 83746.359 | O55: =O50+O51-O53 -> 76767.496 | P55: =P50+P51-P53 -> 69788.633 | Q55: =Q50+Q51-Q53 -> 62809.769 | ... AF55: =AF50+AF51-AF53 -> -4.0017767e-11
B57: 借款还本付息表（新建及改扩建项目流动资金借款）
B58: 序号 | C58: 项目 | D58: 合计 | E58: 单位 | F58: 2020年 | G58: 2021年 | H58: 2022年 | I58: 45107 | J58: 45261 | K58: 2024年 | L58: 2025年 | M58: 2026年 | N58: 2027年 | O58: 2028年 | P58: 2029年 | Q58: 2030年 | R58: 2031年 | S58: 2032年 | T58: 2033年 | U58: 2034年 | V58: 2035年 | W58: 2036年 | X58: 2037年 | Y58: 2038年 | Z58: 2039年 | AA58: 2040年 | AB58: 2041年 | AC58: 2042年 | AD58: 2043年 | AE58: 2044年 | AF58: 53051
F59: 1 | G59: 2 | H59: 3 | I59: 4 | J59: 5 | K59: 6 | L59: 7 | M59: 8 | N59: 9 | O59: 10 | P59: 11 | Q59: 12 | R59: 13 | S59: 14 | T59: 15 | U59: 16 | V59: 17 | W59: 18 | X59: 19 | Y59: 20 | Z59: 21 | AA59: 22 | AB59: 23 | AC59: 24 | AD59: 25 | AE59: 26 | AF59: 27
B60: 1 | C60: 期初借款累计 | E60: 万元 | J60: 0 | K60: =J65 -> 0 | L60: =K65 -> 0 | M60: =L65 -> 0 | N60: =M65 -> 0 | O60: =N65 -> 0 | P60: =O65 -> 0 | Q60: =P65 -> 0 | R60: =Q65 -> 0 | ... AF60: =AE65 -> 0
B61: 2 | C61: 当期借款 | D61: =SUM(F61:AF61) -> 11760 | E61: 万元 | J61: =IF(J59-参数输入表!$I$21<0,0,$L$19) -> 0 | K61: =IF(K59-参数输入表!$I$21<0,0,$L$19) -> 0 | L61: =IF(L59-参数输入表!$I$21<0,0,$L$19) -> 560 | M61: =IF(M59-参数输入表!$I$21<0,0,$L$19) -> 560 | N61: =IF(N59-参数输入表!$I$21<0,0,$L$19) -> 560 | O61: =IF(O59-参数输入表!$I$21<0,0,$L$19) -> 560 | P61: =IF(P59-参数输入表!$I$21<0,0,$L$19) -> 560 | Q61: =IF(Q59-参数输入表!$I$21<0,0,$L$19) -> 560 | ... AF61: =IF(AF59-参数输入表!$I$21<0,0,$L$19) -> 560
B62: 3 | C62: 当期还本付息 | D62: =SUM(F62:AF62) -> 12173.91 | E62: 万元 | J62: =SUM(J63:J64) -> 0 | K62: =SUM(K63:K64) -> 0 | L62: =SUM(L63:L64) -> 580.44 | M62: =SUM(M63:M64) -> 580.44 | N62: =SUM(N63:N64) -> 580.44 | O62: =SUM(O63:O64) -> 580.44 | P62: =SUM(P63:P64) -> 580.44 | Q62: =SUM(Q63:Q64) -> 580.44 | ... AF62: =SUM(AF63:AF64) -> 565.11
C63: 其中：还本 | D63: =SUM(F63:AF63) -> 11760 | E63: 万元 | J63: =J61 -> 0 | K63: =K61 -> 0 | L63: =L61 -> 560 | M63: =M61 -> 560 | N63: =N61 -> 560 | O63: =O61 -> 560 | P63: =P61 -> 560 | Q63: =Q61 -> 560 | ... AF63: =AF61 -> 560
C64: 付息 | D64: =SUM(F64:AF64) -> 413.91 | E64: 万元 | J64: =(J60+J61)*参数输入表!$I$220*(12-MONTH(参数输入表!I8))/12 -> 0 | K64: =(K60+K61)*参数输入表!$I$220 -> 0 | L64: =(L60+L61)*参数输入表!$I$220 -> 20.44 | M64: =(M60+M61)*参数输入表!$I$220 -> 20.44 | N64: =(N60+N61)*参数输入表!$I$220 -> 20.44 | O64: =(O60+O61)*参数输入表!$I$220 -> 20.44 | P64: =(P60+P61)*参数输入表!$I$220 -> 20.44 | Q64: =(Q60+Q61)*参数输入表!$I$220 -> 20.44 | R64: =(R60+R61)*参数输入表!$I$220 -> 20.44 | ... AE64: =(AE60+AE61)*参数输入表!$I$220 -> 20.44 | AF64: =(AF60+AF61)*参数输入表!$I$220*MONTH(参数输入表!$I$6)/12 -> 5.11
B65: 4 | C65: 期末借款余额 | D65: =AF65 -> 0 | E65: 万元 | J65: =J60+J61-J63 -> 0 | K65: =K60+K61-K63 -> 0 | L65: =L60+L61-L63 -> 0 | M65: =M60+M61-M63 -> 0 | N65: =N60+N61-N63 -> 0 | O65: =O60+O61-O63 -> 0 | P65: =P60+P61-P63 -> 0 | Q65: =Q60+Q61-Q63 -> 0 | ... AF65: =AF60+AF61-AF63 -> 0
B67: 借款还本付息表（基准日长期借款）
B68: 序号 | C68: 项目 | D68: 合计 | E68: 单位 | F68: 2020年 | G68: 2021年 | H68: 2022年 | I68: 45107 | J68: 45261 | K68: 2024年 | L68: 2025年 | M68: 2026年 | N68: 2027年 | O68: 2028年 | P68: 2029年 | Q68: 2030年 | R68: 2031年 | S68: 2032年 | T68: 2033年 | U68: 2034年 | V68: 2035年 | W68: 2036年 | X68: 2037年 | Y68: 2038年 | Z68: 2039年 | AA68: 2040年 | AB68: 2041年 | AC68: 2042年 | AD68: 2043年 | AE68: 2044年 | AF68: 53051
F69: 1 | G69: 2 | H69: 3 | I69: 4 | J69: 5 | K69: 6 | L69: 7 | M69: 8 | N69: 9 | O69: 10 | P69: 11 | Q69: 12 | R69: 13 | S69: 14 | T69: 15 | U69: 16 | V69: 17 | W69: 18 | X69: 19 | Y69: 20 | Z69: 21 | AA69: 22 | AB69: 23 | AC69: 24 | AD69: 25 | AE69: 26 | AF69: 27
B70: 1 | C70: 期初借款累计 | E70: 万元 | J70: =I75 -> 27335.071 | K70: =J75 -> 26000 | L70: =K75 -> 23400 | M70: =L75 -> 20800 | N70: =M75 -> 18200 | O70: =N75 -> 15600 | P70: =O75 -> 13000 | Q70: =P75 -> 10400 | ... AF70: =AE75 -> 0
B71: 2 | C71: 当期借款 | D71: =SUM(F71:AF71) -> 0 | E71: 万元 | J71: =参数输入表!$I$163 -> 0 | K71: =参数输入表!$I$164 -> 0 | L71: =参数输入表!$I$165 -> 0 | M71: =参数输入表!$I$166 -> 0 | N71: =参数输入表!$I$167 -> 0 | O71: =参数输入表!$I$168 -> 0 | P71: =参数输入表!$I$169 -> 0 | Q71: =参数输入表!$I$170 -> 0 | R71: =参数输入表!$I$171 -> 0 | S71: =参数输入表!$I$172 -> 0 | T71: =参数输入表!$I$173 -> 0 | U71: =参数输入表!$I$174 -> 0 | V71: =参数输入表!$I$175 -> 0 | W71: =参数输入表!$I$176 -> 0 | X71: =参数输入表!$I$177 -> 0 | Y71: =参数输入表!$I$178 -> 0 | Z71: =参数输入表!$I$179 -> 0 | AA71: =参数输入表!$I$180 -> 0 | AB71: =参数输入表!$I$181 -> 0 | AC71: =参数输入表!$I$182 -> 0 | AD71: =参数输入表!$I$183 -> 0 | AE71: =参数输入表!$I$184 -> 0 | AF71: =参数输入表!$I$185 -> 0
B72: 3 | C72: 当期还本付息 | D72: =SUM(F72:AF72) -> 32035.097 | E72: 万元 | J72: =SUM(J73:J74) -> 1745.0973 | K72: =SUM(K73:K74) -> 3380 | L72: =SUM(L73:L74) -> 3302 | M72: =SUM(M73:M74) -> 3224 | N72: =SUM(N73:N74) -> 3146 | O72: =SUM(O73:O74) -> 3068 | P72: =SUM(P73:P74) -> 2990 | Q72: =SUM(Q73:Q74) -> 2912 | ... AF72: =SUM(AF73:AF74) -> 0
C73: 其中：还本 | D73: =SUM(F73:AF73) -> 27335.071 | E73: 万元 | J73: =参数输入表!$I$191 -> 1335.0712 | K73: =参数输入表!$I$192 -> 2600 | L73: =参数输入表!$I$193 -> 2600 | M73: =参数输入表!$I$194 -> 2600 | N73: =参数输入表!$I$195 -> 2600 | O73: =参数输入表!$I$196 -> 2600 | P73: =参数输入表!$I$197 -> 2600 | Q73: =参数输入表!$I$198 -> 2600 | R73: =参数输入表!$I$199 -> 2600 | S73: =参数输入表!$I$200 -> 2600 | T73: =参数输入表!$I$201 -> 2600 | U73: =参数输入表!$I$202 -> 0 | V73: =参数输入表!$I$203 -> 0 | W73: =参数输入表!$I$204 -> 0 | X73: =参数输入表!$I$205 -> 0 | Y73: =参数输入表!$I$206 -> 0 | Z73: =参数输入表!$I$207 -> 0 | AA73: =参数输入表!$I$208 -> 0 | AB73: =参数输入表!$I$209 -> 0 | AC73: =参数输入表!$I$210 -> 0 | AD73: =参数输入表!$I$211 -> 0 | AE73: =参数输入表!$I$212 -> 0 | AF73: =参数输入表!$I$213 -> 0
C74: 付息 | D74: =SUM(F74:AF74) -> 4700.0261 | E74: 万元 | J74: =(J70+J71/2)*参数输入表!$I$156*(12-MONTH(参数输入表!I8))/12 -> 410.02607 | K74: =(K70+K71/2)*参数输入表!$I$156 -> 780 | L74: =(L70+L71/2)*参数输入表!$I$156 -> 702 | M74: =(M70+M71/2)*参数输入表!$I$156 -> 624 | N74: =(N70+N71/2)*参数输入表!$I$156 -> 546 | O74: =(O70+O71/2)*参数输入表!$I$156 -> 468 | P74: =(P70+P71/2)*参数输入表!$I$156 -> 390 | Q74: =(Q70+Q71/2)*参数输入表!$I$156 -> 312 | R74: =(R70+R71/2)*参数输入表!$I$156 -> 234 | ... AE74: =(AE70+AE71/2)*参数输入表!$I$156 -> 0 | AF74: =(AF70+AF71/2)*参数输入表!$I$156*MONTH(参数输入表!$I$6)/12 -> 0
B75: 4 | C75: 期末借款余额 | D75: =AF75 -> 0 | E75: 万元 | I75: ='表10-资产负债表(标准格式)'!H84+'表10-资产负债表(标准格式)'!H88 -> 27335.071 | J75: =J70+J71-J73 -> 26000 | K75: =K70+K71-K73 -> 23400 | L75: =L70+L71-L73 -> 20800 | M75: =M70+M71-M73 -> 18200 | N75: =N70+N71-N73 -> 15600 | O75: =O70+O71-O73 -> 13000 | P75: =P70+P71-P73 -> 10400 | Q75: =Q70+Q71-Q73 -> 7800 | ... AF75: =AF70+AF71-AF73 -> 0
B77: 借款还本付息表（短期借款）
B78: 序号 | C78: 项目 | D78: 合计 | E78: 单位 | F78: 2020年 | G78: 2021年 | H78: 2022年 | I78: 45107 | J78: 45261 | K78: 2024年 | L78: 2025年 | M78: 2026年 | N78: 2027年 | O78: 2028年 | P78: 2029年 | Q78: 2030年 | R78: 2031年 | S78: 2032年 | T78: 2033年 | U78: 2034年 | V78: 2035年 | W78: 2036年 | X78: 2037年 | Y78: 2038年 | Z78: 2039年 | AA78: 2040年 | AB78: 2041年 | AC78: 2042年 | AD78: 2043年 | AE78: 2044年 | AF78: 53051
F79: 1 | G79: 2 | H79: 3 | I79: 4 | J79: 5 | K79: 6 | L79: 7 | M79: 8 | N79: 9 | O79: 10 | P79: 11 | Q79: 12 | R79: 13 | S79: 14 | T79: 15 | U79: 16 | V79: 17 | W79: 18 | X79: 19 | Y79: 20 | Z79: 21 | AA79: 22 | AB79: 23 | AC79: 24 | AD79: 25 | AE79: 26 | AF79: 27
B80: 1 | C80: 期初借款累计 | E80: 万元 | J80: =I85 -> 11109.158 | K80: =J85 -> 11609.158 | L80: =K85 -> 11609.158 | M80: =L85 -> 11609.158 | N80: =M85 -> 11109.158 | O80: =N85 -> 11109.158 | P80: =O85 -> 11109.158 | Q80: =P85 -> 11109.158 | ... AF80: =AE85 -> 0
B81: 2 | C81: 当期借款 | D81: =SUM(F81:AF81) -> 1500 | E81: 万元 | J81: =参数输入表!$I$236 -> 500 | K81: =参数输入表!$I$237 -> 500 | L81: =参数输入表!$I$238 -> 500 | M81: =参数输入表!$I$239 -> 0 | N81: =参数输入表!$I$240 -> 0 | O81: =参数输入表!$I$241 -> 0 | P81: =参数输入表!$I$242 -> 0 | Q81: =参数输入表!$I$243 -> 0 | R81: =参数输入表!$I$244 -> 0 | S81: =参数输入表!$I$245 -> 0 | T81: =参数输入表!$I$246 -> 0 | U81: =参数输入表!$I$247 -> 0 | V81: =参数输入表!$I$248 -> 0 | W81: =参数输入表!$I$249 -> 0 | X81: =参数输入表!$I$250 -> 0 | Y81: =参数输入表!$I$251 -> 0 | Z81: =参数输入表!$I$252 -> 0 | AA81: =参数输入表!$I$253 -> 0 | AB81: =参数输入表!$I$254 -> 0 | AC81: =参数输入表!$I$255 -> 0 | AD81: =参数输入表!$I$256 -> 0 | AE81: =参数输入表!$I$257 -> 0 | AF81: =参数输入表!$I$258 -> 0
B82: 3 | C82: 当期还本付息 | D82: =SUM(F82:AF82) -> 20210.992 | E82: 万元 | J82: =SUM(J83:J84) -> 211.86713 | K82: =SUM(K83:K84) -> 941.98426 | L82: =SUM(L83:L84) -> 941.98426 | M82: =SUM(M83:M84) -> 923.73426 | N82: =SUM(N83:N84) -> 405.48426 | O82: =SUM(O83:O84) -> 405.48426 | P82: =SUM(P83:P84) -> 405.48426 | Q82: =SUM(Q83:Q84) -> 405.48426 | ... AF82: =SUM(AF83:AF84) -> 0
C83: 其中：还本 | D83: =SUM(F83:AF83) -> 12609.158 | E83: 万元 | J83: =参数输入表!$I$264 -> 0 | K83: =参数输入表!$I$265 -> 500 | L83: =参数输入表!$I$266 -> 500 | M83: =参数输入表!$I$267 -> 500 | N83: =参数输入表!$I$268 -> 0 | O83: =参数输入表!$I$269 -> 0 | P83: =参数输入表!$I$270 -> 0 | Q83: =参数输入表!$I$271 -> 0 | R83: =参数输入表!$I$272 -> 0 | S83: =参数输入表!$I$273 -> 0 | T83: =参数输入表!$I$274 -> 0 | U83: =参数输入表!$I$275 -> 0 | V83: =参数输入表!$I$276 -> 0 | W83: =参数输入表!$I$277 -> 0 | X83: =参数输入表!$I$278 -> 0 | Y83: =参数输入表!$I$279 -> 0 | Z83: =参数输入表!$I$280 -> 0 | AA83: =参数输入表!$I$281 -> 0 | AB83: =参数输入表!$I$282 -> 11109.158 | AC83: =参数输入表!$I$283 -> 0 | AD83: =参数输入表!$I$284 -> 0 | AE83: =参数输入表!$I$285 -> 0 | AF83: =参数输入表!$I$286 -> 0
C84: 付息 | D84: =SUM(F84:AF84) -> 7601.8339 | E84: 万元 | J84: =(J80+J81)*参数输入表!$I$220*(12-MONTH(参数输入表!I8))/12 -> 211.86713 | K84: =(K80+K81)*参数输入表!$I$220 -> 441.98426 | L84: =(L80+L81)*参数输入表!$I$220 -> 441.98426 | M84: =(M80+M81)*参数输入表!$I$220 -> 423.73426 | N84: =(N80+N81)*参数输入表!$I$220 -> 405.48426 | O84: =(O80+O81)*参数输入表!$I$220 -> 405.48426 | P84: =(P80+P81)*参数输入表!$I$220 -> 405.48426 | Q84: =(Q80+Q81)*参数输入表!$I$220 -> 405.48426 | R84: =(R80+R81)*参数输入表!$I$220 -> 405.48426 | ... AE84: =(AE80+AE81)*参数输入表!$I$220 -> 0 | AF84: =(AF80+AF81)*参数输入表!$I$220*MONTH(参数输入表!$I$6)/12 -> 0
B85: 4 | C85: 期末借款余额 | D85: =AF85 -> 0 | E85: 万元 | I85: ='表10-资产负债表(标准格式)'!H59 -> 11109.158 | J85: =J80+J81-J83 -> 11609.158 | K85: =K80+K81-K83 -> 11609.158 | L85: =L80+L81-L83 -> 11609.158 | M85: =M80+M81-M83 -> 11109.158 | N85: =N80+N81-N83 -> 11109.158 | O85: =O80+O81-O83 -> 11109.158 | P85: =P80+P81-P83 -> 11109.158 | Q85: =Q80+Q81-Q83 -> 11109.158 | ... AF85: =AF80+AF81-AF83 -> 0
B87: 借款还本付息表（汇总—等额本息）
B88: 序号 | C88: 项目 | D88: 合计 | E88: 单位 | F88: 2020年 | G88: 2021年 | H88: 2022年 | I88: 45107 | J88: 45261 | K88: 2024年 | L88: 2025年 | M88: 2026年 | N88: 2027年 | O88: 2028年 | P88: 2029年 | Q88: 2030年 | R88: 2031年 | S88: 2032年 | T88: 2033年 | U88: 2034年 | V88: 2035年 | W88: 2036年 | X88: 2037年 | Y88: 2038年 | Z88: 2039年 | AA88: 2040年 | AB88: 2041年 | AC88: 2042年 | AD88: 2043年 | AE88: 2044年 | AF88: 53051
F89: 1 | G89: 2 | H89: 3 | I89: 4 | J89: 5 | K89: 6 | L89: 7 | M89: 8 | N89: 9 | O89: 10 | P89: 11 | Q89: 12 | R89: 13 | S89: 14 | T89: 15 | U89: 16 | V89: 17 | W89: 18 | X89: 19 | Y89: 20 | Z89: 21 | AA89: 22 | AB89: 23 | AC89: 24 | AD89: 25 | AE89: 26 | AF89: 27
B90: 1 | C90: 期初借款累计 | E90: 万元 | J90: =J40+J60+J80+J70 -> 38444.229 | K90: =K40+K60+K80+K70 -> 69098.001 | L90: =L40+L60+L80+L70 -> 139692.11 | M90: =M40+M60+M80+M70 -> 131979.6 | N90: =N40+N60+N80+N70 -> 123547.26 | O90: =O40+O60+O80+O70 -> 115385.63 | P90: =P40+P60+P80+P70 -> 106984.85 | Q90: =Q40+Q60+Q80+Q70 -> 98334.631 | ... AF90: =AF40+AF60+AF80+AF70 -> -1.7961463e-11
B91: 2 | C91: 当期借款 | D91: =SUM(F91:AF91) -> 117942.95 | E91: 万元 | J91: =J41+J61+J81+J71 -> 31988.843 | K91: =K41+K61+K81+K71 -> 73694.106 | L91: =L41+L61+L81+L71 -> 1060 | M91: =M41+M61+M81+M71 -> 560 | N91: =N41+N61+N81+N71 -> 560 | O91: =O41+O61+O81+O71 -> 560 | P91: =P41+P61+P81+P71 -> 560 | Q91: =Q41+Q61+Q81+Q71 -> 560 | ... AF91: =AF41+AF61+AF81+AF71 -> 560
B92: 3 | C92: 当期还本付息 | D92: =SUM(F92:AF92) -> 211307.65 | E92: 万元 | J92: =J42+J62+J82+J72 -> 2007.2804 | K92: =K42+K62+K82+K72 -> 6951.2555 | L92: =L42+L62+L82+L72 -> 14438.295 | M92: =M42+M62+M82+M72 -> 14342.045 | N92: =N42+N62+N82+N72 -> 13745.795 | O92: =O42+O62+O82+O72 -> 13667.795 | P92: =P42+P62+P82+P72 -> 13589.795 | Q92: =Q42+Q62+Q82+Q72 -> 13511.795 | ... AF92: =AF42+AF62+AF82+AF72 -> 565.11
C93: 其中：还本 | D93: =SUM(F93:AF93) -> 156387.18 | E93: 万元 | J93: =J43+J63+J83+J73 -> 1335.0712 | K93: =K43+K63+K83+K73 -> 3100 | L93: =L43+L63+L83+L73 -> 8772.5039 | M93: =M43+M63+M83+M73 -> 8992.3415 | N93: =N43+N63+N83+N73 -> 8721.6322 | O93: =O43+O63+O83+O73 -> 8960.7824 | P93: =P43+P63+P83+P73 -> 9210.216 | Q93: =Q43+Q63+Q83+Q73 -> 9470.3753 | ... AF93: =AF43+AF63+AF83+AF73 -> 560
C94: 付息 | D94: =SUM(F94:AF94) -> 54920.468 | E94: 万元 | J94: =J44+J64+J84+J74 -> 672.2092 | K94: =K44+K64+K84+K74 -> 3851.2555 | L94: =L44+L64+L84+L74 -> 5665.7911 | M94: =M44+M64+M84+M74 -> 5349.7034 | N94: =N44+N64+N84+N74 -> 5024.1627 | O94: =O44+O64+O84+O74 -> 4707.0125 | P94: =P44+P64+P84+P74 -> 4379.5789 | Q94: =Q44+Q64+Q84+Q74 -> 4041.4196 | ... AF94: =AF44+AF64+AF84+AF74 -> 5.11
B95: 4 | C95: 期末借款余额 | D95: =AF95 -> -1.8154548e-11 | E95: 万元 | I95: =I45+I65+I85+I75 -> 38444.229 | J95: =J45+J65+J85+J75 -> 69098.001 | K95: =K45+K65+K85+K75 -> 139692.11 | L95: =L45+L65+L85+L75 -> 131979.6 | M95: =M45+M65+M85+M75 -> 123547.26 | N95: =N45+N65+N85+N75 -> 115385.63 | O95: =O45+O65+O85+O75 -> 106984.85 | P95: =P45+P65+P85+P75 -> 98334.631 | ... AF95: =AF45+AF65+AF85+AF75 -> -1.8154548e-11
B97: 借款还本付息表（汇总—等额本金）
B98: 序号 | C98: 项目 | D98: 合计 | E98: 单位 | F98: 2020年 | G98: 2021年 | H98: 2022年 | I98: 45107 | J98: 45261 | K98: 2024年 | L98: 2025年 | M98: 2026年 | N98: 2027年 | O98: 2028年 | P98: 2029年 | Q98: 2030年 | R98: 2031年 | S98: 2032年 | T98: 2033年 | U98: 2034年 | V98: 2035年 | W98: 2036年 | X98: 2037年 | Y98: 2038年 | Z98: 2039年 | AA98: 2040年 | AB98: 2041年 | AC98: 2042年 | AD98: 2043年 | AE98: 2044年 | AF98: 53051
F99: 1 | G99: 2 | H99: 3 | I99: 4 | J99: 5 | K99: 6 | L99: 7 | M99: 8 | N99: 9 | O99: 10 | P99: 11 | Q99: 12 | R99: 13 | S99: 14 | T99: 15 | U99: 16 | V99: 17 | W99: 18 | X99: 19 | Y99: 20 | Z99: 21 | AA99: 22 | AB99: 23 | AC99: 24 | AD99: 25 | AE99: 26 | AF99: 27
B100: 1 | C100: 期初借款累计 | E100: 万元 | J100: =J50+J60+J80+J70 -> 38444.229 | K100: =K50+K60+K80+K70 -> 69098.001 | L100: =L50+L60+L80+L70 -> 139692.11 | M100: =M50+M60+M80+M70 -> 130113.24 | N100: =N50+N60+N80+N70 -> 120034.38 | O100: =O50+O60+O80+O70 -> 110455.52 | P100: =P50+P60+P80+P70 -> 100876.65 | Q100: =Q50+Q60+Q80+Q70 -> 91297.791 | ... AF100: =AF50+AF60+AF80+AF70 -> -4.0017767e-11
B101: 2 | C101: 当期借款 | D101: =SUM(F101:AF101) -> 117942.95 | E101: 万元 | J101: =J51+J61+J81+J71 -> 31988.843 | K101: =K51+K61+K81+K71 -> 73694.106 | L101: =L51+L61+L81+L71 -> 1060 | M101: =M51+M61+M81+M71 -> 560 | N101: =N51+N61+N81+N71 -> 560 | O101: =O51+O61+O81+O71 -> 560 | P101: =P51+P61+P81+P71 -> 560 | Q101: =Q51+Q61+Q81+Q71 -> 560 | ... AF101: =AF51+AF61+AF81+AF71 -> 560
B102: 3 | C102: 当期还本付息 | D102: =SUM(F102:AF102) -> 205113.88 | E102: 万元 | J102: =J52+J62+J82+J72 -> 1956.9645 | K102: =K52+K62+K82+K72 -> 4321.9843 | L102: =L52+L62+L82+L72 -> 16304.654 | M102: =M52+M62+M82+M72 -> 15908.313 | N102: =N52+N62+N82+N72 -> 15011.972 | O102: =O52+O62+O82+O72 -> 14633.881 | P102: =P52+P62+P82+P72 -> 14255.79 | Q102: =Q52+Q62+Q82+Q72 -> 13877.699 | ... AF102: =AF52+AF62+AF82+AF72 -> 565.11
C103: 其中：还本 | D103: =SUM(F103:AF103) -> 156387.18 | E103: 万元 | J103: =J53+J63+J83+J73 -> 1335.0712 | K103: =K53+K63+K83+K73 -> 3100 | L103: =L53+L63+L83+L73 -> 10638.863 | M103: =M53+M63+M83+M73 -> 10638.863 | N103: =N53+N63+N83+N73 -> 10138.863 | O103: =O53+O63+O83+O73 -> 10138.863 | P103: =P53+P63+P83+P73 -> 10138.863 | Q103: =Q53+Q63+Q83+Q73 -> 10138.863 | ... AF103: =AF53+AF63+AF83+AF73 -> 560
C104: 付息 | D104: =SUM(F104:AF104) -> 48726.704 | E104: 万元 | J104: =J54+J64+J84+J74 -> 621.8932 | K104: =K54+K64+K84+K74 -> 1221.9843 | L104: =L54+L64+L84+L74 -> 5665.7911 | M104: =M54+M64+M84+M74 -> 5269.4499 | N104: =N54+N64+N84+N74 -> 4873.1088 | O104: =O54+O64+O84+O74 -> 4495.0177 | P104: =P54+P64+P84+P74 -> 4116.9266 | Q104: =Q54+Q64+Q84+Q74 -> 3738.8355 | ... AF104: =AF54+AF64+AF84+AF74 -> 5.11
B105: 4 | C105: 期末借款余额 | D105: =AF105 -> -4.0017767e-11 | E105: 万元 | I105: =I55+I65+I85+I75 -> 38444.229 | J105: =J55+J65+J85+J75 -> 69098.001 | K105: =K55+K65+K85+K75 -> 139692.11 | L105: =L55+L65+L85+L75 -> 130113.24 | M105: =M55+M65+M85+M75 -> 120034.38 | N105: =N55+N65+N85+N75 -> 110455.52 | O105: =O55+O65+O85+O75 -> 100876.65 | P105: =P55+P65+P85+P75 -> 91297.791 | ... AF105: =AF55+AF65+AF85+AF75 -> -4.0017767e-11
C108: 当期借款引用“资金筹措表”对应年份债务资金数据
C109: 等额本金/等额本息/其他，作为参数输入表—投融资相关板块中的可选择情形，匹配如下不同的计算方法
C110: （1）等额本息情形下，还本付息采用年金公式先得出每年的 本金+利息 之和（固定值），再结合各年度期初及当期借款金额计算出各年度应付利息，进而推算出每年偿还的本金。
C111: （2）等额本金情形下，每年的本金偿还为固定值（建设期借款总额/还款年限），再结合各年度期初及当期借款金额计算出各年度应付利息。
...

Sheet 表2-折旧摊销表
C1: 中间过程引用（隐藏）
C2: 动态总投资（自主投资_不含流动资金） | D2: =参数输入表!I148 -> 139577.27
C3: 可抵扣进项税 | D3: =参数输入表!I152 -> 14222.844
C4: 固定资产原值 | D4: =D2-D15-D3 -> 123554.42 | F4: 固定资产原值=项目动态总投资（自主投资_不含流动资金）-可抵扣进项税-无形资产原值=项目静态总投资-建设补贴+建设期利息-可抵扣进项税-无形资产原值
C5: 折旧方式 | D5: 直线法/其他 | F5: 无形资产及固定资产均包含在动态总投资中
C6: 折旧年限 | D6: =参数输入表!I438 -> 18
C7: 残值率 | D7: =参数输入表!I439 -> 0
C8: 长期待摊费用（第1年） | D8: =参数输入表!I461/(1+参数输入表!I488) -> 0 | F8: 长期待摊费用=计入长期待摊的成本项/（1+增值税税率）
C9: 长期待摊费用（第6年） | D9: =参数输入表!I466/(1+参数输入表!I488) -> 458.7156
C10: 长期待摊费用（第11年） | D10: =参数输入表!I471/(1+参数输入表!I488) -> 458.7156
C11: 长期待摊费用（第16年） | D11: =参数输入表!I476/(1+参数输入表!I488) -> 458.7156
C12: 长期待摊费用（第21年） | D12: =参数输入表!I481/(1+参数输入表!I488) -> 458.7156
C13: 摊销方式 | D13: 直线法/其他
C14: 摊销年限 | D14: =参数输入表!I487 -> 5
C15: 无形资产原值 | D15: =参数输入表!I441 -> 1800
C16: 摊销方式 | D16: 直线法/其他
C17: 摊销年限 | D17: =参数输入表!I443 -> 18
C18: 残值率 | D18: =参数输入表!I444 -> 0
C19: 大修及更新重置资产原值 | D19: =参数输入表!I507/(1+参数输入表!$I$525) -> 0
C20: 摊销方式 | D20: 直线法/其他
C21: 摊销年限 | D21: =参数输入表!I524 -> 10
B23: 折旧摊销表-资本金（新增部分）
B24: 序号 | C24: 科目 | D24: 合计 | E24: 单位 | F24: 2020年 | G24: 2021年 | H24: 2022年 | I24: 45107 | J24: 45261 | K24: 2024年 | L24: 2025年 | M24: 2026年 | N24: 2027年 | O24: 2028年 | P24: 2029年 | Q24: 2030年 | R24: 2031年 | S24: 2032年 | T24: 2033年 | U24: 2034年 | V24: 2035年 | W24: 2036年 | X24: 2037年 | Y24: 2038年 | Z24: 2039年 | AA24: 2040年 | AB24: 2041年 | AC24: 2042年 | AD24: 2043年 | AE24: 2044年 | AF24: 53051
F25: 1 | G25: 2 | H25: 3 | I25: 4 | J25: 5 | K25: 6 | L25: 7 | M25: 8 | N25: 9 | O25: 10 | P25: 11 | Q25: 12 | R25: 13 | S25: 14 | T25: 15 | U25: 16 | V25: 17 | W25: 18 | X25: 19 | Y25: 20 | Z25: 21 | AA25: 22 | AB25: 23 | AC25: 24 | AD25: 25 | AE25: 26 | AF25: 27
C26: 期末投产比例 | E26: % | J26: =参数输入表!$I$35 -> 0.15 | K26: =参数输入表!$I$36+J26 -> 0.9 | L26: =IF(L25-参数输入表!$I$7-参数输入表!$I$14>0,100%) -> 1 | M26: =IF(M25-参数输入表!$I$7-参数输入表!$I$14>0,100%) -> 1 | N26: =IF(N25-参数输入表!$I$7-参数输入表!$I$14>0,100%) -> 1 | O26: =IF(O25-参数输入表!$I$7-参数输入表!$I$14>0,100%) -> 1 | P26: =IF(P25-参数输入表!$I$7-参数输入表!$I$14>0,100%) -> 1 | Q26: =IF(Q25-参数输入表!$I$7-参数输入表!$I$14>0,100%) -> 1 | R26: =IF(R25-参数输入表!$I$7-参数输入表!$I$14>0,100%) -> 1 | S26: =IF(S25-参数输入表!$I$7-参数输入表!$I$14>0,100%) -> 1 | ... AF26: =IF(AF25-参数输入表!$I$7-参数输入表!$I$14>0,100%) -> 1
B27: 1 | C27: 期末固定资产原值 | E27: 万元 | J27: =IF(J25-参数输入表!$I$14-参数输入表!$I$7<0,(参数输入表!$I$148-参数输入表!$I$152-参数输入表!$I$441+$I$30)*J26,参数输入表!$I$148-参数输入表!$I$152-参数输入表!$I$441+$I$30) -> 18533.163 | K27: =IF(K25-参数输入表!$I$14-参数输入表!$I$7<0,(参数输入表!$I$148-参数输入表!$I$152-参数输入表!$I$441+$I$30)*K26,参数输入表!$I$148-参数输入表!$I$152-参数输入表!$I$441+$I$30) -> 123554.42 | L27: =IF(L25-参数输入表!$I$14-参数输入表!$I$7<0,(参数输入表!$I$148-参数输入表!$I$152-参数输入表!$I$441+$I$30)*L26,参数输入表!$I$148-参数输入表!$I$152-参数输入表!$I$441+$I$30) -> 123554.42 | M27: =IF(M25-参数输入表!$I$14-参数输入表!$I$7<0,(参数输入表!$I$148-参数输入表!$I$152-参数输入表!$I$441+$I$30)*M26,参数输入表!$I$148-参数输入表!$I$152-参数输入表!$I$441+$I$30) -> 123554.42 | N27: =IF(N25-参数输入表!$I$14-参数输入表!$I$7<0,(参数输入表!$I$148-参数输入表!$I$152-参数输入表!$I$441+$I$30)*N26,参数输入表!$I$148-参数输入表!$I$152-参数输入表!$I$441+$I$30) -> 123554.42 | O27: =IF(O25-参数输入表!$I$14-参数输入表!$I$7<0,(参数输入表!$I$148-参数输入表!$I$152-参数输入表!$I$441+$I$30)*O26,参数输入表!$I$148-参数输入表!$I$152-参数输入表!$I$441+$I$30) -> 123554.42 | P27: =IF(P25-参数输入表!$I$14-参数输入表!$I$7<0,(参数输入表!$I$148-参数输入表!$I$152-参数输入表!$I$441+$I$30)*P26,参数输入表!$I$148-参数输入表!$I$152-参数输入表!$I$441+$I$30) -> 123554.42 | Q27: =IF(Q25-参数输入表!$I$14-参数输入表!$I$7<0,(参数输入表!$I$148-参数输入表!$I$152-参数输入表!$I$441+$I$30)*Q26,参数输入表!$I$148-参数输入表!$I$152-参数输入表!$I$441+$I$30) -> 123554.42 | ... AF27: =IF(AF25-参数输入表!$I$14-参数输入表!$I$7<0,(参数输入表!$I$148-参数输入表!$I$152-参数输入表!$I$441+$I$30)*AF26,参数输入表!$I$148-参数输入表!$I$152-参数输入表!$I$441+$I$30) -> 123554.42
C28: 当期新增投资额 | D28: =SUM(F28:AF28) -> 123554.42 | E28: 万元 | J28: ='表1-资金筹措及还本付息表'!J8+'表1-资金筹措及还本付息表'!J9-'新建及改扩建项目投资概算明细 (光伏)'!F26-J69 -> 37178.271 | K28: ='表1-资金筹措及还本付息表'!K8+'表1-资金筹措及还本付息表'!K9-'新建及改扩建项目投资概算明细 (光伏)'!G26-K69 -> 86376.151 | L28: ='表1-资金筹措及还本付息表'!L8+'表1-资金筹措及还本付息表'!L9-'新建及改扩建项目投资概算明细 (光伏)'!H26-L69 -> 0 | M28: ='表1-资金筹措及还本付息表'!M8+'表1-资金筹措及还本付息表'!M9-'新建及改扩建项目投资概算明细 (光伏)'!K26-M69 -> 0 | N28: ='表1-资金筹措及还本付息表'!N8+'表1-资金筹措及还本付息表'!N9-'新建及改扩建项目投资概算明细 (光伏)'!L26-N69 -> 0 | O28: ='表1-资金筹措及还本付息表'!O8+'表1-资金筹措及还本付息表'!O9-'新建及改扩建项目投资概算明细 (光伏)'!M26-O69 -> 0 | P28: ='表1-资金筹措及还本付息表'!P8+'表1-资金筹措及还本付息表'!P9-'新建及改扩建项目投资概算明细 (光伏)'!N26-P69 -> 0 | Q28: ='表1-资金筹措及还本付息表'!Q8+'表1-资金筹措及还本付息表'!Q9-'新建及改扩建项目投资概算明细 (光伏)'!O26-Q69 -> 0 | R28: ='表1-资金筹措及还本付息表'!R8+'表1-资金筹措及还本付息表'!R9-'新建及改扩建项目投资概算明细 (光伏)'!P26-R69 -> 0 | S28: ='表1-资金筹措及还本付息表'!S8+'表1-资金筹措及还本付息表'!S9-'新建及改扩建项目投资概算明细 (光伏)'!Q26-S69 -> 0 | T28: ='表1-资金筹措及还本付息表'!T8+'表1-资金筹措及还本付息表'!T9-'新建及改扩建项目投资概算明细 (光伏)'!R26-T69 -> 0 | ... AF28: ='表1-资金筹措及还本付息表'!AF8+'表1-资金筹措及还本付息表'!AF9-'新建及改扩建项目投资概算明细 (光伏)'!AD26-AF69 -> 0
C29: 新增投资额累计 | E29: 万元 | J29: =I29+J28 -> 37178.271 | K29: =J29+K28 -> 123554.42 | L29: =K29+L28 -> 123554.42 | M29: =L29+M28 -> 123554.42 | N29: =M29+N28 -> 123554.42 | O29: =N29+O28 -> 123554.42 | P29: =O29+P28 -> 123554.42 | Q29: =P29+Q28 -> 123554.42 | ... AF29: =AE29+AF28 -> 123554.42
C30: 期末在建工程 | E30: 万元 | I30: ='表10-资产负债表(标准格式)'!H46 -> 0 | J30: =J29-J27 -> 18645.108 | K30: =K29-K27 -> 0 | L30: =L29-L27 -> 0 | M30: =M29-M27 -> 0 | N30: =N29-N27 -> 0 | O30: =O29-O27 -> 0 | P30: =P29-P27 -> 0 | Q30: =Q29-Q27 -> 0 | ... AF30: =AF29-AF27 -> 0
C31: 当期固定资产折旧 | D31: =SUM(F31:AF31) -> 123554.42 | E31: 万元 | J31: =SUM(J32:J34) -> 1029.6202 | K31: =SUM(K32:K34) -> 6177.7211 | L31: =SUM(L32:L34) -> 6864.1345 | M31: =SUM(M32:M34) -> 6864.1345 | N31: =SUM(N32:N34) -> 6864.1345 | O31: =SUM(O32:O34) -> 6864.1345 | P31: =SUM(P32:P34) -> 6864.1345 | Q31: =SUM(Q32:Q34) -> 6864.1345 | ... AF31: =SUM(AF32:AF34) -> 0
C32: 建设期第1年投产 | D32: =SUM(F32:AF32) -> 18533.163 | E32: 万元 | J32: =(参数输入表!$I$148-参数输入表!$I$152-参数输入表!$I$441+$I$30)*(1-参数输入表!$I$439)*参数输入表!$I$35/参数输入表!$I$438 -> 1029.6202 | K32: =(参数输入表!$I$148-参数输入表!$I$152-参数输入表!$I$441+$I$30)*(1-参数输入表!$I$439)*参数输入表!$I$35/参数输入表!$I$438 -> 1029.6202 | L32: =(参数输入表!$I$148-参数输入表!$I$152-参数输入表!$I$441+$I$30)*(1-参数输入表!$I$439)*参数输入表!$I$35/参数输入表!$I$438 -> 1029.6202 | M32: =(参数输入表!$I$148-参数输入表!$I$152-参数输入表!$I$441+$I$30)*(1-参数输入表!$I$439)*参数输入表!$I$35/参数输入表!$I$438 -> 1029.6202 | N32: =(参数输入表!$I$148-参数输入表!$I$152-参数输入表!$I$441+$I$30)*(1-参数输入表!$I$439)*参数输入表!$I$35/参数输入表!$I$438 -> 1029.6202 | O32: =(参数输入表!$I$148-参数输入表!$I$152-参数输入表!$I$441+$I$30)*(1-参数输入表!$I$439)*参数输入表!$I$35/参数输入表!$I$438 -> 1029.6202 | P32: =(参数输入表!$I$148-参数输入表!$I$152-参数输入表!$I$441+$I$30)*(1-参数输入表!$I$439)*参数输入表!$I$35/参数输入表!$I$438 -> 1029.6202 | Q32: =(参数输入表!$I$148-参数输入表!$I$152-参数输入表!$I$441+$I$30)*(1-参数输入表!$I$439)*参数输入表!$I$35/参数输入表!$I$438 -> 1029.6202 | ... AA32: =(参数输入表!$I$148-参数输入表!$I$152-参数输入表!$I$441+$I$30)*(1-参数输入表!$I$439)*参数输入表!$I$35/参数输入表!$I$438 -> 1029.6202
C33: 建设期第2年投产 | D33: =SUM(F33:AF33) -> 92665.816 | E33: 万元 | K33: =(参数输入表!$I$148-参数输入表!$I$152-参数输入表!$I$441+$I$30)*(1-参数输入表!$I$439)*参数输入表!$I$36/参数输入表!$I$438 -> 5148.1009 | L33: =(参数输入表!$I$148-参数输入表!$I$152-参数输入表!$I$441+$I$30)*(1-参数输入表!$I$439)*参数输入表!$I$36/参数输入表!$I$438 -> 5148.1009 | M33: =(参数输入表!$I$148-参数输入表!$I$152-参数输入表!$I$441+$I$30)*(1-参数输入表!$I$439)*参数输入表!$I$36/参数输入表!$I$438 -> 5148.1009 | N33: =(参数输入表!$I$148-参数输入表!$I$152-参数输入表!$I$441+$I$30)*(1-参数输入表!$I$439)*参数输入表!$I$36/参数输入表!$I$438 -> 5148.1009 | O33: =(参数输入表!$I$148-参数输入表!$I$152-参数输入表!$I$441+$I$30)*(1-参数输入表!$I$439)*参数输入表!$I$36/参数输入表!$I$438 -> 5148.1009 | P33: =(参数输入表!$I$148-参数输入表!$I$152-参数输入表!$I$441+$I$30)*(1-参数输入表!$I$439)*参数输入表!$I$36/参数输入表!$I$438 -> 5148.1009 | Q33: =(参数输入表!$I$148-参数输入表!$I$152-参数输入表!$I$441+$I$30)*(1-参数输入表!$I$439)*参数输入表!$I$36/参数输入表!$I$438 -> 5148.1009 | R33: =(参数输入表!$I$148-参数输入表!$I$152-参数输入表!$I$441+$I$30)*(1-参数输入表!$I$439)*参数输入表!$I$36/参数输入表!$I$438 -> 5148.1009 | ... AB33: =(参数输入表!$I$148-参数输入表!$I$152-参数输入表!$I$441+$I$30)*(1-参数输入表!$I$439)*参数输入表!$I$36/参数输入表!$I$438 -> 5148.1009
C34: 完全投产 | D34: =SUM(F34:AF34) -> 12355.442 | E34: 万元 | L34: =(参数输入表!$I$148-参数输入表!$I$152-参数输入表!$I$441+$I$30)*(1-参数输入表!$I$439)*参数输入表!$I$37/参数输入表!$I$438 -> 686.41345 | M34: =(参数输入表!$I$148-参数输入表!$I$152-参数输入表!$I$441+$I$30)*(1-参数输入表!$I$439)*参数输入表!$I$37/参数输入表!$I$438 -> 686.41345 | N34: =(参数输入表!$I$148-参数输入表!$I$152-参数输入表!$I$441+$I$30)*(1-参数输入表!$I$439)*参数输入表!$I$37/参数输入表!$I$438 -> 686.41345 | O34: =(参数输入表!$I$148-参数输入表!$I$152-参数输入表!$I$441+$I$30)*(1-参数输入表!$I$439)*参数输入表!$I$37/参数输入表!$I$438 -> 686.41345 | P34: =(参数输入表!$I$148-参数输入表!$I$152-参数输入表!$I$441+$I$30)*(1-参数输入表!$I$439)*参数输入表!$I$37/参数输入表!$I$438 -> 686.41345 | Q34: =(参数输入表!$I$148-参数输入表!$I$152-参数输入表!$I$441+$I$30)*(1-参数输入表!$I$439)*参数输入表!$I$37/参数输入表!$I$438 -> 686.41345 | R34: =(参数输入表!$I$148-参数输入表!$I$152-参数输入表!$I$441+$I$30)*(1-参数输入表!$I$439)*参数输入表!$I$37/参数输入表!$I$438 -> 686.41345 | S34: =(参数输入表!$I$148-参数输入表!$I$152-参数输入表!$I$441+$I$30)*(1-参数输入表!$I$439)*参数输入表!$I$37/参数输入表!$I$438 -> 686.41345 | ... AC34: =(参数输入表!$I$148-参数输入表!$I$152-参数输入表!$I$441+$I$30)*(1-参数输入表!$I$439)*参数输入表!$I$37/参数输入表!$I$438 -> 686.41345
C35: 固定资产折旧累计 | E35: 万元 | J35: =I35+J31 -> 1029.6202 | K35: =J35+K31 -> 7207.3413 | L35: =K35+L31 -> 14071.476 | M35: =L35+M31 -> 20935.61 | N35: =M35+N31 -> 27799.745 | O35: =N35+O31 -> 34663.879 | P35: =O35+P31 -> 41528.014 | Q35: =P35+Q31 -> 48392.148 | ... AF35: =AE35+AF31 -> 123554.42
C36: 期末固定资产净值 | E36: 万元 | J36: =J27-J35 -> 17503.543 | K36: =K27-K35 -> 116347.08 | L36: =L27-L35 -> 109482.95 | M36: =M27-M35 -> 102618.81 | N36: =N27-N35 -> 95754.677 | O36: =O27-O35 -> 88890.542 | P36: =P27-P35 -> 82026.408 | Q36: =Q27-Q35 -> 75162.273 | ... AF36: =AF27-AF35 -> 0
B37: 2 | C37: 期初长期待摊费用 | E37: 万元 | F37: 0 | G37: =F67 -> 0 | H37: =G67 -> 0 | I37: =H67 -> 0 | J37: =I67 -> 0 | K37: =J67 -> 0 | L37: =K67 -> 0 | M37: =L67 -> 0 | N37: =M67 -> 366.97248 | ... AF37: =AE67 -> 91.743119
C38: 当期新增长期待摊费用 | D38: =SUM(F38:AF38) -> 1834.8624 | E38: 万元 | F38: =参数输入表!I459/(1+参数输入表!I488) -> 0 | G38: =参数输入表!I460/(1+参数输入表!I488) -> 0 | H38: =参数输入表!I461/(1+参数输入表!I488) -> 0 | I38: =参数输入表!I462/(1+参数输入表!I488) -> 0 | J38: =参数输入表!I463/(1+参数输入表!I488) -> 0 | K38: =参数输入表!I464/(1+参数输入表!I488) -> 0 | L38: =参数输入表!I465/(1+参数输入表!I488) -> 0 | M38: =参数输入表!I466/(1+参数输入表!I488) -> 458.7156 | N38: =参数输入表!I467/(1+参数输入表!I488) -> 0 | O38: =参数输入表!I468/(1+参数输入表!I488) -> 0 | P38: =参数输入表!I469/(1+参数输入表!I488) -> 0 | Q38: =参数输入表!I470/(1+参数输入表!I488) -> 0 | R38: =参数输入表!I471/(1+参数输入表!I488) -> 458.7156 | S38: =参数输入表!I472/(1+参数输入表!I488) -> 0 | T38: =参数输入表!I473/(1+参数输入表!I488) -> 0 | U38: =参数输入表!I474/(1+参数输入表!I488) -> 0 | V38: =参数输入表!I475/(1+参数输入表!I488) -> 0 | W38: =参数输入表!I476/(1+参数输入表!I488) -> 458.7156 | X38: =参数输入表!I477/(1+参数输入表!I488) -> 0 | Y38: =参数输入表!I478/(1+参数输入表!I488) -> 0 | Z38: =参数输入表!I479/(1+参数输入表!I488) -> 0 | AA38: =参数输入表!I480/(1+参数输入表!I488) -> 0 | AB38: =参数输入表!I481/(1+参数输入表!I488) -> 458.7156 | AC38: =参数输入表!I482/(1+参数输入表!I488) -> 0 | AD38: =参数输入表!I483/(1+参数输入表!I488) -> 0 | AE38: =参数输入表!I484/(1+参数输入表!I488) -> 0 | AF38: =参数输入表!I485/(1+参数输入表!I488) -> 0
C39: 当期摊销 | D39: =SUM(F39:AF39) -> 1834.8624 | E39: 万元 | F39: =SUM(F40:F66) -> 0 | G39: =SUM(G40:G66) -> 0 | H39: =SUM(H40:H66) -> 0 | I39: =SUM(I40:I66) -> 0 | J39: =SUM(J40:J66) -> 0 | K39: =SUM(K40:K66) -> 0 | L39: =SUM(L40:L66) -> 0 | M39: =SUM(M40:M66) -> 91.743119 | ... AF39: =SUM(AF40:AF66) -> 91.743119
C40: 合作期第1年 | D40: =SUM(F40:AF40) -> 0 | E40: 万元 | F40: =IF('表2-折旧摊销表'!$AF$25+1-'表2-折旧摊销表'!$F$25>='表2-折旧摊销表'!$D$14,$F$38/$D$14,$F$38/('表2-折旧摊销表'!$AF$25+1-'表2-折旧摊销表'!$F$25)) -> 0 | G40: =IF('表2-折旧摊销表'!$AF$25+1-'表2-折旧摊销表'!$F$25>='表2-折旧摊销表'!$D$14,$F$38/$D$14,$F$38/('表2-折旧摊销表'!$AF$25+1-'表2-折旧摊销表'!$F$25)) -> 0 | H40: =IF('表2-折旧摊销表'!$AF$25+1-'表2-折旧摊销表'!$F$25>='表2-折旧摊销表'!$D$14,$F$38/$D$14,$F$38/('表2-折旧摊销表'!$AF$25+1-'表2-折旧摊销表'!$F$25)) -> 0 | I40: =IF('表2-折旧摊销表'!$AF$25+1-'表2-折旧摊销表'!$F$25>='表2-折旧摊销表'!$D$14,$F$38/$D$14,$F$38/('表2-折旧摊销表'!$AF$25+1-'表2-折旧摊销表'!$F$25)) -> 0 | J40: =IF('表2-折旧摊销表'!$AF$25+1-'表2-折旧摊销表'!$F$25>='表2-折旧摊销表'!$D$14,$F$38/$D$14,$F$38/('表2-折旧摊销表'!$AF$25+1-'表2-折旧摊销表'!$F$25)) -> 0
C41: 合作期第2年 | D41: =SUM(F41:AF41) -> 0 | E41: 万元 | G41: =IF('表2-折旧摊销表'!$AF$25+1-'表2-折旧摊销表'!$G$25>='表2-折旧摊销表'!$D$14,$G$38/$D$14,$G$38/('表2-折旧摊销表'!$AF$25+1-'表2-折旧摊销表'!$G$25)) -> 0 | H41: =IF('表2-折旧摊销表'!$AF$25+1-'表2-折旧摊销表'!$G$25>='表2-折旧摊销表'!$D$14,$G$38/$D$14,$G$38/('表2-折旧摊销表'!$AF$25+1-'表2-折旧摊销表'!$G$25)) -> 0 | I41: =IF('表2-折旧摊销表'!$AF$25+1-'表2-折旧摊销表'!$G$25>='表2-折旧摊销表'!$D$14,$G$38/$D$14,$G$38/('表2-折旧摊销表'!$AF$25+1-'表2-折旧摊销表'!$G$25)) -> 0 | J41: =IF('表2-折旧摊销表'!$AF$25+1-'表2-折旧摊销表'!$G$25>='表2-折旧摊销表'!$D$14,$G$38/$D$14,$G$38/('表2-折旧摊销表'!$AF$25+1-'表2-折旧摊销表'!$G$25)) -> 0 | K41: =IF('表2-折旧摊销表'!$AF$25+1-'表2-折旧摊销表'!$G$25>='表2-折旧摊销表'!$D$14,$G$38/$D$14,$G$38/('表2-折旧摊销表'!$AF$25+1-'表2-折旧摊销表'!$G$25)) -> 0
C42: 合作期第3年 | D42: =SUM(F42:AF42) -> 0 | E42: 万元 | H42: =IF('表2-折旧摊销表'!$AF$25+1-'表2-折旧摊销表'!$H$25>='表2-折旧摊销表'!$D$14,$H$38/$D$14,$H$38/('表2-折旧摊销表'!$AF$25+1-'表2-折旧摊销表'!$H$25)) -> 0 | I42: =IF('表2-折旧摊销表'!$AF$25+1-'表2-折旧摊销表'!$H$25>='表2-折旧摊销表'!$D$14,$H$38/$D$14,$H$38/('表2-折旧摊销表'!$AF$25+1-'表2-折旧摊销表'!$H$25)) -> 0 | J42: =IF('表2-折旧摊销表'!$AF$25+1-'表2-折旧摊销表'!$H$25>='表2-折旧摊销表'!$D$14,$H$38/$D$14,$H$38/('表2-折旧摊销表'!$AF$25+1-'表2-折旧摊销表'!$H$25)) -> 0 | K42: =IF('表2-折旧摊销表'!$AF$25+1-'表2-折旧摊销表'!$H$25>='表2-折旧摊销表'!$D$14,$H$38/$D$14,$H$38/('表2-折旧摊销表'!$AF$25+1-'表2-折旧摊销表'!$H$25)) -> 0 | L42: =IF('表2-折旧摊销表'!$AF$25+1-'表2-折旧摊销表'!$H$25>='表2-折旧摊销表'!$D$14,$H$38/$D$14,$H$38/('表2-折旧摊销表'!$AF$25+1-'表2-折旧摊销表'!$H$25)) -> 0
C43: 合作期第4年 | D43: =SUM(F43:AF43) -> 0 | E43: 万元 | I43: =IF('表2-折旧摊销表'!$AF$25+1-'表2-折旧摊销表'!$I$25>='表2-折旧摊销表'!$D$14,$I$38/$D$14,$I$38/('表2-折旧摊销表'!$AF$25+1-'表2-折旧摊销表'!$I$25)) -> 0 | J43: =IF('表2-折旧摊销表'!$AF$25+1-'表2-折旧摊销表'!$I$25>='表2-折旧摊销表'!$D$14,$I$38/$D$14,$I$38/('表2-折旧摊销表'!$AF$25+1-'表2-折旧摊销表'!$I$25)) -> 0 | K43: =IF('表2-折旧摊销表'!$AF$25+1-'表2-折旧摊销表'!$I$25>='表2-折旧摊销表'!$D$14,$I$38/$D$14,$I$38/('表2-折旧摊销表'!$AF$25+1-'表2-折旧摊销表'!$I$25)) -> 0 | L43: =IF('表2-折旧摊销表'!$AF$25+1-'表2-折旧摊销表'!$I$25>='表2-折旧摊销表'!$D$14,$I$38/$D$14,$I$38/('表2-折旧摊销表'!$AF$25+1-'表2-折旧摊销表'!$I$25)) -> 0 | M43: =IF('表2-折旧摊销表'!$AF$25+1-'表2-折旧摊销表'!$I$25>='表2-折旧摊销表'!$D$14,$I$38/$D$14,$I$38/('表2-折旧摊销表'!$AF$25+1-'表2-折旧摊销表'!$I$25)) -> 0
C44: 合作期第5年 | D44: =SUM(F44:AF44) -> 0 | E44: 万元 | J44: =IF('表2-折旧摊销表'!$AF$25+1-'表2-折旧摊销表'!$J$25>='表2-折旧摊销表'!$D$14,$J$38/$D$14,$J$38/('表2-折旧摊销表'!$AF$25+1-'表2-折旧摊销表'!$J$25)) -> 0 | K44: =IF('表2-折旧摊销表'!$AF$25+1-'表2-折旧摊销表'!$J$25>='表2-折旧摊销表'!$D$14,$J$38/$D$14,$J$38/('表2-折旧摊销表'!$AF$25+1-'表2-折旧摊销表'!$J$25)) -> 0 | L44: =IF('表2-折旧摊销表'!$AF$25+1-'表2-折旧摊销表'!$J$25>='表2-折旧摊销表'!$D$14,$J$38/$D$14,$J$38/('表2-折旧摊销表'!$AF$25+1-'表2-折旧摊销表'!$J$25)) -> 0 | M44: =IF('表2-折旧摊销表'!$AF$25+1-'表2-折旧摊销表'!$J$25>='表2-折旧摊销表'!$D$14,$J$38/$D$14,$J$38/('表2-折旧摊销表'!$AF$25+1-'表2-折旧摊销表'!$J$25)) -> 0 | N44: =IF('表2-折旧摊销表'!$AF$25+1-'表2-折旧摊销表'!$J$25>='表2-折旧摊销表'!$D$14,$J$38/$D$14,$J$38/('表2-折旧摊销表'!$AF$25+1-'表2-折旧摊销表'!$J$25)) -> 0
C45: 合作期第6年 | D45: =SUM(F45:AF45) -> 0 | E45: 万元 | K45: =IF('表2-折旧摊销表'!$AF$25+1-'表2-折旧摊销表'!$K$25>='表2-折旧摊销表'!$D$14,$K$38/$D$14,$K$38/('表2-折旧摊销表'!$AF$25+1-'表2-折旧摊销表'!$K$25)) -> 0 | L45: =IF('表2-折旧摊销表'!$AF$25+1-'表2-折旧摊销表'!$K$25>='表2-折旧摊销表'!$D$14,$K$38/$D$14,$K$38/('表2-折旧摊销表'!$AF$25+1-'表2-折旧摊销表'!$K$25)) -> 0 | M45: =IF('表2-折旧摊销表'!$AF$25+1-'表2-折旧摊销表'!$K$25>='表2-折旧摊销表'!$D$14,$K$38/$D$14,$K$38/('表2-折旧摊销表'!$AF$25+1-'表2-折旧摊销表'!$K$25)) -> 0 | N45: =IF('表2-折旧摊销表'!$AF$25+1-'表2-折旧摊销表'!$K$25>='表2-折旧摊销表'!$D$14,$K$38/$D$14,$K$38/('表2-折旧摊销表'!$AF$25+1-'表2-折旧摊销表'!$K$25)) -> 0 | O45: =IF('表2-折旧摊销表'!$AF$25+1-'表2-折旧摊销表'!$K$25>='表2-折旧摊销表'!$D$14,$K$38/$D$14,$K$38/('表2-折旧摊销表'!$AF$25+1-'表2-折旧摊销表'!$K$25)) -> 0
C46: 合作期第7年 | D46: =SUM(F46:AF46) -> 0 | E46: 万元 | L46: =IF('表2-折旧摊销表'!$AF$25+1-'表2-折旧摊销表'!$L$25>='表2-折旧摊销表'!$D$14,$L$38/$D$14,$L$38/('表2-折旧摊销表'!$AF$25+1-'表2-折旧摊销表'!$L$25)) -> 0 | M46: =IF('表2-折旧摊销表'!$AF$25+1-'表2-折旧摊销表'!$L$25>='表2-折旧摊销表'!$D$14,$L$38/$D$14,$L$38/('表2-折旧摊销表'!$AF$25+1-'表2-折旧摊销表'!$L$25)) -> 0 | N46: =IF('表2-折旧摊销表'!$AF$25+1-'表2-折旧摊销表'!$L$25>='表2-折旧摊销表'!$D$14,$L$38/$D$14,$L$38/('表2-折旧摊销表'!$AF$25+1-'表2-折旧摊销表'!$L$25)) -> 0 | O46: =IF('表2-折旧摊销表'!$AF$25+1-'表2-折旧摊销表'!$L$25>='表2-折旧摊销表'!$D$14,$L$38/$D$14,$L$38/('表2-折旧摊销表'!$AF$25+1-'表2-折旧摊销表'!$L$25)) -> 0 | P46: =IF('表2-折旧摊销表'!$AF$25+1-'表2-折旧摊销表'!$L$25>='表2-折旧摊销表'!$D$14,$L$38/$D$14,$L$38/('表2-折旧摊销表'!$AF$25+1-'表2-折旧摊销表'!$L$25)) -> 0
C47: 合作期第8年 | D47: =SUM(F47:AF47) -> 458.7156 | E47: 万元 | M47: =IF('表2-折旧摊销表'!$AF$25+1-'表2-折旧摊销表'!$M$25>='表2-折旧摊销表'!$D$14,$M$38/$D$14,$M$38/('表2-折旧摊销表'!$AF$25+1-'表2-折旧摊销表'!$M$25)) -> 91.743119 | N47: =IF('表2-折旧摊销表'!$AF$25+1-'表2-折旧摊销表'!$M$25>='表2-折旧摊销表'!$D$14,$M$38/$D$14,$M$38/('表2-折旧摊销表'!$AF$25+1-'表2-折旧摊销表'!$M$25)) -> 91.743119 | O47: =IF('表2-折旧摊销表'!$AF$25+1-'表2-折旧摊销表'!$M$25>='表2-折旧摊销表'!$D$14,$M$38/$D$14,$M$38/('表2-折旧摊销表'!$AF$25+1-'表2-折旧摊销表'!$M$25)) -> 91.743119 | P47: =IF('表2-折旧摊销表'!$AF$25+1-'表2-折旧摊销表'!$M$25>='表2-折旧摊销表'!$D$14,$M$38/$D$14,$M$38/('表2-折旧摊销表'!$AF$25+1-'表2-折旧摊销表'!$M$25)) -> 91.743119 | Q47: =IF('表2-折旧摊销表'!$AF$25+1-'表2-折旧摊销表'!$M$25>='表2-折旧摊销表'!$D$14,$M$38/$D$14,$M$38/('表2-折旧摊销表'!$AF$25+1-'表2-折旧摊销表'!$M$25)) -> 91.743119
C48: 合作期第9年 | D48: =SUM(F48:AF48) -> 0 | E48: 万元 | N48: =IF('表2-折旧摊销表'!$AF$25+1-'表2-折旧摊销表'!$N$25>='表2-折旧摊销表'!$D$14,$N$38/$D$14,$N$38/('表2-折旧摊销表'!$AF$25+1-'表2-折旧摊销表'!$N$25)) -> 0 | O48: =IF('表2-折旧摊销表'!$AF$25+1-'表2-折旧摊销表'!$N$25>='表2-折旧摊销表'!$D$14,$N$38/$D$14,$N$38/('表2-折旧摊销表'!$AF$25+1-'表2-折旧摊销表'!$N$25)) -> 0 | P48: =IF('表2-折旧摊销表'!$AF$25+1-'表2-折旧摊销表'!$N$25>='表2-折旧摊销表'!$D$14,$N$38/$D$14,$N$38/('表2-折旧摊销表'!$AF$25+1-'表2-折旧摊销表'!$N$25)) -> 0 | Q48: =IF('表2-折旧摊销表'!$AF$25+1-'表2-折旧摊销表'!$N$25>='表2-折旧摊销表'!$D$14,$N$38/$D$14,$N$38/('表2-折旧摊销表'!$AF$25+1-'表2-折旧摊销表'!$N$25)) -> 0 | R48: =IF('表2-折旧摊销表'!$AF$25+1-'表2-折旧摊销表'!$N$25>='表2-折旧摊销表'!$D$14,$N$38/$D$14,$N$38/('表2-折旧摊销表'!$AF$25+1-'表2-折旧摊销表'!$N$25)) -> 0
C49: 合作期第10年 | D49: =SUM(F49:AF49) -> 0 | E49: 万元 | O49: =IF('表2-折旧摊销表'!$AF$25+1-'表2-折旧摊销表'!$O$25>='表2-折旧摊销表'!$D$14,$O$38/$D$14,$O$38/('表2-折旧摊销表'!$AF$25+1-'表2-折旧摊销表'!$O$25)) -> 0 | P49: =IF('表2-折旧摊销表'!$AF$25+1-'表2-折旧摊销表'!$O$25>='表2-折旧摊销表'!$D$14,$O$38/$D$14,$O$38/('表2-折旧摊销表'!$AF$25+1-'表2-折旧摊销表'!$O$25)) -> 0 | Q49: =IF('表2-折旧摊销表'!$AF$25+1-'表2-折旧摊销表'!$O$25>='表2-折旧摊销表'!$D$14,$O$38/$D$14,$O$38/('表2-折旧摊销表'!$AF$25+1-'表2-折旧摊销表'!$O$25)) -> 0 | R49: =IF('表2-折旧摊销表'!$AF$25+1-'表2-折旧摊销表'!$O$25>='表2-折旧摊销表'!$D$14,$O$38/$D$14,$O$38/('表2-折旧摊销表'!$AF$25+1-'表2-折旧摊销表'!$O$25)) -> 0 | S49: =IF('表2-折旧摊销表'!$AF$25+1-'表2-折旧摊销表'!$O$25>='表2-折旧摊销表'!$D$14,$O$38/$D$14,$O$38/('表2-折旧摊销表'!$AF$25+1-'表2-折旧摊销表'!$O$25)) -> 0
C50: 合作期第11年 | D50: =SUM(F50:AF50) -> 0 | E50: 万元 | P50: =IF('表2-折旧摊销表'!$AF$25+1-'表2-折旧摊销表'!$P$25>='表2-折旧摊销表'!$D$14,$P$38/$D$14,$P$38/('表2-折旧摊销表'!$AF$25+1-'表2-折旧摊销表'!$P$25)) -> 0 | Q50: =IF('表2-折旧摊销表'!$AF$25+1-'表2-折旧摊销表'!$P$25>='表2-折旧摊销表'!$D$14,$P$38/$D$14,$P$38/('表2-折旧摊销表'!$AF$25+1-'表2-折旧摊销表'!$P$25)) -> 0 | R50: =IF('表2-折旧摊销表'!$AF$25+1-'表2-折旧摊销表'!$P$25>='表2-折旧摊销表'!$D$14,$P$38/$D$14,$P$38/('表2-折旧摊销表'!$AF$25+1-'表2-折旧摊销表'!$P$25)) -> 0 | S50: =IF('表2-折旧摊销表'!$AF$25+1-'表2-折旧摊销表'!$P$25>='表2-折旧摊销表'!$D$14,$P$38/$D$14,$P$38/('表2-折旧摊销表'!$AF$25+1-'表2-折旧摊销表'!$P$25)) -> 0 | T50: =IF('表2-折旧摊销表'!$AF$25+1-'表2-折旧摊销表'!$P$25>='表2-折旧摊销表'!$D$14,$P$38/$D$14,$P$38/('表2-折旧摊销表'!$AF$25+1-'表2-折旧摊销表'!$P$25)) -> 0
C51: 合作期第12年 | D51: =SUM(F51:AF51) -> 0 | E51: 万元 | Q51: =IF('表2-折旧摊销表'!$AF$25+1-'表2-折旧摊销表'!$Q$25>='表2-折旧摊销表'!$D$14,$Q$38/$D$14,$Q$38/('表2-折旧摊销表'!$AF$25+1-'表2-折旧摊销表'!$Q$25)) -> 0 | R51: =IF('表2-折旧摊销表'!$AF$25+1-'表2-折旧摊销表'!$Q$25>='表2-折旧摊销表'!$D$14,$Q$38/$D$14,$Q$38/('表2-折旧摊销表'!$AF$25+1-'表2-折旧摊销表'!$Q$25)) -> 0 | S51: =IF('表2-折旧摊销表'!$AF$25+1-'表2-折旧摊销表'!$Q$25>='表2-折旧摊销表'!$D$14,$Q$38/$D$14,$Q$38/('表2-折旧摊销表'!$AF$25+1-'表2-折旧摊销表'!$Q$25)) -> 0 | T51: =IF('表2-折旧摊销表'!$AF$25+1-'表2-折旧摊销表'!$Q$25>='表2-折旧摊销表'!$D$14,$Q$38/$D$14,$Q$38/('表2-折旧摊销表'!$AF$25+1-'表2-折旧摊销表'!$Q$25)) -> 0 | U51: =IF('表2-折旧摊销表'!$AF$25+1-'表2-折旧摊销表'!$Q$25>='表2-折旧摊销表'!$D$14,$Q$38/$D$14,$Q$38/('表2-折旧摊销表'!$AF$25+1-'表2-折旧摊销表'!$Q$25)) -> 0
C52: 合作期第13年 | D52: =SUM(F52:AF52) -> 458.7156 | E52: 万元 | R52: =IF('表2-折旧摊销表'!$AF$25+1-'表2-折旧摊销表'!$R$25>='表2-折旧摊销表'!$D$14,$R$38/$D$14,$R$38/('表2-折旧摊销表'!$AF$25+1-'表2-折旧摊销表'!$R$25)) -> 91.743119 | S52: =IF('表2-折旧摊销表'!$AF$25+1-'表2-折旧摊销表'!$R$25>='表2-折旧摊销表'!$D$14,$R$38/$D$14,$R$38/('表2-折旧摊销表'!$AF$25+1-'表2-折旧摊销表'!$R$25)) -> 91.743119 | T52: =IF('表2-折旧摊销表'!$AF$25+1-'表2-折旧摊销表'!$R$25>='表2-折旧摊销表'!$D$14,$R$38/$D$14,$R$38/('表2-折旧摊销表'!$AF$25+1-'表2-折旧摊销表'!$R$25)) -> 91.743119 | U52: =IF('表2-折旧摊销表'!$AF$25+1-'表2-折旧摊销表'!$R$25>='表2-折旧摊销表'!$D$14,$R$38/$D$14,$R$38/('表2-折旧摊销表'!$AF$25+1-'表2-折旧摊销表'!$R$25)) -> 91.743119 | V52: =IF('表2-折旧摊销表'!$AF$25+1-'表2-折旧摊销表'!$R$25>='表2-折旧摊销表'!$D$14,$R$38/$D$14,$R$38/('表2-折旧摊销表'!$AF$25+1-'表2-折旧摊销表'!$R$25)) -> 91.743119
C53: 合作期第14年 | D53: =SUM(F53:AF53) -> 0 | E53: 万元 | S53: =IF('表2-折旧摊销表'!$AF$25+1-'表2-折旧摊销表'!$S$25>='表2-折旧摊销表'!$D$14,$S$38/$D$14,$S$38/('表2-折旧摊销表'!$AF$25+1-'表2-折旧摊销表'!$S$25)) -> 0 | T53: =IF('表2-折旧摊销表'!$AF$25+1-'表2-折旧摊销表'!$S$25>='表2-折旧摊销表'!$D$14,$S$38/$D$14,$S$38/('表2-折旧摊销表'!$AF$25+1-'表2-折旧摊销表'!$S$25)) -> 0 | U53: =IF('表2-折旧摊销表'!$AF$25+1-'表2-折旧摊销表'!$S$25>='表2-折旧摊销表'!$D$14,$S$38/$D$14,$S$38/('表2-折旧摊销表'!$AF$25+1-'表2-折旧摊销表'!$S$25)) -> 0 | V53: =IF('表2-折旧摊销表'!$AF$25+1-'表2-折旧摊销表'!$S$25>='表2-折旧摊销表'!$D$14,$S$38/$D$14,$S$38/('表2-折旧摊销表'!$AF$25+1-'表2-折旧摊销表'!$S$25)) -> 0 | W53: =IF('表2-折旧摊销表'!$AF$25+1-'表2-折旧摊销表'!$S$25>='表2-折旧摊销表'!$D$14,$S$38/$D$14,$S$38/('表2-折旧摊销表'!$AF$25+1-'表2-折旧摊销表'!$S$25)) -> 0
C54: 合作期第15年 | D54: =SUM(F54:AF54) -> 0 | E54: 万元 | T54: =IF('表2-折旧摊销表'!$AF$25+1-'表2-折旧摊销表'!$T$25>='表2-折旧摊销表'!$D$14,$T$38/$D$14,$T$38/('表2-折旧摊销表'!$AF$25+1-'表2-折旧摊销表'!$T$25)) -> 0 | U54: =IF('表2-折旧摊销表'!$AF$25+1-'表2-折旧摊销表'!$T$25>='表2-折旧摊销表'!$D$14,$T$38/$D$14,$T$38/('表2-折旧摊销表'!$AF$25+1-'表2-折旧摊销表'!$T$25)) -> 0 | V54: =IF('表2-折旧摊销表'!$AF$25+1-'表2-折旧摊销表'!$T$25>='表2-折旧摊销表'!$D$14,$T$38/$D$14,$T$38/('表2-折旧摊销表'!$AF$25+1-'表2-折旧摊销表'!$T$25)) -> 0 | W54: =IF('表2-折旧摊销表'!$AF$25+1-'表2-折旧摊销表'!$T$25>='表2-折旧摊销表'!$D$14,$T$38/$D$14,$T$38/('表2-折旧摊销表'!$AF$25+1-'表2-折旧摊销表'!$T$25)) -> 0 | X54: =IF('表2-折旧摊销表'!$AF$25+1-'表2-折旧摊销表'!$T$25>='表2-折旧摊销表'!$D$14,$T$38/$D$14,$T$38/('表2-折旧摊销表'!$AF$25+1-'表2-折旧摊销表'!$T$25)) -> 0
C55: 合作期第16年 | D55: =SUM(F55:AF55) -> 0 | E55: 万元 | U55: =IF('表2-折旧摊销表'!$AF$25+1-'表2-折旧摊销表'!$U$25>='表2-折旧摊销表'!$D$14,$U$38/$D$14,$U$38/('表2-折旧摊销表'!$AF$25+1-'表2-折旧摊销表'!$U$25)) -> 0 | V55: =IF('表2-折旧摊销表'!$AF$25+1-'表2-折旧摊销表'!$U$25>='表2-折旧摊销表'!$D$14,$U$38/$D$14,$U$38/('表2-折旧摊销表'!$AF$25+1-'表2-折旧摊销表'!$U$25)) -> 0 | W55: =IF('表2-折旧摊销表'!$AF$25+1-'表2-折旧摊销表'!$U$25>='表2-折旧摊销表'!$D$14,$U$38/$D$14,$U$38/('表2-折旧摊销表'!$AF$25+1-'表2-折旧摊销表'!$U$25)) -> 0 | X55: =IF('表2-折旧摊销表'!$AF$25+1-'表2-折旧摊销表'!$U$25>='表2-折旧摊销表'!$D$14,$U$38/$D$14,$U$38/('表2-折旧摊销表'!$AF$25+1-'表2-折旧摊销表'!$U$25)) -> 0 | Y55: =IF('表2-折旧摊销表'!$AF$25+1-'表2-折旧摊销表'!$U$25>='表2-折旧摊销表'!$D$14,$U$38/$D$14,$U$38/('表2-折旧摊销表'!$AF$25+1-'表2-折旧摊销表'!$U$25)) -> 0
C56: 合作期第17年 | D56: =SUM(F56:AF56) -> 0 | E56: 万元 | V56: =IF('表2-折旧摊销表'!$AF$25+1-'表2-折旧摊销表'!$V$25>='表2-折旧摊销表'!$D$14,$V$38/$D$14,$V$38/('表2-折旧摊销表'!$AF$25+1-'表2-折旧摊销表'!$V$25)) -> 0 | W56: =IF('表2-折旧摊销表'!$AF$25+1-'表2-折旧摊销表'!$V$25>='表2-折旧摊销表'!$D$14,$V$38/$D$14,$V$38/('表2-折旧摊销表'!$AF$25+1-'表2-折旧摊销表'!$V$25)) -> 0 | X56: =IF('表2-折旧摊销表'!$AF$25+1-'表2-折旧摊销表'!$V$25>='表2-折旧摊销表'!$D$14,$V$38/$D$14,$V$38/('表2-折旧摊销表'!$AF$25+1-'表2-折旧摊销表'!$V$25)) -> 0 | Y56: =IF('表2-折旧摊销表'!$AF$25+1-'表2-折旧摊销表'!$V$25>='表2-折旧摊销表'!$D$14,$V$38/$D$14,$V$38/('表2-折旧摊销表'!$AF$25+1-'表2-折旧摊销表'!$V$25)) -> 0 | Z56: =IF('表2-折旧摊销表'!$AF$25+1-'表2-折旧摊销表'!$V$25>='表2-折旧摊销表'!$D$14,$V$38/$D$14,$V$38/('表2-折旧摊销表'!$AF$25+1-'表2-折旧摊销表'!$V$25)) -> 0
C57: 合作期第18年 | D57: =SUM(F57:AF57) -> 458.7156 | E57: 万元 | W57: =IF('表2-折旧摊销表'!$AF$25+1-'表2-折旧摊销表'!$W$25>='表2-折旧摊销表'!$D$14,$W$38/$D$14,$W$38/('表2-折旧摊销表'!$AF$25+1-'表2-折旧摊销表'!$W$25)) -> 91.743119 | X57: =IF('表2-折旧摊销表'!$AF$25+1-'表2-折旧摊销表'!$W$25>='表2-折旧摊销表'!$D$14,$W$38/$D$14,$W$38/('表2-折旧摊销表'!$AF$25+1-'表2-折旧摊销表'!$W$25)) -> 91.743119 | Y57: =IF('表2-折旧摊销表'!$AF$25+1-'表2-折旧摊销表'!$W$25>='表2-折旧摊销表'!$D$14,$W$38/$D$14,$W$38/('表2-折旧摊销表'!$AF$25+1-'表2-折旧摊销表'!$W$25)) -> 91.743119 | Z57: =IF('表2-折旧摊销表'!$AF$25+1-'表2-折旧摊销表'!$W$25>='表2-折旧摊销表'!$D$14,$W$38/$D$14,$W$38/('表2-折旧摊销表'!$AF$25+1-'表2-折旧摊销表'!$W$25)) -> 91.743119 | AA57: =IF('表2-折旧摊销表'!$AF$25+1-'表2-折旧摊销表'!$W$25>='表2-折旧摊销表'!$D$14,$W$38/$D$14,$W$38/('表2-折旧摊销表'!$AF$25+1-'表2-折旧摊销表'!$W$25)) -> 91.743119
C58: 合作期第19年 | D58: =SUM(F58:AF58) -> 0 | E58: 万元 | X58: =IF('表2-折旧摊销表'!$AF$25+1-'表2-折旧摊销表'!$X$25>='表2-折旧摊销表'!$D$14,$X$38/$D$14,$X$38/('表2-折旧摊销表'!$AF$25+1-'表2-折旧摊销表'!$X$25)) -> 0 | Y58: =IF('表2-折旧摊销表'!$AF$25+1-'表2-折旧摊销表'!$X$25>='表2-折旧摊销表'!$D$14,$X$38/$D$14,$X$38/('表2-折旧摊销表'!$AF$25+1-'表2-折旧摊销表'!$X$25)) -> 0 | Z58: =IF('表2-折旧摊销表'!$AF$25+1-'表2-折旧摊销表'!$X$25>='表2-折旧摊销表'!$D$14,$X$38/$D$14,$X$38/('表2-折旧摊销表'!$AF$25+1-'表2-折旧摊销表'!$X$25)) -> 0 | AA58: =IF('表2-折旧摊销表'!$AF$25+1-'表2-折旧摊销表'!$X$25>='表2-折旧摊销表'!$D$14,$X$38/$D$14,$X$38/('表2-折旧摊销表'!$AF$25+1-'表2-折旧摊销表'!$X$25)) -> 0 | AB58: =IF('表2-折旧摊销表'!$AF$25+1-'表2-折旧摊销表'!$X$25>='表2-折旧摊销表'!$D$14,$X$38/$D$14,$X$38/('表2-折旧摊销表'!$AF$25+1-'表2-折旧摊销表'!$X$25)) -> 0
C59: 合作期第20年 | D59: =SUM(F59:AF59) -> 0 | E59: 万元 | Y59: =IF('表2-折旧摊销表'!$AF$25+1-'表2-折旧摊销表'!$Y$25>='表2-折旧摊销表'!$D$14,$Y$38/$D$14,$Y$38/('表2-折旧摊销表'!$AF$25+1-'表2-折旧摊销表'!$Y$25)) -> 0 | Z59: =IF('表2-折旧摊销表'!$AF$25+1-'表2-折旧摊销表'!$Y$25>='表2-折旧摊销表'!$D$14,$Y$38/$D$14,$Y$38/('表2-折旧摊销表'!$AF$25+1-'表2-折旧摊销表'!$Y$25)) -> 0 | AA59: =IF('表2-折旧摊销表'!$AF$25+1-'表2-折旧摊销表'!$Y$25>='表2-折旧摊销表'!$D$14,$Y$38/$D$14,$Y$38/('表2-折旧摊销表'!$AF$25+1-'表2-折旧摊销表'!$Y$25)) -> 0 | AB59: =IF('表2-折旧摊销表'!$AF$25+1-'表2-折旧摊销表'!$Y$25>='表2-折旧摊销表'!$D$14,$Y$38/$D$14,$Y$38/('表2-折旧摊销表'!$AF$25+1-'表2-折旧摊销表'!$Y$25)) -> 0 | AC59: =IF('表2-折旧摊销表'!$AF$25+1-'表2-折旧摊销表'!$Y$25>='表2-折旧摊销表'!$D$14,$Y$38/$D$14,$Y$38/('表2-折旧摊销表'!$AF$25+1-'表2-折旧摊销表'!$Y$25)) -> 0
C60: 合作期第21年 | D60: =SUM(F60:AF60) -> 0 | E60: 万元 | Z60: =IF('表2-折旧摊销表'!$AF$25+1-'表2-折旧摊销表'!$Z$25>='表2-折旧摊销表'!$D$14,$Z$38/$D$14,$Z$38/('表2-折旧摊销表'!$AF$25+1-'表2-折旧摊销表'!$Z$25)) -> 0 | AA60: =IF('表2-折旧摊销表'!$AF$25+1-'表2-折旧摊销表'!$Z$25>='表2-折旧摊销表'!$D$14,$Z$38/$D$14,$Z$38/('表2-折旧摊销表'!$AF$25+1-'表2-折旧摊销表'!$Z$25)) -> 0 | AB60: =IF('表2-折旧摊销表'!$AF$25+1-'表2-折旧摊销表'!$Z$25>='表2-折旧摊销表'!$D$14,$Z$38/$D$14,$Z$38/('表2-折旧摊销表'!$AF$25+1-'表2-折旧摊销表'!$Z$25)) -> 0 | AC60: =IF('表2-折旧摊销表'!$AF$25+1-'表2-折旧摊销表'!$Z$25>='表2-折旧摊销表'!$D$14,$Z$38/$D$14,$Z$38/('表2-折旧摊销表'!$AF$25+1-'表2-折旧摊销表'!$Z$25)) -> 0 | AD60: =IF('表2-折旧摊销表'!$AF$25+1-'表2-折旧摊销表'!$Z$25>='表2-折旧摊销表'!$D$14,$Z$38/$D$14,$Z$38/('表2-折旧摊销表'!$AF$25+1-'表2-折旧摊销表'!$Z$25)) -> 0
C61: 合作期第22年 | D61: =SUM(F61:AF61) -> 0 | E61: 万元 | AA61: =IF('表2-折旧摊销表'!$AF$25+1-'表2-折旧摊销表'!$AA$25>='表2-折旧摊销表'!$D$14,$AA$38/$D$14,$AA$38/('表2-折旧摊销表'!$AF$25+1-'表2-折旧摊销表'!$AA$25)) -> 0 | AB61: =IF('表2-折旧摊销表'!$AF$25+1-'表2-折旧摊销表'!$AA$25>='表2-折旧摊销表'!$D$14,$AA$38/$D$14,$AA$38/('表2-折旧摊销表'!$AF$25+1-'表2-折旧摊销表'!$AA$25)) -> 0 | AC61: =IF('表2-折旧摊销表'!$AF$25+1-'表2-折旧摊销表'!$AA$25>='表2-折旧摊销表'!$D$14,$AA$38/$D$14,$AA$38/('表2-折旧摊销表'!$AF$25+1-'表2-折旧摊销表'!$AA$25)) -> 0 | AD61: =IF('表2-折旧摊销表'!$AF$25+1-'表2-折旧摊销表'!$AA$25>='表2-折旧摊销表'!$D$14,$AA$38/$D$14,$AA$38/('表2-折旧摊销表'!$AF$25+1-'表2-折旧摊销表'!$AA$25)) -> 0 | AE61: =IF('表2-折旧摊销表'!$AF$25+1-'表2-折旧摊销表'!$AA$25>='表2-折旧摊销表'!$D$14,$AA$38/$D$14,$AA$38/('表2-折旧摊销表'!$AF$25+1-'表2-折旧摊销表'!$AA$25)) -> 0
C62: 合作期第23年 | D62: =SUM(F62:AF62) -> 458.7156 | E62: 万元 | AB62: =IF('表2-折旧摊销表'!$AF$25+1-'表2-折旧摊销表'!$AB$25>='表2-折旧摊销表'!$D$14,$AB$38/$D$14,$AB$38/('表2-折旧摊销表'!$AF$25+1-'表2-折旧摊销表'!$AB$25)) -> 91.743119 | AC62: =IF('表2-折旧摊销表'!$AF$25+1-'表2-折旧摊销表'!$AB$25>='表2-折旧摊销表'!$D$14,$AB$38/$D$14,$AB$38/('表2-折旧摊销表'!$AF$25+1-'表2-折旧摊销表'!$AB$25)) -> 91.743119 | AD62: =IF('表2-折旧摊销表'!$AF$25+1-'表2-折旧摊销表'!$AB$25>='表2-折旧摊销表'!$D$14,$AB$38/$D$14,$AB$38/('表2-折旧摊销表'!$AF$25+1-'表2-折旧摊销表'!$AB$25)) -> 91.743119 | AE62: =IF('表2-折旧摊销表'!$AF$25+1-'表2-折旧摊销表'!$AB$25>='表2-折旧摊销表'!$D$14,$AB$38/$D$14,$AB$38/('表2-折旧摊销表'!$AF$25+1-'表2-折旧摊销表'!$AB$25)) -> 91.743119 | AF62: =IF('表2-折旧摊销表'!$AF$25+1-'表2-折旧摊销表'!$AB$25>='表2-折旧摊销表'!$D$14,$AB$38/$D$14,$AB$38/('表2-折旧摊销表'!$AF$25+1-'表2-折旧摊销表'!$AB$25)) -> 91.743119
C63: 合作期第24年 | D63: =SUM(F63:AF63) -> 0 | E63: 万元 | AC63: =IF('表2-折旧摊销表'!$AF$25+1-'表2-折旧摊销表'!$AC$25>='表2-折旧摊销表'!$D$14,$AC$38/$D$14,$AC$38/('表2-折旧摊销表'!$AF$25+1-'表2-折旧摊销表'!$AC$25)) -> 0 | AD63: =IF('表2-折旧摊销表'!$AF$25+1-'表2-折旧摊销表'!$AC$25>='表2-折旧摊销表'!$D$14,$AC$38/$D$14,$AC$38/('表2-折旧摊销表'!$AF$25+1-'表2-折旧摊销表'!$AC$25)) -> 0 | AE63: =IF('表2-折旧摊销表'!$AF$25+1-'表2-折旧摊销表'!$AC$25>='表2-折旧摊销表'!$D$14,$AC$38/$D$14,$AC$38/('表2-折旧摊销表'!$AF$25+1-'表2-折旧摊销表'!$AC$25)) -> 0 | AF63: =IF('表2-折旧摊销表'!$AF$25+1-'表2-折旧摊销表'!$AC$25>='表2-折旧摊销表'!$D$14,$AC$38/$D$14,$AC$38/('表2-折旧摊销表'!$AF$25+1-'表2-折旧摊销表'!$AC$25)) -> 0
C64: 合作期第25年 | D64: =SUM(F64:AF64) -> 0 | E64: 万元 | AD64: =IF('表2-折旧摊销表'!$AF$25+1-'表2-折旧摊销表'!$AD$25>='表2-折旧摊销表'!$D$14,$AD$38/$D$14,$AD$38/('表2-折旧摊销表'!$AF$25+1-'表2-折旧摊销表'!$AD$25)) -> 0 | AE64: =IF('表2-折旧摊销表'!$AF$25+1-'表2-折旧摊销表'!$AD$25>='表2-折旧摊销表'!$D$14,$AD$38/$D$14,$AD$38/('表2-折旧摊销表'!$AF$25+1-'表2-折旧摊销表'!$AD$25)) -> 0 | AF64: =IF('表2-折旧摊销表'!$AF$25+1-'表2-折旧摊销表'!$AD$25>='表2-折旧摊销表'!$D$14,$AD$38/$D$14,$AD$38/('表2-折旧摊销表'!$AF$25+1-'表2-折旧摊销表'!$AD$25)) -> 0
C65: 合作期第26年 | D65: =SUM(F65:AF65) -> 0 | E65: 万元 | AE65: =IF('表2-折旧摊销表'!$AF$25+1-'表2-折旧摊销表'!$AE$25>='表2-折旧摊销表'!$D$14,$AE$38/$D$14,$AE$38/('表2-折旧摊销表'!$AF$25+1-'表2-折旧摊销表'!$AE$25)) -> 0 | AF65: =IF('表2-折旧摊销表'!$AF$25+1-'表2-折旧摊销表'!$AE$25>='表2-折旧摊销表'!$D$14,$AE$38/$D$14,$AE$38/('表2-折旧摊销表'!$AF$25+1-'表2-折旧摊销表'!$AE$25)) -> 0
C66: 合作期第27年 | D66: =SUM(F66:AF66) -> 0 | E66: 万元 | AF66: =IF('表2-折旧摊销表'!$AF$25+1-'表2-折旧摊销表'!$AF$25>='表2-折旧摊销表'!$D$14,$AF$38/$D$14,$AF$38/('表2-折旧摊销表'!$AF$25+1-'表2-折旧摊销表'!$AF$25)) -> 0
C67: 期末长期待摊费用 | E67: 万元 | F67: =F37+F38-F39 -> 0 | G67: =G37+G38-G39 -> 0 | H67: =H37+H38-H39 -> 0 | I67: =I37+I38-I39 -> 0 | J67: =J37+J38-J39 -> 0 | K67: =K37+K38-K39 -> 0 | L67: =L37+L38-L39 -> 0 | M67: =M37+M38-M39 -> 366.97248 | ... AF67: =AF37+AF38-AF39 -> 0
B68: 3 | C68: 期末无形资产原值 | E68: 万元 | F68: 0 | G68: =F77 -> 0 | H68: =G77 -> 0 | I68: =H77 -> 0 | J68: =参数输入表!$I$441*J26 -> 270 | K68: =参数输入表!$I$441*K26 -> 1620 | L68: =参数输入表!$I$441*L26 -> 1800 | M68: =参数输入表!$I$441*M26 -> 1800 | N68: =参数输入表!$I$441*N26 -> 1800 | O68: =参数输入表!$I$441*O26 -> 1800 | P68: =参数输入表!$I$441*P26 -> 1800 | Q68: =参数输入表!$I$441*Q26 -> 1800 | ... AF68: =参数输入表!$I$441*AF26 -> 1800
C69: 当期新增无形资产投资 | D69: =SUM(F69:AF69) -> 1800 | E69: 万元 | J69: =参数输入表!$I$441*参数输入表!$I$18 -> 540 | K69: =参数输入表!$I$441*参数输入表!$I$19 -> 1260
C70: 新增无形资产投资额累计 | E70: 万元 | J70: =I70+J69 -> 540 | K70: =J70+K69 -> 1800 | L70: =K70+L69 -> 1800 | M70: =L70+M69 -> 1800 | N70: =M70+N69 -> 1800 | O70: =N70+O69 -> 1800 | P70: =O70+P69 -> 1800 | Q70: =P70+Q69 -> 1800 | ... AF70: =AE70+AF69 -> 1800
C71: 期末在建工程（无形资产） | E71: 万元 | J71: =J70-J68 -> 270 | K71: =K70-K68 -> 180 | L71: =L70-L68 -> 0 | M71: =M70-M68 -> 0 | N71: =N70-N68 -> 0 | O71: =O70-O68 -> 0 | P71: =P70-P68 -> 0 | Q71: =Q70-Q68 -> 0 | ... AF71: =AF70-AF68 -> 0
C72: 当期无形资产摊销 | D72: =SUM(F72:AF72) -> 1800 | E72: 万元 | F72: =SUM(F73:F75) -> 0 | G72: =SUM(G73:G75) -> 0 | H72: =SUM(H73:H75) -> 0 | I72: =SUM(I73:I75) -> 0 | J72: =SUM(J73:J75) -> 15 | K72: =SUM(K73:K75) -> 90 | L72: =SUM(L73:L75) -> 100 | M72: =SUM(M73:M75) -> 100 | ... AF72: =SUM(AF73:AF75) -> 0
C73: 建设期第1年投产 | D73: =SUM(F73:AF73) -> 270 | E73: 万元 | J73: =参数输入表!$I$441*(1-参数输入表!$I$444)*参数输入表!$I$35/参数输入表!$I$443 -> 15 | K73: =参数输入表!$I$441*(1-参数输入表!$I$444)*参数输入表!$I$35/参数输入表!$I$443 -> 15 | L73: =参数输入表!$I$441*(1-参数输入表!$I$444)*参数输入表!$I$35/参数输入表!$I$443 -> 15 | M73: =参数输入表!$I$441*(1-参数输入表!$I$444)*参数输入表!$I$35/参数输入表!$I$443 -> 15 | N73: =参数输入表!$I$441*(1-参数输入表!$I$444)*参数输入表!$I$35/参数输入表!$I$443 -> 15 | O73: =参数输入表!$I$441*(1-参数输入表!$I$444)*参数输入表!$I$35/参数输入表!$I$443 -> 15 | P73: =参数输入表!$I$441*(1-参数输入表!$I$444)*参数输入表!$I$35/参数输入表!$I$443 -> 15 | Q73: =参数输入表!$I$441*(1-参数输入表!$I$444)*参数输入表!$I$35/参数输入表!$I$443 -> 15 | ... AA73: =参数输入表!$I$441*(1-参数输入表!$I$444)*参数输入表!$I$35/参数输入表!$I$443 -> 15
C74: 建设期第2年投产 | D74: =SUM(F74:AF74) -> 1350 | E74: 万元 | K74: =参数输入表!$I$441*(1-参数输入表!$I$444)*参数输入表!$I$36/参数输入表!$I$443 -> 75 | L74: =参数输入表!$I$441*(1-参数输入表!$I$444)*参数输入表!$I$36/参数输入表!$I$443 -> 75 | M74: =参数输入表!$I$441*(1-参数输入表!$I$444)*参数输入表!$I$36/参数输入表!$I$443 -> 75 | N74: =参数输入表!$I$441*(1-参数输入表!$I$444)*参数输入表!$I$36/参数输入表!$I$443 -> 75 | O74: =参数输入表!$I$441*(1-参数输入表!$I$444)*参数输入表!$I$36/参数输入表!$I$443 -> 75 | P74: =参数输入表!$I$441*(1-参数输入表!$I$444)*参数输入表!$I$36/参数输入表!$I$443 -> 75 | Q74: =参数输入表!$I$441*(1-参数输入表!$I$444)*参数输入表!$I$36/参数输入表!$I$443 -> 75 | R74: =参数输入表!$I$441*(1-参数输入表!$I$444)*参数输入表!$I$36/参数输入表!$I$443 -> 75 | ... AB74: =参数输入表!$I$441*(1-参数输入表!$I$444)*参数输入表!$I$36/参数输入表!$I$443 -> 75
C75: 完全投产 | D75: =SUM(F75:AF75) -> 180 | E75: 万元 | L75: =参数输入表!$I$441*(1-参数输入表!$I$444)*参数输入表!$I$37/参数输入表!$I$443 -> 10 | M75: =参数输入表!$I$441*(1-参数输入表!$I$444)*参数输入表!$I$37/参数输入表!$I$443 -> 10 | N75: =参数输入表!$I$441*(1-参数输入表!$I$444)*参数输入表!$I$37/参数输入表!$I$443 -> 10 | O75: =参数输入表!$I$441*(1-参数输入表!$I$444)*参数输入表!$I$37/参数输入表!$I$443 -> 10 | P75: =参数输入表!$I$441*(1-参数输入表!$I$444)*参数输入表!$I$37/参数输入表!$I$443 -> 10 | Q75: =参数输入表!$I$441*(1-参数输入表!$I$444)*参数输入表!$I$37/参数输入表!$I$443 -> 10 | R75: =参数输入表!$I$441*(1-参数输入表!$I$444)*参数输入表!$I$37/参数输入表!$I$443 -> 10 | S75: =参数输入表!$I$441*(1-参数输入表!$I$444)*参数输入表!$I$37/参数输入表!$I$443 -> 10 | ... AC75: =参数输入表!$I$441*(1-参数输入表!$I$444)*参数输入表!$I$37/参数输入表!$I$443 -> 10
C76: 无形资产摊销累计 | E76: 万元 | J76: =J72 -> 15 | K76: =J76+K72 -> 105 | L76: =K76+L72 -> 205 | M76: =L76+M72 -> 305 | N76: =M76+N72 -> 405 | O76: =N76+O72 -> 505 | P76: =O76+P72 -> 605 | Q76: =P76+Q72 -> 705 | R76: =Q76+R72 -> 805 | ... AF76: =AE76+AF72 -> 1800
C77: 期末无形资产净值 | E77: 万元 | F77: =F68+F69-F72 -> 0 | G77: =G68+G69-G72 -> 0 | H77: =H68+H69-H72 -> 0 | I77: =I68+I69-I72 -> 0 | J77: =J68-J76 -> 255 | K77: =K68-K76 -> 1515 | L77: =L68-L76 -> 1595 | M77: =M68-M76 -> 1495 | N77: =N68-N76 -> 1395 | O77: =O68-O76 -> 1295 | P77: =P68-P76 -> 1195 | Q77: =Q68-Q76 -> 1095 | ... AF77: =AF68-AF76 -> 0
B78: 4 | C78: 期初大修及更新重置资产净值 | E78: 万元 | F78: 0 | G78: =F109 -> 0 | H78: =G109 -> 0 | I78: =H109 -> 0 | J78: =I109 -> 0 | K78: =J109 -> 0 | L78: =K109 -> 0 | M78: =L109 -> 0 | N78: =M109 -> 0 | ... AF78: =AE109 -> 0
C79: 当期新增大修及更新重置资产 | D79: =SUM(F79:AF79) -> 0 | E79: 万元 | F79: =IF(F25-参数输入表!$I$14<=0,0) -> 0 | G79: =IF(G25-参数输入表!$I$14<=0,0) -> 0 | H79: =参数输入表!I498/(1+参数输入表!$I$525) -> 0 | I79: =参数输入表!I499/(1+参数输入表!$I$525) -> 0 | J79: =参数输入表!I500/(1+参数输入表!$I$525) -> 0 | K79: =参数输入表!I501/(1+参数输入表!$I$525) -> 0 | L79: =参数输入表!I502/(1+参数输入表!$I$525) -> 0 | M79: =参数输入表!I503/(1+参数输入表!$I$525) -> 0 | N79: =参数输入表!I504/(1+参数输入表!$I$525) -> 0 | O79: =参数输入表!I505/(1+参数输入表!$I$525) -> 0 | P79: =参数输入表!I506/(1+参数输入表!$I$525) -> 0 | Q79: =参数输入表!I507/(1+参数输入表!$I$525) -> 0 | R79: =参数输入表!I508/(1+参数输入表!$I$525) -> 0 | S79: =参数输入表!I509/(1+参数输入表!$I$525) -> 0 | T79: =参数输入表!I510/(1+参数输入表!$I$525) -> 0 | U79: =参数输入表!I511/(1+参数输入表!$I$525) -> 0 | V79: =参数输入表!I512/(1+参数输入表!$I$525) -> 0 | W79: =参数输入表!I513/(1+参数输入表!$I$525) -> 0 | X79: =参数输入表!I514/(1+参数输入表!$I$525) -> 0 | Y79: =参数输入表!I515/(1+参数输入表!$I$525) -> 0 | Z79: =参数输入表!I516/(1+参数输入表!$I$525) -> 0 | AA79: =参数输入表!I517/(1+参数输入表!$I$525) -> 0 | AB79: =参数输入表!I518/(1+参数输入表!$I$525) -> 0 | AC79: =参数输入表!I519/(1+参数输入表!$I$525) -> 0 | AD79: =参数输入表!I520/(1+参数输入表!$I$525) -> 0 | AE79: =参数输入表!I521/(1+参数输入表!$I$525) -> 0 | AF79: =参数输入表!I522/(1+参数输入表!$I$525) -> 0
C80: 当期大修及更新重置资产折旧摊销 | D80: =SUM(F80:AF80) -> 0 | E80: 万元 | F80: =SUM(F81:F107) -> 0 | G80: =SUM(G81:G107) -> 0 | H80: =SUM(H81:H107) -> 0 | I80: =SUM(I81:I107) -> 0 | J80: =SUM(J81:J107) -> 0 | K80: =SUM(K81:K107) -> 0 | L80: =SUM(L81:L107) -> 0 | M80: =SUM(M81:M107) -> 0 | ... AF80: =SUM(AF81:AF107) -> 0
C81: 合作期第1年 | D81: =SUM(F81:AF81) -> 0 | E81: 万元 | F81: =IF('表2-折旧摊销表'!$AF$25+1-'表2-折旧摊销表'!$F$25>='表2-折旧摊销表'!$D$21,$F$79/$D$21,$F$79/('表2-折旧摊销表'!$AF$25+1-'表2-折旧摊销表'!$F$25)) -> 0 | G81: =IF('表2-折旧摊销表'!$AF$25+1-'表2-折旧摊销表'!$F$25>='表2-折旧摊销表'!$D$21,$F$79/$D$21,$F$79/('表2-折旧摊销表'!$AF$25+1-'表2-折旧摊销表'!$F$25)) -> 0 | H81: =IF('表2-折旧摊销表'!$AF$25+1-'表2-折旧摊销表'!$F$25>='表2-折旧摊销表'!$D$21,$F$79/$D$21,$F$79/('表2-折旧摊销表'!$AF$25+1-'表2-折旧摊销表'!$F$25)) -> 0 | I81: =IF('表2-折旧摊销表'!$AF$25+1-'表2-折旧摊销表'!$F$25>='表2-折旧摊销表'!$D$21,$F$79/$D$21,$F$79/('表2-折旧摊销表'!$AF$25+1-'表2-折旧摊销表'!$F$25)) -> 0 | J81: =IF('表2-折旧摊销表'!$AF$25+1-'表2-折旧摊销表'!$F$25>='表2-折旧摊销表'!$D$21,$F$79/$D$21,$F$79/('表2-折旧摊销表'!$AF$25+1-'表2-折旧摊销表'!$F$25)) -> 0 | K81: =IF('表2-折旧摊销表'!$AF$25+1-'表2-折旧摊销表'!$F$25>='表2-折旧摊销表'!$D$21,$F$79/$D$21,$F$79/('表2-折旧摊销表'!$AF$25+1-'表2-折旧摊销表'!$F$25)) -> 0 | L81: =IF('表2-折旧摊销表'!$AF$25+1-'表2-折旧摊销表'!$F$25>='表2-折旧摊销表'!$D$21,$F$79/$D$21,$F$79/('表2-折旧摊销表'!$AF$25+1-'表2-折旧摊销表'!$F$25)) -> 0 | M81: =IF('表2-折旧摊销表'!$AF$25+1-'表2-折旧摊销表'!$F$25>='表2-折旧摊销表'!$D$21,$F$79/$D$21,$F$79/('表2-折旧摊销表'!$AF$25+1-'表2-折旧摊销表'!$F$25)) -> 0 | ... O81: =IF('表2-折旧摊销表'!$AF$25+1-'表2-折旧摊销表'!$F$25>='表2-折旧摊销表'!$D$21,$F$79/$D$21,$F$79/('表2-折旧摊销表'!$AF$25+1-'表2-折旧摊销表'!$F$25)) -> 0
C82: 合作期第2年 | D82: =SUM(F82:AF82) -> 0 | E82: 万元 | G82: =IF('表2-折旧摊销表'!$AF$25+1-'表2-折旧摊销表'!$G$25>='表2-折旧摊销表'!$D$21,$G$79/$D$21,$G$79/('表2-折旧摊销表'!$AF$25+1-'表2-折旧摊销表'!$G$25)) -> 0 | H82: =IF('表2-折旧摊销表'!$AF$25+1-'表2-折旧摊销表'!$G$25>='表2-折旧摊销表'!$D$21,$G$79/$D$21,$G$79/('表2-折旧摊销表'!$AF$25+1-'表2-折旧摊销表'!$G$25)) -> 0 | I82: =IF('表2-折旧摊销表'!$AF$25+1-'表2-折旧摊销表'!$G$25>='表2-折旧摊销表'!$D$21,$G$79/$D$21,$G$79/('表2-折旧摊销表'!$AF$25+1-'表2-折旧摊销表'!$G$25)) -> 0 | J82: =IF('表2-折旧摊销表'!$AF$25+1-'表2-折旧摊销表'!$G$25>='表2-折旧摊销表'!$D$21,$G$79/$D$21,$G$79/('表2-折旧摊销表'!$AF$25+1-'表2-折旧摊销表'!$G$25)) -> 0 | K82: =IF('表2-折旧摊销表'!$AF$25+1-'表2-折旧摊销表'!$G$25>='表2-折旧摊销表'!$D$21,$G$79/$D$21,$G$79/('表2-折旧摊销表'!$AF$25+1-'表2-折旧摊销表'!$G$25)) -> 0 | L82: =IF('表2-折旧摊销表'!$AF$25+1-'表2-折旧摊销表'!$G$25>='表2-折旧摊销表'!$D$21,$G$79/$D$21,$G$79/('表2-折旧摊销表'!$AF$25+1-'表2-折旧摊销表'!$G$25)) -> 0 | M82: =IF('表2-折旧摊销表'!$AF$25+1-'表2-折旧摊销表'!$G$25>='表2-折旧摊销表'!$D$21,$G$79/$D$21,$G$79/('表2-折旧摊销表'!$AF$25+1-'表2-折旧摊销表'!$G$25)) -> 0 | N82: =IF('表2-折旧摊销表'!$AF$25+1-'表2-折旧摊销表'!$G$25>='表2-折旧摊销表'!$D$21,$G$79/$D$21,$G$79/('表2-折旧摊销表'!$AF$25+1-'表2-折旧摊销表'!$G$25)) -> 0 | ... P82: =IF('表2-折旧摊销表'!$AF$25+1-'表2-折旧摊销表'!$G$25>='表2-折旧摊销表'!$D$21,$G$79/$D$21,$G$79/('表2-折旧摊销表'!$AF$25+1-'表2-折旧摊销表'!$G$25)) -> 0
C83: 合作期第3年 | D83: =SUM(F83:AF83) -> 0 | E83: 万元 | H83: =IF('表2-折旧摊销表'!$AF$25+1-'表2-折旧摊销表'!$H$25>='表2-折旧摊销表'!$D$21,$H$79/$D$21,$H$79/('表2-折旧摊销表'!$AF$25+1-'表2-折旧摊销表'!$H$25)) -> 0 | I83: =IF('表2-折旧摊销表'!$AF$25+1-'表2-折旧摊销表'!$H$25>='表2-折旧摊销表'!$D$21,$H$79/$D$21,$H$79/('表2-折旧摊销表'!$AF$25+1-'表2-折旧摊销表'!$H$25)) -> 0 | J83: =IF('表2-折旧摊销表'!$AF$25+1-'表2-折旧摊销表'!$H$25>='表2-折旧摊销表'!$D$21,$H$79/$D$21,$H$79/('表2-折旧摊销表'!$AF$25+1-'表2-折旧摊销表'!$H$25)) -> 0 | K83: =IF('表2-折旧摊销表'!$AF$25+1-'表2-折旧摊销表'!$H$25>='表2-折旧摊销表'!$D$21,$H$79/$D$21,$H$79/('表2-折旧摊销表'!$AF$25+1-'表2-折旧摊销表'!$H$25)) -> 0 | L83: =IF('表2-折旧摊销表'!$AF$25+1-'表2-折旧摊销表'!$H$25>='表2-折旧摊销表'!$D$21,$H$79/$D$21,$H$79/('表2-折旧摊销表'!$AF$25+1-'表2-折旧摊销表'!$H$25)) -> 0 | M83: =IF('表2-折旧摊销表'!$AF$25+1-'表2-折旧摊销表'!$H$25>='表2-折旧摊销表'!$D$21,$H$79/$D$21,$H$79/('表2-折旧摊销表'!$AF$25+1-'表2-折旧摊销表'!$H$25)) -> 0 | N83: =IF('表2-折旧摊销表'!$AF$25+1-'表2-折旧摊销表'!$H$25>='表2-折旧摊销表'!$D$21,$H$79/$D$21,$H$79/('表2-折旧摊销表'!$AF$25+1-'表2-折旧摊销表'!$H$25)) -> 0 | O83: =IF('表2-折旧摊销表'!$AF$25+1-'表2-折旧摊销表'!$H$25>='表2-折旧摊销表'!$D$21,$H$79/$D$21,$H$79/('表2-折旧摊销表'!$AF$25+1-'表2-折旧摊销表'!$H$25)) -> 0 | ... Q83: =IF('表2-折旧摊销表'!$AF$25+1-'表2-折旧摊销表'!$H$25>='表2-折旧摊销表'!$D$21,$H$79/$D$21,$H$79/('表2-折旧摊销表'!$AF$25+1-'表2-折旧摊销表'!$H$25)) -> 0
C84: 合作期第4年 | D84: =SUM(F84:AF84) -> 0 | E84: 万元 | I84: =IF('表2-折旧摊销表'!$AF$25+1-'表2-折旧摊销表'!$I$25>='表2-折旧摊销表'!$D$21,$I$79/$D$21,$I$79/('表2-折旧摊销表'!$AF$25+1-'表2-折旧摊销表'!$I$25)) -> 0 | J84: =IF('表2-折旧摊销表'!$AF$25+1-'表2-折旧摊销表'!$I$25>='表2-折旧摊销表'!$D$21,$I$79/$D$21,$I$79/('表2-折旧摊销表'!$AF$25+1-'表2-折旧摊销表'!$I$25)) -> 0 | K84: =IF('表2-折旧摊销表'!$AF$25+1-'表2-折旧摊销表'!$I$25>='表2-折旧摊销表'!$D$21,$I$79/$D$21,$I$79/('表2-折旧摊销表'!$AF$25+1-'表2-折旧摊销表'!$I$25)) -> 0 | L84: =IF('表2-折旧摊销表'!$AF$25+1-'表2-折旧摊销表'!$I$25>='表2-折旧摊销表'!$D$21,$I$79/$D$21,$I$79/('表2-折旧摊销表'!$AF$25+1-'表2-折旧摊销表'!$I$25)) -> 0 | M84: =IF('表2-折旧摊销表'!$AF$25+1-'表2-折旧摊销表'!$I$25>='表2-折旧摊销表'!$D$21,$I$79/$D$21,$I$79/('表2-折旧摊销表'!$AF$25+1-'表2-折旧摊销表'!$I$25)) -> 0 | N84: =IF('表2-折旧摊销表'!$AF$25+1-'表2-折旧摊销表'!$I$25>='表2-折旧摊销表'!$D$21,$I$79/$D$21,$I$79/('表2-折旧摊销表'!$AF$25+1-'表2-折旧摊销表'!$I$25)) -> 0 | O84: =IF('表2-折旧摊销表'!$AF$25+1-'表2-折旧摊销表'!$I$25>='表2-折旧摊销表'!$D$21,$I$79/$D$21,$I$79/('表2-折旧摊销表'!$AF$25+1-'表2-折旧摊销表'!$I$25)) -> 0 | P84: =IF('表2-折旧摊销表'!$AF$25+1-'表2-折旧摊销表'!$I$25>='表2-折旧摊销表'!$D$21,$I$79/$D$21,$I$79/('表2-折旧摊销表'!$AF$25+1-'表2-折旧摊销表'!$I$25)) -> 0 | ... R84: =IF('表2-折旧摊销表'!$AF$25+1-'表2-折旧摊销表'!$I$25>='表2-折旧摊销表'!$D$21,$I$79/$D$21,$I$79/('表2-折旧摊销表'!$AF$25+1-'表2-折旧摊销表'!$I$25)) -> 0
C85: 合作期第5年 | D85: =SUM(F85:AF85) -> 0 | E85: 万元 | J85: =IF('表2-折旧摊销表'!$AF$25+1-'表2-折旧摊销表'!$J$25>='表2-折旧摊销表'!$D$21,$J$79/$D$21,$J$79/('表2-折旧摊销表'!$AF$25+1-'表2-折旧摊销表'!$J$25)) -> 0 | K85: =IF('表2-折旧摊销表'!$AF$25+1-'表2-折旧摊销表'!$J$25>='表2-折旧摊销表'!$D$21,$J$79/$D$21,$J$79/('表2-折旧摊销表'!$AF$25+1-'表2-折旧摊销表'!$J$25)) -> 0 | L85: =IF('表2-折旧摊销表'!$AF$25+1-'表2-折旧摊销表'!$J$25>='表2-折旧摊销表'!$D$21,$J$79/$D$21,$J$79/('表2-折旧摊销表'!$AF$25+1-'表2-折旧摊销表'!$J$25)) -> 0 | M85: =IF('表2-折旧摊销表'!$AF$25+1-'表2-折旧摊销表'!$J$25>='表2-折旧摊销表'!$D$21,$J$79/$D$21,$J$79/('表2-折旧摊销表'!$AF$25+1-'表2-折旧摊销表'!$J$25)) -> 0 | N85: =IF('表2-折旧摊销表'!$AF$25+1-'表2-折旧摊销表'!$J$25>='表2-折旧摊销表'!$D$21,$J$79/$D$21,$J$79/('表2-折旧摊销表'!$AF$25+1-'表2-折旧摊销表'!$J$25)) -> 0 | O85: =IF('表2-折旧摊销表'!$AF$25+1-'表2-折旧摊销表'!$J$25>='表2-折旧摊销表'!$D$21,$J$79/$D$21,$J$79/('表2-折旧摊销表'!$AF$25+1-'表2-折旧摊销表'!$J$25)) -> 0 | P85: =IF('表2-折旧摊销表'!$AF$25+1-'表2-折旧摊销表'!$J$25>='表2-折旧摊销表'!$D$21,$J$79/$D$21,$J$79/('表2-折旧摊销表'!$AF$25+1-'表2-折旧摊销表'!$J$25)) -> 0 | Q85: =IF('表2-折旧摊销表'!$AF$25+1-'表2-折旧摊销表'!$J$25>='表2-折旧摊销表'!$D$21,$J$79/$D$21,$J$79/('表2-折旧摊销表'!$AF$25+1-'表2-折旧摊销表'!$J$25)) -> 0 | ... S85: =IF('表2-折旧摊销表'!$AF$25+1-'表2-折旧摊销表'!$J$25>='表2-折旧摊销表'!$D$21,$J$79/$D$21,$J$79/('表2-折旧摊销表'!$AF$25+1-'表2-折旧摊销表'!$J$25)) -> 0
C86: 合作期第6年 | D86: =SUM(F86:AF86) -> 0 | E86: 万元 | K86: =IF('表2-折旧摊销表'!$AF$25+1-'表2-折旧摊销表'!$K$25>='表2-折旧摊销表'!$D$21,$K$79/$D$21,$K$79/('表2-折旧摊销表'!$AF$25+1-'表2-折旧摊销表'!$K$25)) -> 0 | L86: =IF('表2-折旧摊销表'!$AF$25+1-'表2-折旧摊销表'!$K$25>='表2-折旧摊销表'!$D$21,$K$79/$D$21,$K$79/('表2-折旧摊销表'!$AF$25+1-'表2-折旧摊销表'!$K$25)) -> 0 | M86: =IF('表2-折旧摊销表'!$AF$25+1-'表2-折旧摊销表'!$K$25>='表2-折旧摊销表'!$D$21,$K$79/$D$21,$K$79/('表2-折旧摊销表'!$AF$25+1-'表2-折旧摊销表'!$K$25)) -> 0 | N86: =IF('表2-折旧摊销表'!$AF$25+1-'表2-折旧摊销表'!$K$25>='表2-折旧摊销表'!$D$21,$K$79/$D$21,$K$79/('表2-折旧摊销表'!$AF$25+1-'表2-折旧摊销表'!$K$25)) -> 0 | O86: =IF('表2-折旧摊销表'!$AF$25+1-'表2-折旧摊销表'!$K$25>='表2-折旧摊销表'!$D$21,$K$79/$D$21,$K$79/('表2-折旧摊销表'!$AF$25+1-'表2-折旧摊销表'!$K$25)) -> 0 | P86: =IF('表2-折旧摊销表'!$AF$25+1-'表2-折旧摊销表'!$K$25>='表2-折旧摊销表'!$D$21,$K$79/$D$21,$K$79/('表2-折旧摊销表'!$AF$25+1-'表2-折旧摊销表'!$K$25)) -> 0 | Q86: =IF('表2-折旧摊销表'!$AF$25+1-'表2-折旧摊销表'!$K$25>='表2-折旧摊销表'!$D$21,$K$79/$D$21,$K$79/('表2-折旧摊销表'!$AF$25+1-'表2-折旧摊销表'!$K$25)) -> 0 | R86: =IF('表2-折旧摊销表'!$AF$25+1-'表2-折旧摊销表'!$K$25>='表2-折旧摊销表'!$D$21,$K$79/$D$21,$K$79/('表2-折旧摊销表'!$AF$25+1-'表2-折旧摊销表'!$K$25)) -> 0 | ... T86: =IF('表2-折旧摊销表'!$AF$25+1-'表2-折旧摊销表'!$K$25>='表2-折旧摊销表'!$D$21,$K$79/$D$21,$K$79/('表2-折旧摊销表'!$AF$25+1-'表2-折旧摊销表'!$K$25)) -> 0
C87: 合作期第7年 | D87: =SUM(F87:AF87) -> 0 | E87: 万元 | L87: =IF('表2-折旧摊销表'!$AF$25+1-'表2-折旧摊销表'!$L$25>='表2-折旧摊销表'!$D$21,$L$79/$D$21,$L$79/('表2-折旧摊销表'!$AF$25+1-'表2-折旧摊销表'!$L$25)) -> 0 | M87: =IF('表2-折旧摊销表'!$AF$25+1-'表2-折旧摊销表'!$L$25>='表2-折旧摊销表'!$D$21,$L$79/$D$21,$L$79/('表2-折旧摊销表'!$AF$25+1-'表2-折旧摊销表'!$L$25)) -> 0 | N87: =IF('表2-折旧摊销表'!$AF$25+1-'表2-折旧摊销表'!$L$25>='表2-折旧摊销表'!$D$21,$L$79/$D$21,$L$79/('表2-折旧摊销表'!$AF$25+1-'表2-折旧摊销表'!$L$25)) -> 0 | O87: =IF('表2-折旧摊销表'!$AF$25+1-'表2-折旧摊销表'!$L$25>='表2-折旧摊销表'!$D$21,$L$79/$D$21,$L$79/('表2-折旧摊销表'!$AF$25+1-'表2-折旧摊销表'!$L$25)) -> 0 | P87: =IF('表2-折旧摊销表'!$AF$25+1-'表2-折旧摊销表'!$L$25>='表2-折旧摊销表'!$D$21,$L$79/$D$21,$L$79/('表2-折旧摊销表'!$AF$25+1-'表2-折旧摊销表'!$L$25)) -> 0 | Q87: =IF('表2-折旧摊销表'!$AF$25+1-'表2-折旧摊销表'!$L$25>='表2-折旧摊销表'!$D$21,$L$79/$D$21,$L$79/('表2-折旧摊销表'!$AF$25+1-'表2-折旧摊销表'!$L$25)) -> 0 | R87: =IF('表2-折旧摊销表'!$AF$25+1-'表2-折旧摊销表'!$L$25>='表2-折旧摊销表'!$D$21,$L$79/$D$21,$L$79/('表2-折旧摊销表'!$AF$25+1-'表2-折旧摊销表'!$L$25)) -> 0 | S87: =IF('表2-折旧摊销表'!$AF$25+1-'表2-折旧摊销表'!$L$25>='表2-折旧摊销表'!$D$21,$L$79/$D$21,$L$79/('表2-折旧摊销表'!$AF$25+1-'表2-折旧摊销表'!$L$25)) -> 0 | ... U87: =IF('表2-折旧摊销表'!$AF$25+1-'表2-折旧摊销表'!$L$25>='表2-折旧摊销表'!$D$21,$L$79/$D$21,$L$79/('表2-折旧摊销表'!$AF$25+1-'表2-折旧摊销表'!$L$25)) -> 0
C88: 合作期第8年 | D88: =SUM(F88:AF88) -> 0 | E88: 万元 | M88: =IF('表2-折旧摊销表'!$AF$25+1-'表2-折旧摊销表'!$M$25>='表2-折旧摊销表'!$D$21,$M$79/$D$21,$M$79/('表2-折旧摊销表'!$AF$25+1-'表2-折旧摊销表'!$M$25)) -> 0 | N88: =IF('表2-折旧摊销表'!$AF$25+1-'表2-折旧摊销表'!$M$25>='表2-折旧摊销表'!$D$21,$M$79/$D$21,$M$79/('表2-折旧摊销表'!$AF$25+1-'表2-折旧摊销表'!$M$25)) -> 0 | O88: =IF('表2-折旧摊销表'!$AF$25+1-'表2-折旧摊销表'!$M$25>='表2-折旧摊销表'!$D$21,$M$79/$D$21,$M$79/('表2-折旧摊销表'!$AF$25+1-'表2-折旧摊销表'!$M$25)) -> 0 | P88: =IF('表2-折旧摊销表'!$AF$25+1-'表2-折旧摊销表'!$M$25>='表2-折旧摊销表'!$D$21,$M$79/$D$21,$M$79/('表2-折旧摊销表'!$AF$25+1-'表2-折旧摊销表'!$M$25)) -> 0 | Q88: =IF('表2-折旧摊销表'!$AF$25+1-'表2-折旧摊销表'!$M$25>='表2-折旧摊销表'!$D$21,$M$79/$D$21,$M$79/('表2-折旧摊销表'!$AF$25+1-'表2-折旧摊销表'!$M$25)) -> 0 | R88: =IF('表2-折旧摊销表'!$AF$25+1-'表2-折旧摊销表'!$M$25>='表2-折旧摊销表'!$D$21,$M$79/$D$21,$M$79/('表2-折旧摊销表'!$AF$25+1-'表2-折旧摊销表'!$M$25)) -> 0 | S88: =IF('表2-折旧摊销表'!$AF$25+1-'表2-折旧摊销表'!$M$25>='表2-折旧摊销表'!$D$21,$M$79/$D$21,$M$79/('表2-折旧摊销表'!$AF$25+1-'表2-折旧摊销表'!$M$25)) -> 0 | T88: =IF('表2-折旧摊销表'!$AF$25+1-'表2-折旧摊销表'!$M$25>='表2-折旧摊销表'!$D$21,$M$79/$D$21,$M$79/('表2-折旧摊销表'!$AF$25+1-'表2-折旧摊销表'!$M$25)) -> 0 | ... V88: =IF('表2-折旧摊销表'!$AF$25+1-'表2-折旧摊销表'!$M$25>='表2-折旧摊销表'!$D$21,$M$79/$D$21,$M$79/('表2-折旧摊销表'!$AF$25+1-'表2-折旧摊销表'!$M$25)) -> 0
C89: 合作期第9年 | D89: =SUM(F89:AF89) -> 0 | E89: 万元 | N89: =IF('表2-折旧摊销表'!$AF$25+1-'表2-折旧摊销表'!$N$25>='表2-折旧摊销表'!$D$21,$N$79/$D$21,$N$79/('表2-折旧摊销表'!$AF$25+1-'表2-折旧摊销表'!$N$25)) -> 0 | O89: =IF('表2-折旧摊销表'!$AF$25+1-'表2-折旧摊销表'!$N$25>='表2-折旧摊销表'!$D$21,$N$79/$D$21,$N$79/('表2-折旧摊销表'!$AF$25+1-'表2-折旧摊销表'!$N$25)) -> 0 | P89: =IF('表2-折旧摊销表'!$AF$25+1-'表2-折旧摊销表'!$N$25>='表2-折旧摊销表'!$D$21,$N$79/$D$21,$N$79/('表2-折旧摊销表'!$AF$25+1-'表2-折旧摊销表'!$N$25)) -> 0 | Q89: =IF('表2-折旧摊销表'!$AF$25+1-'表2-折旧摊销表'!$N$25>='表2-折旧摊销表'!$D$21,$N$79/$D$21,$N$79/('表2-折旧摊销表'!$AF$25+1-'表2-折旧摊销表'!$N$25)) -> 0 | R89: =IF('表2-折旧摊销表'!$AF$25+1-'表2-折旧摊销表'!$N$25>='表2-折旧摊销表'!$D$21,$N$79/$D$21,$N$79/('表2-折旧摊销表'!$AF$25+1-'表2-折旧摊销表'!$N$25)) -> 0 | S89: =IF('表2-折旧摊销表'!$AF$25+1-'表2-折旧摊销表'!$N$25>='表2-折旧摊销表'!$D$21,$N$79/$D$21,$N$79/('表2-折旧摊销表'!$AF$25+1-'表2-折旧摊销表'!$N$25)) -> 0 | T89: =IF('表2-折旧摊销表'!$AF$25+1-'表2-折旧摊销表'!$N$25>='表2-折旧摊销表'!$D$21,$N$79/$D$21,$N$79/('表2-折旧摊销表'!$AF$25+1-'表2-折旧摊销表'!$N$25)) -> 0 | U89: =IF('表2-折旧摊销表'!$AF$25+1-'表2-折旧摊销表'!$N$25>='表2-折旧摊销表'!$D$21,$N$79/$D$21,$N$79/('表2-折旧摊销表'!$AF$25+1-'表2-折旧摊销表'!$N$25)) -> 0 | ... W89: =IF('表2-折旧摊销表'!$AF$25+1-'表2-折旧摊销表'!$N$25>='表2-折旧摊销表'!$D$21,$N$79/$D$21,$N$79/('表2-折旧摊销表'!$AF$25+1-'表2-折旧摊销表'!$N$25)) -> 0
C90: 合作期第10年 | D90: =SUM(F90:AF90) -> 0 | E90: 万元 | O90: =IF('表2-折旧摊销表'!$AF$25+1-'表2-折旧摊销表'!$O$25>='表2-折旧摊销表'!$D$21,$O$79/$D$21,$O$79/('表2-折旧摊销表'!$AF$25+1-'表2-折旧摊销表'!$O$25)) -> 0 | P90: =IF('表2-折旧摊销表'!$AF$25+1-'表2-折旧摊销表'!$O$25>='表2-折旧摊销表'!$D$21,$O$79/$D$21,$O$79/('表2-折旧摊销表'!$AF$25+1-'表2-折旧摊销表'!$O$25)) -> 0 | Q90: =IF('表2-折旧摊销表'!$AF$25+1-'表2-折旧摊销表'!$O$25>='表2-折旧摊销表'!$D$21,$O$79/$D$21,$O$79/('表2-折旧摊销表'!$AF$25+1-'表2-折旧摊销表'!$O$25)) -> 0 | R90: =IF('表2-折旧摊销表'!$AF$25+1-'表2-折旧摊销表'!$O$25>='表2-折旧摊销表'!$D$21,$O$79/$D$21,$O$79/('表2-折旧摊销表'!$AF$25+1-'表2-折旧摊销表'!$O$25)) -> 0 | S90: =IF('表2-折旧摊销表'!$AF$25+1-'表2-折旧摊销表'!$O$25>='表2-折旧摊销表'!$D$21,$O$79/$D$21,$O$79/('表2-折旧摊销表'!$AF$25+1-'表2-折旧摊销表'!$O$25)) -> 0 | T90: =IF('表2-折旧摊销表'!$AF$25+1-'表2-折旧摊销表'!$O$25>='表2-折旧摊销表'!$D$21,$O$79/$D$21,$O$79/('表2-折旧摊销表'!$AF$25+1-'表2-折旧摊销表'!$O$25)) -> 0 | U90: =IF('表2-折旧摊销表'!$AF$25+1-'表2-折旧摊销表'!$O$25>='表2-折旧摊销表'!$D$21,$O$79/$D$21,$O$79/('表2-折旧摊销表'!$AF$25+1-'表2-折旧摊销表'!$O$25)) -> 0 | V90: =IF('表2-折旧摊销表'!$AF$25+1-'表2-折旧摊销表'!$O$25>='表2-折旧摊销表'!$D$21,$O$79/$D$21,$O$79/('表2-折旧摊销表'!$AF$25+1-'表2-折旧摊销表'!$O$25)) -> 0 | ... X90: =IF('表2-折旧摊销表'!$AF$25+1-'表2-折旧摊销表'!$O$25>='表2-折旧摊销表'!$D$21,$O$79/$D$21,$O$79/('表2-折旧摊销表'!$AF$25+1-'表2-折旧摊销表'!$O$25)) -> 0
C91: 合作期第11年 | D91: =SUM(F91:AF91) -> 0 | E91: 万元 | P91: =IF('表2-折旧摊销表'!$AF$25+1-'表2-折旧摊销表'!$P$25>='表2-折旧摊销表'!$D$21,$P$79/$D$21,$P$79/('表2-折旧摊销表'!$AF$25+1-'表2-折旧摊销表'!$P$25)) -> 0 | Q91: =IF('表2-折旧摊销表'!$AF$25+1-'表2-折旧摊销表'!$P$25>='表2-折旧摊销表'!$D$21,$P$79/$D$21,$P$79/('表2-折旧摊销表'!$AF$25+1-'表2-折旧摊销表'!$P$25)) -> 0 | R91: =IF('表2-折旧摊销表'!$AF$25+1-'表2-折旧摊销表'!$P$25>='表2-折旧摊销表'!$D$21,$P$79/$D$21,$P$79/('表2-折旧摊销表'!$AF$25+1-'表2-折旧摊销表'!$P$25)) -> 0 | S91: =IF('表2-折旧摊销表'!$AF$25+1-'表2-折旧摊销表'!$P$25>='表2-折旧摊销表'!$D$21,$P$79/$D$21,$P$79/('表2-折旧摊销表'!$AF$25+1-'表2-折旧摊销表'!$P$25)) -> 0 | T91: =IF('表2-折旧摊销表'!$AF$25+1-'表2-折旧摊销表'!$P$25>='表2-折旧摊销表'!$D$21,$P$79/$D$21,$P$79/('表2-折旧摊销表'!$AF$25+1-'表2-折旧摊销表'!$P$25)) -> 0 | U91: =IF('表2-折旧摊销表'!$AF$25+1-'表2-折旧摊销表'!$P$25>='表2-折旧摊销表'!$D$21,$P$79/$D$21,$P$79/('表2-折旧摊销表'!$AF$25+1-'表2-折旧摊销表'!$P$25)) -> 0 | V91: =IF('表2-折旧摊销表'!$AF$25+1-'表2-折旧摊销表'!$P$25>='表2-折旧摊销表'!$D$21,$P$79/$D$21,$P$79/('表2-折旧摊销表'!$AF$25+1-'表2-折旧摊销表'!$P$25)) -> 0 | W91: =IF('表2-折旧摊销表'!$AF$25+1-'表2-折旧摊销表'!$P$25>='表2-折旧摊销表'!$D$21,$P$79/$D$21,$P$79/('表2-折旧摊销表'!$AF$25+1-'表2-折旧摊销表'!$P$25)) -> 0 | ... Y91: =IF('表2-折旧摊销表'!$AF$25+1-'表2-折旧摊销表'!$P$25>='表2-折旧摊销表'!$D$21,$P$79/$D$21,$P$79/('表2-折旧摊销表'!$AF$25+1-'表2-折旧摊销表'!$P$25)) -> 0
C92: 合作期第12年 | D92: =SUM(F92:AF92) -> 0 | E92: 万元 | Q92: =IF('表2-折旧摊销表'!$AF$25+1-'表2-折旧摊销表'!$Q$25>='表2-折旧摊销表'!$D$21,$Q$79/$D$21,$Q$79/('表2-折旧摊销表'!$AF$25+1-'表2-折旧摊销表'!$Q$25)) -> 0 | R92: =IF('表2-折旧摊销表'!$AF$25+1-'表2-折旧摊销表'!$Q$25>='表2-折旧摊销表'!$D$21,$Q$79/$D$21,$Q$79/('表2-折旧摊销表'!$AF$25+1-'表2-折旧摊销表'!$Q$25)) -> 0 | S92: =IF('表2-折旧摊销表'!$AF$25+1-'表2-折旧摊销表'!$Q$25>='表2-折旧摊销表'!$D$21,$Q$79/$D$21,$Q$79/('表2-折旧摊销表'!$AF$25+1-'表2-折旧摊销表'!$Q$25)) -> 0 | T92: =IF('表2-折旧摊销表'!$AF$25+1-'表2-折旧摊销表'!$Q$25>='表2-折旧摊销表'!$D$21,$Q$79/$D$21,$Q$79/('表2-折旧摊销表'!$AF$25+1-'表2-折旧摊销表'!$Q$25)) -> 0 | U92: =IF('表2-折旧摊销表'!$AF$25+1-'表2-折旧摊销表'!$Q$25>='表2-折旧摊销表'!$D$21,$Q$79/$D$21,$Q$79/('表2-折旧摊销表'!$AF$25+1-'表2-折旧摊销表'!$Q$25)) -> 0 | V92: =IF('表2-折旧摊销表'!$AF$25+1-'表2-折旧摊销表'!$Q$25>='表2-折旧摊销表'!$D$21,$Q$79/$D$21,$Q$79/('表2-折旧摊销表'!$AF$25+1-'表2-折旧摊销表'!$Q$25)) -> 0 | W92: =IF('表2-折旧摊销表'!$AF$25+1-'表2-折旧摊销表'!$Q$25>='表2-折旧摊销表'!$D$21,$Q$79/$D$21,$Q$79/('表2-折旧摊销表'!$AF$25+1-'表2-折旧摊销表'!$Q$25)) -> 0 | X92: =IF('表2-折旧摊销表'!$AF$25+1-'表2-折旧摊销表'!$Q$25>='表2-折旧摊销表'!$D$21,$Q$79/$D$21,$Q$79/('表2-折旧摊销表'!$AF$25+1-'表2-折旧摊销表'!$Q$25)) -> 0 | ... Z92: =IF('表2-折旧摊销表'!$AF$25+1-'表2-折旧摊销表'!$Q$25>='表2-折旧摊销表'!$D$21,$Q$79/$D$21,$Q$79/('表2-折旧摊销表'!$AF$25+1-'表2-折旧摊销表'!$Q$25)) -> 0
C93: 合作期第13年 | D93: =SUM(F93:AF93) -> 0 | E93: 万元 | R93: =IF('表2-折旧摊销表'!$AF$25+1-'表2-折旧摊销表'!$R$25>='表2-折旧摊销表'!$D$21,$R$79/$D$21,$R$79/('表2-折旧摊销表'!$AF$25+1-'表2-折旧摊销表'!$R$25)) -> 0 | S93: =IF('表2-折旧摊销表'!$AF$25+1-'表2-折旧摊销表'!$R$25>='表2-折旧摊销表'!$D$21,$R$79/$D$21,$R$79/('表2-折旧摊销表'!$AF$25+1-'表2-折旧摊销表'!$R$25)) -> 0 | T93: =IF('表2-折旧摊销表'!$AF$25+1-'表2-折旧摊销表'!$R$25>='表2-折旧摊销表'!$D$21,$R$79/$D$21,$R$79/('表2-折旧摊销表'!$AF$25+1-'表2-折旧摊销表'!$R$25)) -> 0 | U93: =IF('表2-折旧摊销表'!$AF$25+1-'表2-折旧摊销表'!$R$25>='表2-折旧摊销表'!$D$21,$R$79/$D$21,$R$79/('表2-折旧摊销表'!$AF$25+1-'表2-折旧摊销表'!$R$25)) -> 0 | V93: =IF('表2-折旧摊销表'!$AF$25+1-'表2-折旧摊销表'!$R$25>='表2-折旧摊销表'!$D$21,$R$79/$D$21,$R$79/('表2-折旧摊销表'!$AF$25+1-'表2-折旧摊销表'!$R$25)) -> 0 | W93: =IF('表2-折旧摊销表'!$AF$25+1-'表2-折旧摊销表'!$R$25>='表2-折旧摊销表'!$D$21,$R$79/$D$21,$R$79/('表2-折旧摊销表'!$AF$25+1-'表2-折旧摊销表'!$R$25)) -> 0 | X93: =IF('表2-折旧摊销表'!$AF$25+1-'表2-折旧摊销表'!$R$25>='表2-折旧摊销表'!$D$21,$R$79/$D$21,$R$79/('表2-折旧摊销表'!$AF$25+1-'表2-折旧摊销表'!$R$25)) -> 0 | Y93: =IF('表2-折旧摊销表'!$AF$25+1-'表2-折旧摊销表'!$R$25>='表2-折旧摊销表'!$D$21,$R$79/$D$21,$R$79/('表2-折旧摊销表'!$AF$25+1-'表2-折旧摊销表'!$R$25)) -> 0 | ... AA93: =IF('表2-折旧摊销表'!$AF$25+1-'表2-折旧摊销表'!$R$25>='表2-折旧摊销表'!$D$21,$R$79/$D$21,$R$79/('表2-折旧摊销表'!$AF$25+1-'表2-折旧摊销表'!$R$25)) -> 0
C94: 合作期第14年 | D94: =SUM(F94:AF94) -> 0 | E94: 万元 | S94: =IF('表2-折旧摊销表'!$AF$25+1-'表2-折旧摊销表'!$S$25>='表2-折旧摊销表'!$D$21,$S$79/$D$21,$S$79/('表2-折旧摊销表'!$AF$25+1-'表2-折旧摊销表'!$S$25)) -> 0 | T94: =IF('表2-折旧摊销表'!$AF$25+1-'表2-折旧摊销表'!$S$25>='表2-折旧摊销表'!$D$21,$S$79/$D$21,$S$79/('表2-折旧摊销表'!$AF$25+1-'表2-折旧摊销表'!$S$25)) -> 0 | U94: =IF('表2-折旧摊销表'!$AF$25+1-'表2-折旧摊销表'!$S$25>='表2-折旧摊销表'!$D$21,$S$79/$D$21,$S$79/('表2-折旧摊销表'!$AF$25+1-'表2-折旧摊销表'!$S$25)) -> 0 | V94: =IF('表2-折旧摊销表'!$AF$25+1-'表2-折旧摊销表'!$S$25>='表2-折旧摊销表'!$D$21,$S$79/$D$21,$S$79/('表2-折旧摊销表'!$AF$25+1-'表2-折旧摊销表'!$S$25)) -> 0 | W94: =IF('表2-折旧摊销表'!$AF$25+1-'表2-折旧摊销表'!$S$25>='表2-折旧摊销表'!$D$21,$S$79/$D$21,$S$79/('表2-折旧摊销表'!$AF$25+1-'表2-折旧摊销表'!$S$25)) -> 0 | X94: =IF('表2-折旧摊销表'!$AF$25+1-'表2-折旧摊销表'!$S$25>='表2-折旧摊销表'!$D$21,$S$79/$D$21,$S$79/('表2-折旧摊销表'!$AF$25+1-'表2-折旧摊销表'!$S$25)) -> 0 | Y94: =IF('表2-折旧摊销表'!$AF$25+1-'表2-折旧摊销表'!$S$25>='表2-折旧摊销表'!$D$21,$S$79/$D$21,$S$79/('表2-折旧摊销表'!$AF$25+1-'表2-折旧摊销表'!$S$25)) -> 0 | Z94: =IF('表2-折旧摊销表'!$AF$25+1-'表2-折旧摊销表'!$S$25>='表2-折旧摊销表'!$D$21,$S$79/$D$21,$S$79/('表2-折旧摊销表'!$AF$25+1-'表2-折旧摊销表'!$S$25)) -> 0 | ... AB94: =IF('表2-折旧摊销表'!$AF$25+1-'表2-折旧摊销表'!$S$25>='表2-折旧摊销表'!$D$21,$S$79/$D$21,$S$79/('表2-折旧摊销表'!$AF$25+1-'表2-折旧摊销表'!$S$25)) -> 0
C95: 合作期第15年 | D95: =SUM(F95:AF95) -> 0 | E95: 万元 | T95: =IF('表2-折旧摊销表'!$AF$25+1-'表2-折旧摊销表'!$T$25>='表2-折旧摊销表'!$D$21,$T$79/$D$21,$T$79/('表2-折旧摊销表'!$AF$25+1-'表2-折旧摊销表'!$T$25)) -> 0 | U95: =IF('表2-折旧摊销表'!$AF$25+1-'表2-折旧摊销表'!$T$25>='表2-折旧摊销表'!$D$21,$T$79/$D$21,$T$79/('表2-折旧摊销表'!$AF$25+1-'表2-折旧摊销表'!$T$25)) -> 0 | V95: =IF('表2-折旧摊销表'!$AF$25+1-'表2-折旧摊销表'!$T$25>='表2-折旧摊销表'!$D$21,$T$79/$D$21,$T$79/('表2-折旧摊销表'!$AF$25+1-'表2-折旧摊销表'!$T$25)) -> 0 | W95: =IF('表2-折旧摊销表'!$AF$25+1-'表2-折旧摊销表'!$T$25>='表2-折旧摊销表'!$D$21,$T$79/$D$21,$T$79/('表2-折旧摊销表'!$AF$25+1-'表2-折旧摊销表'!$T$25)) -> 0 | X95: =IF('表2-折旧摊销表'!$AF$25+1-'表2-折旧摊销表'!$T$25>='表2-折旧摊销表'!$D$21,$T$79/$D$21,$T$79/('表2-折旧摊销表'!$AF$25+1-'表2-折旧摊销表'!$T$25)) -> 0 | Y95: =IF('表2-折旧摊销表'!$AF$25+1-'表2-折旧摊销表'!$T$25>='表2-折旧摊销表'!$D$21,$T$79/$D$21,$T$79/('表2-折旧摊销表'!$AF$25+1-'表2-折旧摊销表'!$T$25)) -> 0 | Z95: =IF('表2-折旧摊销表'!$AF$25+1-'表2-折旧摊销表'!$T$25>='表2-折旧摊销表'!$D$21,$T$79/$D$21,$T$79/('表2-折旧摊销表'!$AF$25+1-'表2-折旧摊销表'!$T$25)) -> 0 | AA95: =IF('表2-折旧摊销表'!$AF$25+1-'表2-折旧摊销表'!$T$25>='表2-折旧摊销表'!$D$21,$T$79/$D$21,$T$79/('表2-折旧摊销表'!$AF$25+1-'表2-折旧摊销表'!$T$25)) -> 0 | ... AC95: =IF('表2-折旧摊销表'!$AF$25+1-'表2-折旧摊销表'!$T$25>='表2-折旧摊销表'!$D$21,$T$79/$D$21,$T$79/('表2-折旧摊销表'!$AF$25+1-'表2-折旧摊销表'!$T$25)) -> 0
C96: 合作期第16年 | D96: =SUM(F96:AF96) -> 0 | E96: 万元 | U96: =IF('表2-折旧摊销表'!$AF$25+1-'表2-折旧摊销表'!$U$25>='表2-折旧摊销表'!$D$21,$U$79/$D$21,$U$79/('表2-折旧摊销表'!$AF$25+1-'表2-折旧摊销表'!$U$25)) -> 0 | V96: =IF('表2-折旧摊销表'!$AF$25+1-'表2-折旧摊销表'!$U$25>='表2-折旧摊销表'!$D$21,$U$79/$D$21,$U$79/('表2-折旧摊销表'!$AF$25+1-'表2-折旧摊销表'!$U$25)) -> 0 | W96: =IF('表2-折旧摊销表'!$AF$25+1-'表2-折旧摊销表'!$U$25>='表2-折旧摊销表'!$D$21,$U$79/$D$21,$U$79/('表2-折旧摊销表'!$AF$25+1-'表2-折旧摊销表'!$U$25)) -> 0 | X96: =IF('表2-折旧摊销表'!$AF$25+1-'表2-折旧摊销表'!$U$25>='表2-折旧摊销表'!$D$21,$U$79/$D$21,$U$79/('表2-折旧摊销表'!$AF$25+1-'表2-折旧摊销表'!$U$25)) -> 0 | Y96: =IF('表2-折旧摊销表'!$AF$25+1-'表2-折旧摊销表'!$U$25>='表2-折旧摊销表'!$D$21,$U$79/$D$21,$U$79/('表2-折旧摊销表'!$AF$25+1-'表2-折旧摊销表'!$U$25)) -> 0 | Z96: =IF('表2-折旧摊销表'!$AF$25+1-'表2-折旧摊销表'!$U$25>='表2-折旧摊销表'!$D$21,$U$79/$D$21,$U$79/('表2-折旧摊销表'!$AF$25+1-'表2-折旧摊销表'!$U$25)) -> 0 | AA96: =IF('表2-折旧摊销表'!$AF$25+1-'表2-折旧摊销表'!$U$25>='表2-折旧摊销表'!$D$21,$U$79/$D$21,$U$79/('表2-折旧摊销表'!$AF$25+1-'表2-折旧摊销表'!$U$25)) -> 0 | AB96: =IF('表2-折旧摊销表'!$AF$25+1-'表2-折旧摊销表'!$U$25>='表2-折旧摊销表'!$D$21,$U$79/$D$21,$U$79/('表2-折旧摊销表'!$AF$25+1-'表2-折旧摊销表'!$U$25)) -> 0 | ... AD96: =IF('表2-折旧摊销表'!$AF$25+1-'表2-折旧摊销表'!$U$25>='表2-折旧摊销表'!$D$21,$U$79/$D$21,$U$79/('表2-折旧摊销表'!$AF$25+1-'表2-折旧摊销表'!$U$25)) -> 0
C97: 合作期第17年 | D97: =SUM(F97:AF97) -> 0 | E97: 万元 | V97: =IF('表2-折旧摊销表'!$AF$25+1-'表2-折旧摊销表'!$V$25>='表2-折旧摊销表'!$D$21,$V$79/$D$21,$V$79/('表2-折旧摊销表'!$AF$25+1-'表2-折旧摊销表'!$V$25)) -> 0 | W97: =IF('表2-折旧摊销表'!$AF$25+1-'表2-折旧摊销表'!$V$25>='表2-折旧摊销表'!$D$21,$V$79/$D$21,$V$79/('表2-折旧摊销表'!$AF$25+1-'表2-折旧摊销表'!$V$25)) -> 0 | X97: =IF('表2-折旧摊销表'!$AF$25+1-'表2-折旧摊销表'!$V$25>='表2-折旧摊销表'!$D$21,$V$79/$D$21,$V$79/('表2-折旧摊销表'!$AF$25+1-'表2-折旧摊销表'!$V$25)) -> 0 | Y97: =IF('表2-折旧摊销表'!$AF$25+1-'表2-折旧摊销表'!$V$25>='表2-折旧摊销表'!$D$21,$V$79/$D$21,$V$79/('表2-折旧摊销表'!$AF$25+1-'表2-折旧摊销表'!$V$25)) -> 0 | Z97: =IF('表2-折旧摊销表'!$AF$25+1-'表2-折旧摊销表'!$V$25>='表2-折旧摊销表'!$D$21,$V$79/$D$21,$V$79/('表2-折旧摊销表'!$AF$25+1-'表2-折旧摊销表'!$V$25)) -> 0 | AA97: =IF('表2-折旧摊销表'!$AF$25+1-'表2-折旧摊销表'!$V$25>='表2-折旧摊销表'!$D$21,$V$79/$D$21,$V$79/('表2-折旧摊销表'!$AF$25+1-'表2-折旧摊销表'!$V$25)) -> 0 | AB97: =IF('表2-折旧摊销表'!$AF$25+1-'表2-折旧摊销表'!$V$25>='表2-折旧摊销表'!$D$21,$V$79/$D$21,$V$79/('表2-折旧摊销表'!$AF$25+1-'表2-折旧摊销表'!$V$25)) -> 0 | AC97: =IF('表2-折旧摊销表'!$AF$25+1-'表2-折旧摊销表'!$V$25>='表2-折旧摊销表'!$D$21,$V$79/$D$21,$V$79/('表2-折旧摊销表'!$AF$25+1-'表2-折旧摊销表'!$V$25)) -> 0 | ... AE97: =IF('表2-折旧摊销表'!$AF$25+1-'表2-折旧摊销表'!$V$25>='表2-折旧摊销表'!$D$21,$V$79/$D$21,$V$79/('表2-折旧摊销表'!$AF$25+1-'表2-折旧摊销表'!$V$25)) -> 0
C98: 合作期第18年 | D98: =SUM(F98:AF98) -> 0 | E98: 万元 | W98: =IF('表2-折旧摊销表'!$AF$25+1-'表2-折旧摊销表'!$W$25>='表2-折旧摊销表'!$D$21,$W$79/$D$21,$W$79/('表2-折旧摊销表'!$AF$25+1-'表2-折旧摊销表'!$W$25)) -> 0 | X98: =IF('表2-折旧摊销表'!$AF$25+1-'表2-折旧摊销表'!$W$25>='表2-折旧摊销表'!$D$21,$W$79/$D$21,$W$79/('表2-折旧摊销表'!$AF$25+1-'表2-折旧摊销表'!$W$25)) -> 0 | Y98: =IF('表2-折旧摊销表'!$AF$25+1-'表2-折旧摊销表'!$W$25>='表2-折旧摊销表'!$D$21,$W$79/$D$21,$W$79/('表2-折旧摊销表'!$AF$25+1-'表2-折旧摊销表'!$W$25)) -> 0 | Z98: =IF('表2-折旧摊销表'!$AF$25+1-'表2-折旧摊销表'!$W$25>='表2-折旧摊销表'!$D$21,$W$79/$D$21,$W$79/('表2-折旧摊销表'!$AF$25+1-'表2-折旧摊销表'!$W$25)) -> 0 | AA98: =IF('表2-折旧摊销表'!$AF$25+1-'表2-折旧摊销表'!$W$25>='表2-折旧摊销表'!$D$21,$W$79/$D$21,$W$79/('表2-折旧摊销表'!$AF$25+1-'表2-折旧摊销表'!$W$25)) -> 0 | AB98: =IF('表2-折旧摊销表'!$AF$25+1-'表2-折旧摊销表'!$W$25>='表2-折旧摊销表'!$D$21,$W$79/$D$21,$W$79/('表2-折旧摊销表'!$AF$25+1-'表2-折旧摊销表'!$W$25)) -> 0 | AC98: =IF('表2-折旧摊销表'!$AF$25+1-'表2-折旧摊销表'!$W$25>='表2-折旧摊销表'!$D$21,$W$79/$D$21,$W$79/('表2-折旧摊销表'!$AF$25+1-'表2-折旧摊销表'!$W$25)) -> 0 | AD98: =IF('表2-折旧摊销表'!$AF$25+1-'表2-折旧摊销表'!$W$25>='表2-折旧摊销表'!$D$21,$W$79/$D$21,$W$79/('表2-折旧摊销表'!$AF$25+1-'表2-折旧摊销表'!$W$25)) -> 0 | ... AF98: =IF('表2-折旧摊销表'!$AF$25+1-'表2-折旧摊销表'!$W$25>='表2-折旧摊销表'!$D$21,$W$79/$D$21,$W$79/('表2-折旧摊销表'!$AF$25+1-'表2-折旧摊销表'!$W$25)) -> 0
C99: 合作期第19年 | D99: =SUM(F99:AF99) -> 0 | E99: 万元 | X99: =IF('表2-折旧摊销表'!$AF$25+1-'表2-折旧摊销表'!$X$25>='表2-折旧摊销表'!$D$21,$X$79/$D$21,$X$79/('表2-折旧摊销表'!$AF$25+1-'表2-折旧摊销表'!$X$25)) -> 0 | Y99: =IF('表2-折旧摊销表'!$AF$25+1-'表2-折旧摊销表'!$X$25>='表2-折旧摊销表'!$D$21,$X$79/$D$21,$X$79/('表2-折旧摊销表'!$AF$25+1-'表2-折旧摊销表'!$X$25)) -> 0 | Z99: =IF('表2-折旧摊销表'!$AF$25+1-'表2-折旧摊销表'!$X$25>='表2-折旧摊销表'!$D$21,$X$79/$D$21,$X$79/('表2-折旧摊销表'!$AF$25+1-'表2-折旧摊销表'!$X$25)) -> 0 | AA99: =IF('表2-折旧摊销表'!$AF$25+1-'表2-折旧摊销表'!$X$25>='表2-折旧摊销表'!$D$21,$X$79/$D$21,$X$79/('表2-折旧摊销表'!$AF$25+1-'表2-折旧摊销表'!$X$25)) -> 0 | AB99: =IF('表2-折旧摊销表'!$AF$25+1-'表2-折旧摊销表'!$X$25>='表2-折旧摊销表'!$D$21,$X$79/$D$21,$X$79/('表2-折旧摊销表'!$AF$25+1-'表2-折旧摊销表'!$X$25)) -> 0 | AC99: =IF('表2-折旧摊销表'!$AF$25+1-'表2-折旧摊销表'!$X$25>='表2-折旧摊销表'!$D$21,$X$79/$D$21,$X$79/('表2-折旧摊销表'!$AF$25+1-'表2-折旧摊销表'!$X$25)) -> 0 | AD99: =IF('表2-折旧摊销表'!$AF$25+1-'表2-折旧摊销表'!$X$25>='表2-折旧摊销表'!$D$21,$X$79/$D$21,$X$79/('表2-折旧摊销表'!$AF$25+1-'表2-折旧摊销表'!$X$25)) -> 0 | AE99: =IF('表2-折旧摊销表'!$AF$25+1-'表2-折旧摊销表'!$X$25>='表2-折旧摊销表'!$D$21,$X$79/$D$21,$X$79/('表2-折旧摊销表'!$AF$25+1-'表2-折旧摊销表'!$X$25)) -> 0 | AF99: =IF('表2-折旧摊销表'!$AF$25+1-'表2-折旧摊销表'!$X$25>='表2-折旧摊销表'!$D$21,$X$79/$D$21,$X$79/('表2-折旧摊销表'!$AF$25+1-'表2-折旧摊销表'!$X$25)) -> 0
C100: 合作期第20年 | D100: =SUM(F100:AF100) -> 0 | E100: 万元 | Y100: =IF('表2-折旧摊销表'!$AF$25+1-'表2-折旧摊销表'!$Y$25>='表2-折旧摊销表'!$D$21,$Y$79/$D$21,$Y$79/('表2-折旧摊销表'!$AF$25+1-'表2-折旧摊销表'!$Y$25)) -> 0 | Z100: =IF('表2-折旧摊销表'!$AF$25+1-'表2-折旧摊销表'!$Y$25>='表2-折旧摊销表'!$D$21,$Y$79/$D$21,$Y$79/('表2-折旧摊销表'!$AF$25+1-'表2-折旧摊销表'!$Y$25)) -> 0 | AA100: =IF('表2-折旧摊销表'!$AF$25+1-'表2-折旧摊销表'!$Y$25>='表2-折旧摊销表'!$D$21,$Y$79/$D$21,$Y$79/('表2-折旧摊销表'!$AF$25+1-'表2-折旧摊销表'!$Y$25)) -> 0 | AB100: =IF('表2-折旧摊销表'!$AF$25+1-'表2-折旧摊销表'!$Y$25>='表2-折旧摊销表'!$D$21,$Y$79/$D$21,$Y$79/('表2-折旧摊销表'!$AF$25+1-'表2-折旧摊销表'!$Y$25)) -> 0 | AC100: =IF('表2-折旧摊销表'!$AF$25+1-'表2-折旧摊销表'!$Y$25>='表2-折旧摊销表'!$D$21,$Y$79/$D$21,$Y$79/('表2-折旧摊销表'!$AF$25+1-'表2-折旧摊销表'!$Y$25)) -> 0 | AD100: =IF('表2-折旧摊销表'!$AF$25+1-'表2-折旧摊销表'!$Y$25>='表2-折旧摊销表'!$D$21,$Y$79/$D$21,$Y$79/('表2-折旧摊销表'!$AF$25+1-'表2-折旧摊销表'!$Y$25)) -> 0 | AE100: =IF('表2-折旧摊销表'!$AF$25+1-'表2-折旧摊销表'!$Y$25>='表2-折旧摊销表'!$D$21,$Y$79/$D$21,$Y$79/('表2-折旧摊销表'!$AF$25+1-'表2-折旧摊销表'!$Y$25)) -> 0 | AF100: =IF('表2-折旧摊销表'!$AF$25+1-'表2-折旧摊销表'!$Y$25>='表2-折旧摊销表'!$D$21,$Y$79/$D$21,$Y$79/('表2-折旧摊销表'!$AF$25+1-'表2-折旧摊销表'!$Y$25)) -> 0
C101: 合作期第21年 | D101: =SUM(F101:AF101) -> 0 | E101: 万元 | Z101: =IF('表2-折旧摊销表'!$AF$25+1-'表2-折旧摊销表'!$Z$25>='表2-折旧摊销表'!$D$21,$Z$79/$D$21,$Z$79/('表2-折旧摊销表'!$AF$25+1-'表2-折旧摊销表'!$Z$25)) -> 0 | AA101: =IF('表2-折旧摊销表'!$AF$25+1-'表2-折旧摊销表'!$Z$25>='表2-折旧摊销表'!$D$21,$Z$79/$D$21,$Z$79/('表2-折旧摊销表'!$AF$25+1-'表2-折旧摊销表'!$Z$25)) -> 0 | AB101: =IF('表2-折旧摊销表'!$AF$25+1-'表2-折旧摊销表'!$Z$25>='表2-折旧摊销表'!$D$21,$Z$79/$D$21,$Z$79/('表2-折旧摊销表'!$AF$25+1-'表2-折旧摊销表'!$Z$25)) -> 0 | AC101: =IF('表2-折旧摊销表'!$AF$25+1-'表2-折旧摊销表'!$Z$25>='表2-折旧摊销表'!$D$21,$Z$79/$D$21,$Z$79/('表2-折旧摊销表'!$AF$25+1-'表2-折旧摊销表'!$Z$25)) -> 0 | AD101: =IF('表2-折旧摊销表'!$AF$25+1-'表2-折旧摊销表'!$Z$25>='表2-折旧摊销表'!$D$21,$Z$79/$D$21,$Z$79/('表2-折旧摊销表'!$AF$25+1-'表2-折旧摊销表'!$Z$25)) -> 0 | AE101: =IF('表2-折旧摊销表'!$AF$25+1-'表2-折旧摊销表'!$Z$25>='表2-折旧摊销表'!$D$21,$Z$79/$D$21,$Z$79/('表2-折旧摊销表'!$AF$25+1-'表2-折旧摊销表'!$Z$25)) -> 0 | AF101: =IF('表2-折旧摊销表'!$AF$25+1-'表2-折旧摊销表'!$Z$25>='表2-折旧摊销表'!$D$21,$Z$79/$D$21,$Z$79/('表2-折旧摊销表'!$AF$25+1-'表2-折旧摊销表'!$Z$25)) -> 0
...

Sheet 表3-成本费用表
B2: 成本费用表-资本金
B3: 序号 | C3: 项目 | D3: 合计 | E3: 单位 | F3: 2020年 | G3: 2021年 | H3: 2022年 | I3: 45107 | J3: 45261 | K3: 2024年 | L3: 2025年 | M3: 2026年 | N3: 2027年 | O3: 2028年 | P3: 2029年 | Q3: 2030年 | R3: 2031年 | S3: 2032年 | T3: 2033年 | U3: 2034年 | V3: 2035年 | W3: 2036年 | X3: 2037年 | Y3: 2038年 | Z3: 2039年 | AA3: 2040年 | AB3: 2041年 | AC3: 2042年 | AD3: 2043年 | AE3: 2044年 | AF3: 53051
F4: 1 | G4: 2 | H4: 3 | I4: 4 | J4: 5 | K4: 6 | L4: 7 | M4: 8 | N4: 9 | O4: 10 | P4: 11 | Q4: 12 | R4: 13 | S4: 14 | T4: 15 | U4: 16 | V4: 17 | W4: 18 | X4: 19 | Y4: 20 | Z4: 21 | AA4: 22 | AB4: 23 | AC4: 24 | AD4: 25 | AE4: 26 | AF4: 27
C5: 投产比例 | F5: =参数输入表!$I$39 -> 0 | G5: =参数输入表!$I$40 -> 0.03125 | H5: =参数输入表!$I$41 -> 0.03125 | I5: =参数输入表!$I$42 -> 0.03125 | J5: =参数输入表!$I$43 -> 0.1765625 | K5: =参数输入表!$I$44 -> 0.7578125 | L5: =参数输入表!$I$45 -> 1 | M5: =参数输入表!$I$46 -> 1 | N5: =参数输入表!$I$47 -> 1 | O5: =参数输入表!$I$48 -> 1 | P5: =参数输入表!$I$49 -> 1 | Q5: =参数输入表!$I$50 -> 1 | R5: =参数输入表!$I$51 -> 1 | S5: =参数输入表!$I$52 -> 1 | T5: =参数输入表!$I$53 -> 1 | U5: =参数输入表!$I$54 -> 1 | V5: =参数输入表!$I$55 -> 1 | W5: =参数输入表!$I$56 -> 1 | X5: =参数输入表!$I$57 -> 1 | Y5: =参数输入表!$I$58 -> 1 | Z5: =参数输入表!$I$59 -> 1 | AA5: =参数输入表!$I$60 -> 1 | AB5: =参数输入表!$I$61 -> 1 | AC5: =参数输入表!$I$62 -> 1 | AD5: =参数输入表!$I$63 -> 1 | AE5: =参数输入表!$I$64 -> 1 | AF5: =参数输入表!$I$65 -> 1
B6: 一 | C6: 生产经营成本 | D6: =SUM(F6:AF6) -> 280573.04 | E6: 万元 | F6: =F7+F16+F17+F20+F21 -> 0 | G6: =G7+G16+G17+G20+G21 -> 0 | H6: =H7+H16+H17+H20+H21 -> 0 | I6: =I7+I16+I17+I20+I21 -> 2000 | J6: =J7+J16+J17+J20+J21 -> 3055.4966 | K6: =K7+K16+K17+K20+K21 -> 13980.681 | L6: =L7+L16+L17+L20+L21 -> 17011.799 | M6: =M7+M16+M17+M20+M21 -> 17068.903 | ... AF6: =AF7+AF16+AF17+AF20+AF21 -> 4244.5263
B7: 1 | C7: 生产成本 | D7: =SUM(F7:AF7) -> 221338.95 | E7: 万元 | F7: ='表5-利润表-资本金(标准格式)'!F11 -> 0 | G7: ='表5-利润表-资本金(标准格式)'!G11 -> 0 | H7: ='表5-利润表-资本金(标准格式)'!H11 -> 0 | I7: ='表5-利润表-资本金(标准格式)'!I11 -> 2000 | J7: =SUM(J8:J15) -> 2381.5855 | K7: =SUM(K8:K15) -> 10114.817 | L7: =SUM(L8:L15) -> 11326.73 | M7: =SUM(M8:M15) -> 11664.87 | N7: =SUM(N8:N15) -> 11693.67 | O7: =SUM(O8:O15) -> 11722.47 | P7: =SUM(P8:P15) -> 11751.27 | Q7: =SUM(Q8:Q15) -> 11780.07 | ... AF7: =SUM(AF8:AF15) -> 993.64165
B8: 1.1 | C8: 材料费 | D8: =SUM(F8:AF8) -> 1206.75 | E8: 万元 | J8: =参数输入表!$I$289*参数输入表!$I$295/(1+参数输入表!$I$318)*J5*(12-MONTH(参数输入表!$I$8))/12 -> 28.25 | K8: =参数输入表!$I$289*参数输入表!$I$296/(1+参数输入表!$I$318)*K5 -> 242.5 | L8: =参数输入表!$I$289*参数输入表!$I$297/(1+参数输入表!$I$318)*L5 -> 320 | M8: =参数输入表!$I$289*参数输入表!$I$298/(1+参数输入表!$I$318)*M5 -> 32 | N8: =参数输入表!$I$289*参数输入表!$I$299/(1+参数输入表!$I$318)*N5 -> 32 | O8: =参数输入表!$I$289*参数输入表!$I$300/(1+参数输入表!$I$318)*O5 -> 32 | P8: =参数输入表!$I$289*参数输入表!$I$301/(1+参数输入表!$I$318)*P5 -> 32 | Q8: =参数输入表!$I$289*参数输入表!$I$302/(1+参数输入表!$I$318)*Q5 -> 32 | R8: =参数输入表!$I$289*参数输入表!$I$303/(1+参数输入表!$I$318)*R5 -> 32 | S8: =参数输入表!$I$289*参数输入表!$I$304/(1+参数输入表!$I$318)*S5 -> 32 | T8: =参数输入表!$I$289*参数输入表!$I$305/(1+参数输入表!$I$318)*T5 -> 32 | U8: =参数输入表!$I$289*参数输入表!$I$306/(1+参数输入表!$I$318)*U5 -> 32 | V8: =参数输入表!$I$289*参数输入表!$I$307/(1+参数输入表!$I$318)*V5 -> 32 | W8: =参数输入表!$I$289*参数输入表!$I$308/(1+参数输入表!$I$318)*W5 -> 32 | X8: =参数输入表!$I$289*参数输入表!$I$309/(1+参数输入表!$I$318)*X5 -> 32 | Y8: =参数输入表!$I$289*参数输入表!$I$310/(1+参数输入表!$I$318)*Y5 -> 32 | Z8: =参数输入表!$I$289*参数输入表!$I$311/(1+参数输入表!$I$318)*Z5 -> 32 | AA8: =参数输入表!$I$289*参数输入表!$I$312/(1+参数输入表!$I$318)*AA5 -> 32 | AB8: =参数输入表!$I$289*参数输入表!$I$313/(1+参数输入表!$I$318)*AB5 -> 32 | AC8: =参数输入表!$I$289*参数输入表!$I$314/(1+参数输入表!$I$318)*AC5 -> 32 | AD8: =参数输入表!$I$289*参数输入表!$I$315/(1+参数输入表!$I$318)*AD5 -> 32 | AE8: =参数输入表!$I$289*参数输入表!$I$316/(1+参数输入表!$I$318)*AE5 -> 32 | AF8: =参数输入表!$I$289*参数输入表!$I$317/(1+参数输入表!$I$318)*AF5*MONTH(参数输入表!I6)/12 -> 8
B9: 1.2 | C9: 维修费 | D9: =SUM(F9:AF9) -> 13768.266 | E9: 万元 | J9: =参数输入表!$I$320*参数输入表!$I$326/(1+参数输入表!$I$349)*J5*(12-MONTH(参数输入表!I8))/12 -> 0 | K9: =参数输入表!$I$320*参数输入表!$I$327/(1+参数输入表!$I$349)*K5 -> 0 | L9: =参数输入表!$I$320*参数输入表!$I$328/(1+参数输入表!$I$349)*L5 -> 0 | M9: =参数输入表!$I$320*参数输入表!$I$329/(1+参数输入表!$I$349)*M5 -> 483.09706 | N9: =参数输入表!$I$320*参数输入表!$I$330/(1+参数输入表!$I$349)*N5 -> 483.09706 | O9: =参数输入表!$I$320*参数输入表!$I$331/(1+参数输入表!$I$349)*O5 -> 483.09706 | P9: =参数输入表!$I$320*参数输入表!$I$332/(1+参数输入表!$I$349)*P5 -> 483.09706 | Q9: =参数输入表!$I$320*参数输入表!$I$333/(1+参数输入表!$I$349)*Q5 -> 483.09706 | R9: =参数输入表!$I$320*参数输入表!$I$334/(1+参数输入表!$I$349)*R5 -> 644.12941 | S9: =参数输入表!$I$320*参数输入表!$I$335/(1+参数输入表!$I$349)*S5 -> 644.12941 | T9: =参数输入表!$I$320*参数输入表!$I$336/(1+参数输入表!$I$349)*T5 -> 644.12941 | U9: =参数输入表!$I$320*参数输入表!$I$337/(1+参数输入表!$I$349)*U5 -> 644.12941 | V9: =参数输入表!$I$320*参数输入表!$I$338/(1+参数输入表!$I$349)*V5 -> 644.12941 | W9: =参数输入表!$I$320*参数输入表!$I$339/(1+参数输入表!$I$349)*W5 -> 805.16176 | X9: =参数输入表!$I$320*参数输入表!$I$340/(1+参数输入表!$I$349)*X5 -> 805.16176 | Y9: =参数输入表!$I$320*参数输入表!$I$341/(1+参数输入表!$I$349)*Y5 -> 805.16176 | Z9: =参数输入表!$I$320*参数输入表!$I$342/(1+参数输入表!$I$349)*Z5 -> 805.16176 | AA9: =参数输入表!$I$320*参数输入表!$I$343/(1+参数输入表!$I$349)*AA5 -> 805.16176 | AB9: =参数输入表!$I$320*参数输入表!$I$344/(1+参数输入表!$I$349)*AB5 -> 966.19411 | AC9: =参数输入表!$I$320*参数输入表!$I$345/(1+参数输入表!$I$349)*AC5 -> 966.19411 | AD9: =参数输入表!$I$320*参数输入表!$I$346/(1+参数输入表!$I$349)*AD5 -> 966.19411 | AE9: =参数输入表!$I$320*参数输入表!$I$347/(1+参数输入表!$I$349)*AE5 -> 966.19411 | AF9: =参数输入表!$I$320*参数输入表!$I$348/(1+参数输入表!$I$349)*AF5*MONTH(参数输入表!I6)/12 -> 241.54853
B10: 1.3 | C10: 生产人员薪酬及福利 | D10: =SUM(F10:AF10) -> 19563.143 | E10: 万元 | J10: =(参数输入表!$I$383*参数输入表!$I$386+参数输入表!$I$384*参数输入表!$I$387)*(1+参数输入表!$I$388)*(1+参数输入表!$I$389*(J4-参数输入表!$I$7))/(1+参数输入表!$I$390)*J5*(12-MONTH(参数输入表!I8))/12 -> 53.3925 | K10: =(参数输入表!$I$383*参数输入表!$I$386+参数输入表!$I$384*参数输入表!$I$387)*(1+参数输入表!$I$388)*(1+参数输入表!$I$389*(K4-参数输入表!$I$7))/(1+参数输入表!$I$390)*K5 -> 480.15 | L10: =(参数输入表!$I$383*参数输入表!$I$386+参数输入表!$I$384*参数输入表!$I$387)*(1+参数输入表!$I$388)*(1+参数输入表!$I$389*(L4-参数输入表!$I$7))/(1+参数输入表!$I$390)*L5 -> 662.4 | M10: =(参数输入表!$I$383*参数输入表!$I$386+参数输入表!$I$384*参数输入表!$I$387)*(1+参数输入表!$I$388)*(1+参数输入表!$I$389*(M4-参数输入表!$I$7))/(1+参数输入表!$I$390)*M5 -> 691.2 | N10: =(参数输入表!$I$383*参数输入表!$I$386+参数输入表!$I$384*参数输入表!$I$387)*(1+参数输入表!$I$388)*(1+参数输入表!$I$389*(N4-参数输入表!$I$7))/(1+参数输入表!$I$390)*N5 -> 720 | O10: =(参数输入表!$I$383*参数输入表!$I$386+参数输入表!$I$384*参数输入表!$I$387)*(1+参数输入表!$I$388)*(1+参数输入表!$I$389*(O4-参数输入表!$I$7))/(1+参数输入表!$I$390)*O5 -> 748.8 | P10: =(参数输入表!$I$383*参数输入表!$I$386+参数输入表!$I$384*参数输入表!$I$387)*(1+参数输入表!$I$388)*(1+参数输入表!$I$389*(P4-参数输入表!$I$7))/(1+参数输入表!$I$390)*P5 -> 777.6 | Q10: =(参数输入表!$I$383*参数输入表!$I$386+参数输入表!$I$384*参数输入表!$I$387)*(1+参数输入表!$I$388)*(1+参数输入表!$I$389*(Q4-参数输入表!$I$7))/(1+参数输入表!$I$390)*Q5 -> 806.4 | R10: =(参数输入表!$I$383*参数输入表!$I$386+参数输入表!$I$384*参数输入表!$I$387)*(1+参数输入表!$I$388)*(1+参数输入表!$I$389*(R4-参数输入表!$I$7))/(1+参数输入表!$I$390)*R5 -> 835.2 | ... AE10: =(参数输入表!$I$383*参数输入表!$I$386+参数输入表!$I$384*参数输入表!$I$387)*(1+参数输入表!$I$388)*(1+参数输入表!$I$389*(AE4-参数输入表!$I$7))/(1+参数输入表!$I$390)*AE5 -> 1209.6 | AF10: =(参数输入表!$I$383*参数输入表!$I$386+参数输入表!$I$384*参数输入表!$I$387)*(1+参数输入表!$I$388)*(1+参数输入表!$I$389*(AF4-参数输入表!$I$7))/(1+参数输入表!$I$390)*AF5*MONTH(参数输入表!I6)/12 -> 309.6
B11: 1.4 | C11: 长期待摊费用当期摊销 | D11: =SUM(F11:AF11) -> 1834.8624 | E11: 万元 | J11: ='表2-折旧摊销表'!J133 -> 0 | K11: ='表2-折旧摊销表'!K133 -> 0 | L11: ='表2-折旧摊销表'!L133 -> 0 | M11: ='表2-折旧摊销表'!M133 -> 91.743119 | N11: ='表2-折旧摊销表'!N133 -> 91.743119 | O11: ='表2-折旧摊销表'!O133 -> 91.743119 | P11: ='表2-折旧摊销表'!P133 -> 91.743119 | Q11: ='表2-折旧摊销表'!Q133 -> 91.743119 | ... AF11: ='表2-折旧摊销表'!AF133 -> 91.743119
B12: 1.5 | C12: 营业相关资产折旧及摊销 | D12: =SUM(F12:AF12) -> 154737.21 | E12: 万元 | J12: ='表2-折旧摊销表'!J132+'表2-折旧摊销表'!J134 -> 2094.218 | K12: ='表2-折旧摊销表'!K132+'表2-折旧摊销表'!K134 -> 8366.9167 | L12: ='表2-折旧摊销表'!L132+'表2-折旧摊销表'!L134 -> 9063.3301 | M12: ='表2-折旧摊销表'!M132+'表2-折旧摊销表'!M134 -> 9063.3301 | N12: ='表2-折旧摊销表'!N132+'表2-折旧摊销表'!N134 -> 9063.3301 | O12: ='表2-折旧摊销表'!O132+'表2-折旧摊销表'!O134 -> 9063.3301 | P12: ='表2-折旧摊销表'!P132+'表2-折旧摊销表'!P134 -> 9063.3301 | Q12: ='表2-折旧摊销表'!Q132+'表2-折旧摊销表'!Q134 -> 9063.3301 | ... AF12: ='表2-折旧摊销表'!AF132+'表2-折旧摊销表'!AF134 -> 0
B13: 1.6 | C13: 其他费用 | D13: =SUM(F13:AF13) -> 6750.75 | E13: 万元 | J13: =参数输入表!$I$392*参数输入表!$I$393/(1+参数输入表!$I$394)*J5*(12-MONTH(参数输入表!I8))/12 -> 28.25 | K13: =参数输入表!$I$392*参数输入表!$I$393/(1+参数输入表!$I$394)*K5 -> 242.5 | L13: =参数输入表!$I$392*参数输入表!$I$393/(1+参数输入表!$I$394)*L5 -> 320 | M13: =参数输入表!$I$392*参数输入表!$I$393/(1+参数输入表!$I$394)*M5 -> 320 | N13: =参数输入表!$I$392*参数输入表!$I$393/(1+参数输入表!$I$394)*N5 -> 320 | O13: =参数输入表!$I$392*参数输入表!$I$393/(1+参数输入表!$I$394)*O5 -> 320 | P13: =参数输入表!$I$392*参数输入表!$I$393/(1+参数输入表!$I$394)*P5 -> 320 | Q13: =参数输入表!$I$392*参数输入表!$I$393/(1+参数输入表!$I$394)*Q5 -> 320 | R13: =参数输入表!$I$392*参数输入表!$I$393/(1+参数输入表!$I$394)*R5 -> 320 | ... AE13: =参数输入表!$I$392*参数输入表!$I$393/(1+参数输入表!$I$394)*AE5 -> 320 | AF13: =参数输入表!$I$392*参数输入表!$I$393/(1+参数输入表!$I$394)*AF5*MONTH(参数输入表!I6)/12 -> 80
B14: 1.7 | C14: 储能费用 | D14: =SUM(F14:AF14) -> 15526.725 | E14: 万元 | J14: =参数输入表!$I$396*参数输入表!$I$397*1000/10000/(1+参数输入表!$I$398)*J5*(12-MONTH(参数输入表!I8))/12 -> 64.975 | K14: =参数输入表!$I$396*参数输入表!$I$397*1000/10000/(1+参数输入表!$I$398)*K5 -> 557.75 | L14: =参数输入表!$I$396*参数输入表!$I$397*1000/10000/(1+参数输入表!$I$398)*L5 -> 736 | M14: =参数输入表!$I$396*参数输入表!$I$397*1000/10000/(1+参数输入表!$I$398)*M5 -> 736 | N14: =参数输入表!$I$396*参数输入表!$I$397*1000/10000/(1+参数输入表!$I$398)*N5 -> 736 | O14: =参数输入表!$I$396*参数输入表!$I$397*1000/10000/(1+参数输入表!$I$398)*O5 -> 736 | P14: =参数输入表!$I$396*参数输入表!$I$397*1000/10000/(1+参数输入表!$I$398)*P5 -> 736 | Q14: =参数输入表!$I$396*参数输入表!$I$397*1000/10000/(1+参数输入表!$I$398)*Q5 -> 736 | R14: =参数输入表!$I$396*参数输入表!$I$397*1000/10000/(1+参数输入表!$I$398)*R5 -> 736 | ... AE14: =参数输入表!$I$396*参数输入表!$I$397*1000/10000/(1+参数输入表!$I$398)*AE5 -> 736 | AF14: =参数输入表!$I$396*参数输入表!$I$397*1000/10000/(1+参数输入表!$I$398)*AF5*MONTH(参数输入表!I6)/12 -> 184
B15: 1.8 | C15: 场地租金费用 | D15: =SUM(F15:AF15) -> 5951.25 | E15: 万元 | J15: =参数输入表!$I$400*参数输入表!$I$406/10000/(1+参数输入表!$I$429)*(12-MONTH(参数输入表!I8))/12 -> 112.5 | K15: =参数输入表!$I$400*参数输入表!$I$407/10000/(1+参数输入表!$I$429) -> 225 | L15: =参数输入表!$I$400*参数输入表!$I$408/10000/(1+参数输入表!$I$429) -> 225 | M15: =参数输入表!$I$400*参数输入表!$I$409/10000/(1+参数输入表!$I$429) -> 247.5 | N15: =参数输入表!$I$400*参数输入表!$I$410/10000/(1+参数输入表!$I$429) -> 247.5 | O15: =参数输入表!$I$400*参数输入表!$I$411/10000/(1+参数输入表!$I$429) -> 247.5 | P15: =参数输入表!$I$400*参数输入表!$I$412/10000/(1+参数输入表!$I$429) -> 247.5 | Q15: =参数输入表!$I$400*参数输入表!$I$413/10000/(1+参数输入表!$I$429) -> 247.5 | R15: =参数输入表!$I$400*参数输入表!$I$414/10000/(1+参数输入表!$I$429) -> 270 | S15: =参数输入表!$I$400*参数输入表!$I$415/10000/(1+参数输入表!$I$429) -> 270 | T15: =参数输入表!$I$400*参数输入表!$I$416/10000/(1+参数输入表!$I$429) -> 270 | U15: =参数输入表!$I$400*参数输入表!$I$417/10000/(1+参数输入表!$I$429) -> 270 | V15: =参数输入表!$I$400*参数输入表!$I$418/10000/(1+参数输入表!$I$429) -> 270 | W15: =参数输入表!$I$400*参数输入表!$I$419/10000/(1+参数输入表!$I$429) -> 292.5 | X15: =参数输入表!$I$400*参数输入表!$I$420/10000/(1+参数输入表!$I$429) -> 292.5 | Y15: =参数输入表!$I$400*参数输入表!$I$421/10000/(1+参数输入表!$I$429) -> 292.5 | Z15: =参数输入表!$I$400*参数输入表!$I$422/10000/(1+参数输入表!$I$429) -> 292.5 | AA15: =参数输入表!$I$400*参数输入表!$I$423/10000/(1+参数输入表!$I$429) -> 292.5 | AB15: =参数输入表!$I$400*参数输入表!$I$424/10000/(1+参数输入表!$I$429) -> 315 | AC15: =参数输入表!$I$400*参数输入表!$I$425/10000/(1+参数输入表!$I$429) -> 315 | AD15: =参数输入表!$I$400*参数输入表!$I$426/10000/(1+参数输入表!$I$429) -> 315 | AE15: =参数输入表!$I$400*参数输入表!$I$427/10000/(1+参数输入表!$I$429) -> 315 | AF15: =参数输入表!$I$400*参数输入表!$I$428/10000/(1+参数输入表!$I$429)*MONTH(参数输入表!I6)/12 -> 78.75
B16: 2 | C16: 销售费用 | D16: =SUM(F16:AF16) -> 0 | E16: 万元 | F16: ='表5-利润表-资本金(标准格式)'!F20 -> 0 | G16: ='表5-利润表-资本金(标准格式)'!G20 -> 0 | H16: ='表5-利润表-资本金(标准格式)'!H20 -> 0 | I16: ='表5-利润表-资本金(标准格式)'!I20 -> 0 | J16: 0 | K16: 0 | L16: 0 | M16: 0 | N16: 0 | O16: 0 | P16: 0 | Q16: 0 | R16: 0 | S16: 0 | T16: 0 | U16: 0 | V16: 0 | W16: 0 | X16: 0 | Y16: 0 | Z16: 0 | AA16: 0 | AB16: 0 | AC16: 0 | AD16: 0 | AE16: 0 | AF16: 0
B17: 3 | C17: 管理费用 | D17: =SUM(F17:AF17) -> 4313.6169 | E17: 万元 | F17: ='表5-利润表-资本金(标准格式)'!F21 -> 0 | G17: ='表5-利润表-资本金(标准格式)'!G21 -> 0 | H17: ='表5-利润表-资本金(标准格式)'!H21 -> 0 | I17: ='表5-利润表-资本金(标准格式)'!I21 -> 0 | J17: =SUM(J18:J19) -> 1.7018923 | K17: =SUM(K18:K19) -> 14.609164 | L17: =SUM(L18:L19) -> 19.278072 | M17: =SUM(M18:M19) -> 54.329111 | N17: =SUM(N18:N19) -> 54.329111 | O17: =SUM(O18:O19) -> 54.329111 | P17: =SUM(P18:P19) -> 54.329111 | Q17: =SUM(Q18:Q19) -> 54.329111 | ... AF17: =SUM(AF18:AF19) -> 3245.7746
B18: 3.1 | C18: 保险费 | D18: =SUM(F18:AF18) -> 1081.4245 | E18: 万元 | J18: =参数输入表!$I$351*参数输入表!$I$357/(1+参数输入表!$I$380)*J5*(12-MONTH(参数输入表!I8))/12 -> 1.7018923 | K18: =参数输入表!$I$351*参数输入表!$I$358/(1+参数输入表!$I$380)*K5 -> 14.609164 | L18: =参数输入表!$I$351*参数输入表!$I$359/(1+参数输入表!$I$380)*L5 -> 19.278072 | M18: =参数输入表!$I$351*参数输入表!$I$360/(1+参数输入表!$I$380)*M5 -> 54.329111 | N18: =参数输入表!$I$351*参数输入表!$I$361/(1+参数输入表!$I$380)*N5 -> 54.329111 | O18: =参数输入表!$I$351*参数输入表!$I$362/(1+参数输入表!$I$380)*O5 -> 54.329111 | P18: =参数输入表!$I$351*参数输入表!$I$363/(1+参数输入表!$I$380)*P5 -> 54.329111 | Q18: =参数输入表!$I$351*参数输入表!$I$364/(1+参数输入表!$I$380)*Q5 -> 54.329111 | R18: =参数输入表!$I$351*参数输入表!$I$365/(1+参数输入表!$I$380)*R5 -> 54.329111 | S18: =参数输入表!$I$351*参数输入表!$I$366/(1+参数输入表!$I$380)*S5 -> 54.329111 | T18: =参数输入表!$I$351*参数输入表!$I$367/(1+参数输入表!$I$380)*T5 -> 54.329111 | U18: =参数输入表!$I$351*参数输入表!$I$368/(1+参数输入表!$I$380)*U5 -> 54.329111 | V18: =参数输入表!$I$351*参数输入表!$I$369/(1+参数输入表!$I$380)*V5 -> 54.329111 | W18: =参数输入表!$I$351*参数输入表!$I$370/(1+参数输入表!$I$380)*W5 -> 54.329111 | X18: =参数输入表!$I$351*参数输入表!$I$371/(1+参数输入表!$I$380)*X5 -> 54.329111 | Y18: =参数输入表!$I$351*参数输入表!$I$372/(1+参数输入表!$I$380)*Y5 -> 54.329111 | Z18: =参数输入表!$I$351*参数输入表!$I$373/(1+参数输入表!$I$380)*Z5 -> 54.329111 | AA18: =参数输入表!$I$351*参数输入表!$I$374/(1+参数输入表!$I$380)*AA5 -> 54.329111 | AB18: =参数输入表!$I$351*参数输入表!$I$375/(1+参数输入表!$I$380)*AB5 -> 54.329111 | AC18: =参数输入表!$I$351*参数输入表!$I$376/(1+参数输入表!$I$380)*AC5 -> 54.329111 | AD18: =参数输入表!$I$351*参数输入表!$I$377/(1+参数输入表!$I$380)*AD5 -> 54.329111 | AE18: =参数输入表!$I$351*参数输入表!$I$378/(1+参数输入表!$I$380)*AE5 -> 54.329111 | AF18: =参数输入表!$I$351*参数输入表!$I$379/(1+参数输入表!$I$380)*AF5*MONTH(参数输入表!I6)/12 -> 13.582278
B19: 3.2 | C19: 期末拆除费用 | D19: =SUM(F19:AF19) -> 3232.1923 | E19: 万元 | AF19: =参数输入表!$I$431*参数输入表!$I$432/(1+参数输入表!$I$433) -> 3232.1923
B20: 4 | C20: 研发费用 | D20: =SUM(F20:AF20) -> 0 | E20: 万元 | F20: ='表5-利润表-资本金(标准格式)'!F22 -> 0 | G20: ='表5-利润表-资本金(标准格式)'!G22 -> 0 | H20: ='表5-利润表-资本金(标准格式)'!H22 -> 0 | I20: ='表5-利润表-资本金(标准格式)'!I22 -> 0 | J20: 0 | K20: 0 | L20: 0 | M20: 0 | N20: 0 | O20: 0 | P20: 0 | Q20: 0 | R20: 0 | S20: 0 | T20: 0 | U20: 0 | V20: 0 | W20: 0 | X20: 0 | Y20: 0 | Z20: 0 | AA20: 0 | AB20: 0 | AC20: 0 | AD20: 0 | AE20: 0 | AF20: 0
B21: 5 | C21: 财务费用 | D21: =SUM(F21:AF21) -> 54920.468 | E21: 万元 | F21: ='表5-利润表-资本金(标准格式)'!F23 -> 0 | G21: ='表5-利润表-资本金(标准格式)'!G23 -> 0 | H21: ='表5-利润表-资本金(标准格式)'!H23 -> 0 | I21: ='表5-利润表-资本金(标准格式)'!I23 -> 0 | J21: =SUM(J22:J24) -> 672.2092 | K21: =SUM(K22:K24) -> 3851.2555 | L21: =SUM(L22:L24) -> 5665.7911 | M21: =SUM(M22:M24) -> 5349.7034 | N21: =SUM(N22:N24) -> 5024.1627 | O21: =SUM(O22:O24) -> 4707.0125 | P21: =SUM(P22:P24) -> 4379.5789 | Q21: =SUM(Q22:Q24) -> 4041.4196 | ... AF21: =SUM(AF22:AF24) -> 5.11
B22: 5.1 | C22: 长期借款利息 | D22: =SUM(F22:AF22) -> 46904.724 | E22: 万元 | J22: ='表1-资金筹措及还本付息表'!J44+'表1-资金筹措及还本付息表'!J74 -> 460.34207 | K22: ='表1-资金筹措及还本付息表'!K44+'表1-资金筹措及还本付息表'!K74 -> 3409.2712 | L22: ='表1-资金筹措及还本付息表'!L44+'表1-资金筹措及还本付息表'!L74 -> 5203.3668 | M22: ='表1-资金筹措及还本付息表'!M44+'表1-资金筹措及还本付息表'!M74 -> 4905.5291 | N22: ='表1-资金筹措及还本付息表'!N44+'表1-资金筹措及还本付息表'!N74 -> 4598.2385 | O22: ='表1-资金筹措及还本付息表'!O44+'表1-资金筹措及还本付息表'!O74 -> 4281.0883 | P22: ='表1-资金筹措及还本付息表'!P44+'表1-资金筹措及还本付息表'!P74 -> 3953.6546 | Q22: ='表1-资金筹措及还本付息表'!Q44+'表1-资金筹措及还本付息表'!Q74 -> 3615.4953 | ... AF22: ='表1-资金筹措及还本付息表'!AF44+'表1-资金筹措及还本付息表'!AF74 -> -1.9308572e-13
B23: 5.2 | C23: 短期借款利息 | D23: =SUM(F23:AF23) -> 7601.8339 | E23: 万元 | J23: ='表1-资金筹措及还本付息表'!J84 -> 211.86713 | K23: ='表1-资金筹措及还本付息表'!K84 -> 441.98426 | L23: ='表1-资金筹措及还本付息表'!L84 -> 441.98426 | M23: ='表1-资金筹措及还本付息表'!M84 -> 423.73426 | N23: ='表1-资金筹措及还本付息表'!N84 -> 405.48426 | O23: ='表1-资金筹措及还本付息表'!O84 -> 405.48426 | P23: ='表1-资金筹措及还本付息表'!P84 -> 405.48426 | Q23: ='表1-资金筹措及还本付息表'!Q84 -> 405.48426 | ... AF23: ='表1-资金筹措及还本付息表'!AF84 -> 0
B24: 5.3 | C24: 流动资金借款利息 | D24: =SUM(F24:AF24) -> 413.91 | E24: 万元 | J24: ='表1-资金筹措及还本付息表'!J64 -> 0 | K24: ='表1-资金筹措及还本付息表'!K64 -> 0 | L24: ='表1-资金筹措及还本付息表'!L64 -> 20.44 | M24: ='表1-资金筹措及还本付息表'!M64 -> 20.44 | N24: ='表1-资金筹措及还本付息表'!N64 -> 20.44 | O24: ='表1-资金筹措及还本付息表'!O64 -> 20.44 | P24: ='表1-资金筹措及还本付息表'!P64 -> 20.44 | Q24: ='表1-资金筹措及还本付息表'!Q64 -> 20.44 | ... AF24: ='表1-资金筹措及还本付息表'!AF64 -> 5.11
B25: 二 | C25: 营业外支出 | D25: =SUM(F25:AF25) -> 0 | E25: 万元 | F25: ='表5-利润表-资本金(标准格式)'!F41 -> 0 | G25: ='表5-利润表-资本金(标准格式)'!G41 -> 0 | H25: ='表5-利润表-资本金(标准格式)'!H41 -> 0 | I25: ='表5-利润表-资本金(标准格式)'!I41 -> 0 | J25: =参数输入表!$I$533/(1+参数输入表!$I$556) -> 0 | K25: =参数输入表!$I$534/(1+参数输入表!$I$556) -> 0 | L25: =参数输入表!$I$535/(1+参数输入表!$I$556) -> 0 | M25: =参数输入表!$I$536/(1+参数输入表!$I$556) -> 0 | N25: =参数输入表!$I$537/(1+参数输入表!$I$556) -> 0 | O25: =参数输入表!$I$538/(1+参数输入表!$I$556) -> 0 | P25: =参数输入表!$I$539/(1+参数输入表!$I$556) -> 0 | Q25: =参数输入表!$I$540/(1+参数输入表!$I$556) -> 0 | R25: =参数输入表!$I$541/(1+参数输入表!$I$556) -> 0 | S25: =参数输入表!$I$542/(1+参数输入表!$I$556) -> 0 | T25: =参数输入表!$I$543/(1+参数输入表!$I$556) -> 0 | U25: =参数输入表!$I$544/(1+参数输入表!$I$556) -> 0 | V25: =参数输入表!$I$545/(1+参数输入表!$I$556) -> 0 | W25: =参数输入表!$I$546/(1+参数输入表!$I$556) -> 0 | X25: =参数输入表!$I$547/(1+参数输入表!$I$556) -> 0 | Y25: =参数输入表!$I$548/(1+参数输入表!$I$556) -> 0 | Z25: =参数输入表!$I$549/(1+参数输入表!$I$556) -> 0 | AA25: =参数输入表!$I$550/(1+参数输入表!$I$556) -> 0 | AB25: =参数输入表!$I$551/(1+参数输入表!$I$556) -> 0 | AC25: =参数输入表!$I$552/(1+参数输入表!$I$556) -> 0 | AD25: =参数输入表!$I$553/(1+参数输入表!$I$556) -> 0 | AE25: =参数输入表!$I$554/(1+参数输入表!$I$556) -> 0 | AF25: =参数输入表!$I$555/(1+参数输入表!$I$556) -> 0
B27: 成本费用表-全投资
B28: 序号 | C28: 项目 | D28: 合计 | E28: 单位 | F28: 2020年 | G28: 2021年 | H28: 2022年 | I28: 45107 | J28: 45261 | K28: 2024年 | L28: 2025年 | M28: 2026年 | N28: 2027年 | O28: 2028年 | P28: 2029年 | Q28: 2030年 | R28: 2031年 | S28: 2032年 | T28: 2033年 | U28: 2034年 | V28: 2035年 | W28: 2036年 | X28: 2037年 | Y28: 2038年 | Z28: 2039年 | AA28: 2040年 | AB28: 2041年 | AC28: 2042年 | AD28: 2043年 | AE28: 2044年 | AF28: 53051
F29: 1 | G29: 2 | H29: 3 | I29: 4 | J29: 5 | K29: 6 | L29: 7 | M29: 8 | N29: 9 | O29: 10 | P29: 11 | Q29: 12 | R29: 13 | S29: 14 | T29: 15 | U29: 16 | V29: 17 | W29: 18 | X29: 19 | Y29: 20 | Z29: 21 | AA29: 22 | AB29: 23 | AC29: 24 | AD29: 25 | AE29: 26 | AF29: 27
C30: 投产比例 | F30: =参数输入表!$I$39 -> 0 | G30: =参数输入表!$I$40 -> 0.03125 | H30: =参数输入表!$I$41 -> 0.03125 | I30: =参数输入表!$I$42 -> 0.03125 | J30: =参数输入表!$I$43 -> 0.1765625 | K30: =参数输入表!$I$44 -> 0.7578125 | L30: =参数输入表!$I$45 -> 1 | M30: =参数输入表!$I$46 -> 1 | N30: =参数输入表!$I$47 -> 1 | O30: =参数输入表!$I$48 -> 1 | P30: =参数输入表!$I$49 -> 1 | Q30: =参数输入表!$I$50 -> 1 | R30: =参数输入表!$I$51 -> 1 | S30: =参数输入表!$I$52 -> 1 | T30: =参数输入表!$I$53 -> 1 | U30: =参数输入表!$I$54 -> 1 | V30: =参数输入表!$I$55 -> 1 | W30: =参数输入表!$I$56 -> 1 | X30: =参数输入表!$I$57 -> 1 | Y30: =参数输入表!$I$58 -> 1 | Z30: =参数输入表!$I$59 -> 1 | AA30: =参数输入表!$I$60 -> 1 | AB30: =参数输入表!$I$61 -> 1 | AC30: =参数输入表!$I$62 -> 1 | AD30: =参数输入表!$I$63 -> 1 | AE30: =参数输入表!$I$64 -> 1 | AF30: =参数输入表!$I$65 -> 1
B31: 一 | C31: 生产经营成本（全投资） | D31: =SUM(F31:AF31) -> 225075.3 | E31: 万元 | F31: =F32+F41+F42+F45 -> 0 | G31: =G32+G41+G42+G45 -> 0 | H31: =H32+H41+H42+H45 -> 0 | I31: =I32+I41+I42+I45 -> 2000 | J31: =J32+J41+J42+J45 -> 2378.4768 | K31: =K32+K41+K42+K45 -> 10100.563 | L31: =L32+L41+L42+L45 -> 11313.938 | M31: =M32+M41+M42+M45 -> 11687.129 | ... AF31: =AF32+AF41+AF42+AF45 -> 4239.4163
B32: 1 | C32: 生产成本 | D32: =SUM(F32:AF32) -> 220761.69 | E32: 万元 | F32: =F7 -> 0 | G32: =G7 -> 0 | H32: =H7 -> 0 | I32: =I7 -> 2000 | J32: =SUM(J33:J40) -> 2376.7749 | K32: =SUM(K33:K40) -> 10085.953 | L32: =SUM(L33:L40) -> 11294.66 | M32: =SUM(M33:M40) -> 11632.8 | N32: =SUM(N33:N40) -> 11661.6 | O32: =SUM(O33:O40) -> 11690.4 | P32: =SUM(P33:P40) -> 11719.2 | Q32: =SUM(Q33:Q40) -> 11748 | ... AF32: =SUM(AF33:AF40) -> 993.64165
B33: 1.1 | C33: 材料费 | D33: =SUM(F33:AF33) -> 1206.75 | E33: 万元 | J33: =J8 -> 28.25 | K33: =K8 -> 242.5 | L33: =L8 -> 320 | M33: =M8 -> 32 | N33: =N8 -> 32 | O33: =O8 -> 32 | P33: =P8 -> 32 | Q33: =Q8 -> 32 | ... AF33: =AF8 -> 8
B34: 1.2 | C34: 维修费 | D34: =SUM(F34:AF34) -> 13768.266 | E34: 万元 | J34: =J9 -> 0 | K34: =K9 -> 0 | L34: =L9 -> 0 | M34: =M9 -> 483.09706 | N34: =N9 -> 483.09706 | O34: =O9 -> 483.09706 | P34: =P9 -> 483.09706 | Q34: =Q9 -> 483.09706 | ... AF34: =AF9 -> 241.54853
B35: 1.3 | C35: 生产人员薪酬及福利 | D35: =SUM(F35:AF35) -> 19563.143 | E35: 万元 | J35: =J10 -> 53.3925 | K35: =K10 -> 480.15 | L35: =L10 -> 662.4 | M35: =M10 -> 691.2 | N35: =N10 -> 720 | O35: =O10 -> 748.8 | P35: =P10 -> 777.6 | Q35: =Q10 -> 806.4 | ... AF35: =AF10 -> 309.6
B36: 1.4 | C36: 长期待摊费用当期摊销 | D36: =SUM(F36:AF36) -> 1834.8624 | E36: 万元 | J36: =J11 -> 0 | K36: =K11 -> 0 | L36: =L11 -> 0 | M36: =M11 -> 91.743119 | N36: =N11 -> 91.743119 | O36: =O11 -> 91.743119 | P36: =P11 -> 91.743119 | Q36: =Q11 -> 91.743119 | ... AF36: =AF11 -> 91.743119
B37: 1.5 | C37: 营业相关资产折旧及摊销（全投资） | D37: =SUM(F37:AF37) -> 154159.94 | E37: 万元 | J37: ='表2-折旧摊销表'!J201+'表2-折旧摊销表'!J203 -> 2089.4074 | K37: ='表2-折旧摊销表'!K201+'表2-折旧摊销表'!K203 -> 8338.0534 | L37: ='表2-折旧摊销表'!L201+'表2-折旧摊销表'!L203 -> 9031.2598 | M37: ='表2-折旧摊销表'!M201+'表2-折旧摊销表'!M203 -> 9031.2598 | N37: ='表2-折旧摊销表'!N201+'表2-折旧摊销表'!N203 -> 9031.2598 | O37: ='表2-折旧摊销表'!O201+'表2-折旧摊销表'!O203 -> 9031.2598 | P37: ='表2-折旧摊销表'!P201+'表2-折旧摊销表'!P203 -> 9031.2598 | Q37: ='表2-折旧摊销表'!Q201+'表2-折旧摊销表'!Q203 -> 9031.2598 | ... AF37: ='表2-折旧摊销表'!AF201+'表2-折旧摊销表'!AF203 -> 0
B38: 1.6 | C38: 其他费用 | D38: =SUM(F38:AF38) -> 6750.75 | E38: 万元 | J38: =J13 -> 28.25 | K38: =K13 -> 242.5 | L38: =L13 -> 320 | M38: =M13 -> 320 | N38: =N13 -> 320 | O38: =O13 -> 320 | P38: =P13 -> 320 | Q38: =Q13 -> 320 | ... AF38: =AF13 -> 80
B39: 1.7 | C39: 储能费用 | D39: =SUM(F39:AF39) -> 15526.725 | E39: 万元 | J39: =J14 -> 64.975 | K39: =K14 -> 557.75 | L39: =L14 -> 736 | M39: =M14 -> 736 | N39: =N14 -> 736 | O39: =O14 -> 736 | P39: =P14 -> 736 | Q39: =Q14 -> 736 | ... AF39: =AF14 -> 184
B40: 1.8 | C40: 场地租金费用 | D40: =SUM(F40:AF40) -> 5951.25 | E40: 万元 | J40: =J15 -> 112.5 | K40: =K15 -> 225 | L40: =L15 -> 225 | M40: =M15 -> 247.5 | N40: =N15 -> 247.5 | O40: =O15 -> 247.5 | P40: =P15 -> 247.5 | Q40: =Q15 -> 247.5 | ... AF40: =AF15 -> 78.75
B41: 2 | C41: 销售费用 | D41: =SUM(F41:AF41) -> 0 | E41: 万元 | F41: =F16 -> 0 | G41: =G16 -> 0 | H41: =H16 -> 0 | I41: =I16 -> 0 | J41: 0 | K41: 0 | L41: 0 | M41: 0 | N41: 0 | O41: 0 | P41: 0 | Q41: 0 | R41: 0 | S41: 0 | T41: 0 | U41: 0 | V41: 0 | W41: 0 | X41: 0 | Y41: 0 | Z41: 0 | AA41: 0 | AB41: 0 | AC41: 0 | AD41: 0 | AE41: 0 | AF41: 0
B42: 3 | C42: 管理费用 | D42: =SUM(F42:AF42) -> 4313.6169 | E42: 万元 | F42: =F17 -> 0 | G42: =G17 -> 0 | H42: =H17 -> 0 | I42: =I17 -> 0 | J42: =SUM(J43:J44) -> 1.7018923 | K42: =SUM(K43:K44) -> 14.609164 | L42: =SUM(L43:L44) -> 19.278072 | M42: =SUM(M43:M44) -> 54.329111 | N42: =SUM(N43:N44) -> 54.329111 | O42: =SUM(O43:O44) -> 54.329111 | P42: =SUM(P43:P44) -> 54.329111 | Q42: =SUM(Q43:Q44) -> 54.329111 | ... AF42: =SUM(AF43:AF44) -> 3245.7746
B43: 3.1 | C43: 保险费 | D43: =SUM(F43:AF43) -> 1081.4245 | E43: 万元 | J43: =J18 -> 1.7018923 | K43: =K18 -> 14.609164 | L43: =L18 -> 19.278072 | M43: =M18 -> 54.329111 | N43: =N18 -> 54.329111 | O43: =O18 -> 54.329111 | P43: =P18 -> 54.329111 | Q43: =Q18 -> 54.329111 | ... AF43: =AF18 -> 13.582278
B44: 3.2 | C44: 期末拆除费用 | D44: =SUM(F44:AF44) -> 3232.1923 | E44: 万元 | AF44: =AF19 -> 3232.1923
B45: 4 | C45: 研发费用 | D45: =SUM(F45:AF45) -> 0 | E45: 万元 | F45: =F20 -> 0 | G45: =G20 -> 0 | H45: =H20 -> 0 | I45: =I20 -> 0 | J45: 0 | K45: 0 | L45: 0 | M45: 0 | N45: 0 | O45: 0 | P45: 0 | Q45: 0 | R45: 0 | S45: 0 | T45: 0 | U45: 0 | V45: 0 | W45: 0 | X45: 0 | Y45: 0 | Z45: 0 | AA45: 0 | AB45: 0 | AC45: 0 | AD45: 0 | AE45: 0 | AF45: 0
B46: 二 | C46: 营业外支出 | D46: =SUM(F46:AF46) -> 0 | E46: 万元 | F46: =F21 -> 0 | G46: =G21 -> 0 | H46: =H21 -> 0 | I46: =I21 -> 0 | J46: =参数输入表!$I$533/(1+参数输入表!$I$556) -> 0 | K46: =参数输入表!$I$534/(1+参数输入表!$I$556) -> 0 | L46: =参数输入表!$I$535/(1+参数输入表!$I$556) -> 0 | M46: =参数输入表!$I$536/(1+参数输入表!$I$556) -> 0 | N46: =参数输入表!$I$537/(1+参数输入表!$I$556) -> 0 | O46: =参数输入表!$I$538/(1+参数输入表!$I$556) -> 0 | P46: =参数输入表!$I$539/(1+参数输入表!$I$556) -> 0 | Q46: =参数输入表!$I$540/(1+参数输入表!$I$556) -> 0 | R46: =参数输入表!$I$541/(1+参数输入表!$I$556) -> 0 | S46: =参数输入表!$I$542/(1+参数输入表!$I$556) -> 0 | T46: =参数输入表!$I$543/(1+参数输入表!$I$556) -> 0 | U46: =参数输入表!$I$544/(1+参数输入表!$I$556) -> 0 | V46: =参数输入表!$I$545/(1+参数输入表!$I$556) -> 0 | W46: =参数输入表!$I$546/(1+参数输入表!$I$556) -> 0 | X46: =参数输入表!$I$547/(1+参数输入表!$I$556) -> 0 | Y46: =参数输入表!$I$548/(1+参数输入表!$I$556) -> 0 | Z46: =参数输入表!$I$549/(1+参数输入表!$I$556) -> 0 | AA46: =参数输入表!$I$550/(1+参数输入表!$I$556) -> 0 | AB46: =参数输入表!$I$551/(1+参数输入表!$I$556) -> 0 | AC46: =参数输入表!$I$552/(1+参数输入表!$I$556) -> 0 | AD46: =参数输入表!$I$553/(1+参数输入表!$I$556) -> 0 | AE46: =参数输入表!$I$554/(1+参数输入表!$I$556) -> 0 | AF46: =参数输入表!$I$555/(1+参数输入表!$I$556) -> 0
B49: 成本现金支出表
B50: 序号 | C50: 项目 | D50: 合计 | E50: 单位 | F50: 2020年 | G50: 2021年 | H50: 2022年 | I50: 45107 | J50: 45261 | K50: 2024年 | L50: 2025年 | M50: 2026年 | N50: 2027年 | O50: 2028年 | P50: 2029年 | Q50: 2030年 | R50: 2031年 | S50: 2032年 | T50: 2033年 | U50: 2034年 | V50: 2035年 | W50: 2036年 | X50: 2037年 | Y50: 2038年 | Z50: 2039年 | AA50: 2040年 | AB50: 2041年 | AC50: 2042年 | AD50: 2043年 | AE50: 2044年 | AF50: 53051
F51: 1 | G51: 2 | H51: 3 | I51: 4 | J51: 5 | K51: 6 | L51: 7 | M51: 8 | N51: 9 | O51: 10 | P51: 11 | Q51: 12 | R51: 13 | S51: 14 | T51: 15 | U51: 16 | V51: 17 | W51: 18 | X51: 19 | Y51: 20 | Z51: 21 | AA51: 22 | AB51: 23 | AC51: 24 | AD51: 25 | AE51: 26 | AF51: 27
C52: 投产比例 | F52: =参数输入表!$I$39 -> 0 | G52: =参数输入表!$I$40 -> 0.03125 | H52: =参数输入表!$I$41 -> 0.03125 | I52: =参数输入表!$I$42 -> 0.03125 | J52: =参数输入表!$I$43 -> 0.1765625 | K52: =参数输入表!$I$44 -> 0.7578125 | L52: =参数输入表!$I$45 -> 1 | M52: =参数输入表!$I$46 -> 1 | N52: =参数输入表!$I$47 -> 1 | O52: =参数输入表!$I$48 -> 1 | P52: =参数输入表!$I$49 -> 1 | Q52: =参数输入表!$I$50 -> 1 | R52: =参数输入表!$I$51 -> 1 | S52: =参数输入表!$I$52 -> 1 | T52: =参数输入表!$I$53 -> 1 | U52: =参数输入表!$I$54 -> 1 | V52: =参数输入表!$I$55 -> 1 | W52: =参数输入表!$I$56 -> 1 | X52: =参数输入表!$I$57 -> 1 | Y52: =参数输入表!$I$58 -> 1 | Z52: =参数输入表!$I$59 -> 1 | AA52: =参数输入表!$I$60 -> 1 | AB52: =参数输入表!$I$61 -> 1 | AC52: =参数输入表!$I$62 -> 1 | AD52: =参数输入表!$I$63 -> 1 | AE52: =参数输入表!$I$64 -> 1 | AF52: =参数输入表!$I$65 -> 1
B53: 一 | C53: 生产经营现金支出合计 | D53: =SUM(F53:AF53) -> 69080.5 | E53: 万元 | J53: =J54+J62+J63+J66 -> 289.06939 | K53: =K54+K62+K63+K66 -> 1762.5092 | L53: =L54+L62+L63+L66 -> 2282.6781 | M53: =M54+M62+M63+M66 -> 3064.1262 | N53: =N54+N62+N63+N66 -> 2592.9262 | O53: =O54+O62+O63+O66 -> 2621.7262 | P53: =P54+P62+P63+P66 -> 2650.5262 | Q53: =Q54+Q62+Q63+Q66 -> 2679.3262 | ... AF53: =AF54+AF62+AF63+AF66 -> 4147.6732
B54: 1 | C54: 生产相关现金支出 | D54: =SUM(F54:AF54) -> 64766.884 | E54: 万元 | J54: =SUM(J55:J61) -> 287.3675 | K54: =SUM(K55:K61) -> 1747.9 | L54: =SUM(L55:L61) -> 2263.4 | M54: =SUM(M55:M61) -> 3009.7971 | N54: =SUM(N55:N61) -> 2538.5971 | O54: =SUM(O55:O61) -> 2567.3971 | P54: =SUM(P55:P61) -> 2596.1971 | Q54: =SUM(Q55:Q61) -> 2624.9971 | ... AF54: =SUM(AF55:AF61) -> 901.89853
B55: 1.1 | C55: 材料费 | D55: =SUM(F55:AF55) -> 1206.75 | E55: 万元 | J55: =参数输入表!$I$289*参数输入表!$I$295*J52*(12-MONTH(参数输入表!$I$8))/12 -> 28.25 | K55: =参数输入表!$I$289*参数输入表!$I$296*K52 -> 242.5 | L55: =参数输入表!$I$289*参数输入表!$I$297*L52 -> 320 | M55: =参数输入表!$I$289*参数输入表!$I$298*M52 -> 32 | N55: =参数输入表!$I$289*参数输入表!$I$299*N52 -> 32 | O55: =参数输入表!$I$289*参数输入表!$I$300*O52 -> 32 | P55: =参数输入表!$I$289*参数输入表!$I$301*P52 -> 32 | Q55: =参数输入表!$I$289*参数输入表!$I$302*Q52 -> 32 | R55: =参数输入表!$I$289*参数输入表!$I$303*R52 -> 32 | S55: =参数输入表!$I$289*参数输入表!$I$304*S52 -> 32 | T55: =参数输入表!$I$289*参数输入表!$I$305*T52 -> 32 | U55: =参数输入表!$I$289*参数输入表!$I$306*U52 -> 32 | V55: =参数输入表!$I$289*参数输入表!$I$307*V52 -> 32 | W55: =参数输入表!$I$289*参数输入表!$I$308*W52 -> 32 | X55: =参数输入表!$I$289*参数输入表!$I$309*X52 -> 32 | Y55: =参数输入表!$I$289*参数输入表!$I$310*Y52 -> 32 | Z55: =参数输入表!$I$289*参数输入表!$I$311*Z52 -> 32 | AA55: =参数输入表!$I$289*参数输入表!$I$312*AA52 -> 32 | AB55: =参数输入表!$I$289*参数输入表!$I$313*AB52 -> 32 | AC55: =参数输入表!$I$289*参数输入表!$I$314*AC52 -> 32 | AD55: =参数输入表!$I$289*参数输入表!$I$315*AD52 -> 32 | AE55: =参数输入表!$I$289*参数输入表!$I$316*AE52 -> 32 | AF55: =参数输入表!$I$289*参数输入表!$I$317*AF52*MONTH(参数输入表!I6)/12 -> 8
B56: 1.2 | C56: 维修费 | D56: =SUM(F56:AF56) -> 13768.266 | E56: 万元 | J56: =参数输入表!$I$320*参数输入表!$I$326*J52*(12-MONTH(参数输入表!$I$8))/12 -> 0 | K56: =参数输入表!$I$320*参数输入表!$I$327*K52 -> 0 | L56: =参数输入表!$I$320*参数输入表!$I$328*L52 -> 0 | M56: =参数输入表!$I$320*参数输入表!$I$329*M52 -> 483.09706 | N56: =参数输入表!$I$320*参数输入表!$I$330*N52 -> 483.09706 | O56: =参数输入表!$I$320*参数输入表!$I$331*O52 -> 483.09706 | P56: =参数输入表!$I$320*参数输入表!$I$332*P52 -> 483.09706 | Q56: =参数输入表!$I$320*参数输入表!$I$333*Q52 -> 483.09706 | R56: =参数输入表!$I$320*参数输入表!$I$334*R52 -> 644.12941 | S56: =参数输入表!$I$320*参数输入表!$I$335*S52 -> 644.12941 | T56: =参数输入表!$I$320*参数输入表!$I$336*T52 -> 644.12941 | U56: =参数输入表!$I$320*参数输入表!$I$337*U52 -> 644.12941 | V56: =参数输入表!$I$320*参数输入表!$I$338*V52 -> 644.12941 | W56: =参数输入表!$I$320*参数输入表!$I$339*W52 -> 805.16176 | X56: =参数输入表!$I$320*参数输入表!$I$340*X52 -> 805.16176 | Y56: =参数输入表!$I$320*参数输入表!$I$341*Y52 -> 805.16176 | Z56: =参数输入表!$I$320*参数输入表!$I$342*Z52 -> 805.16176 | AA56: =参数输入表!$I$320*参数输入表!$I$343*AA52 -> 805.16176 | AB56: =参数输入表!$I$320*参数输入表!$I$344*AB52 -> 966.19411 | AC56: =参数输入表!$I$320*参数输入表!$I$345*AC52 -> 966.19411 | AD56: =参数输入表!$I$320*参数输入表!$I$346*AD52 -> 966.19411 | AE56: =参数输入表!$I$320*参数输入表!$I$347*AE52 -> 966.19411 | AF56: =参数输入表!$I$320*参数输入表!$I$348*AF52*MONTH(参数输入表!I6)/12 -> 241.54853
B57: 1.3 | C57: 生产人员薪酬及福利 | D57: =SUM(F57:AF57) -> 19563.143 | E57: 万元 | J57: =(参数输入表!$I$383*参数输入表!$I$386+参数输入表!$I$384*参数输入表!$I$387)*(1+参数输入表!$I$388)*(1+参数输入表!$I$389*(J51-参数输入表!$I$7))*J52*(12-MONTH(参数输入表!$I$8))/12 -> 53.3925 | K57: =(参数输入表!$I$383*参数输入表!$I$386+参数输入表!$I$384*参数输入表!$I$387)*(1+参数输入表!$I$388)*(1+参数输入表!$I$389*(K51-参数输入表!$I$7))*K52 -> 480.15 | L57: =(参数输入表!$I$383*参数输入表!$I$386+参数输入表!$I$384*参数输入表!$I$387)*(1+参数输入表!$I$388)*(1+参数输入表!$I$389*(L51-参数输入表!$I$7))*L52 -> 662.4 | M57: =(参数输入表!$I$383*参数输入表!$I$386+参数输入表!$I$384*参数输入表!$I$387)*(1+参数输入表!$I$388)*(1+参数输入表!$I$389*(M51-参数输入表!$I$7))*M52 -> 691.2 | N57: =(参数输入表!$I$383*参数输入表!$I$386+参数输入表!$I$384*参数输入表!$I$387)*(1+参数输入表!$I$388)*(1+参数输入表!$I$389*(N51-参数输入表!$I$7))*N52 -> 720 | O57: =(参数输入表!$I$383*参数输入表!$I$386+参数输入表!$I$384*参数输入表!$I$387)*(1+参数输入表!$I$388)*(1+参数输入表!$I$389*(O51-参数输入表!$I$7))*O52 -> 748.8 | P57: =(参数输入表!$I$383*参数输入表!$I$386+参数输入表!$I$384*参数输入表!$I$387)*(1+参数输入表!$I$388)*(1+参数输入表!$I$389*(P51-参数输入表!$I$7))*P52 -> 777.6 | Q57: =(参数输入表!$I$383*参数输入表!$I$386+参数输入表!$I$384*参数输入表!$I$387)*(1+参数输入表!$I$388)*(1+参数输入表!$I$389*(Q51-参数输入表!$I$7))*Q52 -> 806.4 | R57: =(参数输入表!$I$383*参数输入表!$I$386+参数输入表!$I$384*参数输入表!$I$387)*(1+参数输入表!$I$388)*(1+参数输入表!$I$389*(R51-参数输入表!$I$7))*R52 -> 835.2 | ... AE57: =(参数输入表!$I$383*参数输入表!$I$386+参数输入表!$I$384*参数输入表!$I$387)*(1+参数输入表!$I$388)*(1+参数输入表!$I$389*(AE51-参数输入表!$I$7))*AE52 -> 1209.6 | AF57: =(参数输入表!$I$383*参数输入表!$I$386+参数输入表!$I$384*参数输入表!$I$387)*(1+参数输入表!$I$388)*(1+参数输入表!$I$389*(AF51-参数输入表!$I$7))*AF52*MONTH(参数输入表!I6)/12 -> 309.6
B58: 1.4 | C58: 长期待摊实际支出 | D58: =SUM(F58:AF58) -> 2000 | E58: 万元 | J58: =参数输入表!$I$463 -> 0 | K58: =参数输入表!$I$464 -> 0 | L58: =参数输入表!$I$465 -> 0 | M58: =参数输入表!$I$466 -> 500 | N58: =参数输入表!$I$467 -> 0 | O58: =参数输入表!$I$468 -> 0 | P58: =参数输入表!$I$469 -> 0 | Q58: =参数输入表!$I$470 -> 0 | R58: =参数输入表!$I$471 -> 500 | S58: =参数输入表!$I$472 -> 0 | T58: =参数输入表!$I$473 -> 0 | U58: =参数输入表!$I$474 -> 0 | V58: =参数输入表!$I$475 -> 0 | W58: =参数输入表!$I$476 -> 500 | X58: =参数输入表!$I$477 -> 0 | Y58: =参数输入表!$I$478 -> 0 | Z58: =参数输入表!$I$479 -> 0 | AA58: =参数输入表!$I$480 -> 0 | AB58: =参数输入表!$I$481 -> 500 | AC58: =参数输入表!$I$482 -> 0 | AD58: =参数输入表!$I$483 -> 0 | AE58: =参数输入表!$I$484 -> 0 | AF58: =参数输入表!$I$485 -> 0
B59: 1.5 | C59: 其他费用 | D59: =SUM(F59:AF59) -> 6750.75 | E59: 万元 | J59: =参数输入表!$I$392*参数输入表!$I$393*J52*(12-MONTH(参数输入表!$I$8))/12 -> 28.25 | K59: =参数输入表!$I$392*参数输入表!$I$393*K52 -> 242.5 | L59: =参数输入表!$I$392*参数输入表!$I$393*L52 -> 320 | M59: =参数输入表!$I$392*参数输入表!$I$393*M52 -> 320 | N59: =参数输入表!$I$392*参数输入表!$I$393*N52 -> 320 | O59: =参数输入表!$I$392*参数输入表!$I$393*O52 -> 320 | P59: =参数输入表!$I$392*参数输入表!$I$393*P52 -> 320 | Q59: =参数输入表!$I$392*参数输入表!$I$393*Q52 -> 320 | R59: =参数输入表!$I$392*参数输入表!$I$393*R52 -> 320 | ... AE59: =参数输入表!$I$392*参数输入表!$I$393*AE52 -> 320 | AF59: =参数输入表!$I$392*参数输入表!$I$393*AF52*MONTH(参数输入表!I6)/12 -> 80
B60: 1.6 | C60: 储能费用 | D60: =SUM(F60:AF60) -> 15526.725 | E60: 万元 | J60: =参数输入表!$I$396*参数输入表!$I$397*1000/10000*J52*(12-MONTH(参数输入表!$I$8))/12 -> 64.975 | K60: =参数输入表!$I$396*参数输入表!$I$397*1000/10000*K52 -> 557.75 | L60: =参数输入表!$I$396*参数输入表!$I$397*1000/10000*L52 -> 736 | M60: =参数输入表!$I$396*参数输入表!$I$397*1000/10000*M52 -> 736 | N60: =参数输入表!$I$396*参数输入表!$I$397*1000/10000*N52 -> 736 | O60: =参数输入表!$I$396*参数输入表!$I$397*1000/10000*O52 -> 736 | P60: =参数输入表!$I$396*参数输入表!$I$397*1000/10000*P52 -> 736 | Q60: =参数输入表!$I$396*参数输入表!$I$397*1000/10000*Q52 -> 736 | R60: =参数输入表!$I$396*参数输入表!$I$397*1000/10000*R52 -> 736 | ... AE60: =参数输入表!$I$396*参数输入表!$I$397*1000/10000*AE52 -> 736 | AF60: =参数输入表!$I$396*参数输入表!$I$397*1000/10000*AF52*MONTH(参数输入表!I6)/12 -> 184
B61: 1.7 | C61: 场地租金费用 | D61: =SUM(F61:AF61) -> 5951.25 | E61: 万元 | J61: =参数输入表!$I$400*参数输入表!$I$406/10000*(12-MONTH(参数输入表!$I$8))/12 -> 112.5 | K61: =参数输入表!$I$400*参数输入表!$I$407/10000 -> 225 | L61: =参数输入表!$I$400*参数输入表!$I$408/10000 -> 225 | M61: =参数输入表!$I$400*参数输入表!$I$409/10000 -> 247.5 | N61: =参数输入表!$I$400*参数输入表!$I$410/10000 -> 247.5 | O61: =参数输入表!$I$400*参数输入表!$I$411/10000 -> 247.5 | P61: =参数输入表!$I$400*参数输入表!$I$412/10000 -> 247.5 | Q61: =参数输入表!$I$400*参数输入表!$I$413/10000 -> 247.5 | R61: =参数输入表!$I$400*参数输入表!$I$414/10000 -> 270 | S61: =参数输入表!$I$400*参数输入表!$I$415/10000 -> 270 | T61: =参数输入表!$I$400*参数输入表!$I$416/10000 -> 270 | U61: =参数输入表!$I$400*参数输入表!$I$417/10000 -> 270 | V61: =参数输入表!$I$400*参数输入表!$I$418/10000 -> 270 | W61: =参数输入表!$I$400*参数输入表!$I$419/10000 -> 292.5 | X61: =参数输入表!$I$400*参数输入表!$I$420/10000 -> 292.5 | Y61: =参数输入表!$I$400*参数输入表!$I$421/10000 -> 292.5 | Z61: =参数输入表!$I$400*参数输入表!$I$422/10000 -> 292.5 | AA61: =参数输入表!$I$400*参数输入表!$I$423/10000 -> 292.5 | AB61: =参数输入表!$I$400*参数输入表!$I$424/10000 -> 315 | AC61: =参数输入表!$I$400*参数输入表!$I$425/10000 -> 315 | AD61: =参数输入表!$I$400*参数输入表!$I$426/10000 -> 315 | AE61: =参数输入表!$I$400*参数输入表!$I$427/10000 -> 315 | AF61: =参数输入表!$I$400*参数输入表!$I$428/10000*MONTH(参数输入表!I6)/12 -> 78.75
B62: 2 | C62: 销售费用现金支出 | D62: =SUM(F62:AF62) -> 0 | E62: 万元 | J62: 0 | K62: 0 | L62: 0 | M62: 0 | N62: 0 | O62: 0 | P62: 0 | Q62: 0 | R62: 0 | S62: 0 | T62: 0 | U62: 0 | V62: 0 | W62: 0 | X62: 0 | Y62: 0 | Z62: 0 | AA62: 0 | AB62: 0 | AC62: 0 | AD62: 0 | AE62: 0 | AF62: 0
B63: 3 | C63: 管理费用现金支出 | D63: =SUM(F63:AF63) -> 4313.6169 | E63: 万元 | J63: =SUM(J64:J65) -> 1.7018923 | K63: =SUM(K64:K65) -> 14.609164 | L63: =SUM(L64:L65) -> 19.278072 | M63: =SUM(M64:M65) -> 54.329111 | N63: =SUM(N64:N65) -> 54.329111 | O63: =SUM(O64:O65) -> 54.329111 | P63: =SUM(P64:P65) -> 54.329111 | Q63: =SUM(Q64:Q65) -> 54.329111 | ... AF63: =SUM(AF64:AF65) -> 3245.7746
B64: 3.1 | C64: 保险费 | D64: =SUM(F64:AF64) -> 1081.4245 | E64: 万元 | J64: =参数输入表!$I$351*参数输入表!$I$357*J52*(12-MONTH(参数输入表!$I$8))/12 -> 1.7018923 | K64: =参数输入表!$I$351*参数输入表!$I$358*K52 -> 14.609164 | L64: =参数输入表!$I$351*参数输入表!$I$359*L52 -> 19.278072 | M64: =参数输入表!$I$351*参数输入表!$I$360*M52 -> 54.329111 | N64: =参数输入表!$I$351*参数输入表!$I$361*N52 -> 54.329111 | O64: =参数输入表!$I$351*参数输入表!$I$362*O52 -> 54.329111 | P64: =参数输入表!$I$351*参数输入表!$I$363*P52 -> 54.329111 | Q64: =参数输入表!$I$351*参数输入表!$I$364*Q52 -> 54.329111 | R64: =参数输入表!$I$351*参数输入表!$I$365*R52 -> 54.329111 | S64: =参数输入表!$I$351*参数输入表!$I$366*S52 -> 54.329111 | T64: =参数输入表!$I$351*参数输入表!$I$367*T52 -> 54.329111 | U64: =参数输入表!$I$351*参数输入表!$I$368*U52 -> 54.329111 | V64: =参数输入表!$I$351*参数输入表!$I$369*V52 -> 54.329111 | W64: =参数输入表!$I$351*参数输入表!$I$370*W52 -> 54.329111 | X64: =参数输入表!$I$351*参数输入表!$I$371*X52 -> 54.329111 | Y64: =参数输入表!$I$351*参数输入表!$I$372*Y52 -> 54.329111 | Z64: =参数输入表!$I$351*参数输入表!$I$373*Z52 -> 54.329111 | AA64: =参数输入表!$I$351*参数输入表!$I$374*AA52 -> 54.329111 | AB64: =参数输入表!$I$351*参数输入表!$I$375*AB52 -> 54.329111 | AC64: =参数输入表!$I$351*参数输入表!$I$376*AC52 -> 54.329111 | AD64: =参数输入表!$I$351*参数输入表!$I$377*AD52 -> 54.329111 | AE64: =参数输入表!$I$351*参数输入表!$I$378*AE52 -> 54.329111 | AF64: =参数输入表!$I$351*参数输入表!$I$379*AF52*MONTH(参数输入表!I6)/12 -> 13.582278
B65: 3.2 | C65: 期末拆除费用 | D65: =SUM(F65:AF65) -> 3232.1923 | E65: 万元 | AF65: =参数输入表!$I$431*参数输入表!$I$432 -> 3232.1923
B66: 4 | C66: 研发费用现金支出 | D66: =SUM(F66:AF66) -> 0 | E66: 万元 | J66: 0 | K66: 0 | L66: 0 | M66: 0 | N66: 0 | O66: 0 | P66: 0 | Q66: 0 | R66: 0 | S66: 0 | T66: 0 | U66: 0 | V66: 0 | W66: 0 | X66: 0 | Y66: 0 | Z66: 0 | AA66: 0 | AB66: 0 | AC66: 0 | AD66: 0 | AE66: 0 | AF66: 0
B67: 二 | C67: 营业外现金支出 | D67: =SUM(F67:AF67) -> 0 | E67: 万元 | J67: =参数输入表!$I$533 -> 0 | K67: =参数输入表!$I$534 -> 0 | L67: =参数输入表!$I$535 -> 0 | M67: =参数输入表!$I$536 -> 0 | N67: =参数输入表!$I$537 -> 0 | O67: =参数输入表!$I$538 -> 0 | P67: =参数输入表!$I$539 -> 0 | Q67: =参数输入表!$I$540 -> 0 | R67: =参数输入表!$I$541 -> 0 | S67: =参数输入表!$I$542 -> 0 | T67: =参数输入表!$I$543 -> 0 | U67: =参数输入表!$I$544 -> 0 | V67: =参数输入表!$I$545 -> 0 | W67: =参数输入表!$I$546 -> 0 | X67: =参数输入表!$I$547 -> 0 | Y67: =参数输入表!$I$548 -> 0 | Z67: =参数输入表!$I$549 -> 0 | AA67: =参数输入表!$I$550 -> 0 | AB67: =参数输入表!$I$551 -> 0 | AC67: =参数输入表!$I$552 -> 0 | AD67: =参数输入表!$I$553 -> 0 | AE67: =参数输入表!$I$554 -> 0 | AF67: =参数输入表!$I$555 -> 0
C71: 【成本费用表】中各项成本在参数输入完成后自动生成“不含增值税成本”，直接按照时间序列导入到本表中
C72: 【成本现金支出表】中各项成本在参数输入完成后自动生成“含增值税现金流”，直接按照时间序列导入到本表中
C73: 全投资模式较资本金模式在固定资产折旧有调整，剔除建设期利息对固定资产原值的影响
C74: 标黄部分为相对固定模块，适用于所有项目

Sheet 表4-收入税金表
B2: 收入表
B3: 序号 | C3: 项目 | D3: 合计 | E3: 单位 | F3: 2020年 | G3: 2021年 | H3: 2022年 | I3: 45107 | J3: 2023年12月 | K3: 2024年 | L3: 2025年 | M3: 2026年 | N3: 2027年 | O3: 2028年 | P3: 2029年 | Q3: 2030年 | R3: 2031年 | S3: 2032年 | T3: 2033年 | U3: 2034年 | V3: 2035年 | W3: 2036年 | X3: 2037年 | Y3: 2038年 | Z3: 2039年 | AA3: 2040年 | AB3: 2041年 | AC3: 2042年 | AD3: 2043年 | AE3: 2044年 | AF3: 53051
F4: 1 | G4: 2 | H4: 3 | I4: 4 | J4: 5 | K4: 6 | L4: 7 | M4: 8 | N4: 9 | O4: 10 | P4: 11 | Q4: 12 | R4: 13 | S4: 14 | T4: 15 | U4: 16 | V4: 17 | W4: 18 | X4: 19 | Y4: 20 | Z4: 21 | AA4: 22 | AB4: 23 | AC4: 24 | AD4: 25 | AE4: 26 | AF4: 27
C5: 投产比例 | F5: =参数输入表!$I$39 -> 0 | G5: =参数输入表!$I$40 -> 0.03125 | H5: =参数输入表!$I$41 -> 0.03125 | I5: =参数输入表!$I$42 -> 0.03125 | J5: =参数输入表!$I$43 -> 0.1765625 | K5: =参数输入表!$I$44 -> 0.7578125 | L5: =参数输入表!$I$45 -> 1 | M5: =参数输入表!$I$46 -> 1 | N5: =参数输入表!$I$47 -> 1 | O5: =参数输入表!$I$48 -> 1 | P5: =参数输入表!$I$49 -> 1 | Q5: =参数输入表!$I$50 -> 1 | R5: =参数输入表!$I$51 -> 1 | S5: =参数输入表!$I$52 -> 1 | T5: =参数输入表!$I$53 -> 1 | U5: =参数输入表!$I$54 -> 1 | V5: =参数输入表!$I$55 -> 1 | W5: =参数输入表!$I$56 -> 1 | X5: =参数输入表!$I$57 -> 1 | Y5: =参数输入表!$I$58 -> 1 | Z5: =参数输入表!$I$59 -> 1 | AA5: =参数输入表!$I$60 -> 1 | AB5: =参数输入表!$I$61 -> 1 | AC5: =参数输入表!$I$62 -> 1 | AD5: =参数输入表!$I$63 -> 1 | AE5: =参数输入表!$I$64 -> 1 | AF5: =参数输入表!$I$65 -> 1
B6: 1 | C6: 营业收入 | D6: =SUM(F6:AF6) -> 354199.74 | E6: 万元 | F6: ='表5-利润表-资本金(标准格式)'!F6 -> 0 | G6: ='表5-利润表-资本金(标准格式)'!G6 -> 0 | H6: ='表5-利润表-资本金(标准格式)'!H6 -> 0 | I6: ='表5-利润表-资本金(标准格式)'!I6 -> 2000 | J6: =J7+J19+J15 -> 1656.1591 | K6: =K7+K19+K15 -> 14152.051 | L6: =L7+L19+L15 -> 18589.687 | M6: =M7+M19+M15 -> 18504.498 | N6: =N7+N19+N15 -> 18419.312 | O6: =O7+O19+O15 -> 18334.126 | P6: =P7+P19+P15 -> 18248.938 | Q6: =Q7+Q19+Q15 -> 18163.752 | ... AF6: =AF7+AF19+AF15 -> 3242.0223
B7: 1.1 | C7: 发电销售收入 | D7: =SUM(F7:AF7) -> 270180.41 | E7: 万元 | J7: =J8*(J12-J13-J14)/(1+参数输入表!$I$563) -> 1191.2068 | K7: =K8*(K12-K13-K14)/(1+参数输入表!$I$563) -> 10178.971 | L7: =L8*(L12-L13-L14)/(1+参数输入表!$I$563) -> 13370.773 | M7: =M8*(M12-M13-M14)/(1+参数输入表!$I$563) -> 13309.502 | N7: =N8*(N12-N13-N14)/(1+参数输入表!$I$563) -> 13248.23 | O7: =O8*(O12-O13-O14)/(1+参数输入表!$I$563) -> 13186.959 | P7: =P8*(P12-P13-P14)/(1+参数输入表!$I$563) -> 13125.688 | Q7: =Q8*(Q12-Q13-Q14)/(1+参数输入表!$I$563) -> 13064.416 | ... AF7: =AF8*(AF12-AF13-AF14)/(1+参数输入表!$I$563) -> 3036.3364
C8: 上网电量 | D8: =SUM(F8:AF8) -> 984851.19 | E8: 万度 | J8: =参数输入表!$I$67*参数输入表!$I$68*(1-参数输入表!$I$74)*(1-参数输入表!$I$102)/10*J5*(12-MONTH(参数输入表!I8))/12 -> 4342.1408 | K8: =参数输入表!$I$67*参数输入表!$I$68*(1-参数输入表!$I$75)*(1-参数输入表!$I$103)/10*K5 -> 37103.991 | L8: =参数输入表!$I$67*参数输入表!$I$68*(1-参数输入表!$I$76)*(1-参数输入表!$I$104)/10*L5 -> 48738.624 | M8: =参数输入表!$I$67*参数输入表!$I$68*(1-参数输入表!$I$77)*(1-参数输入表!$I$105)/10*M5 -> 48515.28 | N8: =参数输入表!$I$67*参数输入表!$I$68*(1-参数输入表!$I$78)*(1-参数输入表!$I$106)/10*N5 -> 48291.936 | O8: =参数输入表!$I$67*参数输入表!$I$68*(1-参数输入表!$I$79)*(1-参数输入表!$I$107)/10*O5 -> 48068.592 | P8: =参数输入表!$I$67*参数输入表!$I$68*(1-参数输入表!$I$80)*(1-参数输入表!$I$108)/10*P5 -> 47845.248 | Q8: =参数输入表!$I$67*参数输入表!$I$68*(1-参数输入表!$I$81)*(1-参数输入表!$I$109)/10*Q5 -> 47621.904 | R8: =参数输入表!$I$67*参数输入表!$I$68*(1-参数输入表!$I$82)*(1-参数输入表!$I$110)/10*R5 -> 47398.56 | S8: =参数输入表!$I$67*参数输入表!$I$68*(1-参数输入表!$I$83)*(1-参数输入表!$I$111)/10*S5 -> 47175.216 | T8: =参数输入表!$I$67*参数输入表!$I$68*(1-参数输入表!$I$84)*(1-参数输入表!$I$112)/10*T5 -> 46951.872 | U8: =参数输入表!$I$67*参数输入表!$I$68*(1-参数输入表!$I$85)*(1-参数输入表!$I$113)/10*U5 -> 46728.528 | V8: =参数输入表!$I$67*参数输入表!$I$68*(1-参数输入表!$I$86)*(1-参数输入表!$I$114)/10*V5 -> 46505.184 | W8: =参数输入表!$I$67*参数输入表!$I$68*(1-参数输入表!$I$87)*(1-参数输入表!$I$115)/10*W5 -> 46281.84 | X8: =参数输入表!$I$67*参数输入表!$I$68*(1-参数输入表!$I$88)*(1-参数输入表!$I$116)/10*X5 -> 46058.496 | Y8: =参数输入表!$I$67*参数输入表!$I$68*(1-参数输入表!$I$89)*(1-参数输入表!$I$117)/10*Y5 -> 45835.152 | Z8: =参数输入表!$I$67*参数输入表!$I$68*(1-参数输入表!$I$90)*(1-参数输入表!$I$118)/10*Z5 -> 45611.808 | AA8: =参数输入表!$I$67*参数输入表!$I$68*(1-参数输入表!$I$91)*(1-参数输入表!$I$119)/10*AA5 -> 45388.464 | AB8: =参数输入表!$I$67*参数输入表!$I$68*(1-参数输入表!$I$92)*(1-参数输入表!$I$120)/10*AB5 -> 45165.12 | AC8: =参数输入表!$I$67*参数输入表!$I$68*(1-参数输入表!$I$93)*(1-参数输入表!$I$121)/10*AC5 -> 44941.776 | AD8: =参数输入表!$I$67*参数输入表!$I$68*(1-参数输入表!$I$94)*(1-参数输入表!$I$122)/10*AD5 -> 44718.432 | AE8: =参数输入表!$I$67*参数输入表!$I$68*(1-参数输入表!$I$95)*(1-参数输入表!$I$123)/10*AE5 -> 44495.088 | AF8: =参数输入表!$I$67*参数输入表!$I$68*(1-参数输入表!$I$96)*(1-参数输入表!$I$124)/10*AF5*MONTH(参数输入表!I6)/12 -> 11067.936
C9: 保障内交易电量 | D9: =SUM(F9:AF9) -> 689395.83 | E9: 万度 | J9: =J8*参数输入表!$I$125 -> 3039.4986 | K9: =K8*参数输入表!$I$125 -> 25972.794 | L9: =L8*参数输入表!$I$125 -> 34117.037 | M9: =M8*参数输入表!$I$125 -> 33960.696 | N9: =N8*参数输入表!$I$125 -> 33804.355 | O9: =O8*参数输入表!$I$125 -> 33648.014 | P9: =P8*参数输入表!$I$125 -> 33491.674 | Q9: =Q8*参数输入表!$I$125 -> 33335.333 | ... AF9: =AF8*参数输入表!$I$125 -> 7747.5552
C10: 市场化交易电量 | D10: =SUM(F10:AF10) -> 196970.24 | E10: 万度 | J10: =J8*参数输入表!$I$126 -> 868.42817 | K10: =K8*参数输入表!$I$126 -> 7420.7983 | L10: =L8*参数输入表!$I$126 -> 9747.7248 | M10: =M8*参数输入表!$I$126 -> 9703.056 | N10: =N8*参数输入表!$I$126 -> 9658.3872 | O10: =O8*参数输入表!$I$126 -> 9613.7184 | P10: =P8*参数输入表!$I$126 -> 9569.0496 | Q10: =Q8*参数输入表!$I$126 -> 9524.3808 | ... AF10: =AF8*参数输入表!$I$126 -> 2213.5872
C11: 现货市场交易电量 | D11: =SUM(F11:AF11) -> 98485.119 | E11: 万度 | J11: =J8*参数输入表!$I$127 -> 434.21408 | K11: =K8*参数输入表!$I$127 -> 3710.3991 | L11: =L8*参数输入表!$I$127 -> 4873.8624 | M11: =M8*参数输入表!$I$127 -> 4851.528 | N11: =N8*参数输入表!$I$127 -> 4829.1936 | O11: =O8*参数输入表!$I$127 -> 4806.8592 | P11: =P8*参数输入表!$I$127 -> 4784.5248 | Q11: =Q8*参数输入表!$I$127 -> 4762.1904 | ... AF11: =AF8*参数输入表!$I$127 -> 1106.7936
C12: 加权平均电价（含税） | E12: 元/度 | J12: =参数输入表!$I$560 -> 0.316 | K12: =参数输入表!$I$560 -> 0.316 | L12: =参数输入表!$I$560 -> 0.316 | M12: =参数输入表!$I$560 -> 0.316 | N12: =参数输入表!$I$560 -> 0.316 | O12: =参数输入表!$I$560 -> 0.316 | P12: =参数输入表!$I$560 -> 0.316 | Q12: =参数输入表!$I$560 -> 0.316 | ... AF12: =参数输入表!$I$560 -> 0.316
C13: 电网辅助服务分摊 | E13: 元/度 | J13: =参数输入表!$I$561 -> 0.002 | K13: =参数输入表!$I$561 -> 0.002 | L13: =参数输入表!$I$561 -> 0.002 | M13: =参数输入表!$I$561 -> 0.002 | N13: =参数输入表!$I$561 -> 0.002 | O13: =参数输入表!$I$561 -> 0.002 | P13: =参数输入表!$I$561 -> 0.002 | Q13: =参数输入表!$I$561 -> 0.002 | ... AF13: =参数输入表!$I$561 -> 0.002
C14: 两个细则考核 | E14: 元/度 | J14: =参数输入表!$I$562 -> 0.004 | K14: =参数输入表!$I$562 -> 0.004 | L14: =参数输入表!$I$562 -> 0.004 | M14: =参数输入表!$I$562 -> 0.004 | N14: =参数输入表!$I$562 -> 0.004 | O14: =参数输入表!$I$562 -> 0.004 | P14: =参数输入表!$I$562 -> 0.004 | Q14: =参数输入表!$I$562 -> 0.004 | ... AF14: =参数输入表!$I$562 -> 0.004
B15: 1.2 | C15: 国补收入 | D15: =SUM(F15:AF15) -> 63716.814 | E15: 万元 | J15: =J16*J17*参数输入表!$I$30/10/(1+参数输入表!$I$568) -> 384.26025 | K15: =K16*K17*参数输入表!$I$30/10/(1+参数输入表!$I$568) -> 3283.5391 | L15: =L16*L17*参数输入表!$I$30/10/(1+参数输入表!$I$568) -> 4313.1526 | M15: =M16*M17*参数输入表!$I$30/10/(1+参数输入表!$I$568) -> 4293.3876 | N15: =N16*N17*参数输入表!$I$30/10/(1+参数输入表!$I$568) -> 4273.6227 | O15: =O16*O17*参数输入表!$I$30/10/(1+参数输入表!$I$568) -> 4253.8577 | P15: =P16*P17*参数输入表!$I$30/10/(1+参数输入表!$I$568) -> 4234.0927 | Q15: =Q16*Q17*参数输入表!$I$30/10/(1+参数输入表!$I$568) -> 4214.3278 | ... AF15: =AF16*AF17*参数输入表!$I$30/10/(1+参数输入表!$I$568) -> 0
C16: 补贴电价 | E16: 元/度 | J16: =参数输入表!$I$133 -> 0.1 | K16: =参数输入表!$I$133 -> 0.1 | L16: =参数输入表!$I$133 -> 0.1 | M16: =参数输入表!$I$133 -> 0.1 | N16: =参数输入表!$I$133 -> 0.1 | O16: =参数输入表!$I$133 -> 0.1 | P16: =参数输入表!$I$133 -> 0.1 | Q16: =参数输入表!$I$133 -> 0.1 | ... AF16: =参数输入表!$I$133 -> 0.1
C17: 可获补贴小时数 | D17: =SUM(F17:AF17) -> 22500 | E17: h | J17: =IF(AND((LEFT(J3,4)-YEAR(参数输入表!$I$29))<0,(I18+J8/参数输入表!$I$30*10-参数输入表!$I$27)<=0),J8/参数输入表!$I$30*10,IF(AND((LEFT(J3,4)-YEAR(参数输入表!$I$29))<0,(I18+J8/参数输入表!$I$30*10-参数输入表!$I$27)>0),参数输入表!$I$27-I18,IF((LEFT(J3,4)-YEAR(参数输入表!$I$29))>0,0,MIN(J8/参数输入表!$I$30*10*MONTH(参数输入表!$I$29)/12,参数输入表!$I$27-I18)))) -> 135.6919 | K17: =IF(AND((LEFT(K3,4)-YEAR(参数输入表!$I$29))<0,(J18+K8/参数输入表!$I$30*10-参数输入表!$I$27)<=0),K8/参数输入表!$I$30*10,IF(AND((LEFT(K3,4)-YEAR(参数输入表!$I$29))<0,(J18+K8/参数输入表!$I$30*10-参数输入表!$I$27)>0),参数输入表!$I$27-J18,IF((LEFT(K3,4)-YEAR(参数输入表!$I$29))>0,0,MIN(K8/参数输入表!$I$30*10*MONTH(参数输入表!$I$29)/12,参数输入表!$I$27-J18)))) -> 1159.4997 | L17: =IF(AND((LEFT(L3,4)-YEAR(参数输入表!$I$29))<0,(K18+L8/参数输入表!$I$30*10-参数输入表!$I$27)<=0),L8/参数输入表!$I$30*10,IF(AND((LEFT(L3,4)-YEAR(参数输入表!$I$29))<0,(K18+L8/参数输入表!$I$30*10-参数输入表!$I$27)>0),参数输入表!$I$27-K18,IF((LEFT(L3,4)-YEAR(参数输入表!$I$29))>0,0,MIN(L8/参数输入表!$I$30*10*MONTH(参数输入表!$I$29)/12,参数输入表!$I$27-K18)))) -> 1523.082 | M17: =IF(AND((LEFT(M3,4)-YEAR(参数输入表!$I$29))<0,(L18+M8/参数输入表!$I$30*10-参数输入表!$I$27)<=0),M8/参数输入表!$I$30*10,IF(AND((LEFT(M3,4)-YEAR(参数输入表!$I$29))<0,(L18+M8/参数输入表!$I$30*10-参数输入表!$I$27)>0),参数输入表!$I$27-L18,IF((LEFT(M3,4)-YEAR(参数输入表!$I$29))>0,0,MIN(M8/参数输入表!$I$30*10*MONTH(参数输入表!$I$29)/12,参数输入表!$I$27-L18)))) -> 1516.1025 | N17: =IF(AND((LEFT(N3,4)-YEAR(参数输入表!$I$29))<0,(M18+N8/参数输入表!$I$30*10-参数输入表!$I$27)<=0),N8/参数输入表!$I$30*10,IF(AND((LEFT(N3,4)-YEAR(参数输入表!$I$29))<0,(M18+N8/参数输入表!$I$30*10-参数输入表!$I$27)>0),参数输入表!$I$27-M18,IF((LEFT(N3,4)-YEAR(参数输入表!$I$29))>0,0,MIN(N8/参数输入表!$I$30*10*MONTH(参数输入表!$I$29)/12,参数输入表!$I$27-M18)))) -> 1509.123 | O17: =IF(AND((LEFT(O3,4)-YEAR(参数输入表!$I$29))<0,(N18+O8/参数输入表!$I$30*10-参数输入表!$I$27)<=0),O8/参数输入表!$I$30*10,IF(AND((LEFT(O3,4)-YEAR(参数输入表!$I$29))<0,(N18+O8/参数输入表!$I$30*10-参数输入表!$I$27)>0),参数输入表!$I$27-N18,IF((LEFT(O3,4)-YEAR(参数输入表!$I$29))>0,0,MIN(O8/参数输入表!$I$30*10*MONTH(参数输入表!$I$29)/12,参数输入表!$I$27-N18)))) -> 1502.1435 | P17: =IF(AND((LEFT(P3,4)-YEAR(参数输入表!$I$29))<0,(O18+P8/参数输入表!$I$30*10-参数输入表!$I$27)<=0),P8/参数输入表!$I$30*10,IF(AND((LEFT(P3,4)-YEAR(参数输入表!$I$29))<0,(O18+P8/参数输入表!$I$30*10-参数输入表!$I$27)>0),参数输入表!$I$27-O18,IF((LEFT(P3,4)-YEAR(参数输入表!$I$29))>0,0,MIN(P8/参数输入表!$I$30*10*MONTH(参数输入表!$I$29)/12,参数输入表!$I$27-O18)))) -> 1495.164 | Q17: =IF(AND((LEFT(Q3,4)-YEAR(参数输入表!$I$29))<0,(P18+Q8/参数输入表!$I$30*10-参数输入表!$I$27)<=0),Q8/参数输入表!$I$30*10,IF(AND((LEFT(Q3,4)-YEAR(参数输入表!$I$29))<0,(P18+Q8/参数输入表!$I$30*10-参数输入表!$I$27)>0),参数输入表!$I$27-P18,IF((LEFT(Q3,4)-YEAR(参数输入表!$I$29))>0,0,MIN(Q8/参数输入表!$I$30*10*MONTH(参数输入表!$I$29)/12,参数输入表!$I$27-P18)))) -> 1488.1845 | ... AF17: =IF(AND((LEFT(AF3,4)-YEAR(参数输入表!$I$29))<0,(AE18+AF8/参数输入表!$I$30*10-参数输入表!$I$27)<=0),AF8/参数输入表!$I$30*10,IF(AND((LEFT(AF3,4)-YEAR(参数输入表!$I$29))<0,(AE18+AF8/参数输入表!$I$30*10-参数输入表!$I$27)>0),参数输入表!$I$27-AE18,IF((LEFT(AF3,4)-YEAR(参数输入表!$I$29))>0,0,MIN(AF8/参数输入表!$I$30*10*MONTH(参数输入表!$I$29)/12,参数输入表!$I$27-AE18)))) -> 0
C18: 累计可获补贴小时数 | E18: h | I18: =参数输入表!$I$28 -> 3500 | J18: =I18+J17 -> 3635.6919 | K18: =J18+K17 -> 4795.1916 | L18: =K18+L17 -> 6318.2736 | M18: =L18+M17 -> 7834.3761 | N18: =M18+N17 -> 9343.4991 | O18: =N18+O17 -> 10845.643 | P18: =O18+P17 -> 12340.807 | Q18: =P18+Q17 -> 13828.991 | ... AF18: =AE18+AF17 -> 26000
B19: 1.3 | C19: 绿证交易收入 | D19: =SUM(F19:AF19) -> 18302.512 | E19: 万元 | J19: =J21*J22/10000/(1+参数输入表!$I$574) -> 80.692035 | K19: =K21*K22/10000/(1+参数输入表!$I$574) -> 689.54071 | L19: =L21*L22/10000/(1+参数输入表!$I$574) -> 905.76106 | M19: =M21*M22/10000/(1+参数输入表!$I$574) -> 901.60885 | N19: =N21*N22/10000/(1+参数输入表!$I$574) -> 897.45929 | O19: =O21*O22/10000/(1+参数输入表!$I$574) -> 893.30973 | P19: =P21*P22/10000/(1+参数输入表!$I$574) -> 889.15752 | Q19: =Q21*Q22/10000/(1+参数输入表!$I$574) -> 885.00796 | ... AF19: =AF21*AF22/10000/(1+参数输入表!$I$574) -> 205.68584
C20: 绿证核发电量 | D20: =SUM(F20:AF20) -> 689395.83 | E20: 万度 | J20: =J8*参数输入表!$I$572 -> 3039.4986 | K20: =K8*参数输入表!$I$572 -> 25972.794 | L20: =L8*参数输入表!$I$572 -> 34117.037 | M20: =M8*参数输入表!$I$572 -> 33960.696 | N20: =N8*参数输入表!$I$572 -> 33804.355 | O20: =O8*参数输入表!$I$572 -> 33648.014 | P20: =P8*参数输入表!$I$572 -> 33491.674 | Q20: =Q8*参数输入表!$I$572 -> 33335.333 | ... AF20: =AF8*参数输入表!$I$572 -> 7747.5552
C21: 绿证核发张数 | D21: =SUM(F21:AF21) -> 6893946 | E21: 张 | J21: =INT(J20*10000/1000) -> 30394 | K21: =INT(K20*10000/1000) -> 259727 | L21: =INT(L20*10000/1000) -> 341170 | M21: =INT(M20*10000/1000) -> 339606 | N21: =INT(N20*10000/1000) -> 338043 | O21: =INT(O20*10000/1000) -> 336480 | P21: =INT(P20*10000/1000) -> 334916 | Q21: =INT(Q20*10000/1000) -> 333353 | ... AF21: =INT(AF20*10000/1000) -> 77475
C22: 绿证单价 | E22: 元/张 | J22: =参数输入表!$I$573 -> 30 | K22: =参数输入表!$I$573 -> 30 | L22: =参数输入表!$I$573 -> 30 | M22: =参数输入表!$I$573 -> 30 | N22: =参数输入表!$I$573 -> 30 | O22: =参数输入表!$I$573 -> 30 | P22: =参数输入表!$I$573 -> 30 | Q22: =参数输入表!$I$573 -> 30 | ... AF22: =参数输入表!$I$573 -> 30
B23: 2 | C23: 其他收益 | D23: =SUM(F23:AF23) -> 5974.115 | E23: 万元 | F23: ='表5-利润表-资本金(标准格式)'!F28 -> 0 | G23: ='表5-利润表-资本金(标准格式)'!G28 -> 0 | H23: ='表5-利润表-资本金(标准格式)'!H28 -> 0 | I23: ='表5-利润表-资本金(标准格式)'!I28 -> 0 | J23: =SUM(J24:J25) -> 25 | K23: =SUM(K24:K25) -> 214.60177 | L23: =SUM(L24:L25) -> 283.18584 | M23: =SUM(M24:M25) -> 283.18584 | N23: =SUM(N24:N25) -> 283.18584 | O23: =SUM(O24:O25) -> 283.18584 | P23: =SUM(P24:P25) -> 283.18584 | Q23: =SUM(Q24:Q25) -> 283.18584 | ... AF23: =SUM(AF24:AF25) -> 70.79646
B24: 2.1 | C24: 增值税即征即退 | D24: =SUM(F24:AF24) -> 0 | E24: 万元 | J24: =J32*参数输入表!$I$646 -> 0 | K24: =K32*参数输入表!$I$646 -> 0 | L24: =L32*参数输入表!$I$646 -> 0 | M24: =M32*参数输入表!$I$646 -> 0 | N24: =N32*参数输入表!$I$646 -> 0 | O24: =O32*参数输入表!$I$646 -> 0 | P24: =P32*参数输入表!$I$646 -> 0 | Q24: =Q32*参数输入表!$I$646 -> 0 | ... AF24: =AF32*参数输入表!$I$646 -> 0
B25: 2.2 | C25: 其他收入2 | D25: =SUM(F25:AF25) -> 5974.115 | E25: 万元 | J25: =(参数输入表!$I$579*参数输入表!$I$581)/(1+参数输入表!$I$582)*J5*(12-MONTH(参数输入表!I8))/12 -> 25 | K25: =(参数输入表!$I$579*参数输入表!$I$581)/(1+参数输入表!$I$582)*K5 -> 214.60177 | L25: =(参数输入表!$I$579*参数输入表!$I$581)/(1+参数输入表!$I$582)*L5 -> 283.18584 | M25: =(参数输入表!$I$579*参数输入表!$I$581)/(1+参数输入表!$I$582)*M5 -> 283.18584 | N25: =(参数输入表!$I$579*参数输入表!$I$581)/(1+参数输入表!$I$582)*N5 -> 283.18584 | O25: =(参数输入表!$I$579*参数输入表!$I$581)/(1+参数输入表!$I$582)*O5 -> 283.18584 | P25: =(参数输入表!$I$579*参数输入表!$I$581)/(1+参数输入表!$I$582)*P5 -> 283.18584 | Q25: =(参数输入表!$I$579*参数输入表!$I$581)/(1+参数输入表!$I$582)*Q5 -> 283.18584 | R25: =(参数输入表!$I$579*参数输入表!$I$581)/(1+参数输入表!$I$582)*R5 -> 283.18584 | ... AE25: =(参数输入表!$I$579*参数输入表!$I$581)/(1+参数输入表!$I$582)*AE5 -> 283.18584 | AF25: =(参数输入表!$I$579*参数输入表!$I$581)/(1+参数输入表!$I$582)*AF5*MONTH(参数输入表!I6)/12 -> 70.79646
B26: 3 | C26: 营业外收入 | D26: =SUM(F26:AF26) -> 200 | E26: 万元 | F26: ='表5-利润表-资本金(标准格式)'!F39 -> 0 | G26: ='表5-利润表-资本金(标准格式)'!G39 -> 0 | H26: ='表5-利润表-资本金(标准格式)'!H39 -> 0 | I26: ='表5-利润表-资本金(标准格式)'!I39 -> 0 | J26: =SUM(J27) -> 0 | K26: =SUM(K27) -> 0 | L26: =SUM(L27) -> 10 | M26: =SUM(M27) -> 10 | N26: =SUM(N27) -> 10 | O26: =SUM(O27) -> 10 | P26: =SUM(P27) -> 10 | Q26: =SUM(Q27) -> 10 | ... AF26: =SUM(AF27) -> 0
B27: 3.1 | C27: 政府一次性运营补贴收入 | D27: =SUM(F27:AF27) -> 200 | E27: 万元 | J27: =参数输入表!$I$620*(12-MONTH(参数输入表!I8))/12 -> 0 | K27: =参数输入表!$I$621 -> 0 | L27: =参数输入表!$I$622 -> 10 | M27: =参数输入表!$I$623 -> 10 | N27: =参数输入表!$I$624 -> 10 | O27: =参数输入表!$I$625 -> 10 | P27: =参数输入表!$I$626 -> 10 | Q27: =参数输入表!$I$627 -> 10 | R27: =参数输入表!$I$628 -> 10 | S27: =参数输入表!$I$629 -> 10 | T27: =参数输入表!$I$630 -> 10 | U27: =参数输入表!$I$631 -> 10 | V27: =参数输入表!$I$632 -> 10 | W27: =参数输入表!$I$633 -> 10 | X27: =参数输入表!$I$634 -> 10 | Y27: =参数输入表!$I$635 -> 10 | Z27: =参数输入表!$I$636 -> 10 | AA27: =参数输入表!$I$637 -> 10 | AB27: =参数输入表!$I$638 -> 10 | AC27: =参数输入表!$I$639 -> 10 | AD27: =参数输入表!$I$640 -> 10 | AE27: =参数输入表!$I$641 -> 10 | AF27: =参数输入表!$I$642*MONTH(参数输入表!I6)/12 -> 0
B29: 税金表
B30: 序号 | C30: 项目 | D30: 合计 | E30: 单位 | F30: 2020年 | G30: 2021年 | H30: 2022年 | I30: 45107 | J30: 45261 | K30: 2024年 | L30: 2025年 | M30: 2026年 | N30: 2027年 | O30: 2028年 | P30: 2029年 | Q30: 2030年 | R30: 2031年 | S30: 2032年 | T30: 2033年 | U30: 2034年 | V30: 2035年 | W30: 2036年 | X30: 2037年 | Y30: 2038年 | Z30: 2039年 | AA30: 2040年 | AB30: 2041年 | AC30: 2042年 | AD30: 2043年 | AE30: 2044年 | AF30: 53051
F31: 1 | G31: 2 | H31: 3 | I31: 4 | J31: 5 | K31: 6 | L31: 7 | M31: 8 | N31: 9 | O31: 10 | P31: 11 | Q31: 12 | R31: 13 | S31: 14 | T31: 15 | U31: 16 | V31: 17 | W31: 18 | X31: 19 | Y31: 20 | Z31: 21 | AA31: 22 | AB31: 23 | AC31: 24 | AD31: 25 | AE31: 26 | AF31: 27
B32: 1 | C32: 当期实缴增值税 | D32: =SUM(F32:AF32) -> 29735.571 | E32: 万元 | J32: =IF(J61>0,0,J60-I61) -> 0 | K32: =IF(K61>0,0,K60-J61) -> 0 | L32: =IF(L61>0,0,L60-K61) -> 0 | M32: =IF(M61>0,0,M60-L61) -> 0 | N32: =IF(N61>0,0,N60-M61) -> 0 | O32: =IF(O61>0,0,O60-N61) -> 0 | P32: =IF(P61>0,0,P60-O61) -> 0 | Q32: =IF(Q61>0,0,Q60-P61) -> 0 | ... AF32: =IF(AF61>0,0,AF60-AE61) -> 430.66643
B33: 2 | C33: 增值税销项税 | D33: =SUM(F33:AF33) -> 46562.601 | E33: 万元 | J33: =J34+J38+J40 -> 218.55068 | K33: =K34+K38+K40 -> 1867.6648 | L33: =L34+L38+L40 -> 2453.4734 | M33: =M34+M38+M40 -> 2442.3989 | N33: =N34+N38+N40 -> 2431.3247 | O33: =O34+O38+O40 -> 2420.2506 | P33: =P34+P38+P40 -> 2409.1761 | Q33: =Q34+Q38+Q40 -> 2398.1019 | ... AF33: =AF34+AF38+AF40 -> 430.66643
B34: 2.1 | C34: 营业收入销项税 | D34: =SUM(F34:AF34) -> 45785.966 | E34: 万元 | J34: =SUM(J35:J37) -> 215.30068 | K34: =SUM(K35:K37) -> 1839.7666 | L34: =SUM(L35:L37) -> 2416.6593 | M34: =SUM(M35:M37) -> 2405.5847 | N34: =SUM(N35:N37) -> 2394.5106 | O34: =SUM(O35:O37) -> 2383.4364 | P34: =SUM(P35:P37) -> 2372.3619 | Q34: =SUM(Q35:Q37) -> 2361.2877 | ... AF34: =SUM(AF35:AF37) -> 421.46289
C35: 发电收入销项税 | D35: =SUM(F35:AF35) -> 35123.454 | E35: 万元 | J35: =J7*参数输入表!$I$563 -> 154.85688 | K35: =K7*参数输入表!$I$563 -> 1323.2662 | L35: =L7*参数输入表!$I$563 -> 1738.2005 | M35: =M7*参数输入表!$I$563 -> 1730.2352 | N35: =N7*参数输入表!$I$563 -> 1722.2699 | O35: =O7*参数输入表!$I$563 -> 1714.3047 | P35: =P7*参数输入表!$I$563 -> 1706.3394 | Q35: =Q7*参数输入表!$I$563 -> 1698.3741 | ... AF35: =AF7*参数输入表!$I$563 -> 394.72374
C36: 国补收入销项税 | D36: =SUM(F36:AF36) -> 8283.1858 | E36: 万元 | J36: =J15*参数输入表!$I$563 -> 49.953832 | K36: =K15*参数输入表!$I$563 -> 426.86008 | L36: =L15*参数输入表!$I$563 -> 560.70983 | M36: =M15*参数输入表!$I$563 -> 558.14039 | N36: =N15*参数输入表!$I$563 -> 555.57095 | O36: =O15*参数输入表!$I$563 -> 553.0015 | P36: =P15*参数输入表!$I$563 -> 550.43206 | Q36: =Q15*参数输入表!$I$563 -> 547.86261 | ... AF36: =AF15*参数输入表!$I$563 -> 0
C37: 绿证交易收入销项税 | D37: =SUM(F37:AF37) -> 2379.3265 | E37: 万元 | J37: =J19*参数输入表!$I$574 -> 10.489965 | K37: =K19*参数输入表!$I$574 -> 89.640292 | L37: =L19*参数输入表!$I$574 -> 117.74894 | M37: =M19*参数输入表!$I$574 -> 117.20915 | N37: =N19*参数输入表!$I$574 -> 116.66971 | O37: =O19*参数输入表!$I$574 -> 116.13027 | P37: =P19*参数输入表!$I$574 -> 115.59048 | Q37: =Q19*参数输入表!$I$574 -> 115.05104 | ... AF37: =AF19*参数输入表!$I$574 -> 26.739159
B38: 2.2 | C38: 其他收入销项税 | D38: =SUM(F38:AF38) -> 776.63496 | E38: 万元 | J38: =SUM(J39) -> 3.25 | K38: =SUM(K39) -> 27.89823 | L38: =SUM(L39) -> 36.814159 | M38: =SUM(M39) -> 36.814159 | N38: =SUM(N39) -> 36.814159 | O38: =SUM(O39) -> 36.814159 | P38: =SUM(P39) -> 36.814159 | Q38: =SUM(Q39) -> 36.814159 | ... AF38: =SUM(AF39) -> 9.2035398
C39: 其他收入2销项税 | D39: =SUM(F39:AF39) -> 776.63496 | E39: 万元 | J39: =J25*参数输入表!$I$582 -> 3.25 | K39: =K25*参数输入表!$I$582 -> 27.89823 | L39: =L25*参数输入表!$I$582 -> 36.814159 | M39: =M25*参数输入表!$I$582 -> 36.814159 | N39: =N25*参数输入表!$I$582 -> 36.814159 | O39: =O25*参数输入表!$I$582 -> 36.814159 | P39: =P25*参数输入表!$I$582 -> 36.814159 | Q39: =Q25*参数输入表!$I$582 -> 36.814159 | ... AF39: =AF25*参数输入表!$I$582 -> 9.2035398
B40: 2.3 | C40: 营业外收入销项税 | D40: =SUM(F40:AF40) -> 0 | E40: 万元 | J40: =SUM(J41) -> 0 | K40: =SUM(K41) -> 0 | L40: =SUM(L41) -> 0 | M40: =SUM(M41) -> 0 | N40: =SUM(N41) -> 0 | O40: =SUM(O41) -> 0 | P40: =SUM(P41) -> 0 | Q40: =SUM(Q41) -> 0 | ... AF40: =SUM(AF41) -> 0
C41: （如有） | E41: 万元
B42: 3 | C42: 增值税进项税 | D42: =SUM(F42:AF42) -> 14387.981 | E42: 万元 | J42: =J43+J44+J58+J59 -> 4266.8531 | K42: =K43+K44+K58+K59 -> 9955.9905 | L42: =L43+L44+L58+L59 -> 0 | M42: =M43+M44+M58+M59 -> 41.284404 | N42: =N43+N44+N58+N59 -> 0 | O42: =O43+O44+O58+O59 -> 0 | P42: =P43+P44+P58+P59 -> 0 | Q42: =Q43+Q44+Q58+Q59 -> 0 | ... AF42: =AF43+AF44+AF58+AF59 -> 0
B43: 3.1 | C43: 建设投资进项税 | D43: =SUM(F43:AF43) -> 14222.844 | E43: 万元 | J43: ='新建及改扩建项目投资概算明细 (光伏)'!F26 -> 4266.8531 | K43: ='新建及改扩建项目投资概算明细 (光伏)'!G26 -> 9955.9905 | L43: =IF(L31-参数输入表!$I$14>0,0) -> 0 | M43: =IF(M31-参数输入表!$I$14>0,0) -> 0 | N43: =IF(N31-参数输入表!$I$14>0,0) -> 0 | O43: =IF(O31-参数输入表!$I$14>0,0) -> 0 | P43: =IF(P31-参数输入表!$I$14>0,0) -> 0 | Q43: =IF(Q31-参数输入表!$I$14>0,0) -> 0 | R43: =IF(R31-参数输入表!$I$14>0,0) -> 0 | S43: =IF(S31-参数输入表!$I$14>0,0) -> 0 | ... AF43: =IF(AF31-参数输入表!$I$14>0,0) -> 0
B44: 3.2 | C44: 营业成本进项税 | D44: =SUM(F44:AF44) -> 165.13761 | E44: 万元 | J44: =J45+J53+J54+J57 -> 0 | K44: =K45+K53+K54+K57 -> 0 | L44: =L45+L53+L54+L57 -> 0 | M44: =M45+M53+M54+M57 -> 41.284404 | N44: =N45+N53+N54+N57 -> 0 | O44: =O45+O53+O54+O57 -> 0 | P44: =P45+P53+P54+P57 -> 0 | Q44: =Q45+Q53+Q54+Q57 -> 0 | ... AF44: =AF45+AF53+AF54+AF57 -> 0
B45: 3.2.1 | C45: 生产成本进项税 | D45: =SUM(F45:AF45) -> 165.13761 | E45: 万元 | J45: =SUM(J46:J52) -> 0 | K45: =SUM(K46:K52) -> 0 | L45: =SUM(L46:L52) -> 0 | M45: =SUM(M46:M52) -> 41.284404 | N45: =SUM(N46:N52) -> 0 | O45: =SUM(O46:O52) -> 0 | P45: =SUM(P46:P52) -> 0 | Q45: =SUM(Q46:Q52) -> 0 | ... AF45: =SUM(AF46:AF52) -> 0
C46: 材料费 | D46: =SUM(F46:AF46) -> 0 | E46: 万元 | J46: ='表3-成本费用表'!J55/(1+参数输入表!$I$318)*参数输入表!$I$318 -> 0 | K46: ='表3-成本费用表'!K55/(1+参数输入表!$I$318)*参数输入表!$I$318 -> 0 | L46: ='表3-成本费用表'!L55/(1+参数输入表!$I$318)*参数输入表!$I$318 -> 0 | M46: ='表3-成本费用表'!M55/(1+参数输入表!$I$318)*参数输入表!$I$318 -> 0 | N46: ='表3-成本费用表'!N55/(1+参数输入表!$I$318)*参数输入表!$I$318 -> 0 | O46: ='表3-成本费用表'!O55/(1+参数输入表!$I$318)*参数输入表!$I$318 -> 0 | P46: ='表3-成本费用表'!P55/(1+参数输入表!$I$318)*参数输入表!$I$318 -> 0 | Q46: ='表3-成本费用表'!Q55/(1+参数输入表!$I$318)*参数输入表!$I$318 -> 0 | ... AF46: ='表3-成本费用表'!AF55/(1+参数输入表!$I$318)*参数输入表!$I$318 -> 0
C47: 维修费 | D47: =SUM(F47:AF47) -> 0 | E47: 万元 | J47: ='表3-成本费用表'!J56/(1+参数输入表!$I$349)*参数输入表!$I$349 -> 0 | K47: ='表3-成本费用表'!K56/(1+参数输入表!$I$349)*参数输入表!$I$349 -> 0 | L47: ='表3-成本费用表'!L56/(1+参数输入表!$I$349)*参数输入表!$I$349 -> 0 | M47: ='表3-成本费用表'!M56/(1+参数输入表!$I$349)*参数输入表!$I$349 -> 0 | N47: ='表3-成本费用表'!N56/(1+参数输入表!$I$349)*参数输入表!$I$349 -> 0 | O47: ='表3-成本费用表'!O56/(1+参数输入表!$I$349)*参数输入表!$I$349 -> 0 | P47: ='表3-成本费用表'!P56/(1+参数输入表!$I$349)*参数输入表!$I$349 -> 0 | Q47: ='表3-成本费用表'!Q56/(1+参数输入表!$I$349)*参数输入表!$I$349 -> 0 | ... AF47: ='表3-成本费用表'!AF56/(1+参数输入表!$I$349)*参数输入表!$I$349 -> 0
C48: 生产人员薪酬及福利 | D48: =SUM(F48:AF48) -> 0 | E48: 万元 | J48: ='表3-成本费用表'!J57/(1+参数输入表!$I$390)*参数输入表!$I$390 -> 0 | K48: ='表3-成本费用表'!K57/(1+参数输入表!$I$390)*参数输入表!$I$390 -> 0 | L48: ='表3-成本费用表'!L57/(1+参数输入表!$I$390)*参数输入表!$I$390 -> 0 | M48: ='表3-成本费用表'!M57/(1+参数输入表!$I$390)*参数输入表!$I$390 -> 0 | N48: ='表3-成本费用表'!N57/(1+参数输入表!$I$390)*参数输入表!$I$390 -> 0 | O48: ='表3-成本费用表'!O57/(1+参数输入表!$I$390)*参数输入表!$I$390 -> 0 | P48: ='表3-成本费用表'!P57/(1+参数输入表!$I$390)*参数输入表!$I$390 -> 0 | Q48: ='表3-成本费用表'!Q57/(1+参数输入表!$I$390)*参数输入表!$I$390 -> 0 | ... AF48: ='表3-成本费用表'!AF57/(1+参数输入表!$I$390)*参数输入表!$I$390 -> 0
C49: 计入长期待摊成本项 | D49: =SUM(F49:AF49) -> 165.13761 | E49: 万元 | J49: ='表3-成本费用表'!J58/(1+参数输入表!$I$488)*参数输入表!$I$488 -> 0 | K49: ='表3-成本费用表'!K58/(1+参数输入表!$I$488)*参数输入表!$I$488 -> 0 | L49: ='表3-成本费用表'!L58/(1+参数输入表!$I$488)*参数输入表!$I$488 -> 0 | M49: ='表3-成本费用表'!M58/(1+参数输入表!$I$488)*参数输入表!$I$488 -> 41.284404 | N49: ='表3-成本费用表'!N58/(1+参数输入表!$I$488)*参数输入表!$I$488 -> 0 | O49: ='表3-成本费用表'!O58/(1+参数输入表!$I$488)*参数输入表!$I$488 -> 0 | P49: ='表3-成本费用表'!P58/(1+参数输入表!$I$488)*参数输入表!$I$488 -> 0 | Q49: ='表3-成本费用表'!Q58/(1+参数输入表!$I$488)*参数输入表!$I$488 -> 0 | ... AF49: ='表3-成本费用表'!AF58/(1+参数输入表!$I$488)*参数输入表!$I$488 -> 0
C50: 其他费用 | D50: =SUM(F50:AF50) -> 0 | E50: 万元 | J50: ='表3-成本费用表'!J59/(1+参数输入表!$I$394)*参数输入表!$I$394 -> 0 | K50: ='表3-成本费用表'!K59/(1+参数输入表!$I$394)*参数输入表!$I$394 -> 0 | L50: ='表3-成本费用表'!L59/(1+参数输入表!$I$394)*参数输入表!$I$394 -> 0 | M50: ='表3-成本费用表'!M59/(1+参数输入表!$I$394)*参数输入表!$I$394 -> 0 | N50: ='表3-成本费用表'!N59/(1+参数输入表!$I$394)*参数输入表!$I$394 -> 0 | O50: ='表3-成本费用表'!O59/(1+参数输入表!$I$394)*参数输入表!$I$394 -> 0 | P50: ='表3-成本费用表'!P59/(1+参数输入表!$I$394)*参数输入表!$I$394 -> 0 | Q50: ='表3-成本费用表'!Q59/(1+参数输入表!$I$394)*参数输入表!$I$394 -> 0 | ... AF50: ='表3-成本费用表'!AF59/(1+参数输入表!$I$394)*参数输入表!$I$394 -> 0
C51: 储能费用 | D51: =SUM(F51:AF51) -> 0 | E51: 万元 | J51: ='表3-成本费用表'!J60/(1+参数输入表!$I$398)*参数输入表!$I$398 -> 0 | K51: ='表3-成本费用表'!K60/(1+参数输入表!$I$398)*参数输入表!$I$398 -> 0 | L51: ='表3-成本费用表'!L60/(1+参数输入表!$I$398)*参数输入表!$I$398 -> 0 | M51: ='表3-成本费用表'!M60/(1+参数输入表!$I$398)*参数输入表!$I$398 -> 0 | N51: ='表3-成本费用表'!N60/(1+参数输入表!$I$398)*参数输入表!$I$398 -> 0 | O51: ='表3-成本费用表'!O60/(1+参数输入表!$I$398)*参数输入表!$I$398 -> 0 | P51: ='表3-成本费用表'!P60/(1+参数输入表!$I$398)*参数输入表!$I$398 -> 0 | Q51: ='表3-成本费用表'!Q60/(1+参数输入表!$I$398)*参数输入表!$I$398 -> 0 | ... AF51: ='表3-成本费用表'!AF60/(1+参数输入表!$I$398)*参数输入表!$I$398 -> 0
C52: 场地租金费用 | D52: =SUM(F52:AF52) -> 0 | E52: 万元 | J52: ='表3-成本费用表'!J61/(1+参数输入表!$I$429)*参数输入表!$I$429 -> 0 | K52: ='表3-成本费用表'!K61/(1+参数输入表!$I$429)*参数输入表!$I$429 -> 0 | L52: ='表3-成本费用表'!L61/(1+参数输入表!$I$429)*参数输入表!$I$429 -> 0 | M52: ='表3-成本费用表'!M61/(1+参数输入表!$I$429)*参数输入表!$I$429 -> 0 | N52: ='表3-成本费用表'!N61/(1+参数输入表!$I$429)*参数输入表!$I$429 -> 0 | O52: ='表3-成本费用表'!O61/(1+参数输入表!$I$429)*参数输入表!$I$429 -> 0 | P52: ='表3-成本费用表'!P61/(1+参数输入表!$I$429)*参数输入表!$I$429 -> 0 | Q52: ='表3-成本费用表'!Q61/(1+参数输入表!$I$429)*参数输入表!$I$429 -> 0 | ... AF52: ='表3-成本费用表'!AF61/(1+参数输入表!$I$429)*参数输入表!$I$429 -> 0
B53: 3.2.2 | C53: 销售费用进项税 | D53: =SUM(F53:AF53) -> 0 | E53: 万元 | J53: 0 | K53: 0 | L53: 0 | M53: 0 | N53: 0 | O53: 0 | P53: 0 | Q53: 0 | R53: 0 | S53: 0 | T53: 0 | U53: 0 | V53: 0 | W53: 0 | X53: 0 | Y53: 0 | Z53: 0 | AA53: 0 | AB53: 0 | AC53: 0 | AD53: 0 | AE53: 0 | AF53: 0
B54: 3.2.3 | C54: 管理费用进项税 | D54: =SUM(F54:AF54) -> 0 | E54: 万元 | J54: =SUM(J55:J56) -> 0 | K54: =SUM(K55:K56) -> 0 | L54: =SUM(L55:L56) -> 0 | M54: =SUM(M55:M56) -> 0 | N54: =SUM(N55:N56) -> 0 | O54: =SUM(O55:O56) -> 0 | P54: =SUM(P55:P56) -> 0 | Q54: =SUM(Q55:Q56) -> 0 | ... AF54: =SUM(AF55:AF56) -> 0
C55: 保险费 | D55: =SUM(F55:AF55) -> 0 | E55: 万元 | J55: ='表3-成本费用表'!J64/(1+参数输入表!$I$380)*参数输入表!$I$380 -> 0 | K55: ='表3-成本费用表'!K64/(1+参数输入表!$I$380)*参数输入表!$I$380 -> 0 | L55: ='表3-成本费用表'!L64/(1+参数输入表!$I$380)*参数输入表!$I$380 -> 0 | M55: ='表3-成本费用表'!M64/(1+参数输入表!$I$380)*参数输入表!$I$380 -> 0 | N55: ='表3-成本费用表'!N64/(1+参数输入表!$I$380)*参数输入表!$I$380 -> 0 | O55: ='表3-成本费用表'!O64/(1+参数输入表!$I$380)*参数输入表!$I$380 -> 0 | P55: ='表3-成本费用表'!P64/(1+参数输入表!$I$380)*参数输入表!$I$380 -> 0 | Q55: ='表3-成本费用表'!Q64/(1+参数输入表!$I$380)*参数输入表!$I$380 -> 0 | ... AF55: ='表3-成本费用表'!AF64/(1+参数输入表!$I$380)*参数输入表!$I$380 -> 0
C56: 期末拆除费用 | D56: =SUM(F56:AF56) -> 0 | E56: 万元 | J56: ='表3-成本费用表'!J65/(1+参数输入表!$I$433)*参数输入表!$I$433 -> 0 | K56: ='表3-成本费用表'!K65/(1+参数输入表!$I$433)*参数输入表!$I$433 -> 0 | L56: ='表3-成本费用表'!L65/(1+参数输入表!$I$433)*参数输入表!$I$433 -> 0 | M56: ='表3-成本费用表'!M65/(1+参数输入表!$I$433)*参数输入表!$I$433 -> 0 | N56: ='表3-成本费用表'!N65/(1+参数输入表!$I$433)*参数输入表!$I$433 -> 0 | O56: ='表3-成本费用表'!O65/(1+参数输入表!$I$433)*参数输入表!$I$433 -> 0 | P56: ='表3-成本费用表'!P65/(1+参数输入表!$I$433)*参数输入表!$I$433 -> 0 | Q56: ='表3-成本费用表'!Q65/(1+参数输入表!$I$433)*参数输入表!$I$433 -> 0 | ... AF56: ='表3-成本费用表'!AF65/(1+参数输入表!$I$433)*参数输入表!$I$433 -> 0
B57: 3.2.4 | C57: 研发费用进项税 | D57: =SUM(F57:AF57) -> 0 | E57: 万元 | J57: 0 | K57: 0 | L57: 0 | M57: 0 | N57: 0 | O57: 0 | P57: 0 | Q57: 0 | R57: 0 | S57: 0 | T57: 0 | U57: 0 | V57: 0 | W57: 0 | X57: 0 | Y57: 0 | Z57: 0 | AA57: 0 | AB57: 0 | AC57: 0 | AD57: 0 | AE57: 0 | AF57: 0
B58: 3.3 | C58: 营业外支出进项税 | D58: =SUM(F58:AF58) -> 0 | E58: 万元 | J58: ='表3-成本费用表'!J67/(1+参数输入表!$I$556)*参数输入表!$I$556 -> 0 | K58: ='表3-成本费用表'!K67/(1+参数输入表!$I$556)*参数输入表!$I$556 -> 0 | L58: ='表3-成本费用表'!L67/(1+参数输入表!$I$556)*参数输入表!$I$556 -> 0 | M58: ='表3-成本费用表'!M67/(1+参数输入表!$I$556)*参数输入表!$I$556 -> 0 | N58: ='表3-成本费用表'!N67/(1+参数输入表!$I$556)*参数输入表!$I$556 -> 0 | O58: ='表3-成本费用表'!O67/(1+参数输入表!$I$556)*参数输入表!$I$556 -> 0 | P58: ='表3-成本费用表'!P67/(1+参数输入表!$I$556)*参数输入表!$I$556 -> 0 | Q58: ='表3-成本费用表'!Q67/(1+参数输入表!$I$556)*参数输入表!$I$556 -> 0 | ... AF58: ='表3-成本费用表'!AF67/(1+参数输入表!$I$556)*参数输入表!$I$556 -> 0
B59: 3.4 | C59: 大修及更新重置进项税 | D59: =SUM(F59:AF59) -> 0 | E59: 万元 | J59: =参数输入表!I500/(1+参数输入表!$I$525)*参数输入表!$I$525 -> 0 | K59: =参数输入表!I501/(1+参数输入表!$I$525)*参数输入表!$I$525 -> 0 | L59: =参数输入表!I502/(1+参数输入表!$I$525)*参数输入表!$I$525 -> 0 | M59: =参数输入表!I503/(1+参数输入表!$I$525)*参数输入表!$I$525 -> 0 | N59: =参数输入表!I504/(1+参数输入表!$I$525)*参数输入表!$I$525 -> 0 | O59: =参数输入表!I505/(1+参数输入表!$I$525)*参数输入表!$I$525 -> 0 | P59: =参数输入表!I506/(1+参数输入表!$I$525)*参数输入表!$I$525 -> 0 | Q59: =参数输入表!I507/(1+参数输入表!$I$525)*参数输入表!$I$525 -> 0 | R59: =参数输入表!I508/(1+参数输入表!$I$525)*参数输入表!$I$525 -> 0 | S59: =参数输入表!I509/(1+参数输入表!$I$525)*参数输入表!$I$525 -> 0 | T59: =参数输入表!I510/(1+参数输入表!$I$525)*参数输入表!$I$525 -> 0 | U59: =参数输入表!I511/(1+参数输入表!$I$525)*参数输入表!$I$525 -> 0 | V59: =参数输入表!I512/(1+参数输入表!$I$525)*参数输入表!$I$525 -> 0 | W59: =参数输入表!I513/(1+参数输入表!$I$525)*参数输入表!$I$525 -> 0 | X59: =参数输入表!I514/(1+参数输入表!$I$525)*参数输入表!$I$525 -> 0 | Y59: =参数输入表!I515/(1+参数输入表!$I$525)*参数输入表!$I$525 -> 0 | Z59: =参数输入表!I516/(1+参数输入表!$I$525)*参数输入表!$I$525 -> 0 | AA59: =参数输入表!I517/(1+参数输入表!$I$525)*参数输入表!$I$525 -> 0 | AB59: =参数输入表!I518/(1+参数输入表!$I$525)*参数输入表!$I$525 -> 0 | AC59: =参数输入表!I519/(1+参数输入表!$I$525)*参数输入表!$I$525 -> 0 | AD59: =参数输入表!I520/(1+参数输入表!$I$525)*参数输入表!$I$525 -> 0 | AE59: =参数输入表!I521/(1+参数输入表!$I$525)*参数输入表!$I$525 -> 0 | AF59: =参数输入表!I522/(1+参数输入表!$I$525)*参数输入表!$I$525 -> 0
B60: 4 | C60: 销项税-进项税 | D60: =SUM(F60:AF60) -> 32174.62 | E60: 万元 | J60: =J33-J42 -> -4048.3024 | K60: =K33-K42 -> -8088.3257 | L60: =L33-L42 -> 2453.4734 | M60: =M33-M42 -> 2401.1145 | N60: =N33-N42 -> 2431.3247 | O60: =O33-O42 -> 2420.2506 | P60: =P33-P42 -> 2409.1761 | Q60: =Q33-Q42 -> 2398.1019 | ... AF60: =AF33-AF42 -> 430.66643
B61: 5 | C61: 期末可抵扣进项税余额 | E61: 万元 | I61: =参数输入表!I644 -> 2439.0488 | J61: =IF(I61-J60>0,I61-J60,0) -> 6487.3512 | K61: =IF(J61-K60>0,J61-K60,0) -> 14575.677 | L61: =IF(K61-L60>0,K61-L60,0) -> 12122.203 | M61: =IF(L61-M60>0,L61-M60,0) -> 9721.0889 | N61: =IF(M61-N60>0,M61-N60,0) -> 7289.7642 | O61: =IF(N61-O60>0,N61-O60,0) -> 4869.5136 | P61: =IF(O61-P60>0,O61-P60,0) -> 2460.3375 | Q61: =IF(P61-Q60>0,P61-Q60,0) -> 62.23561 | ... AF61: =IF(AE61-AF60>0,AE61-AF60,0) -> 0
B62: 6 | C62: 增值税附加税 | D62: =SUM(F62:AF62) -> 3568.2685 | E62: 万元 | J62: =SUM(J63:J65) -> 0 | K62: =SUM(K63:K65) -> 0 | L62: =SUM(L63:L65) -> 0 | M62: =SUM(M63:M65) -> 0 | N62: =SUM(N63:N65) -> 0 | O62: =SUM(O63:O65) -> 0 | P62: =SUM(P63:P65) -> 0 | Q62: =SUM(Q63:Q65) -> 0 | ... AF62: =SUM(AF63:AF65) -> 51.679972
B63: 6.1 | C63: 城市维护建设税 | D63: =SUM(F63:AF63) -> 2081.49 | E63: 万元 | J63: =J32*参数输入表!$I$681 -> 0 | K63: =K32*参数输入表!$I$681 -> 0 | L63: =L32*参数输入表!$I$681 -> 0 | M63: =M32*参数输入表!$I$681 -> 0 | N63: =N32*参数输入表!$I$681 -> 0 | O63: =O32*参数输入表!$I$681 -> 0 | P63: =P32*参数输入表!$I$681 -> 0 | Q63: =Q32*参数输入表!$I$681 -> 0 | ... AF63: =AF32*参数输入表!$I$681 -> 30.14665
B64: 6.2 | C64: 教育附加 | D64: =SUM(F64:AF64) -> 892.06714 | E64: 万元 | J64: =J32*参数输入表!$I$685 -> 0 | K64: =K32*参数输入表!$I$685 -> 0 | L64: =L32*参数输入表!$I$685 -> 0 | M64: =M32*参数输入表!$I$685 -> 0 | N64: =N32*参数输入表!$I$685 -> 0 | O64: =O32*参数输入表!$I$685 -> 0 | P64: =P32*参数输入表!$I$685 -> 0 | Q64: =Q32*参数输入表!$I$685 -> 0 | ... AF64: =AF32*参数输入表!$I$685 -> 12.919993
B65: 6.3 | C65: 地方教育附加 | D65: =SUM(F65:AF65) -> 594.71142 | E65: 万元 | J65: =J32*参数输入表!$I$686 -> 0 | K65: =K32*参数输入表!$I$686 -> 0 | L65: =L32*参数输入表!$I$686 -> 0 | M65: =M32*参数输入表!$I$686 -> 0 | N65: =N32*参数输入表!$I$686 -> 0 | O65: =O32*参数输入表!$I$686 -> 0 | P65: =P32*参数输入表!$I$686 -> 0 | Q65: =Q32*参数输入表!$I$686 -> 0 | ... AF65: =AF32*参数输入表!$I$686 -> 8.6133287
B66: 7 | C66: 城镇土地使用税 | D66: =SUM(F66:AF66) -> 0 | E66: 万元 | J66: =参数输入表!$I$688*参数输入表!$I$689/10000 -> 0 | K66: =参数输入表!$I$688*参数输入表!$I$689/10000 -> 0 | L66: =参数输入表!$I$688*参数输入表!$I$689/10000 -> 0 | M66: =参数输入表!$I$688*参数输入表!$I$689/10000 -> 0 | N66: =参数输入表!$I$688*参数输入表!$I$689/10000 -> 0 | O66: =参数输入表!$I$688*参数输入表!$I$689/10000 -> 0 | P66: =参数输入表!$I$688*参数输入表!$I$689/10000 -> 0 | Q66: =参数输入表!$I$688*参数输入表!$I$689/10000 -> 0 | ... AF66: =参数输入表!$I$688*参数输入表!$I$689/10000 -> 0
C68: 增值税即征即退为参数输入表，税金板块可选条件参数，若选择为常规，即没有增值税即征即退优惠，退税比例为0%；若选择即征即退，同步输入即征即退的比例，第n年增值税即征即退金额=第n年当期实缴增值税*退税比例
C69: 增值税即征即退不需要进行收入分类，固化在其他收益项下
C70: 标黄部分为相对固定模块，适用于所有项目
C71: 标蓝部分为计算中间过程，可不展示
B73: 应收账款估算表（不含基准日应收账款）
B74: 序号 | C74: 项目 | D74: 合计 | E74: 单位 | F74: 2020年 | G74: 2021年 | H74: 2022年 | I74: 45107 | J74: 45261 | K74: 2024年 | L74: 2025年 | M74: 2026年 | N74: 2027年 | O74: 2028年 | P74: 2029年 | Q74: 2030年 | R74: 2031年 | S74: 2032年 | T74: 2033年 | U74: 2034年 | V74: 2035年 | W74: 2036年 | X74: 2037年 | Y74: 2038年 | Z74: 2039年 | AA74: 2040年 | AB74: 2041年 | AC74: 2042年 | AD74: 2043年 | AE74: 2044年 | AF74: 53051
F75: 1 | G75: 2 | H75: 3 | I75: 4 | J75: 5 | K75: 6 | L75: 7 | M75: 8 | N75: 9 | O75: 10 | P75: 11 | Q75: 12 | R75: 13 | S75: 14 | T75: 15 | U75: 16 | V75: 17 | W75: 18 | X75: 19 | Y75: 20 | Z75: 21 | AA75: 22 | AB75: 23 | AC75: 24 | AD75: 25 | AE75: 26 | AF75: 27
C76: 应收账款 | E76: 万元 | J76: =('表4-收入税金表'!J7+'表4-收入税金表'!J35)*(1-参数输入表!$I$564)+(J15+J36)*(1-参数输入表!$I$569)+(J19+J37)*(1-参数输入表!$I$575)+('表4-收入税金表'!J25+'表4-收入税金表'!J39)*(1-参数输入表!$I$583) -> 388.41695 | K76: =('表4-收入税金表'!K7+'表4-收入税金表'!K35)*(1-参数输入表!$I$564)+(K15+K36)*(1-参数输入表!$I$569)+(K19+K37)*(1-参数输入表!$I$575)+('表4-收入税金表'!K25+'表4-收入税金表'!K39)*(1-参数输入表!$I$583) -> 3319.6135 | L76: =('表4-收入税金表'!L7+'表4-收入税金表'!L35)*(1-参数输入表!$I$564)+(L15+L36)*(1-参数输入表!$I$569)+(L19+L37)*(1-参数输入表!$I$575)+('表4-收入税金表'!L25+'表4-收入税金表'!L39)*(1-参数输入表!$I$583) -> 4361.2692 | M76: =('表4-收入税金表'!M7+'表4-收入税金表'!M35)*(1-参数输入表!$I$564)+(M15+M36)*(1-参数输入表!$I$569)+(M19+M37)*(1-参数输入表!$I$575)+('表4-收入税金表'!M25+'表4-收入税金表'!M39)*(1-参数输入表!$I$583) -> 4342.0166 | N76: =('表4-收入税金表'!N7+'表4-收入税金表'!N35)*(1-参数输入表!$I$564)+(N15+N36)*(1-参数输入表!$I$569)+(N19+N37)*(1-参数输入表!$I$575)+('表4-收入税金表'!N25+'表4-收入税金表'!N39)*(1-参数输入表!$I$583) -> 4322.7646 | O76: =('表4-收入税金表'!O7+'表4-收入税金表'!O35)*(1-参数输入表!$I$564)+(O15+O36)*(1-参数输入表!$I$569)+(O19+O37)*(1-参数输入表!$I$575)+('表4-收入税金表'!O25+'表4-收入税金表'!O39)*(1-参数输入表!$I$583) -> 4303.5125 | P76: =('表4-收入税金表'!P7+'表4-收入税金表'!P35)*(1-参数输入表!$I$564)+(P15+P36)*(1-参数输入表!$I$569)+(P19+P37)*(1-参数输入表!$I$575)+('表4-收入税金表'!P25+'表4-收入税金表'!P39)*(1-参数输入表!$I$583) -> 4284.2599 | Q76: =('表4-收入税金表'!Q7+'表4-收入税金表'!Q35)*(1-参数输入表!$I$564)+(Q15+Q36)*(1-参数输入表!$I$569)+(Q19+Q37)*(1-参数输入表!$I$575)+('表4-收入税金表'!Q25+'表4-收入税金表'!Q39)*(1-参数输入表!$I$583) -> 4265.0079 | ... AE76: =('表4-收入税金表'!AE7+'表4-收入税金表'!AE35)*(1-参数输入表!$I$564)+(AE15+AE36)*(1-参数输入表!$I$569)+(AE19+AE37)*(1-参数输入表!$I$575)+('表4-收入税金表'!AE25+'表4-收入税金表'!AE39)*(1-参数输入表!$I$583) -> 3105.5745 | AF76: 0
C77: 参数表中所有需要配置“首年支付比例”的收入项都须进行此步计算
B80: 营运资金估算表（仅用于现金流量表-估值）
B81: 序号 | C81: 项目 | D81: 合计 | E81: 单位 | F81: 2020年 | G81: 2021年 | H81: 2022年 | I81: 45107 | J81: 45261 | K81: 2024年 | L81: 2025年 | M81: 2026年 | N81: 2027年 | O81: 2028年 | P81: 2029年 | Q81: 2030年 | R81: 2031年 | S81: 2032年 | T81: 2033年 | U81: 2034年 | V81: 2035年 | W81: 2036年 | X81: 2037年 | Y81: 2038年 | Z81: 2039年 | AA81: 2040年 | AB81: 2041年 | AC81: 2042年 | AD81: 2043年 | AE81: 2044年 | AF81: 53051
F82: 1 | G82: 2 | H82: 3 | I82: 4 | J82: 5 | K82: 6 | L82: 7 | M82: 8 | N82: 9 | O82: 10 | P82: 11 | Q82: 12 | R82: 13 | S82: 14 | T82: 15 | U82: 16 | V82: 17 | W82: 18 | X82: 19 | Y82: 20 | Z82: 21 | AA82: 22 | AB82: 23 | AC82: 24 | AD82: 25 | AE82: 26 | AF82: 27
B83: 一 | C83: 流动资产 | E83: 万元 | I83: =SUM(I84:I92) -> 10648.62 | J83: =SUM(J84:J92) -> 7600.6337 | K83: =SUM(K84:K92) -> 7712.7887 | L83: =SUM(L84:L92) -> 5854.52 | M83: =SUM(M84:M92) -> 5030.8459 | N83: =SUM(N84:N92) -> 4989.51 | O83: =SUM(O84:O92) -> 4948.7683 | P83: =SUM(P84:P92) -> 4907.2977 | ... AF83: =SUM(AF84:AF92) -> 0
B84: 1.1 | C84: 应收账款 | E84: 万元 | I84: ='表10-资产负债表(标准格式)'!H14-折现率、非经营、长投计算表!E26 -> 9817.6276 | J84: =J76+IF(参数输入表!$I$721="手动输入",基准日往来账处理!J13,基准日往来账处理!J91) -> 7206.0446 | K84: =K76+IF(参数输入表!$I$721="手动输入",基准日往来账处理!K13,基准日往来账处理!K91) -> 7137.2411 | L84: =L76+IF(参数输入表!$I$721="手动输入",基准日往来账处理!L13,基准日往来账处理!L91) -> 5178.8968 | M84: =M76+IF(参数输入表!$I$721="手动输入",基准日往来账处理!M13,基准日往来账处理!M91) -> 4342.0166 | N84: =N76+IF(参数输入表!$I$721="手动输入",基准日往来账处理!N13,基准日往来账处理!N91) -> 4322.7646 | O84: =O76+IF(参数输入表!$I$721="手动输入",基准日往来账处理!O13,基准日往来账处理!O91) -> 4303.5125 | P84: =P76+IF(参数输入表!$I$721="手动输入",基准日往来账处理!P13,基准日往来账处理!P91) -> 4284.2599 | Q84: =Q76+IF(参数输入表!$I$721="手动输入",基准日往来账处理!Q13,基准日往来账处理!Q91) -> 4265.0079 | ... AE84: =AE76+IF(参数输入表!$I$721="手动输入",基准日往来账处理!AE13,基准日往来账处理!AE91) -> 3105.5745 | AF84: 0
B85: 1.2 | C85: 存货 | E85: 万元 | I85: ='表10-资产负债表(标准格式)'!H24-折现率、非经营、长投计算表!E31 -> 7.733813 | J85: =I85 -> 7.733813 | K85: =J85 -> 7.733813 | L85: =K85 -> 7.733813 | M85: =L85 -> 7.733813 | N85: =M85 -> 7.733813 | O85: =N85 -> 7.733813 | P85: =O85 -> 7.733813 | Q85: =P85 -> 7.733813 | ... AE85: =AD85 -> 7.733813 | AF85: 0
B86: 1.3 | C86: 最低现金保有量 | E86: 万元 | I86: =IF(参数输入表!I722="自动计算",('表5-利润表-资本金(标准格式)'!I10-'表2-折旧摊销表'!I135+'表5-利润表-资本金(标准格式)'!I50)/MONTH(参数输入表!$I$8),'表10-资产负债表(标准格式)'!H7-参数输入表!I723) -> 185.26496 | J86: =('表3-成本费用表'!J31-'表3-成本费用表'!J36-'表3-成本费用表'!J37+'表5-利润表-资本金(标准格式)'!J19+'表5-利润表-资本金(标准格式)'!J50+'表5-利润表-资本金(标准格式)'!J23)/(12-MONTH(参数输入表!$I$8)) -> 160.2131 | K86: =('表3-成本费用表'!K31-'表3-成本费用表'!K36-'表3-成本费用表'!K37+'表5-利润表-资本金(标准格式)'!K19+'表5-利润表-资本金(标准格式)'!K50+'表5-利润表-资本金(标准格式)'!K23)/12 -> 467.81372 | L86: =('表3-成本费用表'!L31-'表3-成本费用表'!L36-'表3-成本费用表'!L37+'表5-利润表-资本金(标准格式)'!L19+'表5-利润表-资本金(标准格式)'!L50+'表5-利润表-资本金(标准格式)'!L23)/12 -> 667.88935 | M86: =('表3-成本费用表'!M31-'表3-成本费用表'!M36-'表3-成本费用表'!M37+'表5-利润表-资本金(标准格式)'!M19+'表5-利润表-资本金(标准格式)'!M50+'表5-利润表-资本金(标准格式)'!M23)/12 -> 681.09556 | N86: =('表3-成本费用表'!N31-'表3-成本费用表'!N36-'表3-成本费用表'!N37+'表5-利润表-资本金(标准格式)'!N19+'表5-利润表-资本金(标准格式)'!N50+'表5-利润表-资本金(标准格式)'!N23)/12 -> 659.01161 | O86: =('表3-成本费用表'!O31-'表3-成本费用表'!O36-'表3-成本费用表'!O37+'表5-利润表-资本金(标准格式)'!O19+'表5-利润表-资本金(标准格式)'!O50+'表5-利润表-资本金(标准格式)'!O23)/12 -> 637.52198 | P86: =('表3-成本费用表'!P31-'表3-成本费用表'!P36-'表3-成本费用表'!P37+'表5-利润表-资本金(标准格式)'!P19+'表5-利润表-资本金(标准格式)'!P50+'表5-利润表-资本金(标准格式)'!P23)/12 -> 615.3039 | Q86: =('表3-成本费用表'!Q31-'表3-成本费用表'!Q36-'表3-成本费用表'!Q37+'表5-利润表-资本金(标准格式)'!Q19+'表5-利润表-资本金(标准格式)'!Q50+'表5-利润表-资本金(标准格式)'!Q23)/12 -> 592.32613 | R86: =('表3-成本费用表'!R31-'表3-成本费用表'!R36-'表3-成本费用表'!R37+'表5-利润表-资本金(标准格式)'!R19+'表5-利润表-资本金(标准格式)'!R50+'表5-利润表-资本金(标准格式)'!R23)/12 -> 620.62364 | ... AE86: =('表3-成本费用表'!AE31-'表3-成本费用表'!AE36-'表3-成本费用表'!AE37+'表5-利润表-资本金(标准格式)'!AE19+'表5-利润表-资本金(标准格式)'!AE50+'表5-利润表-资本金(标准格式)'!AE23)/12 -> 517.05978 | AF86: 0
B87: 1.4 | C87: 预付账款 | E87: 万元 | I87: ='表10-资产负债表(标准格式)'!H16-折现率、非经营、长投计算表!E27 -> 300 | J87: =IF(参数输入表!$I$721="手动输入",基准日往来账处理!J17,基准日往来账处理!J95) -> 200 | K87: =IF(参数输入表!$I$721="手动输入",基准日往来账处理!K17,基准日往来账处理!K95) -> 100 | L87: =IF(参数输入表!$I$721="手动输入",基准日往来账处理!L17,基准日往来账处理!L95) -> 0 | M87: =IF(参数输入表!$I$721="手动输入",基准日往来账处理!M17,基准日往来账处理!M95) -> 0 | N87: =IF(参数输入表!$I$721="手动输入",基准日往来账处理!N17,基准日往来账处理!N95) -> 0 | O87: =IF(参数输入表!$I$721="手动输入",基准日往来账处理!O17,基准日往来账处理!O95) -> 0 | P87: =IF(参数输入表!$I$721="手动输入",基准日往来账处理!P17,基准日往来账处理!P95) -> 0 | Q87: =IF(参数输入表!$I$721="手动输入",基准日往来账处理!Q17,基准日往来账处理!Q95) -> 0 | ... AE87: =IF(参数输入表!$I$721="手动输入",基准日往来账处理!AE17,基准日往来账处理!AE95) -> 0 | AF87: 0
B88: 1.5 | C88: 应收票据 | E88: 万元 | I88: ='表10-资产负债表(标准格式)'!H13-折现率、非经营、长投计算表!E25 -> 46.642216 | J88: =IF(参数输入表!$I$721="手动输入",基准日往来账处理!J9,基准日往来账处理!J87) -> 26.642216 | K88: =IF(参数输入表!$I$721="手动输入",基准日往来账处理!K9,基准日往来账处理!K87) -> 0 | L88: =IF(参数输入表!$I$721="手动输入",基准日往来账处理!L9,基准日往来账处理!L87) -> 0 | M88: =IF(参数输入表!$I$721="手动输入",基准日往来账处理!M9,基准日往来账处理!M87) -> 0 | N88: =IF(参数输入表!$I$721="手动输入",基准日往来账处理!N9,基准日往来账处理!N87) -> 0 | O88: =IF(参数输入表!$I$721="手动输入",基准日往来账处理!O9,基准日往来账处理!O87) -> 0 | P88: =IF(参数输入表!$I$721="手动输入",基准日往来账处理!P9,基准日往来账处理!P87) -> 0 | Q88: =IF(参数输入表!$I$721="手动输入",基准日往来账处理!Q9,基准日往来账处理!Q87) -> 0 | ... AE88: =IF(参数输入表!$I$721="手动输入",基准日往来账处理!AE9,基准日往来账处理!AE87) -> 0 | AF88: 0
B89: 1.6 | C89: 其他应收款 | E89: 万元 | I89: ='表10-资产负债表(标准格式)'!H21-折现率、非经营、长投计算表!E28 -> 291.35112 | J89: =IF(参数输入表!$I$721="手动输入",基准日往来账处理!J21,基准日往来账处理!J99) -> 0 | K89: =IF(参数输入表!$I$721="手动输入",基准日往来账处理!K21,基准日往来账处理!K99) -> 0 | L89: =IF(参数输入表!$I$721="手动输入",基准日往来账处理!L21,基准日往来账处理!L99) -> 0 | M89: =IF(参数输入表!$I$721="手动输入",基准日往来账处理!M21,基准日往来账处理!M99) -> 0 | N89: =IF(参数输入表!$I$721="手动输入",基准日往来账处理!N21,基准日往来账处理!N99) -> 0 | O89: =IF(参数输入表!$I$721="手动输入",基准日往来账处理!O21,基准日往来账处理!O99) -> 0 | P89: =IF(参数输入表!$I$721="手动输入",基准日往来账处理!P21,基准日往来账处理!P99) -> 0 | Q89: =IF(参数输入表!$I$721="手动输入",基准日往来账处理!Q21,基准日往来账处理!Q99) -> 0 | ... AE89: =IF(参数输入表!$I$721="手动输入",基准日往来账处理!AE21,基准日往来账处理!AE99) -> 0 | AF89: 0
B90: 1.7 | C90: 一年内到期的非流动资产 | E90: 万元 | I90: ='表10-资产负债表(标准格式)'!H29-折现率、非经营、长投计算表!E32 -> 0 | J90: =I90 -> 0 | K90: =J90 -> 0 | L90: =K90 -> 0 | M90: =L90 -> 0 | N90: =M90 -> 0 | O90: =N90 -> 0 | P90: =O90 -> 0 | Q90: =P90 -> 0 | ... AE90: =AD90 -> 0 | AF90: 0
B91: 1.8 | C91: 合同资产 | E91: 万元 | I91: ='表10-资产负债表(标准格式)'!$H$27-折现率、非经营、长投计算表!$E$29 -> 0 | J91: =IF(参数输入表!$I$721="手动输入",基准日往来账处理!J29,基准日往来账处理!J107) -> 0 | K91: =IF(参数输入表!$I$721="手动输入",基准日往来账处理!K29,基准日往来账处理!K107) -> 0 | L91: =IF(参数输入表!$I$721="手动输入",基准日往来账处理!L29,基准日往来账处理!L107) -> 0 | M91: =IF(参数输入表!$I$721="手动输入",基准日往来账处理!M29,基准日往来账处理!M107) -> 0 | N91: =IF(参数输入表!$I$721="手动输入",基准日往来账处理!N29,基准日往来账处理!N107) -> 0 | O91: =IF(参数输入表!$I$721="手动输入",基准日往来账处理!O29,基准日往来账处理!O107) -> 0 | P91: =IF(参数输入表!$I$721="手动输入",基准日往来账处理!P29,基准日往来账处理!P107) -> 0 | Q91: =IF(参数输入表!$I$721="手动输入",基准日往来账处理!Q29,基准日往来账处理!Q107) -> 0 | ... AE91: =IF(参数输入表!$I$721="手动输入",基准日往来账处理!AE29,基准日往来账处理!AE107) -> 0 | AF91: 0
B92: 1.9 | C92: 其他流动资产（不含可抵扣进项） | E92: 万元 | I92: ='表10-资产负债表(标准格式)'!H30-参数输入表!I644-折现率、非经营、长投计算表!$E$33 -> 0 | J92: =I92 -> 0 | K92: =J92 -> 0 | L92: =K92 -> 0 | M92: =L92 -> 0 | N92: =M92 -> 0 | O92: =N92 -> 0 | P92: =O92 -> 0 | Q92: =P92 -> 0 | ... AE92: =AD92 -> 0 | AF92: 0
B93: 二 | C93: 流动负债 | E93: 万元 | I93: =SUM(I94:I101) -> 318.31223 | J93: =SUM(J94:J101) -> 196.74505 | K93: =SUM(K94:K101) -> 44.426828 | L93: =SUM(L94:L101) -> 24.426828 | M93: =SUM(M94:M101) -> 0 | N93: =SUM(N94:N101) -> 0 | O93: =SUM(O94:O101) -> 0 | P93: =SUM(P94:P101) -> 0 | ... AF93: =SUM(AF94:AF101) -> 0
B94: 2.1 | C94: 应付账款 | E94: 万元 | I94: ='表10-资产负债表(标准格式)'!H66-折现率、非经营、长投计算表!E44 -> 232.31822 | J94: =IF(参数输入表!$I$721="手动输入",基准日往来账处理!J42,基准日往来账处理!J120) -> 132.31822 | K94: =IF(参数输入表!$I$721="手动输入",基准日往来账处理!K42,基准日往来账处理!K120) -> 0 | L94: =IF(参数输入表!$I$721="手动输入",基准日往来账处理!L42,基准日往来账处理!L120) -> 0 | M94: =IF(参数输入表!$I$721="手动输入",基准日往来账处理!M42,基准日往来账处理!M120) -> 0 | N94: =IF(参数输入表!$I$721="手动输入",基准日往来账处理!N42,基准日往来账处理!N120) -> 0 | O94: =IF(参数输入表!$I$721="手动输入",基准日往来账处理!O42,基准日往来账处理!O120) -> 0 | P94: =IF(参数输入表!$I$721="手动输入",基准日往来账处理!P42,基准日往来账处理!P120) -> 0 | Q94: =IF(参数输入表!$I$721="手动输入",基准日往来账处理!Q42,基准日往来账处理!Q120) -> 0 | ... AE94: =IF(参数输入表!$I$721="手动输入",基准日往来账处理!AE42,基准日往来账处理!AE120) -> 0 | AF94: 0
B95: 2.2 | C95: 应付票据 | E95: 万元 | I95: ='表10-资产负债表(标准格式)'!H65-折现率、非经营、长投计算表!E43 -> 0 | J95: =IF(参数输入表!$I$721="手动输入",基准日往来账处理!J38,基准日往来账处理!J116) -> 0 | K95: =IF(参数输入表!$I$721="手动输入",基准日往来账处理!K38,基准日往来账处理!K116) -> 0 | L95: =IF(参数输入表!$I$721="手动输入",基准日往来账处理!L38,基准日往来账处理!L116) -> 0 | M95: =IF(参数输入表!$I$721="手动输入",基准日往来账处理!M38,基准日往来账处理!M116) -> 0 | N95: =IF(参数输入表!$I$721="手动输入",基准日往来账处理!N38,基准日往来账处理!N116) -> 0 | O95: =IF(参数输入表!$I$721="手动输入",基准日往来账处理!O38,基准日往来账处理!O116) -> 0 | P95: =IF(参数输入表!$I$721="手动输入",基准日往来账处理!P38,基准日往来账处理!P116) -> 0 | Q95: =IF(参数输入表!$I$721="手动输入",基准日往来账处理!Q38,基准日往来账处理!Q116) -> 0 | ... AE95: =IF(参数输入表!$I$721="手动输入",基准日往来账处理!AE38,基准日往来账处理!AE116) -> 0 | AF95: 0
B96: 2.3 | C96: 预收账款 | E96: 万元 | I96: ='表10-资产负债表(标准格式)'!H67-折现率、非经营、长投计算表!E45 -> 0 | J96: =IF(参数输入表!$I$721="手动输入",基准日往来账处理!J46,基准日往来账处理!J124) -> 0 | K96: =IF(参数输入表!$I$721="手动输入",基准日往来账处理!K46,基准日往来账处理!K124) -> 0 | L96: =IF(参数输入表!$I$721="手动输入",基准日往来账处理!L46,基准日往来账处理!L124) -> 0 | M96: =IF(参数输入表!$I$721="手动输入",基准日往来账处理!M46,基准日往来账处理!M124) -> 0 | N96: =IF(参数输入表!$I$721="手动输入",基准日往来账处理!N46,基准日往来账处理!N124) -> 0 | O96: =IF(参数输入表!$I$721="手动输入",基准日往来账处理!O46,基准日往来账处理!O124) -> 0 | P96: =IF(参数输入表!$I$721="手动输入",基准日往来账处理!P46,基准日往来账处理!P124) -> 0 | Q96: =IF(参数输入表!$I$721="手动输入",基准日往来账处理!Q46,基准日往来账处理!Q124) -> 0 | ... AE96: =IF(参数输入表!$I$721="手动输入",基准日往来账处理!AE46,基准日往来账处理!AE124) -> 0 | AF96: 0
B97: 2.4 | C97: 应付职工薪酬 | E97: 万元 | I97: ='表10-资产负债表(标准格式)'!H73-折现率、非经营、长投计算表!E47 -> 0.616196 | J97: =IF(参数输入表!$I$721="手动输入",基准日往来账处理!J50,基准日往来账处理!J128) -> 0 | K97: =IF(参数输入表!$I$721="手动输入",基准日往来账处理!K50,基准日往来账处理!K128) -> 0 | L97: =IF(参数输入表!$I$721="手动输入",基准日往来账处理!L50,基准日往来账处理!L128) -> 0 | M97: =IF(参数输入表!$I$721="手动输入",基准日往来账处理!M50,基准日往来账处理!M128) -> 0 | N97: =IF(参数输入表!$I$721="手动输入",基准日往来账处理!N50,基准日往来账处理!N128) -> 0 | O97: =IF(参数输入表!$I$721="手动输入",基准日往来账处理!O50,基准日往来账处理!O128) -> 0 | P97: =IF(参数输入表!$I$721="手动输入",基准日往来账处理!P50,基准日往来账处理!P128) -> 0 | Q97: =IF(参数输入表!$I$721="手动输入",基准日往来账处理!Q50,基准日往来账处理!Q128) -> 0 | ... AE97: =IF(参数输入表!$I$721="手动输入",基准日往来账处理!AE50,基准日往来账处理!AE128) -> 0 | AF97: 0
B98: 2.5 | C98: 应交税费 | E98: 万元 | I98: ='表10-资产负债表(标准格式)'!H77-折现率、非经营、长投计算表!E48 -> 0.950986 | J98: =IF(参数输入表!$I$721="手动输入",基准日往来账处理!J54,基准日往来账处理!J132) -> 0 | K98: =IF(参数输入表!$I$721="手动输入",基准日往来账处理!K54,基准日往来账处理!K132) -> 0 | L98: =IF(参数输入表!$I$721="手动输入",基准日往来账处理!L54,基准日往来账处理!L132) -> 0 | M98: =IF(参数输入表!$I$721="手动输入",基准日往来账处理!M54,基准日往来账处理!M132) -> 0 | N98: =IF(参数输入表!$I$721="手动输入",基准日往来账处理!N54,基准日往来账处理!N132) -> 0 | O98: =IF(参数输入表!$I$721="手动输入",基准日往来账处理!O54,基准日往来账处理!O132) -> 0 | P98: =IF(参数输入表!$I$721="手动输入",基准日往来账处理!P54,基准日往来账处理!P132) -> 0 | Q98: =IF(参数输入表!$I$721="手动输入",基准日往来账处理!Q54,基准日往来账处理!Q132) -> 0 | ... AE98: =IF(参数输入表!$I$721="手动输入",基准日往来账处理!AE54,基准日往来账处理!AE132) -> 0 | AF98: 0
B99: 2.6 | C99: 其他应付款 | E99: 万元 | I99: ='表10-资产负债表(标准格式)'!H79-折现率、非经营、长投计算表!E49 -> 84.426828 | J99: =IF(参数输入表!$I$721="手动输入",基准日往来账处理!J58,基准日往来账处理!J136) -> 64.426828 | K99: =IF(参数输入表!$I$721="手动输入",基准日往来账处理!K58,基准日往来账处理!K136) -> 44.426828 | L99: =IF(参数输入表!$I$721="手动输入",基准日往来账处理!L58,基准日往来账处理!L136) -> 24.426828 | M99: =IF(参数输入表!$I$721="手动输入",基准日往来账处理!M58,基准日往来账处理!M136) -> 0 | N99: =IF(参数输入表!$I$721="手动输入",基准日往来账处理!N58,基准日往来账处理!N136) -> 0 | O99: =IF(参数输入表!$I$721="手动输入",基准日往来账处理!O58,基准日往来账处理!O136) -> 0 | P99: =IF(参数输入表!$I$721="手动输入",基准日往来账处理!P58,基准日往来账处理!P136) -> 0 | Q99: =IF(参数输入表!$I$721="手动输入",基准日往来账处理!Q58,基准日往来账处理!Q136) -> 0 | ... AE99: =IF(参数输入表!$I$721="手动输入",基准日往来账处理!AE58,基准日往来账处理!AE136) -> 0 | AF99: 0
B100: 2.7 | C100: 合同负债 | E100: 万元 | I100: ='表10-资产负债表(标准格式)'!$H$68-折现率、非经营、长投计算表!$E$46 -> 0 | J100: =IF(参数输入表!$I$721="手动输入",基准日往来账处理!J66,基准日往来账处理!J144) -> 0 | K100: =IF(参数输入表!$I$721="手动输入",基准日往来账处理!K66,基准日往来账处理!K144) -> 0 | L100: =IF(参数输入表!$I$721="手动输入",基准日往来账处理!L66,基准日往来账处理!L144) -> 0 | M100: =IF(参数输入表!$I$721="手动输入",基准日往来账处理!M66,基准日往来账处理!M144) -> 0 | N100: =IF(参数输入表!$I$721="手动输入",基准日往来账处理!N66,基准日往来账处理!N144) -> 0 | O100: =IF(参数输入表!$I$721="手动输入",基准日往来账处理!O66,基准日往来账处理!O144) -> 0 | P100: =IF(参数输入表!$I$721="手动输入",基准日往来账处理!P66,基准日往来账处理!P144) -> 0 | Q100: =IF(参数输入表!$I$721="手动输入",基准日往来账处理!Q66,基准日往来账处理!Q144) -> 0 | ... AE100: =IF(参数输入表!$I$721="手动输入",基准日往来账处理!AE66,基准日往来账处理!AE144) -> 0 | AF100: 0
B101: 2.8 | C101: 其他流动负债 | E101: 万元 | I101: ='表10-资产负债表(标准格式)'!H85-折现率、非经营、长投计算表!E52 -> 0 | J101: =I101 -> 0 | K101: =J101 -> 0 | L101: =K101 -> 0 | M101: =L101 -> 0 | N101: =M101 -> 0 | O101: =N101 -> 0 | P101: =O101 -> 0 | Q101: =P101 -> 0 | ... AE101: =AD101 -> 0 | AF101: 0
B102: 三 | C102: 营运资金 | E102: 万元 | I102: =I83-I93 -> 10330.308 | J102: =J83-J93 -> 7403.8887 | K102: =K83-K93 -> 7668.3618 | L102: =L83-L93 -> 5830.0931 | M102: =M83-M93 -> 5030.8459 | N102: =N83-N93 -> 4989.51 | O102: =O83-O93 -> 4948.7683 | P102: =P83-P93 -> 4907.2977 | ... AF102: =AF83-AF93 -> 0
B103: 四 | C103: 营运资金当期增加额 | E103: 万元 | J103: =J102-I102 -> -2926.4189 | K103: =K102-J102 -> 264.47318 | L103: =L102-K102 -> -1838.2687 | M103: =M102-L102 -> -799.24721 | N103: =N102-M102 -> -41.335963 | O103: =O102-N102 -> -40.741636 | P103: =P102-O102 -> -41.470681 | Q103: =Q102-P102 -> -42.229781 | ... AF103: =AF102-AE102 -> -3630.368

Sheet 表5-利润表-资本金(标准格式)
B2: 利润表-资本金
B3: 序号 | C3: 项目 | D3: 合计 | E3: 单位 | F3: 2020年 | G3: 2021年 | H3: 2022年 | I3: 45107 | J3: 45261 | K3: 2024年 | L3: 2025年 | M3: 2026年 | N3: 2027年 | O3: 2028年 | P3: 2029年 | Q3: 2030年 | R3: 2031年 | S3: 2032年 | T3: 2033年 | U3: 2034年 | V3: 2035年 | W3: 2036年 | X3: 2037年 | Y3: 2038年 | Z3: 2039年 | AA3: 2040年 | AB3: 2041年 | AC3: 2042年 | AD3: 2043年 | AE3: 2044年 | AF3: 53051
F4: 1 | G4: 2 | H4: 3 | I4: 4 | J4: 5 | K4: 6 | L4: 7 | M4: 8 | N4: 9 | O4: 10 | P4: 11 | Q4: 12 | R4: 13 | S4: 14 | T4: 15 | U4: 16 | V4: 17 | W4: 18 | X4: 19 | Y4: 20 | Z4: 21 | AA4: 22 | AB4: 23 | AC4: 24 | AD4: 25 | AE4: 26 | AF4: 27
B5: 一、 | C5: 营业总收入 | D5: =SUM(F5:AF5) -> 354199.74 | E5: 万元 | F5: =SUM(F6:F9) -> 0 | G5: =SUM(G6:G9) -> 0 | H5: =SUM(H6:H9) -> 0 | I5: =SUM(I6:I9) -> 2000 | J5: =SUM(J6:J9) -> 1656.1591 | K5: =SUM(K6:K9) -> 14152.051 | L5: =SUM(L6:L9) -> 18589.687 | M5: =SUM(M6:M9) -> 18504.498 | ... AF5: =SUM(AF6:AF9) -> 3242.0223
C6: 其中：营业收入 | D6: =SUM(F6:AF6) -> 354199.74 | E6: 万元 | I6: 2000 | J6: ='表4-收入税金表'!J6 -> 1656.1591 | K6: ='表4-收入税金表'!K6 -> 14152.051 | L6: ='表4-收入税金表'!L6 -> 18589.687 | M6: ='表4-收入税金表'!M6 -> 18504.498 | N6: ='表4-收入税金表'!N6 -> 18419.312 | O6: ='表4-收入税金表'!O6 -> 18334.126 | P6: ='表4-收入税金表'!P6 -> 18248.938 | Q6: ='表4-收入税金表'!Q6 -> 18163.752 | ... AF6: ='表4-收入税金表'!AF6 -> 3242.0223
C7: △利息收入 | E7: 万元
C8: △已赚保费 | E8: 万元
C9: △手续费及佣金收入 | E9: 万元
B10: 二、 | C10: 营业总成本 | D10: =SUM(F10:AF10) -> 284141.31 | E10: 万元 | F10: =SUM(F11:F23)+F27 -> 0 | G10: =SUM(G11:G23)+G27 -> 0 | H10: =SUM(H11:H23)+H27 -> 0 | I10: =SUM(I11:I23)+I27 -> 2000 | J10: =SUM(J11:J23)+J27 -> 3055.4966 | K10: =SUM(K11:K23)+K27 -> 13980.681 | L10: =SUM(L11:L23)+L27 -> 17011.799 | M10: =SUM(M11:M23)+M27 -> 17068.903 | ... AF10: =SUM(AF11:AF23)+AF27 -> 4296.2062
C11: 其中：营业成本 | D11: =SUM(F11:AF11) -> 221338.95 | E11: 万元 | I11: 2000 | J11: ='表3-成本费用表'!J7 -> 2381.5855 | K11: ='表3-成本费用表'!K7 -> 10114.817 | L11: ='表3-成本费用表'!L7 -> 11326.73 | M11: ='表3-成本费用表'!M7 -> 11664.87 | N11: ='表3-成本费用表'!N7 -> 11693.67 | O11: ='表3-成本费用表'!O7 -> 11722.47 | P11: ='表3-成本费用表'!P7 -> 11751.27 | Q11: ='表3-成本费用表'!Q7 -> 11780.07 | ... AF11: ='表3-成本费用表'!AF7 -> 993.64165
C12: △利息支出 | E12: 万元
C13: △手续费及佣金支出 | E13: 万元
C14: △退保金 | E14: 万元
C15: △赔付支出净额 | E15: 万元
C16: △提取保险责任准备金净额 | E16: 万元
C17: △保单红利支出 | E17: 万元
C18: △分保费用 | E18: 万元
C19: 税金及附加 | D19: =SUM(F19:AF19) -> 3568.2685 | E19: 万元 | J19: ='表4-收入税金表'!J62+'表4-收入税金表'!J66 -> 0 | K19: ='表4-收入税金表'!K62+'表4-收入税金表'!K66 -> 0 | L19: ='表4-收入税金表'!L62+'表4-收入税金表'!L66 -> 0 | M19: ='表4-收入税金表'!M62+'表4-收入税金表'!M66 -> 0 | N19: ='表4-收入税金表'!N62+'表4-收入税金表'!N66 -> 0 | O19: ='表4-收入税金表'!O62+'表4-收入税金表'!O66 -> 0 | P19: ='表4-收入税金表'!P62+'表4-收入税金表'!P66 -> 0 | Q19: ='表4-收入税金表'!Q62+'表4-收入税金表'!Q66 -> 0 | ... AF19: ='表4-收入税金表'!AF62+'表4-收入税金表'!AF66 -> 51.679972
C20: 销售费用 | D20: =SUM(F20:AF20) -> 0 | E20: 万元 | J20: ='表3-成本费用表'!J16 -> 0 | K20: ='表3-成本费用表'!K16 -> 0 | L20: ='表3-成本费用表'!L16 -> 0 | M20: ='表3-成本费用表'!M16 -> 0 | N20: ='表3-成本费用表'!N16 -> 0 | O20: ='表3-成本费用表'!O16 -> 0 | P20: ='表3-成本费用表'!P16 -> 0 | Q20: ='表3-成本费用表'!Q16 -> 0 | ... AF20: ='表3-成本费用表'!AF16 -> 0
C21: 管理费用 | D21: =SUM(F21:AF21) -> 4313.6169 | E21: 万元 | J21: ='表3-成本费用表'!J17 -> 1.7018923 | K21: ='表3-成本费用表'!K17 -> 14.609164 | L21: ='表3-成本费用表'!L17 -> 19.278072 | M21: ='表3-成本费用表'!M17 -> 54.329111 | N21: ='表3-成本费用表'!N17 -> 54.329111 | O21: ='表3-成本费用表'!O17 -> 54.329111 | P21: ='表3-成本费用表'!P17 -> 54.329111 | Q21: ='表3-成本费用表'!Q17 -> 54.329111 | ... AF21: ='表3-成本费用表'!AF17 -> 3245.7746
C22: 研发费用 | D22: =SUM(F22:AF22) -> 0 | E22: 万元 | J22: ='表3-成本费用表'!J20 -> 0 | K22: ='表3-成本费用表'!K20 -> 0 | L22: ='表3-成本费用表'!L20 -> 0 | M22: ='表3-成本费用表'!M20 -> 0 | N22: ='表3-成本费用表'!N20 -> 0 | O22: ='表3-成本费用表'!O20 -> 0 | P22: ='表3-成本费用表'!P20 -> 0 | Q22: ='表3-成本费用表'!Q20 -> 0 | ... AF22: ='表3-成本费用表'!AF20 -> 0
C23: 财务费用 | D23: =SUM(F23:AF23) -> 54920.468 | E23: 万元 | J23: =J24-J25+J26 -> 672.2092 | K23: =K24-K25+K26 -> 3851.2555 | L23: =L24-L25+L26 -> 5665.7911 | M23: =M24-M25+M26 -> 5349.7034 | N23: =N24-N25+N26 -> 5024.1627 | O23: =O24-O25+O26 -> 4707.0125 | P23: =P24-P25+P26 -> 4379.5789 | Q23: =Q24-Q25+Q26 -> 4041.4196 | ... AF23: =AF24-AF25+AF26 -> 5.11
C24: 其中：利息费用 | D24: =SUM(F24:AF24) -> 54920.468 | E24: 万元 | J24: ='表3-成本费用表'!J21 -> 672.2092 | K24: ='表3-成本费用表'!K21 -> 3851.2555 | L24: ='表3-成本费用表'!L21 -> 5665.7911 | M24: ='表3-成本费用表'!M21 -> 5349.7034 | N24: ='表3-成本费用表'!N21 -> 5024.1627 | O24: ='表3-成本费用表'!O21 -> 4707.0125 | P24: ='表3-成本费用表'!P21 -> 4379.5789 | Q24: ='表3-成本费用表'!Q21 -> 4041.4196 | ... AF24: ='表3-成本费用表'!AF21 -> 5.11
C25: 利息收入 | E25: 万元
C26: 汇兑净损失（净收益以“-”号填列） | E26: 万元
C27: 其他 | E27: 万元
C28: 加：其他收益 | D28: =SUM(F28:AF28) -> 5974.115 | E28: 万元 | J28: ='表4-收入税金表'!J23 -> 25 | K28: ='表4-收入税金表'!K23 -> 214.60177 | L28: ='表4-收入税金表'!L23 -> 283.18584 | M28: ='表4-收入税金表'!M23 -> 283.18584 | N28: ='表4-收入税金表'!N23 -> 283.18584 | O28: ='表4-收入税金表'!O23 -> 283.18584 | P28: ='表4-收入税金表'!P23 -> 283.18584 | Q28: ='表4-收入税金表'!Q23 -> 283.18584 | ... AF28: ='表4-收入税金表'!AF23 -> 70.79646
C29: 投资收益（损失以“-”号填列） | E29: 万元
C30: 其中：对联营企业和合营企业的投资收益 | E30: 万元
C31: 以摊余成本计量的金融资产终止确认收益 | E31: 万元
C32: △汇兑收益（损失以“-”号填列） | E32: 万元
C33: 净敞口套期收益（损失以“-”号填列） | E33: 万元
C34: 公允价值变动收益（损失以“-”号填列） | E34: 万元
C35: 信用减值损失（损失以“-”号填列） | E35: 万元
C36: 资产减值损失（损失以“-”号填列） | E36: 万元
C37: 资产处置收益（损失以“-”号填列） | E37: 万元
B38: 三、 | C38: 营业利润（亏损以“－”号填列） | D38: =SUM(F38:AF38) -> 76032.548 | E38: 万元 | F38: =F5-F10+F28+F29+SUM(F32:F37) -> 0 | G38: =G5-G10+G28+G29+SUM(G32:G37) -> 0 | H38: =H5-H10+H28+H29+SUM(H32:H37) -> 0 | I38: =I5-I10+I28+I29+SUM(I32:I37) -> 0 | J38: =J5-J10+J28+J29+SUM(J32:J37) -> -1374.3375 | K38: =K5-K10+K28+K29+SUM(K32:K37) -> 385.97128 | L38: =L5-L10+L28+L29+SUM(L32:L37) -> 1861.0732 | M38: =M5-M10+M28+M29+SUM(M32:M37) -> 1718.7811 | ... AF38: =AF5-AF10+AF28+AF29+SUM(AF32:AF37) -> -983.38752
C39: 加：营业外收入 | D39: =SUM(F39:AF39) -> 200 | E39: 万元 | J39: ='表4-收入税金表'!J26 -> 0 | K39: ='表4-收入税金表'!K26 -> 0 | L39: ='表4-收入税金表'!L26 -> 10 | M39: ='表4-收入税金表'!M26 -> 10 | N39: ='表4-收入税金表'!N26 -> 10 | O39: ='表4-收入税金表'!O26 -> 10 | P39: ='表4-收入税金表'!P26 -> 10 | Q39: ='表4-收入税金表'!Q26 -> 10 | ... AF39: ='表4-收入税金表'!AF26 -> 0
C40: 其中：政府补助 | D40: =SUM(F40:AF40) -> 200 | E40: 万元 | J40: ='表4-收入税金表'!J27 -> 0 | K40: ='表4-收入税金表'!K27 -> 0 | L40: ='表4-收入税金表'!L27 -> 10 | M40: ='表4-收入税金表'!M27 -> 10 | N40: ='表4-收入税金表'!N27 -> 10 | O40: ='表4-收入税金表'!O27 -> 10 | P40: ='表4-收入税金表'!P27 -> 10 | Q40: ='表4-收入税金表'!Q27 -> 10 | ... AF40: ='表4-收入税金表'!AF27 -> 0
C41: 减：营业外支出 | D41: =SUM(F41:AF41) -> 0 | E41: 万元 | J41: ='表3-成本费用表'!J25 -> 0 | K41: ='表3-成本费用表'!K25 -> 0 | L41: ='表3-成本费用表'!L25 -> 0 | M41: ='表3-成本费用表'!M25 -> 0 | N41: ='表3-成本费用表'!N25 -> 0 | O41: ='表3-成本费用表'!O25 -> 0 | P41: ='表3-成本费用表'!P25 -> 0 | Q41: ='表3-成本费用表'!Q25 -> 0 | ... AF41: ='表3-成本费用表'!AF25 -> 0
B42: 四、 | C42: 利润总额（亏损总额以“－”号填列） | D42: =SUM(F42:AF42) -> 76232.548 | E42: 万元 | F42: =F38+F39-F41 -> 0 | G42: =G38+G39-G41 -> 0 | H42: =H38+H39-H41 -> 0 | I42: =I38+I39-I41 -> 0 | J42: =J38+J39-J41 -> -1374.3375 | K42: =K38+K39-K41 -> 385.97128 | L42: =L38+L39-L41 -> 1871.0732 | M42: =M38+M39-M41 -> 1728.7811 | ... AF42: =AF38+AF39-AF41 -> -983.38752
C43: 弥补以前年度亏损 | D43: =SUM(F43:AF43) -> 1374.3375 | E43: 万元 | F43: =SUM(F44:F48) -> 0 | G43: =SUM(G44:G48) -> 0 | H43: =SUM(H44:H48) -> 0 | I43: =SUM(I44:I48) -> 0 | J43: =SUM(J44:J48) -> 0 | K43: =SUM(K44:K48) -> 385.97128 | L43: =SUM(L44:L48) -> 988.36623 | M43: =SUM(M44:M48) -> 0 | ... AF43: =SUM(AF44:AF48) -> 0
C44: 弥补前序第一年亏损 | E44: 万元 | J44: =IF(I42>0,0,IF(J42<0,0,MIN(J42-SUM(J45:J48),-I42))) -> 0 | K44: =IF(J42>0,0,IF(K42<0,0,MIN(K42-SUM(K45:K48),-J42))) -> 385.97128 | L44: =IF(K42>0,0,IF(L42<0,0,MIN(L42-SUM(L45:L48),-K42))) -> 0 | M44: =IF(L42>0,0,IF(M42<0,0,MIN(M42-SUM(M45:M48),-L42))) -> 0 | N44: =IF(M42>0,0,IF(N42<0,0,MIN(N42-SUM(N45:N48),-M42))) -> 0 | O44: =IF(N42>0,0,IF(O42<0,0,MIN(O42-SUM(O45:O48),-N42))) -> 0 | P44: =IF(O42>0,0,IF(P42<0,0,MIN(P42-SUM(P45:P48),-O42))) -> 0 | Q44: =IF(P42>0,0,IF(Q42<0,0,MIN(Q42-SUM(Q45:Q48),-P42))) -> 0 | ... AF44: =IF(AE42>0,0,IF(AF42<0,0,MIN(AF42-SUM(AF45:AF48),-AE42))) -> 0
C45: 弥补前序第二年亏损 | E45: 万元 | J45: =IF(H42>0,0,IF(J42<0,0,MIN(J42-SUM(J46:J48),-H42-I44))) -> 0 | K45: =IF(I42>0,0,IF(K42<0,0,MIN(K42-SUM(K46:K48),-I42-J44))) -> 0 | L45: =IF(J42>0,0,IF(L42<0,0,MIN(L42-SUM(L46:L48),-J42-K44))) -> 988.36623 | M45: =IF(K42>0,0,IF(M42<0,0,MIN(M42-SUM(M46:M48),-K42-L44))) -> 0 | N45: =IF(L42>0,0,IF(N42<0,0,MIN(N42-SUM(N46:N48),-L42-M44))) -> 0 | O45: =IF(M42>0,0,IF(O42<0,0,MIN(O42-SUM(O46:O48),-M42-N44))) -> 0 | P45: =IF(N42>0,0,IF(P42<0,0,MIN(P42-SUM(P46:P48),-N42-O44))) -> 0 | Q45: =IF(O42>0,0,IF(Q42<0,0,MIN(Q42-SUM(Q46:Q48),-O42-P44))) -> 0 | ... AF45: =IF(AD42>0,0,IF(AF42<0,0,MIN(AF42-SUM(AF46:AF48),-AD42-AE44))) -> 0
C46: 弥补前序第三年亏损 | E46: 万元 | J46: =IF(G42>0,0,IF(J42<0,0,MIN(J42-SUM(J47:J48),-G42-H44-I45))) -> 0 | K46: =IF(H42>0,0,IF(K42<0,0,MIN(K42-SUM(K47:K48),-H42-I44-J45))) -> 0 | L46: =IF(I42>0,0,IF(L42<0,0,MIN(L42-SUM(L47:L48),-I42-J44-K45))) -> 0 | M46: =IF(J42>0,0,IF(M42<0,0,MIN(M42-SUM(M47:M48),-J42-K44-L45))) -> 0 | N46: =IF(K42>0,0,IF(N42<0,0,MIN(N42-SUM(N47:N48),-K42-L44-M45))) -> 0 | O46: =IF(L42>0,0,IF(O42<0,0,MIN(O42-SUM(O47:O48),-L42-M44-N45))) -> 0 | P46: =IF(M42>0,0,IF(P42<0,0,MIN(P42-SUM(P47:P48),-M42-N44-O45))) -> 0 | Q46: =IF(N42>0,0,IF(Q42<0,0,MIN(Q42-SUM(Q47:Q48),-N42-O44-P45))) -> 0 | ... AF46: =IF(AC42>0,0,IF(AF42<0,0,MIN(AF42-SUM(AF47:AF48),-AC42-AD44-AE45))) -> 0
C47: 弥补前序第四年亏损 | E47: 万元 | J47: =IF(F42>0,0,IF(J42<0,0,MIN(J42-J48,-F42-G44-H45-I46))) -> 0 | K47: =IF(G42>0,0,IF(K42<0,0,MIN(K42-K48,-G42-H44-I45-J46))) -> 0 | L47: =IF(H42>0,0,IF(L42<0,0,MIN(L42-L48,-H42-I44-J45-K46))) -> 0 | M47: =IF(I42>0,0,IF(M42<0,0,MIN(M42-M48,-I42-J44-K45-L46))) -> 0 | N47: =IF(J42>0,0,IF(N42<0,0,MIN(N42-N48,-J42-K44-L45-M46))) -> 0 | O47: =IF(K42>0,0,IF(O42<0,0,MIN(O42-O48,-K42-L44-M45-N46))) -> 0 | P47: =IF(L42>0,0,IF(P42<0,0,MIN(P42-P48,-L42-M44-N45-O46))) -> 0 | Q47: =IF(M42>0,0,IF(Q42<0,0,MIN(Q42-Q48,-M42-N44-O45-P46))) -> 0 | ... AF47: =IF(AB42>0,0,IF(AF42<0,0,MIN(AF42-AF48,-AB42-AC44-AD45-AE46))) -> 0
C48: 弥补前序第五年亏损 | E48: 万元 | K48: =IF(F42>0,0,IF(K42<0,0,MIN(K42,-F42-G44-H45-I46-J47))) -> 0 | L48: =IF(G42>0,0,IF(L42<0,0,MIN(L42,-G42-H44-I45-J46-K47))) -> 0 | M48: =IF(H42>0,0,IF(M42<0,0,MIN(M42,-H42-I44-J45-K46-L47))) -> 0 | N48: =IF(I42>0,0,IF(N42<0,0,MIN(N42,-I42-J44-K45-L46-M47))) -> 0 | O48: =IF(J42>0,0,IF(O42<0,0,MIN(O42,-J42-K44-L45-M46-N47))) -> 0 | P48: =IF(K42>0,0,IF(P42<0,0,MIN(P42,-K42-L44-M45-N46-O47))) -> 0 | Q48: =IF(L42>0,0,IF(Q42<0,0,MIN(Q42,-L42-M44-N45-O46-P47))) -> 0 | R48: =IF(M42>0,0,IF(R42<0,0,MIN(R42,-M42-N44-O45-P46-Q47))) -> 0 | ... AF48: =IF(AA42>0,0,IF(AF42<0,0,MIN(AF42,-AA42-AB44-AC45-AD46-AE47))) -> 0
C49: 应税所得额 | D49: =SUM(F49:AF49) -> 77215.936 | E49: 万元 | F49: =IF(F42-F43>0,F42-F43,0) -> 0 | G49: =IF(G42-G43>0,G42-G43,0) -> 0 | H49: =IF(H42-H43>0,H42-H43,0) -> 0 | I49: =IF(I42-I43>0,I42-I43,0) -> 0 | J49: =IF(J42-J43>0,J42-J43,0) -> 0 | K49: =IF(K42-K43>0,K42-K43,0) -> 0 | L49: =IF(L42-L43>0,L42-L43,0) -> 882.70692 | M49: =IF(M42-M43>0,M42-M43,0) -> 1728.7811 | ... AF49: =IF(AF42-AF43>0,AF42-AF43,0) -> 0
